Workbook

Sheet Question 1
A1: 1) | B1: Using the Black-Scholes equations, and assuming that the current Apple share price is $255,
A2: life of option is 8 months, annualized volatility is 30%, annualized continuously compounded risk-free rate is 5%.
A3: and annualized continously compounded dividend rate is 2%
A4: ai) At the money forward call option
A5: aii) At the money spot put option
A7: ai) | B7: S0 | D7: 255 | F7: aii) | G7: S0 | I7: =D7 -> 255
B8: sigma | D8: 0.3 | G8: sigma | I8: =D8 -> 0.3
B9: risk-free rate | D9: =-LN(EXP(-0.04))/(8/12) -> 0.06 | G9: risk-free rate | I9: =D9 -> 0.06
B10: dividend rate | D10: 0.04 | G10: dividend rate | I10: =D10 -> 0.04
B11: option life | D11: =8/12 -> 0.66666667 | G11: option life | I11: =D11 -> 0.66666667
B12: strike | D12: =D7*EXP((D9-D10)*D11) -> 258.42277 | G12: strike | I12: =I7 -> 255
B14: d1 | D14: =(LN(D7/D12)+((D9-D10+(0.5*D8*D8))*D11))/(D8*SQRT(D11)) -> 0.12247449 | G14: d1 | I14: =(LN(I7/I12)+((I9-I10+(0.5*I8*I8))*I11))/(I8*SQRT(I11)) -> 0.17690759
B15: d2 | D15: =D14-(D8*SQRT(D11)) -> -0.12247449 | G15: d2 | I15: =I14-(I8*SQRT(I11)) -> -0.068041382
B16: ATM Forward Put Premium | D16: =(-D7*EXP(-D10*D11)*NORMSDIST(-D14))+(D12*EXP(-D9*D11)*NORMSDIST(-D15)) -> 24.202489 | G16: ATM Spot call Premium | I16: =(I7*EXP(-I10*I11)*NORMSDIST(I14))-(I12*EXP(-I9*I11)*NORMSDIST(I15)) -> 25.721921
A18: bi) | B18: Call (K) - Put(K) = S0*exp(-qT) - K*exp(-rT) | F18: bii) | G18: Call (K) - Put(K) = S0*exp(-qT) - K*exp(-rT)
B19: ATM Fwd Put | C19: =D16 -> 24.202489 | G19: ATM Spot Call | H19: =I16 -> 25.721921
B20: S0 | C20: =D7 -> 255 | G20: S0 | H20: =I7 -> 255
B21: K | C21: =D12 -> 258.42277 | G21: K | H21: =I12 -> 255
B22: Exp(-rT) | C22: =EXP(-D9*D11) -> 0.96078944 | G22: Exp(-rT) | H22: =C22 -> 0.96078944
B23: Exp(-qT) | C23: =EXP(-D10*D11) -> 0.97368575 | G23: Exp(-qT) | H23: =C23 -> 0.97368575
B25: ATM Fwd Call | C25: =C19-(C21*C22)+(C20*C23) -> 24.202489 | G25: ATM spot Put | H25: =H19+(H21*H22)-(H20*H23) -> 22.433362

Sheet Question 2a_1
A1: Option type | B1: =K3 -> C | C1: =L3 -> C | D1: =M3 -> C | E1: =N3 -> C | F1: Net Effect | G1: Payoff To Replicate | H1: Slippage | I1: Replication Position | K1: Option 1 | L1: Option 2 | M1: Option 3 | N1: Option 4
I2: Inputs | J2: Current Stock Price ($) | K2: 110
A3: Stock price At Maturity | B3: Profit | J3: Option Type | K3: C | L3: C | M3: C | N3: C
A4: 70 | B4: =(MAX(IF($B$1="C",1,-1)*(A4-$K$5),0)-IF($K$10="Y",$K$13*EXP($K$6*$K$9),0))*$K$4 -> 0 | C4: =(MAX(IF($C$1="C",1,-1)*(A4-$L$5),0)-IF($K$10="Y",$L$13*EXP($K$6*$K$9),0))*$L$4 -> 0 | D4: =(MAX(IF($D$1="C",1,-1)*(A4-$M$5),0)-IF($K$10="Y",$M$13*EXP($K$6*$K$9),0))*$M$4 -> 0 | E4: =(MAX(IF($E$1="C",1,-1)*(A4-$N$5),0)-IF($K$10="Y",$N$13*EXP($K$6*$K$9),0))*$N$4 -> 0 | F4: =SUM(B4:E4) -> 0 | G4: =IF(A4<=$K$18,0,IF(A4>$K$19,0,$K$19-A4)) -> 0 | H4: =F4-G4 -> 0 | J4: Postion | K4: 2000000 | L4: =-K4 -> -2000000 | M4: -1 | N4: 1 | AL4: ST | AM4: payoff
A5: =A4+1 -> 71 | B5: =(MAX(IF($B$1="C",1,-1)*(A5-$K$5),0)-IF($K$10="Y",$K$13*EXP($K$6*$K$9),0))*$K$4 -> 0 | C5: =(MAX(IF($C$1="C",1,-1)*(A5-$L$5),0)-IF($K$10="Y",$L$13*EXP($K$6*$K$9),0))*$L$4 -> 0 | D5: =(MAX(IF($D$1="C",1,-1)*(A5-$M$5),0)-IF($K$10="Y",$M$13*EXP($K$6*$K$9),0))*$M$4 -> 0 | E5: =(MAX(IF($E$1="C",1,-1)*(A5-$N$5),0)-IF($K$10="Y",$N$13*EXP($K$6*$K$9),0))*$N$4 -> 0 | F5: =SUM(B5:E5) -> 0 | G5: =IF(A5<=$K$18,0,IF(A5>$K$19,0,$K$19-A5)) -> 0 | H5: =F5-G5 -> 0 | J5: Strike Price ($) | K5: 80 | L5: 80.00001 | M5: 80 | N5: 100 | AL5: 0 | AM5: =MAX(0,(AL5^2)-120) -> 0
A6: =A5+1 -> 72 | B6: =(MAX(IF($B$1="C",1,-1)*(A6-$K$5),0)-IF($K$10="Y",$K$13*EXP($K$6*$K$9),0))*$K$4 -> 0 | C6: =(MAX(IF($C$1="C",1,-1)*(A6-$L$5),0)-IF($K$10="Y",$L$13*EXP($K$6*$K$9),0))*$L$4 -> 0 | D6: =(MAX(IF($D$1="C",1,-1)*(A6-$M$5),0)-IF($K$10="Y",$M$13*EXP($K$6*$K$9),0))*$M$4 -> 0 | E6: =(MAX(IF($E$1="C",1,-1)*(A6-$N$5),0)-IF($K$10="Y",$N$13*EXP($K$6*$K$9),0))*$N$4 -> 0 | F6: =SUM(B6:E6) -> 0 | G6: =IF(A6<=$K$18,0,IF(A6>$K$19,0,$K$19-A6)) -> 0 | H6: =F6-G6 -> 0 | J6: Risk Free Rate (%) | K6: 0.04 | AL6: =AL5+2 -> 2 | AM6: =MAX(0,(AL6^2)-120) -> 0
A7: =A6+1 -> 73 | B7: =(MAX(IF($B$1="C",1,-1)*(A7-$K$5),0)-IF($K$10="Y",$K$13*EXP($K$6*$K$9),0))*$K$4 -> 0 | C7: =(MAX(IF($C$1="C",1,-1)*(A7-$L$5),0)-IF($K$10="Y",$L$13*EXP($K$6*$K$9),0))*$L$4 -> 0 | D7: =(MAX(IF($D$1="C",1,-1)*(A7-$M$5),0)-IF($K$10="Y",$M$13*EXP($K$6*$K$9),0))*$M$4 -> 0 | E7: =(MAX(IF($E$1="C",1,-1)*(A7-$N$5),0)-IF($K$10="Y",$N$13*EXP($K$6*$K$9),0))*$N$4 -> 0 | F7: =SUM(B7:E7) -> 0 | G7: =IF(A7<=$K$18,0,IF(A7>$K$19,0,$K$19-A7)) -> 0 | H7: =F7-G7 -> 0 | J7: Dividend Rate (%) | K7: 0.01 | AL7: =AL6+2 -> 4 | AM7: =MAX(0,(AL7^2)-120) -> 0
A8: =A7+1 -> 74 | B8: =(MAX(IF($B$1="C",1,-1)*(A8-$K$5),0)-IF($K$10="Y",$K$13*EXP($K$6*$K$9),0))*$K$4 -> 0 | C8: =(MAX(IF($C$1="C",1,-1)*(A8-$L$5),0)-IF($K$10="Y",$L$13*EXP($K$6*$K$9),0))*$L$4 -> 0 | D8: =(MAX(IF($D$1="C",1,-1)*(A8-$M$5),0)-IF($K$10="Y",$M$13*EXP($K$6*$K$9),0))*$M$4 -> 0 | E8: =(MAX(IF($E$1="C",1,-1)*(A8-$N$5),0)-IF($K$10="Y",$N$13*EXP($K$6*$K$9),0))*$N$4 -> 0 | F8: =SUM(B8:E8) -> 0 | G8: =IF(A8<=$K$18,0,IF(A8>$K$19,0,$K$19-A8)) -> 0 | H8: =F8-G8 -> 0 | J8: Volatility Rate (%) | K8: 0.3 | AL8: =AL7+2 -> 6 | AM8: =MAX(0,(AL8^2)-120) -> 0
A9: =A8+1 -> 75 | B9: =(MAX(IF($B$1="C",1,-1)*(A9-$K$5),0)-IF($K$10="Y",$K$13*EXP($K$6*$K$9),0))*$K$4 -> 0 | C9: =(MAX(IF($C$1="C",1,-1)*(A9-$L$5),0)-IF($K$10="Y",$L$13*EXP($K$6*$K$9),0))*$L$4 -> 0 | D9: =(MAX(IF($D$1="C",1,-1)*(A9-$M$5),0)-IF($K$10="Y",$M$13*EXP($K$6*$K$9),0))*$M$4 -> 0 | E9: =(MAX(IF($E$1="C",1,-1)*(A9-$N$5),0)-IF($K$10="Y",$N$13*EXP($K$6*$K$9),0))*$N$4 -> 0 | F9: =SUM(B9:E9) -> 0 | G9: =IF(A9<=$K$18,0,IF(A9>$K$19,0,$K$19-A9)) -> 0 | H9: =F9-G9 -> 0 | J9: Option Life (years) | K9: 1 | AL9: =AL8+2 -> 8 | AM9: =MAX(0,(AL9^2)-120) -> 0
A10: =A9+1 -> 76 | B10: =(MAX(IF($B$1="C",1,-1)*(A10-$K$5),0)-IF($K$10="Y",$K$13*EXP($K$6*$K$9),0))*$K$4 -> 0 | C10: =(MAX(IF($C$1="C",1,-1)*(A10-$L$5),0)-IF($K$10="Y",$L$13*EXP($K$6*$K$9),0))*$L$4 -> 0 | D10: =(MAX(IF($D$1="C",1,-1)*(A10-$M$5),0)-IF($K$10="Y",$M$13*EXP($K$6*$K$9),0))*$M$4 -> 0 | E10: =(MAX(IF($E$1="C",1,-1)*(A10-$N$5),0)-IF($K$10="Y",$N$13*EXP($K$6*$K$9),0))*$N$4 -> 0 | F10: =SUM(B10:E10) -> 0 | G10: =IF(A10<=$K$18,0,IF(A10>$K$19,0,$K$19-A10)) -> 0 | H10: =F10-G10 -> 0 | J10: Include Premium | K10: N | AL10: =AL9+2 -> 10 | AM10: =MAX(0,(AL10^2)-120) -> 0
A11: =A10+1 -> 77 | B11: =(MAX(IF($B$1="C",1,-1)*(A11-$K$5),0)-IF($K$10="Y",$K$13*EXP($K$6*$K$9),0))*$K$4 -> 0 | C11: =(MAX(IF($C$1="C",1,-1)*(A11-$L$5),0)-IF($K$10="Y",$L$13*EXP($K$6*$K$9),0))*$L$4 -> 0 | D11: =(MAX(IF($D$1="C",1,-1)*(A11-$M$5),0)-IF($K$10="Y",$M$13*EXP($K$6*$K$9),0))*$M$4 -> 0 | E11: =(MAX(IF($E$1="C",1,-1)*(A11-$N$5),0)-IF($K$10="Y",$N$13*EXP($K$6*$K$9),0))*$N$4 -> 0 | F11: =SUM(B11:E11) -> 0 | G11: =IF(A11<=$K$18,0,IF(A11>$K$19,0,$K$19-A11)) -> 0 | H11: =F11-G11 -> 0 | I11: Computations | J11: d1 | K11: =(LN($K$2/K5)+(($K$6-$K$7+(0.5*$K$8*$K$8))*$K$9))/($K$8*SQRT($K$9)) -> 1.3115124 | L11: =(LN($K$2/L5)+(($K$6-$K$7+(0.5*$K$8*$K$8))*$K$9))/($K$8*SQRT($K$9)) -> 1.311512 | M11: =(LN($K$2/M5)+(($K$6-$K$7+(0.5*$K$8*$K$8))*$K$9))/($K$8*SQRT($K$9)) -> 1.3115124 | N11: =(LN($K$2/N5)+(($K$6-$K$7+(0.5*$K$8*$K$8))*$K$9))/($K$8*SQRT($K$9)) -> 0.5677006 | AL11: =AL10+2 -> 12 | AM11: =MAX(0,(AL11^2)-120) -> 24
A12: =A11+1 -> 78 | B12: =(MAX(IF($B$1="C",1,-1)*(A12-$K$5),0)-IF($K$10="Y",$K$13*EXP($K$6*$K$9),0))*$K$4 -> 0 | C12: =(MAX(IF($C$1="C",1,-1)*(A12-$L$5),0)-IF($K$10="Y",$L$13*EXP($K$6*$K$9),0))*$L$4 -> 0 | D12: =(MAX(IF($D$1="C",1,-1)*(A12-$M$5),0)-IF($K$10="Y",$M$13*EXP($K$6*$K$9),0))*$M$4 -> 0 | E12: =(MAX(IF($E$1="C",1,-1)*(A12-$N$5),0)-IF($K$10="Y",$N$13*EXP($K$6*$K$9),0))*$N$4 -> 0 | F12: =SUM(B12:E12) -> 0 | G12: =IF(A12<=$K$18,0,IF(A12>$K$19,0,$K$19-A12)) -> 0 | H12: =F12-G12 -> 0 | J12: d2 | K12: =K11-($K$8*SQRT($K$9)) -> 1.0115124 | L12: =L11-($K$8*SQRT($K$9)) -> 1.011512 | M12: =M11-($K$8*SQRT($K$9)) -> 1.0115124 | N12: =N11-($K$8*SQRT($K$9)) -> 0.2677006 | AL12: =AL11+2 -> 14 | AM12: =MAX(0,(AL12^2)-120) -> 76
A13: =A12+1 -> 79 | B13: =(MAX(IF($B$1="C",1,-1)*(A13-$K$5),0)-IF($K$10="Y",$K$13*EXP($K$6*$K$9),0))*$K$4 -> 0 | C13: =(MAX(IF($C$1="C",1,-1)*(A13-$L$5),0)-IF($K$10="Y",$L$13*EXP($K$6*$K$9),0))*$L$4 -> 0 | D13: =(MAX(IF($D$1="C",1,-1)*(A13-$M$5),0)-IF($K$10="Y",$M$13*EXP($K$6*$K$9),0))*$M$4 -> 0 | E13: =(MAX(IF($E$1="C",1,-1)*(A13-$N$5),0)-IF($K$10="Y",$N$13*EXP($K$6*$K$9),0))*$N$4 -> 0 | F13: =SUM(B13:E13) -> 0 | G13: =IF(A13<=$K$18,0,IF(A13>$K$19,0,$K$19-A13)) -> 0 | H13: =F13-G13 -> 0 | J13: Premium | K13: =IF(K3="C",($K$2*EXP(-$K$7*$K$9)*NORMSDIST(K11))-(K5*EXP(-$K$6*$K$9)*NORMSDIST(K12)),(-$K$2*EXP(-$K$7*$K$9)*NORMSDIST(-K11))-(-K5*EXP(-$K$6*$K$9)*NORMSDIST(-K12))) -> 33.695335 | L13: =IF(L3="C",($K$2*EXP(-$K$7*$K$9)*NORMSDIST(L11))-(L5*EXP(-$K$6*$K$9)*NORMSDIST(L12)),(-$K$2*EXP(-$K$7*$K$9)*NORMSDIST(-L11))-(-L5*EXP(-$K$6*$K$9)*NORMSDIST(-L12))) -> 33.695327 | M13: =IF(M3="C",($K$2*EXP(-$K$7*$K$9)*NORMSDIST(M11))-(M5*EXP(-$K$6*$K$9)*NORMSDIST(M12)),(-$K$2*EXP(-$K$7*$K$9)*NORMSDIST(-M11))-(-M5*EXP(-$K$6*$K$9)*NORMSDIST(-M12))) -> 33.695335 | N13: =IF(N3="C",($K$2*EXP(-$K$7*$K$9)*NORMSDIST(N11))-(N5*EXP(-$K$6*$K$9)*NORMSDIST(N12)),(-$K$2*EXP(-$K$7*$K$9)*NORMSDIST(-N11))-(-N5*EXP(-$K$6*$K$9)*NORMSDIST(-N12))) -> 19.675271 | AL13: =AL12+2 -> 16 | AM13: =MAX(0,(AL13^2)-120) -> 136
A14: =A13+1 -> 80 | B14: =(MAX(IF($B$1="C",1,-1)*(A14-$K$5),0)-IF($K$10="Y",$K$13*EXP($K$6*$K$9),0))*$K$4 -> 0 | C14: =(MAX(IF($C$1="C",1,-1)*(A14-$L$5),0)-IF($K$10="Y",$L$13*EXP($K$6*$K$9),0))*$L$4 -> 0 | D14: =(MAX(IF($D$1="C",1,-1)*(A14-$M$5),0)-IF($K$10="Y",$M$13*EXP($K$6*$K$9),0))*$M$4 -> 0 | E14: =(MAX(IF($E$1="C",1,-1)*(A14-$N$5),0)-IF($K$10="Y",$N$13*EXP($K$6*$K$9),0))*$N$4 -> 0 | F14: =SUM(B14:E14) -> 0 | G14: =IF(A14<=$K$18,0,IF(A14>$K$19,0,$K$19-A14)) -> 0 | H14: =F14-G14 -> 0 | J14: Total Premium | K14: =SUMPRODUCT(K4:N4,K13:N13) -> 2.2002581 | AL14: =AL13+2 -> 18 | AM14: =MAX(0,(AL14^2)-120) -> 204
A15: =A14+1 -> 81 | B15: =(MAX(IF($B$1="C",1,-1)*(A15-$K$5),0)-IF($K$10="Y",$K$13*EXP($K$6*$K$9),0))*$K$4 -> 2000000 | C15: =(MAX(IF($C$1="C",1,-1)*(A15-$L$5),0)-IF($K$10="Y",$L$13*EXP($K$6*$K$9),0))*$L$4 -> -1999980 | D15: =(MAX(IF($D$1="C",1,-1)*(A15-$M$5),0)-IF($K$10="Y",$M$13*EXP($K$6*$K$9),0))*$M$4 -> -1 | E15: =(MAX(IF($E$1="C",1,-1)*(A15-$N$5),0)-IF($K$10="Y",$N$13*EXP($K$6*$K$9),0))*$N$4 -> 0 | F15: =SUM(B15:E15) -> 19 | G15: =IF(A15<=$K$18,0,IF(A15>$K$19,0,$K$19-A15)) -> 19 | H15: =F15-G15 -> 6.2864274e-09 | AL15: =AL14+2 -> 20 | AM15: =MAX(0,(AL15^2)-120) -> 280
A16: =A15+1 -> 82 | B16: =(MAX(IF($B$1="C",1,-1)*(A16-$K$5),0)-IF($K$10="Y",$K$13*EXP($K$6*$K$9),0))*$K$4 -> 4000000 | C16: =(MAX(IF($C$1="C",1,-1)*(A16-$L$5),0)-IF($K$10="Y",$L$13*EXP($K$6*$K$9),0))*$L$4 -> -3999980 | D16: =(MAX(IF($D$1="C",1,-1)*(A16-$M$5),0)-IF($K$10="Y",$M$13*EXP($K$6*$K$9),0))*$M$4 -> -2 | E16: =(MAX(IF($E$1="C",1,-1)*(A16-$N$5),0)-IF($K$10="Y",$N$13*EXP($K$6*$K$9),0))*$N$4 -> 0 | F16: =SUM(B16:E16) -> 18 | G16: =IF(A16<=$K$18,0,IF(A16>$K$19,0,$K$19-A16)) -> 18 | H16: =F16-G16 -> 6.519258e-09 | AL16: =AL15+2 -> 22 | AM16: =MAX(0,(AL16^2)-120) -> 364
A17: =A16+1 -> 83 | B17: =(MAX(IF($B$1="C",1,-1)*(A17-$K$5),0)-IF($K$10="Y",$K$13*EXP($K$6*$K$9),0))*$K$4 -> 6000000 | C17: =(MAX(IF($C$1="C",1,-1)*(A17-$L$5),0)-IF($K$10="Y",$L$13*EXP($K$6*$K$9),0))*$L$4 -> -5999980 | D17: =(MAX(IF($D$1="C",1,-1)*(A17-$M$5),0)-IF($K$10="Y",$M$13*EXP($K$6*$K$9),0))*$M$4 -> -3 | E17: =(MAX(IF($E$1="C",1,-1)*(A17-$N$5),0)-IF($K$10="Y",$N$13*EXP($K$6*$K$9),0))*$N$4 -> 0 | F17: =SUM(B17:E17) -> 17 | G17: =IF(A17<=$K$18,0,IF(A17>$K$19,0,$K$19-A17)) -> 17 | H17: =F17-G17 -> 6.519258e-09 | J17: Structure To Price | AL17: =AL16+2 -> 24 | AM17: =MAX(0,(AL17^2)-120) -> 456
A18: =A17+1 -> 84 | B18: =(MAX(IF($B$1="C",1,-1)*(A18-$K$5),0)-IF($K$10="Y",$K$13*EXP($K$6*$K$9),0))*$K$4 -> 8000000 | C18: =(MAX(IF($C$1="C",1,-1)*(A18-$L$5),0)-IF($K$10="Y",$L$13*EXP($K$6*$K$9),0))*$L$4 -> -7999980 | D18: =(MAX(IF($D$1="C",1,-1)*(A18-$M$5),0)-IF($K$10="Y",$M$13*EXP($K$6*$K$9),0))*$M$4 -> -4 | E18: =(MAX(IF($E$1="C",1,-1)*(A18-$N$5),0)-IF($K$10="Y",$N$13*EXP($K$6*$K$9),0))*$N$4 -> 0 | F18: =SUM(B18:E18) -> 16 | G18: =IF(A18<=$K$18,0,IF(A18>$K$19,0,$K$19-A18)) -> 16 | H18: =F18-G18 -> 6.519258e-09 | J18: Lower Strike | K18: 80 | AL18: =AL17+2 -> 26 | AM18: =MAX(0,(AL18^2)-120) -> 556
A19: =A18+1 -> 85 | B19: =(MAX(IF($B$1="C",1,-1)*(A19-$K$5),0)-IF($K$10="Y",$K$13*EXP($K$6*$K$9),0))*$K$4 -> 10000000 | C19: =(MAX(IF($C$1="C",1,-1)*(A19-$L$5),0)-IF($K$10="Y",$L$13*EXP($K$6*$K$9),0))*$L$4 -> -9999980 | D19: =(MAX(IF($D$1="C",1,-1)*(A19-$M$5),0)-IF($K$10="Y",$M$13*EXP($K$6*$K$9),0))*$M$4 -> -5 | E19: =(MAX(IF($E$1="C",1,-1)*(A19-$N$5),0)-IF($K$10="Y",$N$13*EXP($K$6*$K$9),0))*$N$4 -> 0 | F19: =SUM(B19:E19) -> 15 | G19: =IF(A19<=$K$18,0,IF(A19>$K$19,0,$K$19-A19)) -> 15 | H19: =F19-G19 -> 5.5879354e-09 | J19: Higher Strike | K19: 100 | AL19: =AL18+2 -> 28 | AM19: =MAX(0,(AL19^2)-120) -> 664
A20: =A19+1 -> 86 | B20: =(MAX(IF($B$1="C",1,-1)*(A20-$K$5),0)-IF($K$10="Y",$K$13*EXP($K$6*$K$9),0))*$K$4 -> 12000000 | C20: =(MAX(IF($C$1="C",1,-1)*(A20-$L$5),0)-IF($K$10="Y",$L$13*EXP($K$6*$K$9),0))*$L$4 -> -11999980 | D20: =(MAX(IF($D$1="C",1,-1)*(A20-$M$5),0)-IF($K$10="Y",$M$13*EXP($K$6*$K$9),0))*$M$4 -> -6 | E20: =(MAX(IF($E$1="C",1,-1)*(A20-$N$5),0)-IF($K$10="Y",$N$13*EXP($K$6*$K$9),0))*$N$4 -> 0 | F20: =SUM(B20:E20) -> 14 | G20: =IF(A20<=$K$18,0,IF(A20>$K$19,0,$K$19-A20)) -> 14 | H20: =F20-G20 -> 5.5879354e-09 | J20: Exact Value | K20: =K13-L13-((K19-K18)*NORMSDIST(L12)*EXP(-K6*K9)) -> -16.220314 | AL20: =AL19+2 -> 30 | AM20: =MAX(0,(AL20^2)-120) -> 780
A21: =A20+1 -> 87 | B21: =(MAX(IF($B$1="C",1,-1)*(A21-$K$5),0)-IF($K$10="Y",$K$13*EXP($K$6*$K$9),0))*$K$4 -> 14000000 | C21: =(MAX(IF($C$1="C",1,-1)*(A21-$L$5),0)-IF($K$10="Y",$L$13*EXP($K$6*$K$9),0))*$L$4 -> -13999980 | D21: =(MAX(IF($D$1="C",1,-1)*(A21-$M$5),0)-IF($K$10="Y",$M$13*EXP($K$6*$K$9),0))*$M$4 -> -7 | E21: =(MAX(IF($E$1="C",1,-1)*(A21-$N$5),0)-IF($K$10="Y",$N$13*EXP($K$6*$K$9),0))*$N$4 -> 0 | F21: =SUM(B21:E21) -> 13 | G21: =IF(A21<=$K$18,0,IF(A21>$K$19,0,$K$19-A21)) -> 13 | H21: =F21-G21 -> 5.5879354e-09 | AL21: =AL20+2 -> 32 | AM21: =MAX(0,(AL21^2)-120) -> 904
A22: =A21+1 -> 88 | B22: =(MAX(IF($B$1="C",1,-1)*(A22-$K$5),0)-IF($K$10="Y",$K$13*EXP($K$6*$K$9),0))*$K$4 -> 16000000 | C22: =(MAX(IF($C$1="C",1,-1)*(A22-$L$5),0)-IF($K$10="Y",$L$13*EXP($K$6*$K$9),0))*$L$4 -> -15999980 | D22: =(MAX(IF($D$1="C",1,-1)*(A22-$M$5),0)-IF($K$10="Y",$M$13*EXP($K$6*$K$9),0))*$M$4 -> -8 | E22: =(MAX(IF($E$1="C",1,-1)*(A22-$N$5),0)-IF($K$10="Y",$N$13*EXP($K$6*$K$9),0))*$N$4 -> 0 | F22: =SUM(B22:E22) -> 12 | G22: =IF(A22<=$K$18,0,IF(A22>$K$19,0,$K$19-A22)) -> 12 | H22: =F22-G22 -> 5.5879354e-09 | AL22: =AL21+2 -> 34 | AM22: =MAX(0,(AL22^2)-120) -> 1036
A23: =A22+1 -> 89 | B23: =(MAX(IF($B$1="C",1,-1)*(A23-$K$5),0)-IF($K$10="Y",$K$13*EXP($K$6*$K$9),0))*$K$4 -> 18000000 | C23: =(MAX(IF($C$1="C",1,-1)*(A23-$L$5),0)-IF($K$10="Y",$L$13*EXP($K$6*$K$9),0))*$L$4 -> -17999980 | D23: =(MAX(IF($D$1="C",1,-1)*(A23-$M$5),0)-IF($K$10="Y",$M$13*EXP($K$6*$K$9),0))*$M$4 -> -9 | E23: =(MAX(IF($E$1="C",1,-1)*(A23-$N$5),0)-IF($K$10="Y",$N$13*EXP($K$6*$K$9),0))*$N$4 -> 0 | F23: =SUM(B23:E23) -> 11 | G23: =IF(A23<=$K$18,0,IF(A23>$K$19,0,$K$19-A23)) -> 11 | H23: =F23-G23 -> 7.4505806e-09 | AL23: =AL22+2 -> 36 | AM23: =MAX(0,(AL23^2)-120) -> 1176
A24: =A23+1 -> 90 | B24: =(MAX(IF($B$1="C",1,-1)*(A24-$K$5),0)-IF($K$10="Y",$K$13*EXP($K$6*$K$9),0))*$K$4 -> 20000000 | C24: =(MAX(IF($C$1="C",1,-1)*(A24-$L$5),0)-IF($K$10="Y",$L$13*EXP($K$6*$K$9),0))*$L$4 -> -19999980 | D24: =(MAX(IF($D$1="C",1,-1)*(A24-$M$5),0)-IF($K$10="Y",$M$13*EXP($K$6*$K$9),0))*$M$4 -> -10 | E24: =(MAX(IF($E$1="C",1,-1)*(A24-$N$5),0)-IF($K$10="Y",$N$13*EXP($K$6*$K$9),0))*$N$4 -> 0 | F24: =SUM(B24:E24) -> 10 | G24: =IF(A24<=$K$18,0,IF(A24>$K$19,0,$K$19-A24)) -> 10 | H24: =F24-G24 -> 7.4505806e-09 | AL24: =AL23+2 -> 38 | AM24: =MAX(0,(AL24^2)-120) -> 1324
A25: =A24+1 -> 91 | B25: =(MAX(IF($B$1="C",1,-1)*(A25-$K$5),0)-IF($K$10="Y",$K$13*EXP($K$6*$K$9),0))*$K$4 -> 22000000 | C25: =(MAX(IF($C$1="C",1,-1)*(A25-$L$5),0)-IF($K$10="Y",$L$13*EXP($K$6*$K$9),0))*$L$4 -> -21999980 | D25: =(MAX(IF($D$1="C",1,-1)*(A25-$M$5),0)-IF($K$10="Y",$M$13*EXP($K$6*$K$9),0))*$M$4 -> -11 | E25: =(MAX(IF($E$1="C",1,-1)*(A25-$N$5),0)-IF($K$10="Y",$N$13*EXP($K$6*$K$9),0))*$N$4 -> 0 | F25: =SUM(B25:E25) -> 9 | G25: =IF(A25<=$K$18,0,IF(A25>$K$19,0,$K$19-A25)) -> 9 | H25: =F25-G25 -> 7.4505806e-09 | AL25: =AL24+2 -> 40 | AM25: =MAX(0,(AL25^2)-120) -> 1480
A26: =A25+1 -> 92 | B26: =(MAX(IF($B$1="C",1,-1)*(A26-$K$5),0)-IF($K$10="Y",$K$13*EXP($K$6*$K$9),0))*$K$4 -> 24000000 | C26: =(MAX(IF($C$1="C",1,-1)*(A26-$L$5),0)-IF($K$10="Y",$L$13*EXP($K$6*$K$9),0))*$L$4 -> -23999980 | D26: =(MAX(IF($D$1="C",1,-1)*(A26-$M$5),0)-IF($K$10="Y",$M$13*EXP($K$6*$K$9),0))*$M$4 -> -12 | E26: =(MAX(IF($E$1="C",1,-1)*(A26-$N$5),0)-IF($K$10="Y",$N$13*EXP($K$6*$K$9),0))*$N$4 -> 0 | F26: =SUM(B26:E26) -> 8 | G26: =IF(A26<=$K$18,0,IF(A26>$K$19,0,$K$19-A26)) -> 8 | H26: =F26-G26 -> 7.4505806e-09 | AL26: =AL25+2 -> 42 | AM26: =MAX(0,(AL26^2)-120) -> 1644
A27: =A26+1 -> 93 | B27: =(MAX(IF($B$1="C",1,-1)*(A27-$K$5),0)-IF($K$10="Y",$K$13*EXP($K$6*$K$9),0))*$K$4 -> 26000000 | C27: =(MAX(IF($C$1="C",1,-1)*(A27-$L$5),0)-IF($K$10="Y",$L$13*EXP($K$6*$K$9),0))*$L$4 -> -25999980 | D27: =(MAX(IF($D$1="C",1,-1)*(A27-$M$5),0)-IF($K$10="Y",$M$13*EXP($K$6*$K$9),0))*$M$4 -> -13 | E27: =(MAX(IF($E$1="C",1,-1)*(A27-$N$5),0)-IF($K$10="Y",$N$13*EXP($K$6*$K$9),0))*$N$4 -> 0 | F27: =SUM(B27:E27) -> 7 | G27: =IF(A27<=$K$18,0,IF(A27>$K$19,0,$K$19-A27)) -> 7 | H27: =F27-G27 -> 7.4505806e-09 | AL27: =AL26+2 -> 44 | AM27: =MAX(0,(AL27^2)-120) -> 1816
A28: =A27+1 -> 94 | B28: =(MAX(IF($B$1="C",1,-1)*(A28-$K$5),0)-IF($K$10="Y",$K$13*EXP($K$6*$K$9),0))*$K$4 -> 28000000 | C28: =(MAX(IF($C$1="C",1,-1)*(A28-$L$5),0)-IF($K$10="Y",$L$13*EXP($K$6*$K$9),0))*$L$4 -> -27999980 | D28: =(MAX(IF($D$1="C",1,-1)*(A28-$M$5),0)-IF($K$10="Y",$M$13*EXP($K$6*$K$9),0))*$M$4 -> -14 | E28: =(MAX(IF($E$1="C",1,-1)*(A28-$N$5),0)-IF($K$10="Y",$N$13*EXP($K$6*$K$9),0))*$N$4 -> 0 | F28: =SUM(B28:E28) -> 6 | G28: =IF(A28<=$K$18,0,IF(A28>$K$19,0,$K$19-A28)) -> 6 | H28: =F28-G28 -> 7.4505806e-09 | AL28: =AL27+2 -> 46 | AM28: =MAX(0,(AL28^2)-120) -> 1996
A29: =A28+1 -> 95 | B29: =(MAX(IF($B$1="C",1,-1)*(A29-$K$5),0)-IF($K$10="Y",$K$13*EXP($K$6*$K$9),0))*$K$4 -> 30000000 | C29: =(MAX(IF($C$1="C",1,-1)*(A29-$L$5),0)-IF($K$10="Y",$L$13*EXP($K$6*$K$9),0))*$L$4 -> -29999980 | D29: =(MAX(IF($D$1="C",1,-1)*(A29-$M$5),0)-IF($K$10="Y",$M$13*EXP($K$6*$K$9),0))*$M$4 -> -15 | E29: =(MAX(IF($E$1="C",1,-1)*(A29-$N$5),0)-IF($K$10="Y",$N$13*EXP($K$6*$K$9),0))*$N$4 -> 0 | F29: =SUM(B29:E29) -> 5 | G29: =IF(A29<=$K$18,0,IF(A29>$K$19,0,$K$19-A29)) -> 5 | H29: =F29-G29 -> 7.4505806e-09 | AL29: =AL28+2 -> 48 | AM29: =MAX(0,(AL29^2)-120) -> 2184
A30: =A29+1 -> 96 | B30: =(MAX(IF($B$1="C",1,-1)*(A30-$K$5),0)-IF($K$10="Y",$K$13*EXP($K$6*$K$9),0))*$K$4 -> 32000000 | C30: =(MAX(IF($C$1="C",1,-1)*(A30-$L$5),0)-IF($K$10="Y",$L$13*EXP($K$6*$K$9),0))*$L$4 -> -31999980 | D30: =(MAX(IF($D$1="C",1,-1)*(A30-$M$5),0)-IF($K$10="Y",$M$13*EXP($K$6*$K$9),0))*$M$4 -> -16 | E30: =(MAX(IF($E$1="C",1,-1)*(A30-$N$5),0)-IF($K$10="Y",$N$13*EXP($K$6*$K$9),0))*$N$4 -> 0 | F30: =SUM(B30:E30) -> 4 | G30: =IF(A30<=$K$18,0,IF(A30>$K$19,0,$K$19-A30)) -> 4 | H30: =F30-G30 -> 7.4505806e-09 | AL30: =AL29+2 -> 50 | AM30: =MAX(0,(AL30^2)-120) -> 2380
A31: =A30+1 -> 97 | B31: =(MAX(IF($B$1="C",1,-1)*(A31-$K$5),0)-IF($K$10="Y",$K$13*EXP($K$6*$K$9),0))*$K$4 -> 34000000 | C31: =(MAX(IF($C$1="C",1,-1)*(A31-$L$5),0)-IF($K$10="Y",$L$13*EXP($K$6*$K$9),0))*$L$4 -> -33999980 | D31: =(MAX(IF($D$1="C",1,-1)*(A31-$M$5),0)-IF($K$10="Y",$M$13*EXP($K$6*$K$9),0))*$M$4 -> -17 | E31: =(MAX(IF($E$1="C",1,-1)*(A31-$N$5),0)-IF($K$10="Y",$N$13*EXP($K$6*$K$9),0))*$N$4 -> 0 | F31: =SUM(B31:E31) -> 3 | G31: =IF(A31<=$K$18,0,IF(A31>$K$19,0,$K$19-A31)) -> 3 | H31: =F31-G31 -> 7.4505806e-09 | AL31: =AL30+2 -> 52 | AM31: =MAX(0,(AL31^2)-120) -> 2584
A32: =A31+1 -> 98 | B32: =(MAX(IF($B$1="C",1,-1)*(A32-$K$5),0)-IF($K$10="Y",$K$13*EXP($K$6*$K$9),0))*$K$4 -> 36000000 | C32: =(MAX(IF($C$1="C",1,-1)*(A32-$L$5),0)-IF($K$10="Y",$L$13*EXP($K$6*$K$9),0))*$L$4 -> -35999980 | D32: =(MAX(IF($D$1="C",1,-1)*(A32-$M$5),0)-IF($K$10="Y",$M$13*EXP($K$6*$K$9),0))*$M$4 -> -18 | E32: =(MAX(IF($E$1="C",1,-1)*(A32-$N$5),0)-IF($K$10="Y",$N$13*EXP($K$6*$K$9),0))*$N$4 -> 0 | F32: =SUM(B32:E32) -> 2 | G32: =IF(A32<=$K$18,0,IF(A32>$K$19,0,$K$19-A32)) -> 2 | H32: =F32-G32 -> 7.4505806e-09 | AL32: =AL31+2 -> 54 | AM32: =MAX(0,(AL32^2)-120) -> 2796
... A104: =A103+1 -> 170 | B104: =(MAX(IF($B$1="C",1,-1)*(A104-$K$5),0)-IF($K$10="Y",$K$13*EXP($K$6*$K$9),0))*$K$4 -> 180000000 | C104: =(MAX(IF($C$1="C",1,-1)*(A104-$L$5),0)-IF($K$10="Y",$L$13*EXP($K$6*$K$9),0))*$L$4 -> -179999980 | D104: =(MAX(IF($D$1="C",1,-1)*(A104-$M$5),0)-IF($K$10="Y",$M$13*EXP($K$6*$K$9),0))*$M$4 -> -90 | E104: =(MAX(IF($E$1="C",1,-1)*(A104-$N$5),0)-IF($K$10="Y",$N$13*EXP($K$6*$K$9),0))*$N$4 -> 70 | F104: =SUM(B104:E104) -> 0 | G104: =IF(A104<=$K$18,0,IF(A104>$K$19,0,$K$19-A104)) -> 0 | H104: =F104-G104 -> 0 | AL104: =AL103+2 -> 198 | AM104: =MAX(0,(AL104^2)-120) -> 39084
AL105: =AL104+2 -> 200 | AM105: =MAX(0,(AL105^2)-120) -> 39880
AL106: =AL105+2 -> 202 | AM106: =MAX(0,(AL106^2)-120) -> 40684
AL107: =AL106+2 -> 204 | AM107: =MAX(0,(AL107^2)-120) -> 41496
AL108: =AL107+2 -> 206 | AM108: =MAX(0,(AL108^2)-120) -> 42316
AL109: =AL108+2 -> 208 | AM109: =MAX(0,(AL109^2)-120) -> 43144
AL110: =AL109+2 -> 210 | AM110: =MAX(0,(AL110^2)-120) -> 43980
AL111: =AL110+2 -> 212 | AM111: =MAX(0,(AL111^2)-120) -> 44824
AL112: =AL111+2 -> 214 | AM112: =MAX(0,(AL112^2)-120) -> 45676
AL113: =AL112+2 -> 216 | AM113: =MAX(0,(AL113^2)-120) -> 46536
AL114: =AL113+2 -> 218 | AM114: =MAX(0,(AL114^2)-120) -> 47404
AL115: =AL114+2 -> 220 | AM115: =MAX(0,(AL115^2)-120) -> 48280
AL116: =AL115+2 -> 222 | AM116: =MAX(0,(AL116^2)-120) -> 49164
... AL128: =AL127+2 -> 246 | AM128: =MAX(0,(AL128^2)-120) -> 60396

Sheet Question 2a_2
A1: Option type | B1: =K3 -> C | C1: =L3 -> C | D1: =M3 -> C | E1: =N3 -> C | F1: Net Effect | G1: Payoff To Replicate | H1: Slippage | I1: Replication Position | K1: Option 1 | L1: Option 2 | M1: Option 3 | N1: Option 4
I2: Inputs | J2: Current Stock Price ($) | K2: 110
A3: Stock price At Maturity | B3: Profit | J3: Option Type | K3: C | L3: =K3 -> C | M3: =L3 -> C | N3: =M3 -> C
A4: 70 | B4: =(MAX(IF($B$1="C",1,-1)*(A4-$K$5),0)-IF($K$10="Y",$K$13*EXP($K$6*$K$9),0))*$K$4 -> 0 | C4: =(MAX(IF($C$1="C",1,-1)*(A4-$L$5),0)-IF($K$10="Y",$L$13*EXP($K$6*$K$9),0))*$L$4 -> 0 | D4: =(MAX(IF($D$1="C",1,-1)*(A4-$M$5),0)-IF($K$10="Y",$M$13*EXP($K$6*$K$9),0))*$M$4 -> 0 | E4: =(MAX(IF($E$1="C",1,-1)*(A4-$N$5),0)-IF($K$10="Y",$N$13*EXP($K$6*$K$9),0))*$N$4 -> 0 | F4: =SUM(B4:E4) -> 0 | G4: =IF(A4<=$K$18,0,IF(A4>$K$19,0,A4-$K$18)) -> 0 | H4: =F4-G4 -> 0 | J4: Postion | K4: 1 | L4: -1 | M4: -200000 | N4: =-M4 -> 200000 | AL4: ST | AM4: payoff
A5: =A4+1 -> 71 | B5: =(MAX(IF($B$1="C",1,-1)*(A5-$K$5),0)-IF($K$10="Y",$K$13*EXP($K$6*$K$9),0))*$K$4 -> 0 | C5: =(MAX(IF($C$1="C",1,-1)*(A5-$L$5),0)-IF($K$10="Y",$L$13*EXP($K$6*$K$9),0))*$L$4 -> 0 | D5: =(MAX(IF($D$1="C",1,-1)*(A5-$M$5),0)-IF($K$10="Y",$M$13*EXP($K$6*$K$9),0))*$M$4 -> 0 | E5: =(MAX(IF($E$1="C",1,-1)*(A5-$N$5),0)-IF($K$10="Y",$N$13*EXP($K$6*$K$9),0))*$N$4 -> 0 | F5: =SUM(B5:E5) -> 0 | G5: =IF(A5<=$K$18,0,IF(A5>$K$19,0,A5-$K$18)) -> 0 | H5: =F5-G5 -> 0 | J5: Strike Price ($) | K5: 100 | L5: 120 | M5: 120 | N5: 120.0001 | AL5: 0 | AM5: =MAX(0,(AL5^2)-120) -> 0
A6: =A5+1 -> 72 | B6: =(MAX(IF($B$1="C",1,-1)*(A6-$K$5),0)-IF($K$10="Y",$K$13*EXP($K$6*$K$9),0))*$K$4 -> 0 | C6: =(MAX(IF($C$1="C",1,-1)*(A6-$L$5),0)-IF($K$10="Y",$L$13*EXP($K$6*$K$9),0))*$L$4 -> 0 | D6: =(MAX(IF($D$1="C",1,-1)*(A6-$M$5),0)-IF($K$10="Y",$M$13*EXP($K$6*$K$9),0))*$M$4 -> 0 | E6: =(MAX(IF($E$1="C",1,-1)*(A6-$N$5),0)-IF($K$10="Y",$N$13*EXP($K$6*$K$9),0))*$N$4 -> 0 | F6: =SUM(B6:E6) -> 0 | G6: =IF(A6<=$K$18,0,IF(A6>$K$19,0,A6-$K$18)) -> 0 | H6: =F6-G6 -> 0 | J6: Risk Free Rate (%) | K6: 0.04 | AL6: =AL5+2 -> 2 | AM6: =MAX(0,(AL6^2)-120) -> 0
A7: =A6+1 -> 73 | B7: =(MAX(IF($B$1="C",1,-1)*(A7-$K$5),0)-IF($K$10="Y",$K$13*EXP($K$6*$K$9),0))*$K$4 -> 0 | C7: =(MAX(IF($C$1="C",1,-1)*(A7-$L$5),0)-IF($K$10="Y",$L$13*EXP($K$6*$K$9),0))*$L$4 -> 0 | D7: =(MAX(IF($D$1="C",1,-1)*(A7-$M$5),0)-IF($K$10="Y",$M$13*EXP($K$6*$K$9),0))*$M$4 -> 0 | E7: =(MAX(IF($E$1="C",1,-1)*(A7-$N$5),0)-IF($K$10="Y",$N$13*EXP($K$6*$K$9),0))*$N$4 -> 0 | F7: =SUM(B7:E7) -> 0 | G7: =IF(A7<=$K$18,0,IF(A7>$K$19,0,A7-$K$18)) -> 0 | H7: =F7-G7 -> 0 | J7: Dividend Rate (%) | K7: 0.01 | AL7: =AL6+2 -> 4 | AM7: =MAX(0,(AL7^2)-120) -> 0
A8: =A7+1 -> 74 | B8: =(MAX(IF($B$1="C",1,-1)*(A8-$K$5),0)-IF($K$10="Y",$K$13*EXP($K$6*$K$9),0))*$K$4 -> 0 | C8: =(MAX(IF($C$1="C",1,-1)*(A8-$L$5),0)-IF($K$10="Y",$L$13*EXP($K$6*$K$9),0))*$L$4 -> 0 | D8: =(MAX(IF($D$1="C",1,-1)*(A8-$M$5),0)-IF($K$10="Y",$M$13*EXP($K$6*$K$9),0))*$M$4 -> 0 | E8: =(MAX(IF($E$1="C",1,-1)*(A8-$N$5),0)-IF($K$10="Y",$N$13*EXP($K$6*$K$9),0))*$N$4 -> 0 | F8: =SUM(B8:E8) -> 0 | G8: =IF(A8<=$K$18,0,IF(A8>$K$19,0,A8-$K$18)) -> 0 | H8: =F8-G8 -> 0 | J8: Volatility Rate (%) | K8: 0.3 | AL8: =AL7+2 -> 6 | AM8: =MAX(0,(AL8^2)-120) -> 0
A9: =A8+1 -> 75 | B9: =(MAX(IF($B$1="C",1,-1)*(A9-$K$5),0)-IF($K$10="Y",$K$13*EXP($K$6*$K$9),0))*$K$4 -> 0 | C9: =(MAX(IF($C$1="C",1,-1)*(A9-$L$5),0)-IF($K$10="Y",$L$13*EXP($K$6*$K$9),0))*$L$4 -> 0 | D9: =(MAX(IF($D$1="C",1,-1)*(A9-$M$5),0)-IF($K$10="Y",$M$13*EXP($K$6*$K$9),0))*$M$4 -> 0 | E9: =(MAX(IF($E$1="C",1,-1)*(A9-$N$5),0)-IF($K$10="Y",$N$13*EXP($K$6*$K$9),0))*$N$4 -> 0 | F9: =SUM(B9:E9) -> 0 | G9: =IF(A9<=$K$18,0,IF(A9>$K$19,0,A9-$K$18)) -> 0 | H9: =F9-G9 -> 0 | J9: Option Life (years) | K9: 1 | AL9: =AL8+2 -> 8 | AM9: =MAX(0,(AL9^2)-120) -> 0
A10: =A9+1 -> 76 | B10: =(MAX(IF($B$1="C",1,-1)*(A10-$K$5),0)-IF($K$10="Y",$K$13*EXP($K$6*$K$9),0))*$K$4 -> 0 | C10: =(MAX(IF($C$1="C",1,-1)*(A10-$L$5),0)-IF($K$10="Y",$L$13*EXP($K$6*$K$9),0))*$L$4 -> 0 | D10: =(MAX(IF($D$1="C",1,-1)*(A10-$M$5),0)-IF($K$10="Y",$M$13*EXP($K$6*$K$9),0))*$M$4 -> 0 | E10: =(MAX(IF($E$1="C",1,-1)*(A10-$N$5),0)-IF($K$10="Y",$N$13*EXP($K$6*$K$9),0))*$N$4 -> 0 | F10: =SUM(B10:E10) -> 0 | G10: =IF(A10<=$K$18,0,IF(A10>$K$19,0,A10-$K$18)) -> 0 | H10: =F10-G10 -> 0 | J10: Include Premium | K10: N | AL10: =AL9+2 -> 10 | AM10: =MAX(0,(AL10^2)-120) -> 0
A11: =A10+1 -> 77 | B11: =(MAX(IF($B$1="C",1,-1)*(A11-$K$5),0)-IF($K$10="Y",$K$13*EXP($K$6*$K$9),0))*$K$4 -> 0 | C11: =(MAX(IF($C$1="C",1,-1)*(A11-$L$5),0)-IF($K$10="Y",$L$13*EXP($K$6*$K$9),0))*$L$4 -> 0 | D11: =(MAX(IF($D$1="C",1,-1)*(A11-$M$5),0)-IF($K$10="Y",$M$13*EXP($K$6*$K$9),0))*$M$4 -> 0 | E11: =(MAX(IF($E$1="C",1,-1)*(A11-$N$5),0)-IF($K$10="Y",$N$13*EXP($K$6*$K$9),0))*$N$4 -> 0 | F11: =SUM(B11:E11) -> 0 | G11: =IF(A11<=$K$18,0,IF(A11>$K$19,0,A11-$K$18)) -> 0 | H11: =F11-G11 -> 0 | I11: Computations | J11: d1 | K11: =(LN($K$2/K5)+(($K$6-$K$7+(0.5*$K$8*$K$8))*$K$9))/($K$8*SQRT($K$9)) -> 0.5677006 | L11: =(LN($K$2/L5)+(($K$6-$K$7+(0.5*$K$8*$K$8))*$K$9))/($K$8*SQRT($K$9)) -> -0.040037923 | M11: =(LN($K$2/M5)+(($K$6-$K$7+(0.5*$K$8*$K$8))*$K$9))/($K$8*SQRT($K$9)) -> -0.040037923 | N11: =(LN($K$2/N5)+(($K$6-$K$7+(0.5*$K$8*$K$8))*$K$9))/($K$8*SQRT($K$9)) -> -0.040040701 | AL11: =AL10+2 -> 12 | AM11: =MAX(0,(AL11^2)-120) -> 24
A12: =A11+1 -> 78 | B12: =(MAX(IF($B$1="C",1,-1)*(A12-$K$5),0)-IF($K$10="Y",$K$13*EXP($K$6*$K$9),0))*$K$4 -> 0 | C12: =(MAX(IF($C$1="C",1,-1)*(A12-$L$5),0)-IF($K$10="Y",$L$13*EXP($K$6*$K$9),0))*$L$4 -> 0 | D12: =(MAX(IF($D$1="C",1,-1)*(A12-$M$5),0)-IF($K$10="Y",$M$13*EXP($K$6*$K$9),0))*$M$4 -> 0 | E12: =(MAX(IF($E$1="C",1,-1)*(A12-$N$5),0)-IF($K$10="Y",$N$13*EXP($K$6*$K$9),0))*$N$4 -> 0 | F12: =SUM(B12:E12) -> 0 | G12: =IF(A12<=$K$18,0,IF(A12>$K$19,0,A12-$K$18)) -> 0 | H12: =F12-G12 -> 0 | J12: d2 | K12: =K11-($K$8*SQRT($K$9)) -> 0.2677006 | L12: =L11-($K$8*SQRT($K$9)) -> -0.34003792 | M12: =M11-($K$8*SQRT($K$9)) -> -0.34003792 | N12: =N11-($K$8*SQRT($K$9)) -> -0.3400407 | AL12: =AL11+2 -> 14 | AM12: =MAX(0,(AL12^2)-120) -> 76
A13: =A12+1 -> 79 | B13: =(MAX(IF($B$1="C",1,-1)*(A13-$K$5),0)-IF($K$10="Y",$K$13*EXP($K$6*$K$9),0))*$K$4 -> 0 | C13: =(MAX(IF($C$1="C",1,-1)*(A13-$L$5),0)-IF($K$10="Y",$L$13*EXP($K$6*$K$9),0))*$L$4 -> 0 | D13: =(MAX(IF($D$1="C",1,-1)*(A13-$M$5),0)-IF($K$10="Y",$M$13*EXP($K$6*$K$9),0))*$M$4 -> 0 | E13: =(MAX(IF($E$1="C",1,-1)*(A13-$N$5),0)-IF($K$10="Y",$N$13*EXP($K$6*$K$9),0))*$N$4 -> 0 | F13: =SUM(B13:E13) -> 0 | G13: =IF(A13<=$K$18,0,IF(A13>$K$19,0,A13-$K$18)) -> 0 | H13: =F13-G13 -> 0 | J13: Premium | K13: =IF(K3="C",($K$2*EXP(-$K$7*$K$9)*NORMSDIST(K11))-(K5*EXP(-$K$6*$K$9)*NORMSDIST(K12)),(-$K$2*EXP(-$K$7*$K$9)*NORMSDIST(-K11))-(-K5*EXP(-$K$6*$K$9)*NORMSDIST(-K12))) -> 19.675271 | L13: =IF(L3="C",($K$2*EXP(-$K$7*$K$9)*NORMSDIST(L11))-(L5*EXP(-$K$6*$K$9)*NORMSDIST(L12)),(-$K$2*EXP(-$K$7*$K$9)*NORMSDIST(-L11))-(-L5*EXP(-$K$6*$K$9)*NORMSDIST(-L12))) -> 10.410428 | M13: =IF(M3="C",($K$2*EXP(-$K$7*$K$9)*NORMSDIST(M11))-(M5*EXP(-$K$6*$K$9)*NORMSDIST(M12)),(-$K$2*EXP(-$K$7*$K$9)*NORMSDIST(-M11))-(-M5*EXP(-$K$6*$K$9)*NORMSDIST(-M12))) -> 10.410428 | N13: =IF(N3="C",($K$2*EXP(-$K$7*$K$9)*NORMSDIST(N11))-(N5*EXP(-$K$6*$K$9)*NORMSDIST(N12)),(-$K$2*EXP(-$K$7*$K$9)*NORMSDIST(-N11))-(-N5*EXP(-$K$6*$K$9)*NORMSDIST(-N12))) -> 10.410393 | AL13: =AL12+2 -> 16 | AM13: =MAX(0,(AL13^2)-120) -> 136
A14: =A13+1 -> 80 | B14: =(MAX(IF($B$1="C",1,-1)*(A14-$K$5),0)-IF($K$10="Y",$K$13*EXP($K$6*$K$9),0))*$K$4 -> 0 | C14: =(MAX(IF($C$1="C",1,-1)*(A14-$L$5),0)-IF($K$10="Y",$L$13*EXP($K$6*$K$9),0))*$L$4 -> 0 | D14: =(MAX(IF($D$1="C",1,-1)*(A14-$M$5),0)-IF($K$10="Y",$M$13*EXP($K$6*$K$9),0))*$M$4 -> 0 | E14: =(MAX(IF($E$1="C",1,-1)*(A14-$N$5),0)-IF($K$10="Y",$N$13*EXP($K$6*$K$9),0))*$N$4 -> 0 | F14: =SUM(B14:E14) -> 0 | G14: =IF(A14<=$K$18,0,IF(A14>$K$19,0,A14-$K$18)) -> 0 | H14: =F14-G14 -> 0 | J14: Total Premium | K14: =SUMPRODUCT(K4:N4,K13:N13) -> 2.2143111 | AL14: =AL13+2 -> 18 | AM14: =MAX(0,(AL14^2)-120) -> 204
A15: =A14+1 -> 81 | B15: =(MAX(IF($B$1="C",1,-1)*(A15-$K$5),0)-IF($K$10="Y",$K$13*EXP($K$6*$K$9),0))*$K$4 -> 0 | C15: =(MAX(IF($C$1="C",1,-1)*(A15-$L$5),0)-IF($K$10="Y",$L$13*EXP($K$6*$K$9),0))*$L$4 -> 0 | D15: =(MAX(IF($D$1="C",1,-1)*(A15-$M$5),0)-IF($K$10="Y",$M$13*EXP($K$6*$K$9),0))*$M$4 -> 0 | E15: =(MAX(IF($E$1="C",1,-1)*(A15-$N$5),0)-IF($K$10="Y",$N$13*EXP($K$6*$K$9),0))*$N$4 -> 0 | F15: =SUM(B15:E15) -> 0 | G15: =IF(A15<=$K$18,0,IF(A15>$K$19,0,A15-$K$18)) -> 0 | H15: =F15-G15 -> 0 | AL15: =AL14+2 -> 20 | AM15: =MAX(0,(AL15^2)-120) -> 280
A16: =A15+1 -> 82 | B16: =(MAX(IF($B$1="C",1,-1)*(A16-$K$5),0)-IF($K$10="Y",$K$13*EXP($K$6*$K$9),0))*$K$4 -> 0 | C16: =(MAX(IF($C$1="C",1,-1)*(A16-$L$5),0)-IF($K$10="Y",$L$13*EXP($K$6*$K$9),0))*$L$4 -> 0 | D16: =(MAX(IF($D$1="C",1,-1)*(A16-$M$5),0)-IF($K$10="Y",$M$13*EXP($K$6*$K$9),0))*$M$4 -> 0 | E16: =(MAX(IF($E$1="C",1,-1)*(A16-$N$5),0)-IF($K$10="Y",$N$13*EXP($K$6*$K$9),0))*$N$4 -> 0 | F16: =SUM(B16:E16) -> 0 | G16: =IF(A16<=$K$18,0,IF(A16>$K$19,0,A16-$K$18)) -> 0 | H16: =F16-G16 -> 0 | AL16: =AL15+2 -> 22 | AM16: =MAX(0,(AL16^2)-120) -> 364
A17: =A16+1 -> 83 | B17: =(MAX(IF($B$1="C",1,-1)*(A17-$K$5),0)-IF($K$10="Y",$K$13*EXP($K$6*$K$9),0))*$K$4 -> 0 | C17: =(MAX(IF($C$1="C",1,-1)*(A17-$L$5),0)-IF($K$10="Y",$L$13*EXP($K$6*$K$9),0))*$L$4 -> 0 | D17: =(MAX(IF($D$1="C",1,-1)*(A17-$M$5),0)-IF($K$10="Y",$M$13*EXP($K$6*$K$9),0))*$M$4 -> 0 | E17: =(MAX(IF($E$1="C",1,-1)*(A17-$N$5),0)-IF($K$10="Y",$N$13*EXP($K$6*$K$9),0))*$N$4 -> 0 | F17: =SUM(B17:E17) -> 0 | G17: =IF(A17<=$K$18,0,IF(A17>$K$19,0,A17-$K$18)) -> 0 | H17: =F17-G17 -> 0 | J17: Structure To Price | AL17: =AL16+2 -> 24 | AM17: =MAX(0,(AL17^2)-120) -> 456
A18: =A17+1 -> 84 | B18: =(MAX(IF($B$1="C",1,-1)*(A18-$K$5),0)-IF($K$10="Y",$K$13*EXP($K$6*$K$9),0))*$K$4 -> 0 | C18: =(MAX(IF($C$1="C",1,-1)*(A18-$L$5),0)-IF($K$10="Y",$L$13*EXP($K$6*$K$9),0))*$L$4 -> 0 | D18: =(MAX(IF($D$1="C",1,-1)*(A18-$M$5),0)-IF($K$10="Y",$M$13*EXP($K$6*$K$9),0))*$M$4 -> 0 | E18: =(MAX(IF($E$1="C",1,-1)*(A18-$N$5),0)-IF($K$10="Y",$N$13*EXP($K$6*$K$9),0))*$N$4 -> 0 | F18: =SUM(B18:E18) -> 0 | G18: =IF(A18<=$K$18,0,IF(A18>$K$19,0,A18-$K$18)) -> 0 | H18: =F18-G18 -> 0 | J18: Lower Strike | K18: 100 | AL18: =AL17+2 -> 26 | AM18: =MAX(0,(AL18^2)-120) -> 556
A19: =A18+1 -> 85 | B19: =(MAX(IF($B$1="C",1,-1)*(A19-$K$5),0)-IF($K$10="Y",$K$13*EXP($K$6*$K$9),0))*$K$4 -> 0 | C19: =(MAX(IF($C$1="C",1,-1)*(A19-$L$5),0)-IF($K$10="Y",$L$13*EXP($K$6*$K$9),0))*$L$4 -> 0 | D19: =(MAX(IF($D$1="C",1,-1)*(A19-$M$5),0)-IF($K$10="Y",$M$13*EXP($K$6*$K$9),0))*$M$4 -> 0 | E19: =(MAX(IF($E$1="C",1,-1)*(A19-$N$5),0)-IF($K$10="Y",$N$13*EXP($K$6*$K$9),0))*$N$4 -> 0 | F19: =SUM(B19:E19) -> 0 | G19: =IF(A19<=$K$18,0,IF(A19>$K$19,0,A19-$K$18)) -> 0 | H19: =F19-G19 -> 0 | J19: Higher Strike | K19: 120 | AL19: =AL18+2 -> 28 | AM19: =MAX(0,(AL19^2)-120) -> 664
A20: =A19+1 -> 86 | B20: =(MAX(IF($B$1="C",1,-1)*(A20-$K$5),0)-IF($K$10="Y",$K$13*EXP($K$6*$K$9),0))*$K$4 -> 0 | C20: =(MAX(IF($C$1="C",1,-1)*(A20-$L$5),0)-IF($K$10="Y",$L$13*EXP($K$6*$K$9),0))*$L$4 -> 0 | D20: =(MAX(IF($D$1="C",1,-1)*(A20-$M$5),0)-IF($K$10="Y",$M$13*EXP($K$6*$K$9),0))*$M$4 -> 0 | E20: =(MAX(IF($E$1="C",1,-1)*(A20-$N$5),0)-IF($K$10="Y",$N$13*EXP($K$6*$K$9),0))*$N$4 -> 0 | F20: =SUM(B20:E20) -> 0 | G20: =IF(A20<=$K$18,0,IF(A20>$K$19,0,A20-$K$18)) -> 0 | H20: =F20-G20 -> 0 | J20: Exact Value | K20: =-K13+L13-((K19-K18)*NORMSDIST(-K12)*EXP(-K6*K9)) -> -16.844797 | AL20: =AL19+2 -> 30 | AM20: =MAX(0,(AL20^2)-120) -> 780
A21: =A20+1 -> 87 | B21: =(MAX(IF($B$1="C",1,-1)*(A21-$K$5),0)-IF($K$10="Y",$K$13*EXP($K$6*$K$9),0))*$K$4 -> 0 | C21: =(MAX(IF($C$1="C",1,-1)*(A21-$L$5),0)-IF($K$10="Y",$L$13*EXP($K$6*$K$9),0))*$L$4 -> 0 | D21: =(MAX(IF($D$1="C",1,-1)*(A21-$M$5),0)-IF($K$10="Y",$M$13*EXP($K$6*$K$9),0))*$M$4 -> 0 | E21: =(MAX(IF($E$1="C",1,-1)*(A21-$N$5),0)-IF($K$10="Y",$N$13*EXP($K$6*$K$9),0))*$N$4 -> 0 | F21: =SUM(B21:E21) -> 0 | G21: =IF(A21<=$K$18,0,IF(A21>$K$19,0,A21-$K$18)) -> 0 | H21: =F21-G21 -> 0 | AL21: =AL20+2 -> 32 | AM21: =MAX(0,(AL21^2)-120) -> 904
A22: =A21+1 -> 88 | B22: =(MAX(IF($B$1="C",1,-1)*(A22-$K$5),0)-IF($K$10="Y",$K$13*EXP($K$6*$K$9),0))*$K$4 -> 0 | C22: =(MAX(IF($C$1="C",1,-1)*(A22-$L$5),0)-IF($K$10="Y",$L$13*EXP($K$6*$K$9),0))*$L$4 -> 0 | D22: =(MAX(IF($D$1="C",1,-1)*(A22-$M$5),0)-IF($K$10="Y",$M$13*EXP($K$6*$K$9),0))*$M$4 -> 0 | E22: =(MAX(IF($E$1="C",1,-1)*(A22-$N$5),0)-IF($K$10="Y",$N$13*EXP($K$6*$K$9),0))*$N$4 -> 0 | F22: =SUM(B22:E22) -> 0 | G22: =IF(A22<=$K$18,0,IF(A22>$K$19,0,A22-$K$18)) -> 0 | H22: =F22-G22 -> 0 | AL22: =AL21+2 -> 34 | AM22: =MAX(0,(AL22^2)-120) -> 1036
A23: =A22+1 -> 89 | B23: =(MAX(IF($B$1="C",1,-1)*(A23-$K$5),0)-IF($K$10="Y",$K$13*EXP($K$6*$K$9),0))*$K$4 -> 0 | C23: =(MAX(IF($C$1="C",1,-1)*(A23-$L$5),0)-IF($K$10="Y",$L$13*EXP($K$6*$K$9),0))*$L$4 -> 0 | D23: =(MAX(IF($D$1="C",1,-1)*(A23-$M$5),0)-IF($K$10="Y",$M$13*EXP($K$6*$K$9),0))*$M$4 -> 0 | E23: =(MAX(IF($E$1="C",1,-1)*(A23-$N$5),0)-IF($K$10="Y",$N$13*EXP($K$6*$K$9),0))*$N$4 -> 0 | F23: =SUM(B23:E23) -> 0 | G23: =IF(A23<=$K$18,0,IF(A23>$K$19,0,A23-$K$18)) -> 0 | H23: =F23-G23 -> 0 | AL23: =AL22+2 -> 36 | AM23: =MAX(0,(AL23^2)-120) -> 1176
A24: =A23+1 -> 90 | B24: =(MAX(IF($B$1="C",1,-1)*(A24-$K$5),0)-IF($K$10="Y",$K$13*EXP($K$6*$K$9),0))*$K$4 -> 0 | C24: =(MAX(IF($C$1="C",1,-1)*(A24-$L$5),0)-IF($K$10="Y",$L$13*EXP($K$6*$K$9),0))*$L$4 -> 0 | D24: =(MAX(IF($D$1="C",1,-1)*(A24-$M$5),0)-IF($K$10="Y",$M$13*EXP($K$6*$K$9),0))*$M$4 -> 0 | E24: =(MAX(IF($E$1="C",1,-1)*(A24-$N$5),0)-IF($K$10="Y",$N$13*EXP($K$6*$K$9),0))*$N$4 -> 0 | F24: =SUM(B24:E24) -> 0 | G24: =IF(A24<=$K$18,0,IF(A24>$K$19,0,A24-$K$18)) -> 0 | H24: =F24-G24 -> 0 | AL24: =AL23+2 -> 38 | AM24: =MAX(0,(AL24^2)-120) -> 1324
A25: =A24+1 -> 91 | B25: =(MAX(IF($B$1="C",1,-1)*(A25-$K$5),0)-IF($K$10="Y",$K$13*EXP($K$6*$K$9),0))*$K$4 -> 0 | C25: =(MAX(IF($C$1="C",1,-1)*(A25-$L$5),0)-IF($K$10="Y",$L$13*EXP($K$6*$K$9),0))*$L$4 -> 0 | D25: =(MAX(IF($D$1="C",1,-1)*(A25-$M$5),0)-IF($K$10="Y",$M$13*EXP($K$6*$K$9),0))*$M$4 -> 0 | E25: =(MAX(IF($E$1="C",1,-1)*(A25-$N$5),0)-IF($K$10="Y",$N$13*EXP($K$6*$K$9),0))*$N$4 -> 0 | F25: =SUM(B25:E25) -> 0 | G25: =IF(A25<=$K$18,0,IF(A25>$K$19,0,A25-$K$18)) -> 0 | H25: =F25-G25 -> 0 | AL25: =AL24+2 -> 40 | AM25: =MAX(0,(AL25^2)-120) -> 1480
A26: =A25+1 -> 92 | B26: =(MAX(IF($B$1="C",1,-1)*(A26-$K$5),0)-IF($K$10="Y",$K$13*EXP($K$6*$K$9),0))*$K$4 -> 0 | C26: =(MAX(IF($C$1="C",1,-1)*(A26-$L$5),0)-IF($K$10="Y",$L$13*EXP($K$6*$K$9),0))*$L$4 -> 0 | D26: =(MAX(IF($D$1="C",1,-1)*(A26-$M$5),0)-IF($K$10="Y",$M$13*EXP($K$6*$K$9),0))*$M$4 -> 0 | E26: =(MAX(IF($E$1="C",1,-1)*(A26-$N$5),0)-IF($K$10="Y",$N$13*EXP($K$6*$K$9),0))*$N$4 -> 0 | F26: =SUM(B26:E26) -> 0 | G26: =IF(A26<=$K$18,0,IF(A26>$K$19,0,A26-$K$18)) -> 0 | H26: =F26-G26 -> 0 | AL26: =AL25+2 -> 42 | AM26: =MAX(0,(AL26^2)-120) -> 1644
A27: =A26+1 -> 93 | B27: =(MAX(IF($B$1="C",1,-1)*(A27-$K$5),0)-IF($K$10="Y",$K$13*EXP($K$6*$K$9),0))*$K$4 -> 0 | C27: =(MAX(IF($C$1="C",1,-1)*(A27-$L$5),0)-IF($K$10="Y",$L$13*EXP($K$6*$K$9),0))*$L$4 -> 0 | D27: =(MAX(IF($D$1="C",1,-1)*(A27-$M$5),0)-IF($K$10="Y",$M$13*EXP($K$6*$K$9),0))*$M$4 -> 0 | E27: =(MAX(IF($E$1="C",1,-1)*(A27-$N$5),0)-IF($K$10="Y",$N$13*EXP($K$6*$K$9),0))*$N$4 -> 0 | F27: =SUM(B27:E27) -> 0 | G27: =IF(A27<=$K$18,0,IF(A27>$K$19,0,A27-$K$18)) -> 0 | H27: =F27-G27 -> 0 | AL27: =AL26+2 -> 44 | AM27: =MAX(0,(AL27^2)-120) -> 1816
A28: =A27+1 -> 94 | B28: =(MAX(IF($B$1="C",1,-1)*(A28-$K$5),0)-IF($K$10="Y",$K$13*EXP($K$6*$K$9),0))*$K$4 -> 0 | C28: =(MAX(IF($C$1="C",1,-1)*(A28-$L$5),0)-IF($K$10="Y",$L$13*EXP($K$6*$K$9),0))*$L$4 -> 0 | D28: =(MAX(IF($D$1="C",1,-1)*(A28-$M$5),0)-IF($K$10="Y",$M$13*EXP($K$6*$K$9),0))*$M$4 -> 0 | E28: =(MAX(IF($E$1="C",1,-1)*(A28-$N$5),0)-IF($K$10="Y",$N$13*EXP($K$6*$K$9),0))*$N$4 -> 0 | F28: =SUM(B28:E28) -> 0 | G28: =IF(A28<=$K$18,0,IF(A28>$K$19,0,A28-$K$18)) -> 0 | H28: =F28-G28 -> 0 | AL28: =AL27+2 -> 46 | AM28: =MAX(0,(AL28^2)-120) -> 1996
A29: =A28+1 -> 95 | B29: =(MAX(IF($B$1="C",1,-1)*(A29-$K$5),0)-IF($K$10="Y",$K$13*EXP($K$6*$K$9),0))*$K$4 -> 0 | C29: =(MAX(IF($C$1="C",1,-1)*(A29-$L$5),0)-IF($K$10="Y",$L$13*EXP($K$6*$K$9),0))*$L$4 -> 0 | D29: =(MAX(IF($D$1="C",1,-1)*(A29-$M$5),0)-IF($K$10="Y",$M$13*EXP($K$6*$K$9),0))*$M$4 -> 0 | E29: =(MAX(IF($E$1="C",1,-1)*(A29-$N$5),0)-IF($K$10="Y",$N$13*EXP($K$6*$K$9),0))*$N$4 -> 0 | F29: =SUM(B29:E29) -> 0 | G29: =IF(A29<=$K$18,0,IF(A29>$K$19,0,A29-$K$18)) -> 0 | H29: =F29-G29 -> 0 | AL29: =AL28+2 -> 48 | AM29: =MAX(0,(AL29^2)-120) -> 2184
A30: =A29+1 -> 96 | B30: =(MAX(IF($B$1="C",1,-1)*(A30-$K$5),0)-IF($K$10="Y",$K$13*EXP($K$6*$K$9),0))*$K$4 -> 0 | C30: =(MAX(IF($C$1="C",1,-1)*(A30-$L$5),0)-IF($K$10="Y",$L$13*EXP($K$6*$K$9),0))*$L$4 -> 0 | D30: =(MAX(IF($D$1="C",1,-1)*(A30-$M$5),0)-IF($K$10="Y",$M$13*EXP($K$6*$K$9),0))*$M$4 -> 0 | E30: =(MAX(IF($E$1="C",1,-1)*(A30-$N$5),0)-IF($K$10="Y",$N$13*EXP($K$6*$K$9),0))*$N$4 -> 0 | F30: =SUM(B30:E30) -> 0 | G30: =IF(A30<=$K$18,0,IF(A30>$K$19,0,A30-$K$18)) -> 0 | H30: =F30-G30 -> 0 | AL30: =AL29+2 -> 50 | AM30: =MAX(0,(AL30^2)-120) -> 2380
A31: =A30+1 -> 97 | B31: =(MAX(IF($B$1="C",1,-1)*(A31-$K$5),0)-IF($K$10="Y",$K$13*EXP($K$6*$K$9),0))*$K$4 -> 0 | C31: =(MAX(IF($C$1="C",1,-1)*(A31-$L$5),0)-IF($K$10="Y",$L$13*EXP($K$6*$K$9),0))*$L$4 -> 0 | D31: =(MAX(IF($D$1="C",1,-1)*(A31-$M$5),0)-IF($K$10="Y",$M$13*EXP($K$6*$K$9),0))*$M$4 -> 0 | E31: =(MAX(IF($E$1="C",1,-1)*(A31-$N$5),0)-IF($K$10="Y",$N$13*EXP($K$6*$K$9),0))*$N$4 -> 0 | F31: =SUM(B31:E31) -> 0 | G31: =IF(A31<=$K$18,0,IF(A31>$K$19,0,A31-$K$18)) -> 0 | H31: =F31-G31 -> 0 | AL31: =AL30+2 -> 52 | AM31: =MAX(0,(AL31^2)-120) -> 2584
A32: =A31+1 -> 98 | B32: =(MAX(IF($B$1="C",1,-1)*(A32-$K$5),0)-IF($K$10="Y",$K$13*EXP($K$6*$K$9),0))*$K$4 -> 0 | C32: =(MAX(IF($C$1="C",1,-1)*(A32-$L$5),0)-IF($K$10="Y",$L$13*EXP($K$6*$K$9),0))*$L$4 -> 0 | D32: =(MAX(IF($D$1="C",1,-1)*(A32-$M$5),0)-IF($K$10="Y",$M$13*EXP($K$6*$K$9),0))*$M$4 -> 0 | E32: =(MAX(IF($E$1="C",1,-1)*(A32-$N$5),0)-IF($K$10="Y",$N$13*EXP($K$6*$K$9),0))*$N$4 -> 0 | F32: =SUM(B32:E32) -> 0 | G32: =IF(A32<=$K$18,0,IF(A32>$K$19,0,A32-$K$18)) -> 0 | H32: =F32-G32 -> 0 | AL32: =AL31+2 -> 54 | AM32: =MAX(0,(AL32^2)-120) -> 2796
... A104: =A103+1 -> 170 | B104: =(MAX(IF($B$1="C",1,-1)*(A104-$K$5),0)-IF($K$10="Y",$K$13*EXP($K$6*$K$9),0))*$K$4 -> 70 | C104: =(MAX(IF($C$1="C",1,-1)*(A104-$L$5),0)-IF($K$10="Y",$L$13*EXP($K$6*$K$9),0))*$L$4 -> -50 | D104: =(MAX(IF($D$1="C",1,-1)*(A104-$M$5),0)-IF($K$10="Y",$M$13*EXP($K$6*$K$9),0))*$M$4 -> -10000000 | E104: =(MAX(IF($E$1="C",1,-1)*(A104-$N$5),0)-IF($K$10="Y",$N$13*EXP($K$6*$K$9),0))*$N$4 -> 9999980 | F104: =SUM(B104:E104) -> 0 | G104: =IF(A104<=$K$18,0,IF(A104>$K$19,0,A104-$K$18)) -> 0 | H104: =F104-G104 -> 0 | AL104: =AL103+2 -> 198 | AM104: =MAX(0,(AL104^2)-120) -> 39084
AL105: =AL104+2 -> 200 | AM105: =MAX(0,(AL105^2)-120) -> 39880
AL106: =AL105+2 -> 202 | AM106: =MAX(0,(AL106^2)-120) -> 40684
AL107: =AL106+2 -> 204 | AM107: =MAX(0,(AL107^2)-120) -> 41496
AL108: =AL107+2 -> 206 | AM108: =MAX(0,(AL108^2)-120) -> 42316
AL109: =AL108+2 -> 208 | AM109: =MAX(0,(AL109^2)-120) -> 43144
AL110: =AL109+2 -> 210 | AM110: =MAX(0,(AL110^2)-120) -> 43980
AL111: =AL110+2 -> 212 | AM111: =MAX(0,(AL111^2)-120) -> 44824
AL112: =AL111+2 -> 214 | AM112: =MAX(0,(AL112^2)-120) -> 45676
AL113: =AL112+2 -> 216 | AM113: =MAX(0,(AL113^2)-120) -> 46536
AL114: =AL113+2 -> 218 | AM114: =MAX(0,(AL114^2)-120) -> 47404
AL115: =AL114+2 -> 220 | AM115: =MAX(0,(AL115^2)-120) -> 48280
AL116: =AL115+2 -> 222 | AM116: =MAX(0,(AL116^2)-120) -> 49164
... AL128: =AL127+2 -> 246 | AM128: =MAX(0,(AL128^2)-120) -> 60396

Sheet Question 2a_3
A1: Option type | B1: Structure 1 | C1: Structure 2 | D1: Net Effect | E1: Payoff To Replicate | F1: Slippage | G1: Replication Position | I1: Option 1 | J1: Option 2 | K1: Option 3 | L1: Option 4
G2: Inputs | H2: Current Stock Price ($) | I2: 110
A3: Stock price At Maturity | B3: Profit | H3: Option Type | I3: P | J3: =I3 -> P | K3: C | L3: C
A4: 70 | B4: ='Question 2a_1'!F4 -> 0 | C4: ='Question 2a_2'!F4 -> 0 | D4: =SUM(B4:C4) -> 0 | E4: =IF(A4<=$I$18,0,IF(A4<=$I$19,$I$19-A4,IF(A4<=$I$20,A4-$I$19,0))) -> 0 | F4: =D4-E4 -> 0 | H4: Postion | I4: 0 | J4: 0 | K4: 0 | L4: =-K4 -> 0 | AJ4: ST | AK4: payoff
A5: =A4+1 -> 71 | B5: ='Question 2a_1'!F5 -> 0 | C5: ='Question 2a_2'!F5 -> 0 | D5: =SUM(B5:C5) -> 0 | E5: =IF(A5<=$I$18,0,IF(A5<=$I$19,$I$19-A5,IF(A5<=$I$20,A5-$I$19,0))) -> 0 | F5: =D5-E5 -> 0 | H5: Strike Price ($) | I5: 80 | J5: 100 | K5: 100 | L5: 120 | AJ5: 0 | AK5: =MAX(0,(AJ5^2)-120) -> 0
A6: =A5+1 -> 72 | B6: ='Question 2a_1'!F6 -> 0 | C6: ='Question 2a_2'!F6 -> 0 | D6: =SUM(B6:C6) -> 0 | E6: =IF(A6<=$I$18,0,IF(A6<=$I$19,$I$19-A6,IF(A6<=$I$20,A6-$I$19,0))) -> 0 | F6: =D6-E6 -> 0 | H6: Risk Free Rate (%) | I6: 0.04 | AJ6: =AJ5+2 -> 2 | AK6: =MAX(0,(AJ6^2)-120) -> 0
A7: =A6+1 -> 73 | B7: ='Question 2a_1'!F7 -> 0 | C7: ='Question 2a_2'!F7 -> 0 | D7: =SUM(B7:C7) -> 0 | E7: =IF(A7<=$I$18,0,IF(A7<=$I$19,$I$19-A7,IF(A7<=$I$20,A7-$I$19,0))) -> 0 | F7: =D7-E7 -> 0 | H7: Dividend Rate (%) | I7: 0.01 | AJ7: =AJ6+2 -> 4 | AK7: =MAX(0,(AJ7^2)-120) -> 0
A8: =A7+1 -> 74 | B8: ='Question 2a_1'!F8 -> 0 | C8: ='Question 2a_2'!F8 -> 0 | D8: =SUM(B8:C8) -> 0 | E8: =IF(A8<=$I$18,0,IF(A8<=$I$19,$I$19-A8,IF(A8<=$I$20,A8-$I$19,0))) -> 0 | F8: =D8-E8 -> 0 | H8: Volatility Rate (%) | I8: 0.3 | AJ8: =AJ7+2 -> 6 | AK8: =MAX(0,(AJ8^2)-120) -> 0
A9: =A8+1 -> 75 | B9: ='Question 2a_1'!F9 -> 0 | C9: ='Question 2a_2'!F9 -> 0 | D9: =SUM(B9:C9) -> 0 | E9: =IF(A9<=$I$18,0,IF(A9<=$I$19,$I$19-A9,IF(A9<=$I$20,A9-$I$19,0))) -> 0 | F9: =D9-E9 -> 0 | H9: Option Life (years) | I9: 1 | AJ9: =AJ8+2 -> 8 | AK9: =MAX(0,(AJ9^2)-120) -> 0
A10: =A9+1 -> 76 | B10: ='Question 2a_1'!F10 -> 0 | C10: ='Question 2a_2'!F10 -> 0 | D10: =SUM(B10:C10) -> 0 | E10: =IF(A10<=$I$18,0,IF(A10<=$I$19,$I$19-A10,IF(A10<=$I$20,A10-$I$19,0))) -> 0 | F10: =D10-E10 -> 0 | H10: Include Premium | I10: N | AJ10: =AJ9+2 -> 10 | AK10: =MAX(0,(AJ10^2)-120) -> 0
A11: =A10+1 -> 77 | B11: ='Question 2a_1'!F11 -> 0 | C11: ='Question 2a_2'!F11 -> 0 | D11: =SUM(B11:C11) -> 0 | E11: =IF(A11<=$I$18,0,IF(A11<=$I$19,$I$19-A11,IF(A11<=$I$20,A11-$I$19,0))) -> 0 | F11: =D11-E11 -> 0 | G11: Computations | H11: d1 | I11: =(LN($I$2/I5)+(($I$6-$I$7+(0.5*$I$8*$I$8))*$I$9))/($I$8*SQRT($I$9)) -> 1.3115124 | J11: =(LN($I$2/J5)+(($I$6-$I$7+(0.5*$I$8*$I$8))*$I$9))/($I$8*SQRT($I$9)) -> 0.5677006 | K11: =(LN($I$2/K5)+(($I$6-$I$7+(0.5*$I$8*$I$8))*$I$9))/($I$8*SQRT($I$9)) -> 0.5677006 | L11: =(LN($I$2/L5)+(($I$6-$I$7+(0.5*$I$8*$I$8))*$I$9))/($I$8*SQRT($I$9)) -> -0.040037923 | AJ11: =AJ10+2 -> 12 | AK11: =MAX(0,(AJ11^2)-120) -> 24
A12: =A11+1 -> 78 | B12: ='Question 2a_1'!F12 -> 0 | C12: ='Question 2a_2'!F12 -> 0 | D12: =SUM(B12:C12) -> 0 | E12: =IF(A12<=$I$18,0,IF(A12<=$I$19,$I$19-A12,IF(A12<=$I$20,A12-$I$19,0))) -> 0 | F12: =D12-E12 -> 0 | H12: d2 | I12: =I11-($I$8*SQRT($I$9)) -> 1.0115124 | J12: =J11-($I$8*SQRT($I$9)) -> 0.2677006 | K12: =K11-($I$8*SQRT($I$9)) -> 0.2677006 | L12: =L11-($I$8*SQRT($I$9)) -> -0.34003792 | AJ12: =AJ11+2 -> 14 | AK12: =MAX(0,(AJ12^2)-120) -> 76
A13: =A12+1 -> 79 | B13: ='Question 2a_1'!F13 -> 0 | C13: ='Question 2a_2'!F13 -> 0 | D13: =SUM(B13:C13) -> 0 | E13: =IF(A13<=$I$18,0,IF(A13<=$I$19,$I$19-A13,IF(A13<=$I$20,A13-$I$19,0))) -> 0 | F13: =D13-E13 -> 0 | H13: Premium | I13: =IF(I3="C",($I$2*EXP(-$I$7*$I$9)*NORMSDIST(I11))-(I5*EXP(-$I$6*$I$9)*NORMSDIST(I12)),(-$I$2*EXP(-$I$7*$I$9)*NORMSDIST(-I11))-(-I5*EXP(-$I$6*$I$9)*NORMSDIST(-I12))) -> 1.6530087 | J13: =IF(J3="C",($I$2*EXP(-$I$7*$I$9)*NORMSDIST(J11))-(J5*EXP(-$I$6*$I$9)*NORMSDIST(J12)),(-$I$2*EXP(-$I$7*$I$9)*NORMSDIST(-J11))-(-J5*EXP(-$I$6*$I$9)*NORMSDIST(-J12))) -> 6.8487329 | K13: =IF(K3="C",($I$2*EXP(-$I$7*$I$9)*NORMSDIST(K11))-(K5*EXP(-$I$6*$I$9)*NORMSDIST(K12)),(-$I$2*EXP(-$I$7*$I$9)*NORMSDIST(-K11))-(-K5*EXP(-$I$6*$I$9)*NORMSDIST(-K12))) -> 19.675271 | L13: =IF(L3="C",($I$2*EXP(-$I$7*$I$9)*NORMSDIST(L11))-(L5*EXP(-$I$6*$I$9)*NORMSDIST(L12)),(-$I$2*EXP(-$I$7*$I$9)*NORMSDIST(-L11))-(-L5*EXP(-$I$6*$I$9)*NORMSDIST(-L12))) -> 10.410428 | AJ13: =AJ12+2 -> 16 | AK13: =MAX(0,(AJ13^2)-120) -> 136
A14: =A13+1 -> 80 | B14: ='Question 2a_1'!F14 -> 0 | C14: ='Question 2a_2'!F14 -> 0 | D14: =SUM(B14:C14) -> 0 | E14: =IF(A14<=$I$18,0,IF(A14<=$I$19,$I$19-A14,IF(A14<=$I$20,A14-$I$19,0))) -> 0 | F14: =D14-E14 -> 0 | H14: Total Premium | I14: ='Question 2a_1'!K14+'Question 2a_2'!K14 -> 4.4145692 | AJ14: =AJ13+2 -> 18 | AK14: =MAX(0,(AJ14^2)-120) -> 204
A15: =A14+1 -> 81 | B15: ='Question 2a_1'!F15 -> 19 | C15: ='Question 2a_2'!F15 -> 0 | D15: =SUM(B15:C15) -> 19 | E15: =IF(A15<=$I$18,0,IF(A15<=$I$19,$I$19-A15,IF(A15<=$I$20,A15-$I$19,0))) -> 19 | F15: =D15-E15 -> 6.2864274e-09 | AJ15: =AJ14+2 -> 20 | AK15: =MAX(0,(AJ15^2)-120) -> 280
A16: =A15+1 -> 82 | B16: ='Question 2a_1'!F16 -> 18 | C16: ='Question 2a_2'!F16 -> 0 | D16: =SUM(B16:C16) -> 18 | E16: =IF(A16<=$I$18,0,IF(A16<=$I$19,$I$19-A16,IF(A16<=$I$20,A16-$I$19,0))) -> 18 | F16: =D16-E16 -> 6.519258e-09 | AJ16: =AJ15+2 -> 22 | AK16: =MAX(0,(AJ16^2)-120) -> 364
A17: =A16+1 -> 83 | B17: ='Question 2a_1'!F17 -> 17 | C17: ='Question 2a_2'!F17 -> 0 | D17: =SUM(B17:C17) -> 17 | E17: =IF(A17<=$I$18,0,IF(A17<=$I$19,$I$19-A17,IF(A17<=$I$20,A17-$I$19,0))) -> 17 | F17: =D17-E17 -> 6.519258e-09 | H17: Structure To Price | AJ17: =AJ16+2 -> 24 | AK17: =MAX(0,(AJ17^2)-120) -> 456
A18: =A17+1 -> 84 | B18: ='Question 2a_1'!F18 -> 16 | C18: ='Question 2a_2'!F18 -> 0 | D18: =SUM(B18:C18) -> 16 | E18: =IF(A18<=$I$18,0,IF(A18<=$I$19,$I$19-A18,IF(A18<=$I$20,A18-$I$19,0))) -> 16 | F18: =D18-E18 -> 6.519258e-09 | H18: Lower Strike | I18: 80 | AJ18: =AJ17+2 -> 26 | AK18: =MAX(0,(AJ18^2)-120) -> 556
A19: =A18+1 -> 85 | B19: ='Question 2a_1'!F19 -> 15 | C19: ='Question 2a_2'!F19 -> 0 | D19: =SUM(B19:C19) -> 15 | E19: =IF(A19<=$I$18,0,IF(A19<=$I$19,$I$19-A19,IF(A19<=$I$20,A19-$I$19,0))) -> 15 | F19: =D19-E19 -> 5.5879354e-09 | H19: Mid Strike | I19: 100 | AJ19: =AJ18+2 -> 28 | AK19: =MAX(0,(AJ19^2)-120) -> 664
A20: =A19+1 -> 86 | B20: ='Question 2a_1'!F20 -> 14 | C20: ='Question 2a_2'!F20 -> 0 | D20: =SUM(B20:C20) -> 14 | E20: =IF(A20<=$I$18,0,IF(A20<=$I$19,$I$19-A20,IF(A20<=$I$20,A20-$I$19,0))) -> 14 | F20: =D20-E20 -> 5.5879354e-09 | H20: Upper Strike | I20: 120 | AJ20: =AJ19+2 -> 30 | AK20: =MAX(0,(AJ20^2)-120) -> 780
A21: =A20+1 -> 87 | B21: ='Question 2a_1'!F21 -> 13 | C21: ='Question 2a_2'!F21 -> 0 | D21: =SUM(B21:C21) -> 13 | E21: =IF(A21<=$I$18,0,IF(A21<=$I$19,$I$19-A21,IF(A21<=$I$20,A21-$I$19,0))) -> 13 | F21: =D21-E21 -> 5.5879354e-09 | H21: Exact Value | I21: =(J13-I13)+(K13-L13)-((I19-I18)*NORMSDIST(-I12)*EXP(-I6*I9))-((I20-I19)*NORMSDIST(L12)*EXP(-I6*I9)) -> 4.4145602 | AJ21: =AJ20+2 -> 32 | AK21: =MAX(0,(AJ21^2)-120) -> 904
A22: =A21+1 -> 88 | B22: ='Question 2a_1'!F22 -> 12 | C22: ='Question 2a_2'!F22 -> 0 | D22: =SUM(B22:C22) -> 12 | E22: =IF(A22<=$I$18,0,IF(A22<=$I$19,$I$19-A22,IF(A22<=$I$20,A22-$I$19,0))) -> 12 | F22: =D22-E22 -> 5.5879354e-09 | AJ22: =AJ21+2 -> 34 | AK22: =MAX(0,(AJ22^2)-120) -> 1036
A23: =A22+1 -> 89 | B23: ='Question 2a_1'!F23 -> 11 | C23: ='Question 2a_2'!F23 -> 0 | D23: =SUM(B23:C23) -> 11 | E23: =IF(A23<=$I$18,0,IF(A23<=$I$19,$I$19-A23,IF(A23<=$I$20,A23-$I$19,0))) -> 11 | F23: =D23-E23 -> 7.4505806e-09 | AJ23: =AJ22+2 -> 36 | AK23: =MAX(0,(AJ23^2)-120) -> 1176
A24: =A23+1 -> 90 | B24: ='Question 2a_1'!F24 -> 10 | C24: ='Question 2a_2'!F24 -> 0 | D24: =SUM(B24:C24) -> 10 | E24: =IF(A24<=$I$18,0,IF(A24<=$I$19,$I$19-A24,IF(A24<=$I$20,A24-$I$19,0))) -> 10 | F24: =D24-E24 -> 7.4505806e-09 | AJ24: =AJ23+2 -> 38 | AK24: =MAX(0,(AJ24^2)-120) -> 1324
A25: =A24+1 -> 91 | B25: ='Question 2a_1'!F25 -> 9 | C25: ='Question 2a_2'!F25 -> 0 | D25: =SUM(B25:C25) -> 9 | E25: =IF(A25<=$I$18,0,IF(A25<=$I$19,$I$19-A25,IF(A25<=$I$20,A25-$I$19,0))) -> 9 | F25: =D25-E25 -> 7.4505806e-09 | AJ25: =AJ24+2 -> 40 | AK25: =MAX(0,(AJ25^2)-120) -> 1480
A26: =A25+1 -> 92 | B26: ='Question 2a_1'!F26 -> 8 | C26: ='Question 2a_2'!F26 -> 0 | D26: =SUM(B26:C26) -> 8 | E26: =IF(A26<=$I$18,0,IF(A26<=$I$19,$I$19-A26,IF(A26<=$I$20,A26-$I$19,0))) -> 8 | F26: =D26-E26 -> 7.4505806e-09 | AJ26: =AJ25+2 -> 42 | AK26: =MAX(0,(AJ26^2)-120) -> 1644
A27: =A26+1 -> 93 | B27: ='Question 2a_1'!F27 -> 7 | C27: ='Question 2a_2'!F27 -> 0 | D27: =SUM(B27:C27) -> 7 | E27: =IF(A27<=$I$18,0,IF(A27<=$I$19,$I$19-A27,IF(A27<=$I$20,A27-$I$19,0))) -> 7 | F27: =D27-E27 -> 7.4505806e-09 | AJ27: =AJ26+2 -> 44 | AK27: =MAX(0,(AJ27^2)-120) -> 1816
A28: =A27+1 -> 94 | B28: ='Question 2a_1'!F28 -> 6 | C28: ='Question 2a_2'!F28 -> 0 | D28: =SUM(B28:C28) -> 6 | E28: =IF(A28<=$I$18,0,IF(A28<=$I$19,$I$19-A28,IF(A28<=$I$20,A28-$I$19,0))) -> 6 | F28: =D28-E28 -> 7.4505806e-09 | AJ28: =AJ27+2 -> 46 | AK28: =MAX(0,(AJ28^2)-120) -> 1996
A29: =A28+1 -> 95 | B29: ='Question 2a_1'!F29 -> 5 | C29: ='Question 2a_2'!F29 -> 0 | D29: =SUM(B29:C29) -> 5 | E29: =IF(A29<=$I$18,0,IF(A29<=$I$19,$I$19-A29,IF(A29<=$I$20,A29-$I$19,0))) -> 5 | F29: =D29-E29 -> 7.4505806e-09 | AJ29: =AJ28+2 -> 48 | AK29: =MAX(0,(AJ29^2)-120) -> 2184
A30: =A29+1 -> 96 | B30: ='Question 2a_1'!F30 -> 4 | C30: ='Question 2a_2'!F30 -> 0 | D30: =SUM(B30:C30) -> 4 | E30: =IF(A30<=$I$18,0,IF(A30<=$I$19,$I$19-A30,IF(A30<=$I$20,A30-$I$19,0))) -> 4 | F30: =D30-E30 -> 7.4505806e-09 | AJ30: =AJ29+2 -> 50 | AK30: =MAX(0,(AJ30^2)-120) -> 2380
A31: =A30+1 -> 97 | B31: ='Question 2a_1'!F31 -> 3 | C31: ='Question 2a_2'!F31 -> 0 | D31: =SUM(B31:C31) -> 3 | E31: =IF(A31<=$I$18,0,IF(A31<=$I$19,$I$19-A31,IF(A31<=$I$20,A31-$I$19,0))) -> 3 | F31: =D31-E31 -> 7.4505806e-09 | AJ31: =AJ30+2 -> 52 | AK31: =MAX(0,(AJ31^2)-120) -> 2584
A32: =A31+1 -> 98 | B32: ='Question 2a_1'!F32 -> 2 | C32: ='Question 2a_2'!F32 -> 0 | D32: =SUM(B32:C32) -> 2 | E32: =IF(A32<=$I$18,0,IF(A32<=$I$19,$I$19-A32,IF(A32<=$I$20,A32-$I$19,0))) -> 2 | F32: =D32-E32 -> 7.4505806e-09 | AJ32: =AJ31+2 -> 54 | AK32: =MAX(0,(AJ32^2)-120) -> 2796
A33: =A32+1 -> 99 | B33: ='Question 2a_1'!F33 -> 1 | C33: ='Question 2a_2'!F33 -> 0 | D33: =SUM(B33:C33) -> 1 | E33: =IF(A33<=$I$18,0,IF(A33<=$I$19,$I$19-A33,IF(A33<=$I$20,A33-$I$19,0))) -> 1 | F33: =D33-E33 -> 7.4505806e-09 | AJ33: =AJ32+2 -> 56 | AK33: =MAX(0,(AJ33^2)-120) -> 3016
... A104: =A103+1 -> 170 | B104: ='Question 2a_1'!F104 -> 0 | C104: ='Question 2a_2'!F104 -> 0 | D104: =SUM(B104:C104) -> 0 | E104: =IF(A104<=$I$18,0,IF(A104<=$I$19,$I$19-A104,IF(A104<=$I$20,A104-$I$19,0))) -> 0 | F104: =D104-E104 -> 0 | AJ104: =AJ103+2 -> 198 | AK104: =MAX(0,(AJ104^2)-120) -> 39084
AJ105: =AJ104+2 -> 200 | AK105: =MAX(0,(AJ105^2)-120) -> 39880
AJ106: =AJ105+2 -> 202 | AK106: =MAX(0,(AJ106^2)-120) -> 40684
AJ107: =AJ106+2 -> 204 | AK107: =MAX(0,(AJ107^2)-120) -> 41496
AJ108: =AJ107+2 -> 206 | AK108: =MAX(0,(AJ108^2)-120) -> 42316
AJ109: =AJ108+2 -> 208 | AK109: =MAX(0,(AJ109^2)-120) -> 43144
AJ110: =AJ109+2 -> 210 | AK110: =MAX(0,(AJ110^2)-120) -> 43980
AJ111: =AJ110+2 -> 212 | AK111: =MAX(0,(AJ111^2)-120) -> 44824
AJ112: =AJ111+2 -> 214 | AK112: =MAX(0,(AJ112^2)-120) -> 45676
AJ113: =AJ112+2 -> 216 | AK113: =MAX(0,(AJ113^2)-120) -> 46536
AJ114: =AJ113+2 -> 218 | AK114: =MAX(0,(AJ114^2)-120) -> 47404
AJ115: =AJ114+2 -> 220 | AK115: =MAX(0,(AJ115^2)-120) -> 48280
AJ116: =AJ115+2 -> 222 | AK116: =MAX(0,(AJ116^2)-120) -> 49164
... AJ128: =AJ127+2 -> 246 | AK128: =MAX(0,(AJ128^2)-120) -> 60396

Sheet Question 2b
A1: S0 | B1: 110 | E1: Working | F1: Delta t | G1: =B8/B9 -> 0.033333333
A2: X1 | B2: 80 | F2: u | G2: =EXP(B5*SQRT(G1)) -> 1.0563
A3: X2 | B3: 100 | F3: d | G3: =1/G2 -> 0.94670073
A4: X3 | B4: 120 | F4: p | G4: =(EXP((B6-B7)*G1)-G3)/(G2-G3) -> 0.49543907
A5: volatility | B5: 0.3 | F5: Option Value | G5: =A108 -> 2.8657106
A6: Risk free | B6: 0.04
A7: Dividend | B7: 0.01
A8: Term (yrs) | B8: 1
A9: n | B9: 30
A14: 0 | B14: Delta t | C14: 2 Delta t | D14: 3 Delta t | E14: 4 Delta t | F14: 5 Delta t | G14: 6 Delta t | H14: 7 Delta t | I14: 8 Delta t | J14: 9 Delta t | K14: 10 Delta t | L14: 11 Delta t | M14: 12 Delta t | N14: 13 Delta t | O14: 14 Delta t | P14: 15 Delta t | Q14: 16 Delta t | R14: 17 Delta t | S14: 18 Delta t | T14: 19 Delta t | U14: 20 Delta t | V14: 21 Delta t | W14: 22 Delta t | X14: 23 Delta t | Y14: 24 Delta t | Z14: 25 Delta t | AA14: 26 Delta t | AB14: 27 Delta t | AC14: 28 Delta t | AD14: 29 Delta t | AE14: 30 Delta t
AE15: =$G$2*AD16 -> 568.86778
AD16: =$G$2*AC17 -> 538.54754
AC17: =$G$2*AB18 -> 509.84335 | AE17: =$G$2*AD18 -> 509.84335
AB18: =$G$2*AA19 -> 482.66907 | AD18: =$G$2*AC19 -> 482.66907
AA19: =$G$2*Z20 -> 456.94316 | AC19: =$G$2*AB20 -> 456.94316 | AE19: =$G$2*AD20 -> 456.94316
Z20: =$G$2*Y21 -> 432.58843 | AB20: =$G$2*AA21 -> 432.58843 | AD20: =$G$2*AC21 -> 432.58843
Y21: =$G$2*X22 -> 409.53178 | AA21: =$G$2*Z22 -> 409.53178 | AC21: =$G$2*AB22 -> 409.53178 | AE21: =$G$2*AD22 -> 409.53178
X22: =$G$2*W23 -> 387.70403 | Z22: =$G$2*Y23 -> 387.70403 | AB22: =$G$2*AA23 -> 387.70403 | AD22: =$G$2*AC23 -> 387.70403
W23: =$G$2*V24 -> 367.03969 | Y23: =$G$2*X24 -> 367.03969 | AA23: =$G$2*Z24 -> 367.03969 | AC23: =$G$2*AB24 -> 367.03969 | AE23: =$G$2*AD24 -> 367.03969
V24: =$G$2*U25 -> 347.47674 | X24: =$G$2*W25 -> 347.47674 | Z24: =$G$2*Y25 -> 347.47674 | AB24: =$G$2*AA25 -> 347.47674 | AD24: =$G$2*AC25 -> 347.47674
U25: =$G$2*T26 -> 328.95649 | W25: =$G$2*V26 -> 328.95649 | Y25: =$G$2*X26 -> 328.95649 | AA25: =$G$2*Z26 -> 328.95649 | AC25: =$G$2*AB26 -> 328.95649 | AE25: =$G$2*AD26 -> 328.95649
T26: =$G$2*S27 -> 311.42335 | V26: =$G$2*U27 -> 311.42335 | X26: =$G$2*W27 -> 311.42335 | Z26: =$G$2*Y27 -> 311.42335 | AB26: =$G$2*AA27 -> 311.42335 | AD26: =$G$2*AC27 -> 311.42335
S27: =$G$2*R28 -> 294.82471 | U27: =$G$2*T28 -> 294.82471 | W27: =$G$2*V28 -> 294.82471 | Y27: =$G$2*X28 -> 294.82471 | AA27: =$G$2*Z28 -> 294.82471 | AC27: =$G$2*AB28 -> 294.82471 | AE27: =$G$2*AD28 -> 294.82471
R28: =$G$2*Q29 -> 279.11077 | T28: =$G$2*S29 -> 279.11077 | V28: =$G$2*U29 -> 279.11077 | X28: =$G$2*W29 -> 279.11077 | Z28: =$G$2*Y29 -> 279.11077 | AB28: =$G$2*AA29 -> 279.11077 | AD28: =$G$2*AC29 -> 279.11077
Q29: =$G$2*P30 -> 264.23437 | S29: =$G$2*R30 -> 264.23437 | U29: =$G$2*T30 -> 264.23437 | W29: =$G$2*V30 -> 264.23437 | Y29: =$G$2*X30 -> 264.23437 | AA29: =$G$2*Z30 -> 264.23437 | AC29: =$G$2*AB30 -> 264.23437 | AE29: =$G$2*AD30 -> 264.23437
P30: =$G$2*O31 -> 250.15087 | R30: =$G$2*Q31 -> 250.15087 | T30: =$G$2*S31 -> 250.15087 | V30: =$G$2*U31 -> 250.15087 | X30: =$G$2*W31 -> 250.15087 | Z30: =$G$2*Y31 -> 250.15087 | AB30: =$G$2*AA31 -> 250.15087 | AD30: =$G$2*AC31 -> 250.15087
O31: =$G$2*N32 -> 236.81801 | Q31: =$G$2*P32 -> 236.81801 | S31: =$G$2*R32 -> 236.81801 | U31: =$G$2*T32 -> 236.81801 | W31: =$G$2*V32 -> 236.81801 | Y31: =$G$2*X32 -> 236.81801 | AA31: =$G$2*Z32 -> 236.81801 | AC31: =$G$2*AB32 -> 236.81801 | AE31: =$G$2*AD32 -> 236.81801
N32: =$G$2*M33 -> 224.19578 | P32: =$G$2*O33 -> 224.19578 | R32: =$G$2*Q33 -> 224.19578 | T32: =$G$2*S33 -> 224.19578 | V32: =$G$2*U33 -> 224.19578 | X32: =$G$2*W33 -> 224.19578 | Z32: =$G$2*Y33 -> 224.19578 | AB32: =$G$2*AA33 -> 224.19578 | AD32: =$G$2*AC33 -> 224.19578
M33: =$G$2*L34 -> 212.24631 | O33: =$G$2*N34 -> 212.24631 | Q33: =$G$2*P34 -> 212.24631 | S33: =$G$2*R34 -> 212.24631 | U33: =$G$2*T34 -> 212.24631 | W33: =$G$2*V34 -> 212.24631 | Y33: =$G$2*X34 -> 212.24631 | AA33: =$G$2*Z34 -> 212.24631 | AC33: =$G$2*AB34 -> 212.24631 | AE33: =$G$2*AD34 -> 212.24631
L34: =$G$2*K35 -> 200.93374 | N34: =$G$2*M35 -> 200.93374 | P34: =$G$2*O35 -> 200.93374 | R34: =$G$2*Q35 -> 200.93374 | T34: =$G$2*S35 -> 200.93374 | V34: =$G$2*U35 -> 200.93374 | X34: =$G$2*W35 -> 200.93374 | Z34: =$G$2*Y35 -> 200.93374 | AB34: =$G$2*AA35 -> 200.93374 | AD34: =$G$2*AC35 -> 200.93374
K35: =$G$2*J36 -> 190.22411 | M35: =$G$2*L36 -> 190.22411 | O35: =$G$2*N36 -> 190.22411 | Q35: =$G$2*P36 -> 190.22411 | S35: =$G$2*R36 -> 190.22411 | U35: =$G$2*T36 -> 190.22411 | W35: =$G$2*V36 -> 190.22411 | Y35: =$G$2*X36 -> 190.22411 | AA35: =$G$2*Z36 -> 190.22411 | AC35: =$G$2*AB36 -> 190.22411 | AE35: =$G$2*AD36 -> 190.22411
J36: =$G$2*I37 -> 180.08531 | L36: =$G$2*K37 -> 180.08531 | N36: =$G$2*M37 -> 180.08531 | P36: =$G$2*O37 -> 180.08531 | R36: =$G$2*Q37 -> 180.08531 | T36: =$G$2*S37 -> 180.08531 | V36: =$G$2*U37 -> 180.08531 | X36: =$G$2*W37 -> 180.08531 | Z36: =$G$2*Y37 -> 180.08531 | AB36: =$G$2*AA37 -> 180.08531 | AD36: =$G$2*AC37 -> 180.08531
I37: =$G$2*H38 -> 170.48689 | K37: =$G$2*J38 -> 170.48689 | M37: =$G$2*L38 -> 170.48689 | O37: =$G$2*N38 -> 170.48689 | Q37: =$G$2*P38 -> 170.48689 | S37: =$G$2*R38 -> 170.48689 | U37: =$G$2*T38 -> 170.48689 | W37: =$G$2*V38 -> 170.48689 | Y37: =$G$2*X38 -> 170.48689 | AA37: =$G$2*Z38 -> 170.48689 | AC37: =$G$2*AB38 -> 170.48689 | AE37: =$G$2*AD38 -> 170.48689
H38: =$G$2*G39 -> 161.40006 | J38: =$G$2*I39 -> 161.40006 | L38: =$G$2*K39 -> 161.40006 | N38: =$G$2*M39 -> 161.40006 | P38: =$G$2*O39 -> 161.40006 | R38: =$G$2*Q39 -> 161.40006 | T38: =$G$2*S39 -> 161.40006 | V38: =$G$2*U39 -> 161.40006 | X38: =$G$2*W39 -> 161.40006 | Z38: =$G$2*Y39 -> 161.40006 | AB38: =$G$2*AA39 -> 161.40006 | AD38: =$G$2*AC39 -> 161.40006
G39: =$G$2*F40 -> 152.79756 | I39: =$G$2*H40 -> 152.79756 | K39: =$G$2*J40 -> 152.79756 | M39: =$G$2*L40 -> 152.79756 | O39: =$G$2*N40 -> 152.79756 | Q39: =$G$2*P40 -> 152.79756 | S39: =$G$2*R40 -> 152.79756 | U39: =$G$2*T40 -> 152.79756 | W39: =$G$2*V40 -> 152.79756 | Y39: =$G$2*X40 -> 152.79756 | AA39: =$G$2*Z40 -> 152.79756 | AC39: =$G$2*AB40 -> 152.79756 | AE39: =$G$2*AD40 -> 152.79756
F40: =$G$2*E41 -> 144.65356 | H40: =$G$2*G41 -> 144.65356 | J40: =$G$2*I41 -> 144.65356 | L40: =$G$2*K41 -> 144.65356 | N40: =$G$2*M41 -> 144.65356 | P40: =$G$2*O41 -> 144.65356 | R40: =$G$2*Q41 -> 144.65356 | T40: =$G$2*S41 -> 144.65356 | V40: =$G$2*U41 -> 144.65356 | X40: =$G$2*W41 -> 144.65356 | Z40: =$G$2*Y41 -> 144.65356 | AB40: =$G$2*AA41 -> 144.65356 | AD40: =$G$2*AC41 -> 144.65356
E41: =$G$2*D42 -> 136.94363 | G41: =$G$2*F42 -> 136.94363 | I41: =$G$2*H42 -> 136.94363 | K41: =$G$2*J42 -> 136.94363 | M41: =$G$2*L42 -> 136.94363 | O41: =$G$2*N42 -> 136.94363 | Q41: =$G$2*P42 -> 136.94363 | S41: =$G$2*R42 -> 136.94363 | U41: =$G$2*T42 -> 136.94363 | W41: =$G$2*V42 -> 136.94363 | Y41: =$G$2*X42 -> 136.94363 | AA41: =$G$2*Z42 -> 136.94363 | AC41: =$G$2*AB42 -> 136.94363 | AE41: =$G$2*AD42 -> 136.94363
D42: =$G$2*C43 -> 129.64464 | F42: =$G$2*E43 -> 129.64464 | H42: =$G$2*G43 -> 129.64464 | J42: =$G$2*I43 -> 129.64464 | L42: =$G$2*K43 -> 129.64464 | N42: =$G$2*M43 -> 129.64464 | P42: =$G$2*O43 -> 129.64464 | R42: =$G$2*Q43 -> 129.64464 | T42: =$G$2*S43 -> 129.64464 | V42: =$G$2*U43 -> 129.64464 | X42: =$G$2*W43 -> 129.64464 | Z42: =$G$2*Y43 -> 129.64464 | AB42: =$G$2*AA43 -> 129.64464 | AD42: =$G$2*AC43 -> 129.64464
C43: =$G$2*B44 -> 122.73467 | E43: =$G$2*D44 -> 122.73467 | G43: =$G$2*F44 -> 122.73467 | I43: =$G$2*H44 -> 122.73467 | K43: =$G$2*J44 -> 122.73467 | M43: =$G$2*L44 -> 122.73467 | O43: =$G$2*N44 -> 122.73467 | Q43: =$G$2*P44 -> 122.73467 | S43: =$G$2*R44 -> 122.73467 | U43: =$G$2*T44 -> 122.73467 | W43: =$G$2*V44 -> 122.73467 | Y43: =$G$2*X44 -> 122.73467 | AA43: =$G$2*Z44 -> 122.73467 | AC43: =$G$2*AB44 -> 122.73467 | AE43: =$G$2*AD44 -> 122.73467
B44: =$G$2*A45 -> 116.193 | D44: =$G$2*C45 -> 116.193 | F44: =$G$2*E45 -> 116.193 | H44: =$G$2*G45 -> 116.193 | J44: =$G$2*I45 -> 116.193 | L44: =$G$2*K45 -> 116.193 | N44: =$G$2*M45 -> 116.193 | P44: =$G$2*O45 -> 116.193 | R44: =$G$2*Q45 -> 116.193 | T44: =$G$2*S45 -> 116.193 | V44: =$G$2*U45 -> 116.193 | X44: =$G$2*W45 -> 116.193 | Z44: =$G$2*Y45 -> 116.193 | AB44: =$G$2*AA45 -> 116.193 | AD44: =$G$2*AC45 -> 116.193
A45: =B1 -> 110 | C45: =$G$2*B46 -> 110 | E45: =$G$2*D46 -> 110 | G45: =$G$2*F46 -> 110 | I45: =$G$2*H46 -> 110 | K45: =$G$2*J46 -> 110 | M45: =$G$2*L46 -> 110 | O45: =$G$2*N46 -> 110 | Q45: =$G$2*P46 -> 110 | S45: =$G$2*R46 -> 110 | U45: =$G$2*T46 -> 110 | W45: =$G$2*V46 -> 110 | Y45: =$G$2*X46 -> 110 | AA45: =$G$2*Z46 -> 110 | AC45: =$G$2*AB46 -> 110 | AE45: =$G$2*AD46 -> 110
B46: =A45*$G$3 -> 104.13708 | D46: =$G$2*C47 -> 104.13708 | F46: =$G$2*E47 -> 104.13708 | H46: =$G$2*G47 -> 104.13708 | J46: =$G$2*I47 -> 104.13708 | L46: =$G$2*K47 -> 104.13708 | N46: =$G$2*M47 -> 104.13708 | P46: =$G$2*O47 -> 104.13708 | R46: =$G$2*Q47 -> 104.13708 | T46: =$G$2*S47 -> 104.13708 | V46: =$G$2*U47 -> 104.13708 | X46: =$G$2*W47 -> 104.13708 | Z46: =$G$2*Y47 -> 104.13708 | AB46: =$G$2*AA47 -> 104.13708 | AD46: =$G$2*AC47 -> 104.13708
C47: =B46*$G$3 -> 98.58665 | E47: =$G$2*D48 -> 98.58665 | G47: =$G$2*F48 -> 98.58665 | I47: =$G$2*H48 -> 98.58665 | K47: =$G$2*J48 -> 98.58665 | M47: =$G$2*L48 -> 98.58665 | O47: =$G$2*N48 -> 98.58665 | Q47: =$G$2*P48 -> 98.58665 | S47: =$G$2*R48 -> 98.58665 | U47: =$G$2*T48 -> 98.58665 | W47: =$G$2*V48 -> 98.58665 | Y47: =$G$2*X48 -> 98.58665 | AA47: =$G$2*Z48 -> 98.58665 | AC47: =$G$2*AB48 -> 98.58665 | AE47: =$G$2*AD48 -> 98.58665
D48: =C47*$G$3 -> 93.332053 | F48: =$G$2*E49 -> 93.332053 | H48: =$G$2*G49 -> 93.332053 | J48: =$G$2*I49 -> 93.332053 | L48: =$G$2*K49 -> 93.332053 | N48: =$G$2*M49 -> 93.332053 | P48: =$G$2*O49 -> 93.332053 | R48: =$G$2*Q49 -> 93.332053 | T48: =$G$2*S49 -> 93.332053 | V48: =$G$2*U49 -> 93.332053 | X48: =$G$2*W49 -> 93.332053 | Z48: =$G$2*Y49 -> 93.332053 | AB48: =$G$2*AA49 -> 93.332053 | AD48: =$G$2*AC49 -> 93.332053
E49: =D48*$G$3 -> 88.357523 | G49: =$G$2*F50 -> 88.357523 | I49: =$G$2*H50 -> 88.357523 | K49: =$G$2*J50 -> 88.357523 | M49: =$G$2*L50 -> 88.357523 | O49: =$G$2*N50 -> 88.357523 | Q49: =$G$2*P50 -> 88.357523 | S49: =$G$2*R50 -> 88.357523 | U49: =$G$2*T50 -> 88.357523 | W49: =$G$2*V50 -> 88.357523 | Y49: =$G$2*X50 -> 88.357523 | AA49: =$G$2*Z50 -> 88.357523 | AC49: =$G$2*AB50 -> 88.357523 | AE49: =$G$2*AD50 -> 88.357523
F50: =E49*$G$3 -> 83.648131 | H50: =$G$2*G51 -> 83.648131 | J50: =$G$2*I51 -> 83.648131 | L50: =$G$2*K51 -> 83.648131 | N50: =$G$2*M51 -> 83.648131 | P50: =$G$2*O51 -> 83.648131 | R50: =$G$2*Q51 -> 83.648131 | T50: =$G$2*S51 -> 83.648131 | V50: =$G$2*U51 -> 83.648131 | X50: =$G$2*W51 -> 83.648131 | Z50: =$G$2*Y51 -> 83.648131 | AB50: =$G$2*AA51 -> 83.648131 | AD50: =$G$2*AC51 -> 83.648131
G51: =F50*$G$3 -> 79.189747 | I51: =$G$2*H52 -> 79.189747 | K51: =$G$2*J52 -> 79.189747 | M51: =$G$2*L52 -> 79.189747 | O51: =$G$2*N52 -> 79.189747 | Q51: =$G$2*P52 -> 79.189747 | S51: =$G$2*R52 -> 79.189747 | U51: =$G$2*T52 -> 79.189747 | W51: =$G$2*V52 -> 79.189747 | Y51: =$G$2*X52 -> 79.189747 | AA51: =$G$2*Z52 -> 79.189747 | AC51: =$G$2*AB52 -> 79.189747 | AE51: =$G$2*AD52 -> 79.189747
H52: =G51*$G$3 -> 74.968991 | J52: =$G$2*I53 -> 74.968991 | L52: =$G$2*K53 -> 74.968991 | N52: =$G$2*M53 -> 74.968991 | P52: =$G$2*O53 -> 74.968991 | R52: =$G$2*Q53 -> 74.968991 | T52: =$G$2*S53 -> 74.968991 | V52: =$G$2*U53 -> 74.968991 | X52: =$G$2*W53 -> 74.968991 | Z52: =$G$2*Y53 -> 74.968991 | AB52: =$G$2*AA53 -> 74.968991 | AD52: =$G$2*AC53 -> 74.968991
I53: =H52*$G$3 -> 70.973198 | K53: =$G$2*J54 -> 70.973198 | M53: =$G$2*L54 -> 70.973198 | O53: =$G$2*N54 -> 70.973198 | Q53: =$G$2*P54 -> 70.973198 | S53: =$G$2*R54 -> 70.973198 | U53: =$G$2*T54 -> 70.973198 | W53: =$G$2*V54 -> 70.973198 | Y53: =$G$2*X54 -> 70.973198 | AA53: =$G$2*Z54 -> 70.973198 | AC53: =$G$2*AB54 -> 70.973198 | AE53: =$G$2*AD54 -> 70.973198
J54: =I53*$G$3 -> 67.190379 | L54: =$G$2*K55 -> 67.190379 | N54: =$G$2*M55 -> 67.190379 | P54: =$G$2*O55 -> 67.190379 | R54: =$G$2*Q55 -> 67.190379 | T54: =$G$2*S55 -> 67.190379 | V54: =$G$2*U55 -> 67.190379 | X54: =$G$2*W55 -> 67.190379 | Z54: =$G$2*Y55 -> 67.190379 | AB54: =$G$2*AA55 -> 67.190379 | AD54: =$G$2*AC55 -> 67.190379
K55: =J54*$G$3 -> 63.609181 | M55: =$G$2*L56 -> 63.609181 | O55: =$G$2*N56 -> 63.609181 | Q55: =$G$2*P56 -> 63.609181 | S55: =$G$2*R56 -> 63.609181 | U55: =$G$2*T56 -> 63.609181 | W55: =$G$2*V56 -> 63.609181 | Y55: =$G$2*X56 -> 63.609181 | AA55: =$G$2*Z56 -> 63.609181 | AC55: =$G$2*AB56 -> 63.609181 | AE55: =$G$2*AD56 -> 63.609181
L56: =K55*$G$3 -> 60.218858 | N56: =$G$2*M57 -> 60.218858 | P56: =$G$2*O57 -> 60.218858 | R56: =$G$2*Q57 -> 60.218858 | T56: =$G$2*S57 -> 60.218858 | V56: =$G$2*U57 -> 60.218858 | X56: =$G$2*W57 -> 60.218858 | Z56: =$G$2*Y57 -> 60.218858 | AB56: =$G$2*AA57 -> 60.218858 | AD56: =$G$2*AC57 -> 60.218858
M57: =L56*$G$3 -> 57.009236 | O57: =$G$2*N58 -> 57.009236 | Q57: =$G$2*P58 -> 57.009236 | S57: =$G$2*R58 -> 57.009236 | U57: =$G$2*T58 -> 57.009236 | W57: =$G$2*V58 -> 57.009236 | Y57: =$G$2*X58 -> 57.009236 | AA57: =$G$2*Z58 -> 57.009236 | AC57: =$G$2*AB58 -> 57.009236 | AE57: =$G$2*AD58 -> 57.009236
N58: =M57*$G$3 -> 53.970686 | P58: =$G$2*O59 -> 53.970686 | R58: =$G$2*Q59 -> 53.970686 | T58: =$G$2*S59 -> 53.970686 | V58: =$G$2*U59 -> 53.970686 | X58: =$G$2*W59 -> 53.970686 | Z58: =$G$2*Y59 -> 53.970686 | AB58: =$G$2*AA59 -> 53.970686 | AD58: =$G$2*AC59 -> 53.970686
O59: =N58*$G$3 -> 51.094087 | Q59: =$G$2*P60 -> 51.094087 | S59: =$G$2*R60 -> 51.094087 | U59: =$G$2*T60 -> 51.094087 | W59: =$G$2*V60 -> 51.094087 | Y59: =$G$2*X60 -> 51.094087 | AA59: =$G$2*Z60 -> 51.094087 | AC59: =$G$2*AB60 -> 51.094087 | AE59: =$G$2*AD60 -> 51.094087
P60: =O59*$G$3 -> 48.37081 | R60: =$G$2*Q61 -> 48.37081 | T60: =$G$2*S61 -> 48.37081 | V60: =$G$2*U61 -> 48.37081 | X60: =$G$2*W61 -> 48.37081 | Z60: =$G$2*Y61 -> 48.37081 | AB60: =$G$2*AA61 -> 48.37081 | AD60: =$G$2*AC61 -> 48.37081
Q61: =P60*$G$3 -> 45.792681 | S61: =$G$2*R62 -> 45.792681 | U61: =$G$2*T62 -> 45.792681 | W61: =$G$2*V62 -> 45.792681 | Y61: =$G$2*X62 -> 45.792681 | AA61: =$G$2*Z62 -> 45.792681 | AC61: =$G$2*AB62 -> 45.792681 | AE61: =$G$2*AD62 -> 45.792681
R62: =Q61*$G$3 -> 43.351964 | T62: =$G$2*S63 -> 43.351964 | V62: =$G$2*U63 -> 43.351964 | X62: =$G$2*W63 -> 43.351964 | Z62: =$G$2*Y63 -> 43.351964 | AB62: =$G$2*AA63 -> 43.351964 | AD62: =$G$2*AC63 -> 43.351964
S63: =R62*$G$3 -> 41.041336 | U63: =$G$2*T64 -> 41.041336 | W63: =$G$2*V64 -> 41.041336 | Y63: =$G$2*X64 -> 41.041336 | AA63: =$G$2*Z64 -> 41.041336 | AC63: =$G$2*AB64 -> 41.041336 | AE63: =$G$2*AD64 -> 41.041336
T64: =S63*$G$3 -> 38.853863 | V64: =$G$2*U65 -> 38.853863 | X64: =$G$2*W65 -> 38.853863 | Z64: =$G$2*Y65 -> 38.853863 | AB64: =$G$2*AA65 -> 38.853863 | AD64: =$G$2*AC65 -> 38.853863
U65: =T64*$G$3 -> 36.78298 | W65: =$G$2*V66 -> 36.78298 | Y65: =$G$2*X66 -> 36.78298 | AA65: =$G$2*Z66 -> 36.78298 | AC65: =$G$2*AB66 -> 36.78298 | AE65: =$G$2*AD66 -> 36.78298
V66: =U65*$G$3 -> 34.822474 | X66: =$G$2*W67 -> 34.822474 | Z66: =$G$2*Y67 -> 34.822474 | AB66: =$G$2*AA67 -> 34.822474 | AD66: =$G$2*AC67 -> 34.822474
W67: =V66*$G$3 -> 32.966462 | Y67: =$G$2*X68 -> 32.966462 | AA67: =$G$2*Z68 -> 32.966462 | AC67: =$G$2*AB68 -> 32.966462 | AE67: =$G$2*AD68 -> 32.966462
X68: =W67*$G$3 -> 31.209374 | Z68: =$G$2*Y69 -> 31.209374 | AB68: =$G$2*AA69 -> 31.209374 | AD68: =$G$2*AC69 -> 31.209374
Y69: =X68*$G$3 -> 29.545937 | AA69: =$G$2*Z70 -> 29.545937 | AC69: =$G$2*AB70 -> 29.545937 | AE69: =$G$2*AD70 -> 29.545937
Z70: =Y69*$G$3 -> 27.97116 | AB70: =$G$2*AA71 -> 27.97116 | AD70: =$G$2*AC71 -> 27.97116
AA71: =Z70*$G$3 -> 26.480317 | AC71: =$G$2*AB72 -> 26.480317 | AE71: =$G$2*AD72 -> 26.480317
AB72: =AA71*$G$3 -> 25.068936 | AD72: =$G$2*AC73 -> 25.068936
AC73: =AB72*$G$3 -> 23.73278 | AE73: =$G$2*AD74 -> 23.73278
AD74: =AC73*$G$3 -> 22.46784
AE75: =AD74*$G$3 -> 21.27032
AE78: =IF(AE15<=$B$2,0,IF(AE15<=$B$3,$B$3-AE15,IF(AE15<=$B$4,AE15-$B$3,0))) -> 0
AD79: =(($G$4*AE78)+((1-$G$4)*AE80))*EXP(-$B$6*$G$1) -> 0
AC80: =(($G$4*AD79)+((1-$G$4)*AD81))*EXP(-$B$6*$G$1) -> 0 | AE80: =IF(AE17<=$B$2,0,IF(AE17<=$B$3,$B$3-AE17,IF(AE17<=$B$4,AE17-$B$3,0))) -> 0
AB81: =(($G$4*AC80)+((1-$G$4)*AC82))*EXP(-$B$6*$G$1) -> 0 | AD81: =(($G$4*AE80)+((1-$G$4)*AE82))*EXP(-$B$6*$G$1) -> 0
AA82: =(($G$4*AB81)+((1-$G$4)*AB83))*EXP(-$B$6*$G$1) -> 0 | AC82: =(($G$4*AD81)+((1-$G$4)*AD83))*EXP(-$B$6*$G$1) -> 0 | AE82: =IF(AE19<=$B$2,0,IF(AE19<=$B$3,$B$3-AE19,IF(AE19<=$B$4,AE19-$B$3,0))) -> 0
Z83: =(($G$4*AA82)+((1-$G$4)*AA84))*EXP(-$B$6*$G$1) -> 0 | AB83: =(($G$4*AC82)+((1-$G$4)*AC84))*EXP(-$B$6*$G$1) -> 0 | AD83: =(($G$4*AE82)+((1-$G$4)*AE84))*EXP(-$B$6*$G$1) -> 0
Y84: =(($G$4*Z83)+((1-$G$4)*Z85))*EXP(-$B$6*$G$1) -> 0 | AA84: =(($G$4*AB83)+((1-$G$4)*AB85))*EXP(-$B$6*$G$1) -> 0 | AC84: =(($G$4*AD83)+((1-$G$4)*AD85))*EXP(-$B$6*$G$1) -> 0 | AE84: =IF(AE21<=$B$2,0,IF(AE21<=$B$3,$B$3-AE21,IF(AE21<=$B$4,AE21-$B$3,0))) -> 0
X85: =(($G$4*Y84)+((1-$G$4)*Y86))*EXP(-$B$6*$G$1) -> 0 | Z85: =(($G$4*AA84)+((1-$G$4)*AA86))*EXP(-$B$6*$G$1) -> 0 | AB85: =(($G$4*AC84)+((1-$G$4)*AC86))*EXP(-$B$6*$G$1) -> 0 | AD85: =(($G$4*AE84)+((1-$G$4)*AE86))*EXP(-$B$6*$G$1) -> 0
W86: =(($G$4*X85)+((1-$G$4)*X87))*EXP(-$B$6*$G$1) -> 0 | Y86: =(($G$4*Z85)+((1-$G$4)*Z87))*EXP(-$B$6*$G$1) -> 0 | AA86: =(($G$4*AB85)+((1-$G$4)*AB87))*EXP(-$B$6*$G$1) -> 0 | AC86: =(($G$4*AD85)+((1-$G$4)*AD87))*EXP(-$B$6*$G$1) -> 0 | AE86: =IF(AE23<=$B$2,0,IF(AE23<=$B$3,$B$3-AE23,IF(AE23<=$B$4,AE23-$B$3,0))) -> 0
V87: =(($G$4*W86)+((1-$G$4)*W88))*EXP(-$B$6*$G$1) -> 0 | X87: =(($G$4*Y86)+((1-$G$4)*Y88))*EXP(-$B$6*$G$1) -> 0 | Z87: =(($G$4*AA86)+((1-$G$4)*AA88))*EXP(-$B$6*$G$1) -> 0 | AB87: =(($G$4*AC86)+((1-$G$4)*AC88))*EXP(-$B$6*$G$1) -> 0 | AD87: =(($G$4*AE86)+((1-$G$4)*AE88))*EXP(-$B$6*$G$1) -> 0
U88: =(($G$4*V87)+((1-$G$4)*V89))*EXP(-$B$6*$G$1) -> 0 | W88: =(($G$4*X87)+((1-$G$4)*X89))*EXP(-$B$6*$G$1) -> 0 | Y88: =(($G$4*Z87)+((1-$G$4)*Z89))*EXP(-$B$6*$G$1) -> 0 | AA88: =(($G$4*AB87)+((1-$G$4)*AB89))*EXP(-$B$6*$G$1) -> 0 | AC88: =(($G$4*AD87)+((1-$G$4)*AD89))*EXP(-$B$6*$G$1) -> 0 | AE88: =IF(AE25<=$B$2,0,IF(AE25<=$B$3,$B$3-AE25,IF(AE25<=$B$4,AE25-$B$3,0))) -> 0
T89: =(($G$4*U88)+((1-$G$4)*U90))*EXP(-$B$6*$G$1) -> 0 | V89: =(($G$4*W88)+((1-$G$4)*W90))*EXP(-$B$6*$G$1) -> 0 | X89: =(($G$4*Y88)+((1-$G$4)*Y90))*EXP(-$B$6*$G$1) -> 0 | Z89: =(($G$4*AA88)+((1-$G$4)*AA90))*EXP(-$B$6*$G$1) -> 0 | AB89: =(($G$4*AC88)+((1-$G$4)*AC90))*EXP(-$B$6*$G$1) -> 0 | AD89: =(($G$4*AE88)+((1-$G$4)*AE90))*EXP(-$B$6*$G$1) -> 0
S90: =(($G$4*T89)+((1-$G$4)*T91))*EXP(-$B$6*$G$1) -> 0 | U90: =(($G$4*V89)+((1-$G$4)*V91))*EXP(-$B$6*$G$1) -> 0 | W90: =(($G$4*X89)+((1-$G$4)*X91))*EXP(-$B$6*$G$1) -> 0 | Y90: =(($G$4*Z89)+((1-$G$4)*Z91))*EXP(-$B$6*$G$1) -> 0 | AA90: =(($G$4*AB89)+((1-$G$4)*AB91))*EXP(-$B$6*$G$1) -> 0 | AC90: =(($G$4*AD89)+((1-$G$4)*AD91))*EXP(-$B$6*$G$1) -> 0 | AE90: =IF(AE27<=$B$2,0,IF(AE27<=$B$3,$B$3-AE27,IF(AE27<=$B$4,AE27-$B$3,0))) -> 0
R91: =(($G$4*S90)+((1-$G$4)*S92))*EXP(-$B$6*$G$1) -> 0 | T91: =(($G$4*U90)+((1-$G$4)*U92))*EXP(-$B$6*$G$1) -> 0 | V91: =(($G$4*W90)+((1-$G$4)*W92))*EXP(-$B$6*$G$1) -> 0 | X91: =(($G$4*Y90)+((1-$G$4)*Y92))*EXP(-$B$6*$G$1) -> 0 | Z91: =(($G$4*AA90)+((1-$G$4)*AA92))*EXP(-$B$6*$G$1) -> 0 | AB91: =(($G$4*AC90)+((1-$G$4)*AC92))*EXP(-$B$6*$G$1) -> 0 | AD91: =(($G$4*AE90)+((1-$G$4)*AE92))*EXP(-$B$6*$G$1) -> 0
Q92: =(($G$4*R91)+((1-$G$4)*R93))*EXP(-$B$6*$G$1) -> 0 | S92: =(($G$4*T91)+((1-$G$4)*T93))*EXP(-$B$6*$G$1) -> 0 | U92: =(($G$4*V91)+((1-$G$4)*V93))*EXP(-$B$6*$G$1) -> 0 | W92: =(($G$4*X91)+((1-$G$4)*X93))*EXP(-$B$6*$G$1) -> 0 | Y92: =(($G$4*Z91)+((1-$G$4)*Z93))*EXP(-$B$6*$G$1) -> 0 | AA92: =(($G$4*AB91)+((1-$G$4)*AB93))*EXP(-$B$6*$G$1) -> 0 | AC92: =(($G$4*AD91)+((1-$G$4)*AD93))*EXP(-$B$6*$G$1) -> 0 | AE92: =IF(AE29<=$B$2,0,IF(AE29<=$B$3,$B$3-AE29,IF(AE29<=$B$4,AE29-$B$3,0))) -> 0
P93: =(($G$4*Q92)+((1-$G$4)*Q94))*EXP(-$B$6*$G$1) -> 0.00034278232 | R93: =(($G$4*S92)+((1-$G$4)*S94))*EXP(-$B$6*$G$1) -> 0 | T93: =(($G$4*U92)+((1-$G$4)*U94))*EXP(-$B$6*$G$1) -> 0 | V93: =(($G$4*W92)+((1-$G$4)*W94))*EXP(-$B$6*$G$1) -> 0 | X93: =(($G$4*Y92)+((1-$G$4)*Y94))*EXP(-$B$6*$G$1) -> 0 | Z93: =(($G$4*AA92)+((1-$G$4)*AA94))*EXP(-$B$6*$G$1) -> 0 | AB93: =(($G$4*AC92)+((1-$G$4)*AC94))*EXP(-$B$6*$G$1) -> 0 | AD93: =(($G$4*AE92)+((1-$G$4)*AE94))*EXP(-$B$6*$G$1) -> 0
O94: =(($G$4*P93)+((1-$G$4)*P95))*EXP(-$B$6*$G$1) -> 0.0027380354 | Q94: =(($G$4*R93)+((1-$G$4)*R95))*EXP(-$B$6*$G$1) -> 0.00068027396 | S94: =(($G$4*T93)+((1-$G$4)*T95))*EXP(-$B$6*$G$1) -> 0 | U94: =(($G$4*V93)+((1-$G$4)*V95))*EXP(-$B$6*$G$1) -> 0 | W94: =(($G$4*X93)+((1-$G$4)*X95))*EXP(-$B$6*$G$1) -> 0 | Y94: =(($G$4*Z93)+((1-$G$4)*Z95))*EXP(-$B$6*$G$1) -> 0 | AA94: =(($G$4*AB93)+((1-$G$4)*AB95))*EXP(-$B$6*$G$1) -> 0 | AC94: =(($G$4*AD93)+((1-$G$4)*AD95))*EXP(-$B$6*$G$1) -> 0 | AE94: =IF(AE31<=$B$2,0,IF(AE31<=$B$3,$B$3-AE31,IF(AE31<=$B$4,AE31-$B$3,0))) -> 0
N95: =(($G$4*O94)+((1-$G$4)*O96))*EXP(-$B$6*$G$1) -> 0.011719135 | P95: =(($G$4*Q94)+((1-$G$4)*Q96))*EXP(-$B$6*$G$1) -> 0.0050972254 | R95: =(($G$4*S94)+((1-$G$4)*S96))*EXP(-$B$6*$G$1) -> 0.0013500482 | T95: =(($G$4*U94)+((1-$G$4)*U96))*EXP(-$B$6*$G$1) -> 0 | V95: =(($G$4*W94)+((1-$G$4)*W96))*EXP(-$B$6*$G$1) -> 0 | X95: =(($G$4*Y94)+((1-$G$4)*Y96))*EXP(-$B$6*$G$1) -> 0 | Z95: =(($G$4*AA94)+((1-$G$4)*AA96))*EXP(-$B$6*$G$1) -> 0 | AB95: =(($G$4*AC94)+((1-$G$4)*AC96))*EXP(-$B$6*$G$1) -> 0 | AD95: =(($G$4*AE94)+((1-$G$4)*AE96))*EXP(-$B$6*$G$1) -> 0
M96: =(($G$4*N95)+((1-$G$4)*N97))*EXP(-$B$6*$G$1) -> 0.035696697 | O96: =(($G$4*P95)+((1-$G$4)*P97))*EXP(-$B$6*$G$1) -> 0.020568856 | Q96: =(($G$4*R95)+((1-$G$4)*R97))*EXP(-$B$6*$G$1) -> 0.0094478023 | S96: =(($G$4*T95)+((1-$G$4)*T97))*EXP(-$B$6*$G$1) -> 0.0026792592 | U96: =(($G$4*V95)+((1-$G$4)*V97))*EXP(-$B$6*$G$1) -> 0 | W96: =(($G$4*X95)+((1-$G$4)*X97))*EXP(-$B$6*$G$1) -> 0 | Y96: =(($G$4*Z95)+((1-$G$4)*Z97))*EXP(-$B$6*$G$1) -> 0 | AA96: =(($G$4*AB95)+((1-$G$4)*AB97))*EXP(-$B$6*$G$1) -> 0 | AC96: =(($G$4*AD95)+((1-$G$4)*AD97))*EXP(-$B$6*$G$1) -> 0 | AE96: =IF(AE33<=$B$2,0,IF(AE33<=$B$3,$B$3-AE33,IF(AE33<=$B$4,AE33-$B$3,0))) -> 0
L97: =(($G$4*M96)+((1-$G$4)*M98))*EXP(-$B$6*$G$1) -> 0.086731587 | N97: =(($G$4*O96)+((1-$G$4)*O98))*EXP(-$B$6*$G$1) -> 0.059335166 | P97: =(($G$4*Q96)+((1-$G$4)*Q98))*EXP(-$B$6*$G$1) -> 0.035815169 | R97: =(($G$4*S96)+((1-$G$4)*S98))*EXP(-$B$6*$G$1) -> 0.017424142 | T97: =(($G$4*U96)+((1-$G$4)*U98))*EXP(-$B$6*$G$1) -> 0.0053171653 | V97: =(($G$4*W96)+((1-$G$4)*W98))*EXP(-$B$6*$G$1) -> 0 | X97: =(($G$4*Y96)+((1-$G$4)*Y98))*EXP(-$B$6*$G$1) -> 0 | Z97: =(($G$4*AA96)+((1-$G$4)*AA98))*EXP(-$B$6*$G$1) -> 0 | AB97: =(($G$4*AC96)+((1-$G$4)*AC98))*EXP(-$B$6*$G$1) -> 0 | AD97: =(($G$4*AE96)+((1-$G$4)*AE98))*EXP(-$B$6*$G$1) -> 0
K98: =(($G$4*L97)+((1-$G$4)*L99))*EXP(-$B$6*$G$1) -> 0.17866619 | M98: =(($G$4*N97)+((1-$G$4)*N99))*EXP(-$B$6*$G$1) -> 0.13707317 | O98: =(($G$4*P97)+((1-$G$4)*P99))*EXP(-$B$6*$G$1) -> 0.097557528 | Q98: =(($G$4*R97)+((1-$G$4)*R99))*EXP(-$B$6*$G$1) -> 0.061800552 | S98: =(($G$4*T97)+((1-$G$4)*T99))*EXP(-$B$6*$G$1) -> 0.031948529 | U98: =(($G$4*V97)+((1-$G$4)*V99))*EXP(-$B$6*$G$1) -> 0.010552263 | W98: =(($G$4*X97)+((1-$G$4)*X99))*EXP(-$B$6*$G$1) -> 0 | Y98: =(($G$4*Z97)+((1-$G$4)*Z99))*EXP(-$B$6*$G$1) -> 0 | AA98: =(($G$4*AB97)+((1-$G$4)*AB99))*EXP(-$B$6*$G$1) -> 0 | AC98: =(($G$4*AD97)+((1-$G$4)*AD99))*EXP(-$B$6*$G$1) -> 0 | AE98: =IF(AE35<=$B$2,0,IF(AE35<=$B$3,$B$3-AE35,IF(AE35<=$B$4,AE35-$B$3,0))) -> 0
J99: =(($G$4*K98)+((1-$G$4)*K100))*EXP(-$B$6*$G$1) -> 0.32397085 | L99: =(($G$4*M98)+((1-$G$4)*M100))*EXP(-$B$6*$G$1) -> 0.26941118 | N99: =(($G$4*O98)+((1-$G$4)*O100))*EXP(-$B$6*$G$1) -> 0.21376824 | P99: =(($G$4*Q98)+((1-$G$4)*Q100))*EXP(-$B$6*$G$1) -> 0.15844163 | R99: =(($G$4*S98)+((1-$G$4)*S100))*EXP(-$B$6*$G$1) -> 0.10553811 | T99: =(($G$4*U98)+((1-$G$4)*U100))*EXP(-$B$6*$G$1) -> 0.058182912 | V99: =(($G$4*W98)+((1-$G$4)*W100))*EXP(-$B$6*$G$1) -> 0.020941657 | X99: =(($G$4*Y98)+((1-$G$4)*Y100))*EXP(-$B$6*$G$1) -> 0 | Z99: =(($G$4*AA98)+((1-$G$4)*AA100))*EXP(-$B$6*$G$1) -> 0 | AB99: =(($G$4*AC98)+((1-$G$4)*AC100))*EXP(-$B$6*$G$1) -> 0 | AD99: =(($G$4*AE98)+((1-$G$4)*AE100))*EXP(-$B$6*$G$1) -> 0
I100: =(($G$4*J99)+((1-$G$4)*J101))*EXP(-$B$6*$G$1) -> 0.53020527 | K100: =(($G$4*L99)+((1-$G$4)*L101))*EXP(-$B$6*$G$1) -> 0.46750525 | M100: =(($G$4*N99)+((1-$G$4)*N101))*EXP(-$B$6*$G$1) -> 0.40006909 | O100: =(($G$4*P99)+((1-$G$4)*P101))*EXP(-$B$6*$G$1) -> 0.32844326 | Q100: =(($G$4*R99)+((1-$G$4)*R101))*EXP(-$B$6*$G$1) -> 0.25375453 | S100: =(($G$4*T99)+((1-$G$4)*T101))*EXP(-$B$6*$G$1) -> 0.17807636 | U100: =(($G$4*V99)+((1-$G$4)*V101))*EXP(-$B$6*$G$1) -> 0.10510631 | W100: =(($G$4*X99)+((1-$G$4)*X101))*EXP(-$B$6*$G$1) -> 0.04156009 | Y100: =(($G$4*Z99)+((1-$G$4)*Z101))*EXP(-$B$6*$G$1) -> 0 | AA100: =(($G$4*AB99)+((1-$G$4)*AB101))*EXP(-$B$6*$G$1) -> 0 | AC100: =(($G$4*AD99)+((1-$G$4)*AD101))*EXP(-$B$6*$G$1) -> 0 | AE100: =IF(AE37<=$B$2,0,IF(AE37<=$B$3,$B$3-AE37,IF(AE37<=$B$4,AE37-$B$3,0))) -> 0
H101: =(($G$4*I100)+((1-$G$4)*I102))*EXP(-$B$6*$G$1) -> 0.79715929 | J101: =(($G$4*K100)+((1-$G$4)*K102))*EXP(-$B$6*$G$1) -> 0.73411325 | L101: =(($G$4*M100)+((1-$G$4)*M102))*EXP(-$B$6*$G$1) -> 0.66325425 | N101: =(($G$4*O100)+((1-$G$4)*O102))*EXP(-$B$6*$G$1) -> 0.58405975 | P101: =(($G$4*Q100)+((1-$G$4)*Q102))*EXP(-$B$6*$G$1) -> 0.49623998 | R101: =(($G$4*S100)+((1-$G$4)*S102))*EXP(-$B$6*$G$1) -> 0.39996238 | T101: =(($G$4*U100)+((1-$G$4)*U102))*EXP(-$B$6*$G$1) -> 0.29627316 | V101: =(($G$4*W100)+((1-$G$4)*W102))*EXP(-$B$6*$G$1) -> 0.1880273 | X101: =(($G$4*Y100)+((1-$G$4)*Y102))*EXP(-$B$6*$G$1) -> 0.082478722 | Z101: =(($G$4*AA100)+((1-$G$4)*AA102))*EXP(-$B$6*$G$1) -> 0 | AB101: =(($G$4*AC100)+((1-$G$4)*AC102))*EXP(-$B$6*$G$1) -> 0 | AD101: =(($G$4*AE100)+((1-$G$4)*AE102))*EXP(-$B$6*$G$1) -> 0
G102: =(($G$4*H101)+((1-$G$4)*H103))*EXP(-$B$6*$G$1) -> 1.1155178 | I102: =(($G$4*J101)+((1-$G$4)*J103))*EXP(-$B$6*$G$1) -> 1.061395 | K102: =(($G$4*L101)+((1-$G$4)*L103))*EXP(-$B$6*$G$1) -> 0.99784253 | M102: =(($G$4*N101)+((1-$G$4)*N103))*EXP(-$B$6*$G$1) -> 0.9234352 | O102: =(($G$4*P101)+((1-$G$4)*P103))*EXP(-$B$6*$G$1) -> 0.83659944 | Q102: =(($G$4*R101)+((1-$G$4)*R103))*EXP(-$B$6*$G$1) -> 0.7356538 | S102: =(($G$4*T101)+((1-$G$4)*T103))*EXP(-$B$6*$G$1) -> 0.61889459 | U102: =(($G$4*V101)+((1-$G$4)*V103))*EXP(-$B$6*$G$1) -> 0.48476738 | W102: =(($G$4*X101)+((1-$G$4)*X103))*EXP(-$B$6*$G$1) -> 0.33234376 | Y102: =(($G$4*Z101)+((1-$G$4)*Z103))*EXP(-$B$6*$G$1) -> 0.16368443 | AA102: =(($G$4*AB101)+((1-$G$4)*AB103))*EXP(-$B$6*$G$1) -> 0 | AC102: =(($G$4*AD101)+((1-$G$4)*AD103))*EXP(-$B$6*$G$1) -> 0 | AE102: =IF(AE39<=$B$2,0,IF(AE39<=$B$3,$B$3-AE39,IF(AE39<=$B$4,AE39-$B$3,0))) -> 0
F103: =(($G$4*G102)+((1-$G$4)*G104))*EXP(-$B$6*$G$1) -> 1.4674238 | H103: =(($G$4*I102)+((1-$G$4)*I104))*EXP(-$B$6*$G$1) -> 1.4310705 | J103: =(($G$4*K102)+((1-$G$4)*K104))*EXP(-$B$6*$G$1) -> 1.3855666 | L103: =(($G$4*M102)+((1-$G$4)*M104))*EXP(-$B$6*$G$1) -> 1.3290205 | N103: =(($G$4*O102)+((1-$G$4)*O104))*EXP(-$B$6*$G$1) -> 1.259117 | P103: =(($G$4*Q102)+((1-$G$4)*Q104))*EXP(-$B$6*$G$1) -> 1.1730179 | R103: =(($G$4*S102)+((1-$G$4)*S104))*EXP(-$B$6*$G$1) -> 1.0672216 | T103: =(($G$4*U102)+((1-$G$4)*U104))*EXP(-$B$6*$G$1) -> 0.93731997 | V103: =(($G$4*W102)+((1-$G$4)*W104))*EXP(-$B$6*$G$1) -> 0.77742464 | X103: =(($G$4*Y102)+((1-$G$4)*Y104))*EXP(-$B$6*$G$1) -> 0.57857036 | Z103: =(($G$4*AA102)+((1-$G$4)*AA104))*EXP(-$B$6*$G$1) -> 0.32484247 | AB103: =(($G$4*AC102)+((1-$G$4)*AC104))*EXP(-$B$6*$G$1) -> 0 | AD103: =(($G$4*AE102)+((1-$G$4)*AE104))*EXP(-$B$6*$G$1) -> 0
E104: =(($G$4*F103)+((1-$G$4)*F105))*EXP(-$B$6*$G$1) -> 1.8287797 | G104: =(($G$4*H103)+((1-$G$4)*H105))*EXP(-$B$6*$G$1) -> 1.8168481 | I104: =(($G$4*J103)+((1-$G$4)*J105))*EXP(-$B$6*$G$1) -> 1.797847 | K104: =(($G$4*L103)+((1-$G$4)*L105))*EXP(-$B$6*$G$1) -> 1.7699451 | M104: =(($G$4*N103)+((1-$G$4)*N105))*EXP(-$B$6*$G$1) -> 1.7307876 | O104: =(($G$4*P103)+((1-$G$4)*P105))*EXP(-$B$6*$G$1) -> 1.6773255 | Q104: =(($G$4*R103)+((1-$G$4)*R105))*EXP(-$B$6*$G$1) -> 1.6055767 | S104: =(($G$4*T103)+((1-$G$4)*T105))*EXP(-$B$6*$G$1) -> 1.5102655 | U104: =(($G$4*V103)+((1-$G$4)*V105))*EXP(-$B$6*$G$1) -> 1.3841695 | W104: =(($G$4*X103)+((1-$G$4)*X105))*EXP(-$B$6*$G$1) -> 1.2165147 | Y104: =(($G$4*Z103)+((1-$G$4)*Z105))*EXP(-$B$6*$G$1) -> 0.98748558 | AA104: =(($G$4*AB103)+((1-$G$4)*AB105))*EXP(-$B$6*$G$1) -> 0.64467116 | AC104: =(($G$4*AD103)+((1-$G$4)*AD105))*EXP(-$B$6*$G$1) -> 0 | AE104: =IF(AE41<=$B$2,0,IF(AE41<=$B$3,$B$3-AE41,IF(AE41<=$B$4,AE41-$B$3,0))) -> 0
D105: =(($G$4*E104)+((1-$G$4)*E106))*EXP(-$B$6*$G$1) -> 2.1727017 | F105: =(($G$4*G104)+((1-$G$4)*G106))*EXP(-$B$6*$G$1) -> 2.1884387 | H105: =(($G$4*I104)+((1-$G$4)*I106))*EXP(-$B$6*$G$1) -> 2.2004556 | J105: =(($G$4*K104)+((1-$G$4)*K106))*EXP(-$B$6*$G$1) -> 2.2074278 | L105: =(($G$4*M104)+((1-$G$4)*M106))*EXP(-$B$6*$G$1) -> 2.2075786 | N105: =(($G$4*O104)+((1-$G$4)*O106))*EXP(-$B$6*$G$1) -> 2.1985076 | P105: =(($G$4*Q104)+((1-$G$4)*Q106))*EXP(-$B$6*$G$1) -> 2.1769512 | R105: =(($G$4*S104)+((1-$G$4)*S106))*EXP(-$B$6*$G$1) -> 2.1384447 | T105: =(($G$4*U104)+((1-$G$4)*U106))*EXP(-$B$6*$G$1) -> 2.0768465 | V105: =(($G$4*W104)+((1-$G$4)*W106))*EXP(-$B$6*$G$1) -> 1.9836054 | X105: =(($G$4*Y104)+((1-$G$4)*Y106))*EXP(-$B$6*$G$1) -> 1.8461427 | Z105: =(($G$4*AA104)+((1-$G$4)*AA106))*EXP(-$B$6*$G$1) -> 1.6407601 | AB105: =(($G$4*AC104)+((1-$G$4)*AC106))*EXP(-$B$6*$G$1) -> 1.2793921 | AD105: =(($G$4*AE104)+((1-$G$4)*AE106))*EXP(-$B$6*$G$1) -> 0
C106: =(($G$4*D105)+((1-$G$4)*D107))*EXP(-$B$6*$G$1) -> 2.4733289 | E106: =(($G$4*F105)+((1-$G$4)*F107))*EXP(-$B$6*$G$1) -> 2.5161512 | G106: =(($G$4*H105)+((1-$G$4)*H107))*EXP(-$B$6*$G$1) -> 2.5590983 | I106: =(($G$4*J105)+((1-$G$4)*J107))*EXP(-$B$6*$G$1) -> 2.6016042 | K106: =(($G$4*L105)+((1-$G$4)*L107))*EXP(-$B$6*$G$1) -> 2.6428386 | M106: =(($G$4*N105)+((1-$G$4)*N107))*EXP(-$B$6*$G$1) -> 2.6815873 | O106: =(($G$4*P105)+((1-$G$4)*P107))*EXP(-$B$6*$G$1) -> 2.716081 | Q106: =(($G$4*R105)+((1-$G$4)*R107))*EXP(-$B$6*$G$1) -> 2.7437525 | S106: =(($G$4*T105)+((1-$G$4)*T107))*EXP(-$B$6*$G$1) -> 2.7609219 | U106: =(($G$4*V105)+((1-$G$4)*V107))*EXP(-$B$6*$G$1) -> 2.7624926 | W106: =(($G$4*X105)+((1-$G$4)*X107))*EXP(-$B$6*$G$1) -> 2.7420732 | Y106: =(($G$4*Z105)+((1-$G$4)*Z107))*EXP(-$B$6*$G$1) -> 2.6941581 | AA106: =(($G$4*AB105)+((1-$G$4)*AB107))*EXP(-$B$6*$G$1) -> 2.6231797 | AC106: =(($G$4*AD105)+((1-$G$4)*AD107))*EXP(-$B$6*$G$1) -> 2.5390375 | AE106: =IF(AE43<=$B$2,0,IF(AE43<=$B$3,$B$3-AE43,IF(AE43<=$B$4,AE43-$B$3,0))) -> 0
...

Sheet Question 2c
D8: Option (van trunc) | G8: ='Question 2a_3'!I21 -> 4.4145602
D9: Discount Factor | G9: =EXP(-0.05*1) -> 0.95122942
D10: d2 (80) | G10: ='Question 2a_3'!I12 -> 1.0115124
D11: d2 (120) | G11: ='Question 2a_3'!L12 -> -0.34003792
D12: Prob (ST>80) | G12: =NORMSDIST(G10) -> 0.84411438
D13: Prob (ST>120) | G13: =NORMSDIST(G11) -> 0.36691398
D14: Prob (80 < ST < 120), prob of exercise | G14: =G12-G13 -> 0.4772004
D15: Total value | G15: =G8/(G9*G14) -> 9.7252632

Sheet Question 3a

Sheet Question 3b
A1: Option type | B1: =K3 -> P | C1: =L3 -> P | D1: =M3 -> C | E1: =N3 -> C | F1: Net Effect | G1: Payoff To Replicate | H1: Slippage | I1: Replication Position | K1: Option 1 | L1: Option 2 | M1: Option 3 | N1: Option 4
I2: Inputs | J2: Current Stock Price ($) | K2: 100
A3: Stock price At Maturity | B3: Profit | J3: Option Type | K3: P | L3: P | M3: C | N3: C
A4: 50 | B4: =(MAX(IF($B$1="C",1,-1)*(A4-$K$5),0)-IF($K$10="Y",$K$13*EXP($K$6*$K$9),0))*$K$4 -> 40 | C4: =(MAX(IF($C$1="C",1,-1)*(A4-$L$5),0)-IF($K$10="Y",$L$13*EXP($K$6*$K$9),0))*$L$4 -> 0 | D4: =(MAX(IF($D$1="C",1,-1)*(A4-$M$5),0)-IF($K$10="Y",$M$13*EXP($K$6*$K$9),0))*$M$4 -> 0 | E4: =(MAX(IF($E$1="C",1,-1)*(A4-$N$5),0)-IF($K$10="Y",$N$13*EXP($K$6*$K$9),0))*$N$4 -> 0 | F4: =SUM(B4:E4) -> 40 | G4: =IF(A4<=$K$18,$K$18-A4,IF(A4>$K$19,A4-$K$19,0)) -> 40 | H4: =F4-G4 -> 0 | J4: Postion | K4: 1 | L4: 0 | M4: 0 | N4: 1 | AL4: ST | AM4: payoff
A5: =A4+1 -> 51 | B5: =(MAX(IF($B$1="C",1,-1)*(A5-$K$5),0)-IF($K$10="Y",$K$13*EXP($K$6*$K$9),0))*$K$4 -> 39 | C5: =(MAX(IF($C$1="C",1,-1)*(A5-$L$5),0)-IF($K$10="Y",$L$13*EXP($K$6*$K$9),0))*$L$4 -> 0 | D5: =(MAX(IF($D$1="C",1,-1)*(A5-$M$5),0)-IF($K$10="Y",$M$13*EXP($K$6*$K$9),0))*$M$4 -> 0 | E5: =(MAX(IF($E$1="C",1,-1)*(A5-$N$5),0)-IF($K$10="Y",$N$13*EXP($K$6*$K$9),0))*$N$4 -> 0 | F5: =SUM(B5:E5) -> 39 | G5: =IF(A5<=$K$18,$K$18-A5,IF(A5>$K$19,A5-$K$19,0)) -> 39 | H5: =F5-G5 -> 0 | J5: Strike Price ($) | K5: 90 | L5: 100 | M5: 100 | N5: 110 | AL5: 0 | AM5: =MAX(0,(AL5^2)-120) -> 0
A6: =A5+1 -> 52 | B6: =(MAX(IF($B$1="C",1,-1)*(A6-$K$5),0)-IF($K$10="Y",$K$13*EXP($K$6*$K$9),0))*$K$4 -> 38 | C6: =(MAX(IF($C$1="C",1,-1)*(A6-$L$5),0)-IF($K$10="Y",$L$13*EXP($K$6*$K$9),0))*$L$4 -> 0 | D6: =(MAX(IF($D$1="C",1,-1)*(A6-$M$5),0)-IF($K$10="Y",$M$13*EXP($K$6*$K$9),0))*$M$4 -> 0 | E6: =(MAX(IF($E$1="C",1,-1)*(A6-$N$5),0)-IF($K$10="Y",$N$13*EXP($K$6*$K$9),0))*$N$4 -> 0 | F6: =SUM(B6:E6) -> 38 | G6: =IF(A6<=$K$18,$K$18-A6,IF(A6>$K$19,A6-$K$19,0)) -> 38 | H6: =F6-G6 -> 0 | J6: Risk Free Rate (%) | K6: 0.05 | AL6: =AL5+2 -> 2 | AM6: =MAX(0,(AL6^2)-120) -> 0
A7: =A6+1 -> 53 | B7: =(MAX(IF($B$1="C",1,-1)*(A7-$K$5),0)-IF($K$10="Y",$K$13*EXP($K$6*$K$9),0))*$K$4 -> 37 | C7: =(MAX(IF($C$1="C",1,-1)*(A7-$L$5),0)-IF($K$10="Y",$L$13*EXP($K$6*$K$9),0))*$L$4 -> 0 | D7: =(MAX(IF($D$1="C",1,-1)*(A7-$M$5),0)-IF($K$10="Y",$M$13*EXP($K$6*$K$9),0))*$M$4 -> 0 | E7: =(MAX(IF($E$1="C",1,-1)*(A7-$N$5),0)-IF($K$10="Y",$N$13*EXP($K$6*$K$9),0))*$N$4 -> 0 | F7: =SUM(B7:E7) -> 37 | G7: =IF(A7<=$K$18,$K$18-A7,IF(A7>$K$19,A7-$K$19,0)) -> 37 | H7: =F7-G7 -> 0 | J7: Dividend Rate (%) | K7: 0.02 | AL7: =AL6+2 -> 4 | AM7: =MAX(0,(AL7^2)-120) -> 0
A8: =A7+1 -> 54 | B8: =(MAX(IF($B$1="C",1,-1)*(A8-$K$5),0)-IF($K$10="Y",$K$13*EXP($K$6*$K$9),0))*$K$4 -> 36 | C8: =(MAX(IF($C$1="C",1,-1)*(A8-$L$5),0)-IF($K$10="Y",$L$13*EXP($K$6*$K$9),0))*$L$4 -> 0 | D8: =(MAX(IF($D$1="C",1,-1)*(A8-$M$5),0)-IF($K$10="Y",$M$13*EXP($K$6*$K$9),0))*$M$4 -> 0 | E8: =(MAX(IF($E$1="C",1,-1)*(A8-$N$5),0)-IF($K$10="Y",$N$13*EXP($K$6*$K$9),0))*$N$4 -> 0 | F8: =SUM(B8:E8) -> 36 | G8: =IF(A8<=$K$18,$K$18-A8,IF(A8>$K$19,A8-$K$19,0)) -> 36 | H8: =F8-G8 -> 0 | J8: Volatility Rate (%) | K8: 0.3 | AL8: =AL7+2 -> 6 | AM8: =MAX(0,(AL8^2)-120) -> 0
A9: =A8+1 -> 55 | B9: =(MAX(IF($B$1="C",1,-1)*(A9-$K$5),0)-IF($K$10="Y",$K$13*EXP($K$6*$K$9),0))*$K$4 -> 35 | C9: =(MAX(IF($C$1="C",1,-1)*(A9-$L$5),0)-IF($K$10="Y",$L$13*EXP($K$6*$K$9),0))*$L$4 -> 0 | D9: =(MAX(IF($D$1="C",1,-1)*(A9-$M$5),0)-IF($K$10="Y",$M$13*EXP($K$6*$K$9),0))*$M$4 -> 0 | E9: =(MAX(IF($E$1="C",1,-1)*(A9-$N$5),0)-IF($K$10="Y",$N$13*EXP($K$6*$K$9),0))*$N$4 -> 0 | F9: =SUM(B9:E9) -> 35 | G9: =IF(A9<=$K$18,$K$18-A9,IF(A9>$K$19,A9-$K$19,0)) -> 35 | H9: =F9-G9 -> 0 | J9: Option Life (years) | K9: 0.5 | AL9: =AL8+2 -> 8 | AM9: =MAX(0,(AL9^2)-120) -> 0
A10: =A9+1 -> 56 | B10: =(MAX(IF($B$1="C",1,-1)*(A10-$K$5),0)-IF($K$10="Y",$K$13*EXP($K$6*$K$9),0))*$K$4 -> 34 | C10: =(MAX(IF($C$1="C",1,-1)*(A10-$L$5),0)-IF($K$10="Y",$L$13*EXP($K$6*$K$9),0))*$L$4 -> 0 | D10: =(MAX(IF($D$1="C",1,-1)*(A10-$M$5),0)-IF($K$10="Y",$M$13*EXP($K$6*$K$9),0))*$M$4 -> 0 | E10: =(MAX(IF($E$1="C",1,-1)*(A10-$N$5),0)-IF($K$10="Y",$N$13*EXP($K$6*$K$9),0))*$N$4 -> 0 | F10: =SUM(B10:E10) -> 34 | G10: =IF(A10<=$K$18,$K$18-A10,IF(A10>$K$19,A10-$K$19,0)) -> 34 | H10: =F10-G10 -> 0 | J10: Include Premium | K10: N | AL10: =AL9+2 -> 10 | AM10: =MAX(0,(AL10^2)-120) -> 0
A11: =A10+1 -> 57 | B11: =(MAX(IF($B$1="C",1,-1)*(A11-$K$5),0)-IF($K$10="Y",$K$13*EXP($K$6*$K$9),0))*$K$4 -> 33 | C11: =(MAX(IF($C$1="C",1,-1)*(A11-$L$5),0)-IF($K$10="Y",$L$13*EXP($K$6*$K$9),0))*$L$4 -> 0 | D11: =(MAX(IF($D$1="C",1,-1)*(A11-$M$5),0)-IF($K$10="Y",$M$13*EXP($K$6*$K$9),0))*$M$4 -> 0 | E11: =(MAX(IF($E$1="C",1,-1)*(A11-$N$5),0)-IF($K$10="Y",$N$13*EXP($K$6*$K$9),0))*$N$4 -> 0 | F11: =SUM(B11:E11) -> 33 | G11: =IF(A11<=$K$18,$K$18-A11,IF(A11>$K$19,A11-$K$19,0)) -> 33 | H11: =F11-G11 -> 0 | I11: Computations | J11: d1 | K11: =(LN($K$2/K5)+(($K$6-$K$7+(0.5*$K$8*$K$8))*$K$9))/($K$8*SQRT($K$9)) -> 0.67345093 | L11: =(LN($K$2/L5)+(($K$6-$K$7+(0.5*$K$8*$K$8))*$K$9))/($K$8*SQRT($K$9)) -> 0.1767767 | M11: =(LN($K$2/M5)+(($K$6-$K$7+(0.5*$K$8*$K$8))*$K$9))/($K$8*SQRT($K$9)) -> 0.1767767 | N11: =(LN($K$2/N5)+(($K$6-$K$7+(0.5*$K$8*$K$8))*$K$9))/($K$8*SQRT($K$9)) -> -0.2725198 | AL11: =AL10+2 -> 12 | AM11: =MAX(0,(AL11^2)-120) -> 24
A12: =A11+1 -> 58 | B12: =(MAX(IF($B$1="C",1,-1)*(A12-$K$5),0)-IF($K$10="Y",$K$13*EXP($K$6*$K$9),0))*$K$4 -> 32 | C12: =(MAX(IF($C$1="C",1,-1)*(A12-$L$5),0)-IF($K$10="Y",$L$13*EXP($K$6*$K$9),0))*$L$4 -> 0 | D12: =(MAX(IF($D$1="C",1,-1)*(A12-$M$5),0)-IF($K$10="Y",$M$13*EXP($K$6*$K$9),0))*$M$4 -> 0 | E12: =(MAX(IF($E$1="C",1,-1)*(A12-$N$5),0)-IF($K$10="Y",$N$13*EXP($K$6*$K$9),0))*$N$4 -> 0 | F12: =SUM(B12:E12) -> 32 | G12: =IF(A12<=$K$18,$K$18-A12,IF(A12>$K$19,A12-$K$19,0)) -> 32 | H12: =F12-G12 -> 0 | J12: d2 | K12: =K11-($K$8*SQRT($K$9)) -> 0.46131889 | L12: =L11-($K$8*SQRT($K$9)) -> -0.035355339 | M12: =M11-($K$8*SQRT($K$9)) -> -0.035355339 | N12: =N11-($K$8*SQRT($K$9)) -> -0.48465184 | AL12: =AL11+2 -> 14 | AM12: =MAX(0,(AL12^2)-120) -> 76
A13: =A12+1 -> 59 | B13: =(MAX(IF($B$1="C",1,-1)*(A13-$K$5),0)-IF($K$10="Y",$K$13*EXP($K$6*$K$9),0))*$K$4 -> 31 | C13: =(MAX(IF($C$1="C",1,-1)*(A13-$L$5),0)-IF($K$10="Y",$L$13*EXP($K$6*$K$9),0))*$L$4 -> 0 | D13: =(MAX(IF($D$1="C",1,-1)*(A13-$M$5),0)-IF($K$10="Y",$M$13*EXP($K$6*$K$9),0))*$M$4 -> 0 | E13: =(MAX(IF($E$1="C",1,-1)*(A13-$N$5),0)-IF($K$10="Y",$N$13*EXP($K$6*$K$9),0))*$N$4 -> 0 | F13: =SUM(B13:E13) -> 31 | G13: =IF(A13<=$K$18,$K$18-A13,IF(A13>$K$19,A13-$K$19,0)) -> 31 | H13: =F13-G13 -> 0 | J13: Premium | K13: =IF(K3="C",($K$2*EXP(-$K$7*$K$9)*NORMSDIST(K11))-(K5*EXP(-$K$6*$K$9)*NORMSDIST(K12)),(-$K$2*EXP(-$K$7*$K$9)*NORMSDIST(-K11))-(-K5*EXP(-$K$6*$K$9)*NORMSDIST(-K12))) -> 3.5055504 | L13: =IF(L3="C",($K$2*EXP(-$K$7*$K$9)*NORMSDIST(L11))-(L5*EXP(-$K$6*$K$9)*NORMSDIST(L12)),(-$K$2*EXP(-$K$7*$K$9)*NORMSDIST(-L11))-(-L5*EXP(-$K$6*$K$9)*NORMSDIST(-L12))) -> 7.5843684 | M13: =IF(M3="C",($K$2*EXP(-$K$7*$K$9)*NORMSDIST(M11))-(M5*EXP(-$K$6*$K$9)*NORMSDIST(M12)),(-$K$2*EXP(-$K$7*$K$9)*NORMSDIST(-M11))-(-M5*EXP(-$K$6*$K$9)*NORMSDIST(-M12))) -> 9.0583605 | N13: =IF(N3="C",($K$2*EXP(-$K$7*$K$9)*NORMSDIST(N11))-(N5*EXP(-$K$6*$K$9)*NORMSDIST(N12)),(-$K$2*EXP(-$K$7*$K$9)*NORMSDIST(-N11))-(-N5*EXP(-$K$6*$K$9)*NORMSDIST(-N12))) -> 5.1873717 | AL13: =AL12+2 -> 16 | AM13: =MAX(0,(AL13^2)-120) -> 136
A14: =A13+1 -> 60 | B14: =(MAX(IF($B$1="C",1,-1)*(A14-$K$5),0)-IF($K$10="Y",$K$13*EXP($K$6*$K$9),0))*$K$4 -> 30 | C14: =(MAX(IF($C$1="C",1,-1)*(A14-$L$5),0)-IF($K$10="Y",$L$13*EXP($K$6*$K$9),0))*$L$4 -> 0 | D14: =(MAX(IF($D$1="C",1,-1)*(A14-$M$5),0)-IF($K$10="Y",$M$13*EXP($K$6*$K$9),0))*$M$4 -> 0 | E14: =(MAX(IF($E$1="C",1,-1)*(A14-$N$5),0)-IF($K$10="Y",$N$13*EXP($K$6*$K$9),0))*$N$4 -> 0 | F14: =SUM(B14:E14) -> 30 | G14: =IF(A14<=$K$18,$K$18-A14,IF(A14>$K$19,A14-$K$19,0)) -> 30 | H14: =F14-G14 -> 0 | J14: Total Premium | K14: =SUMPRODUCT(K4:N4,K13:N13) -> 8.6929221 | AL14: =AL13+2 -> 18 | AM14: =MAX(0,(AL14^2)-120) -> 204
A15: =A14+1 -> 61 | B15: =(MAX(IF($B$1="C",1,-1)*(A15-$K$5),0)-IF($K$10="Y",$K$13*EXP($K$6*$K$9),0))*$K$4 -> 29 | C15: =(MAX(IF($C$1="C",1,-1)*(A15-$L$5),0)-IF($K$10="Y",$L$13*EXP($K$6*$K$9),0))*$L$4 -> 0 | D15: =(MAX(IF($D$1="C",1,-1)*(A15-$M$5),0)-IF($K$10="Y",$M$13*EXP($K$6*$K$9),0))*$M$4 -> 0 | E15: =(MAX(IF($E$1="C",1,-1)*(A15-$N$5),0)-IF($K$10="Y",$N$13*EXP($K$6*$K$9),0))*$N$4 -> 0 | F15: =SUM(B15:E15) -> 29 | G15: =IF(A15<=$K$18,$K$18-A15,IF(A15>$K$19,A15-$K$19,0)) -> 29 | H15: =F15-G15 -> 0 | AL15: =AL14+2 -> 20 | AM15: =MAX(0,(AL15^2)-120) -> 280
A16: =A15+1 -> 62 | B16: =(MAX(IF($B$1="C",1,-1)*(A16-$K$5),0)-IF($K$10="Y",$K$13*EXP($K$6*$K$9),0))*$K$4 -> 28 | C16: =(MAX(IF($C$1="C",1,-1)*(A16-$L$5),0)-IF($K$10="Y",$L$13*EXP($K$6*$K$9),0))*$L$4 -> 0 | D16: =(MAX(IF($D$1="C",1,-1)*(A16-$M$5),0)-IF($K$10="Y",$M$13*EXP($K$6*$K$9),0))*$M$4 -> 0 | E16: =(MAX(IF($E$1="C",1,-1)*(A16-$N$5),0)-IF($K$10="Y",$N$13*EXP($K$6*$K$9),0))*$N$4 -> 0 | F16: =SUM(B16:E16) -> 28 | G16: =IF(A16<=$K$18,$K$18-A16,IF(A16>$K$19,A16-$K$19,0)) -> 28 | H16: =F16-G16 -> 0 | AL16: =AL15+2 -> 22 | AM16: =MAX(0,(AL16^2)-120) -> 364
A17: =A16+1 -> 63 | B17: =(MAX(IF($B$1="C",1,-1)*(A17-$K$5),0)-IF($K$10="Y",$K$13*EXP($K$6*$K$9),0))*$K$4 -> 27 | C17: =(MAX(IF($C$1="C",1,-1)*(A17-$L$5),0)-IF($K$10="Y",$L$13*EXP($K$6*$K$9),0))*$L$4 -> 0 | D17: =(MAX(IF($D$1="C",1,-1)*(A17-$M$5),0)-IF($K$10="Y",$M$13*EXP($K$6*$K$9),0))*$M$4 -> 0 | E17: =(MAX(IF($E$1="C",1,-1)*(A17-$N$5),0)-IF($K$10="Y",$N$13*EXP($K$6*$K$9),0))*$N$4 -> 0 | F17: =SUM(B17:E17) -> 27 | G17: =IF(A17<=$K$18,$K$18-A17,IF(A17>$K$19,A17-$K$19,0)) -> 27 | H17: =F17-G17 -> 0 | J17: Structure To Price | AL17: =AL16+2 -> 24 | AM17: =MAX(0,(AL17^2)-120) -> 456
A18: =A17+1 -> 64 | B18: =(MAX(IF($B$1="C",1,-1)*(A18-$K$5),0)-IF($K$10="Y",$K$13*EXP($K$6*$K$9),0))*$K$4 -> 26 | C18: =(MAX(IF($C$1="C",1,-1)*(A18-$L$5),0)-IF($K$10="Y",$L$13*EXP($K$6*$K$9),0))*$L$4 -> 0 | D18: =(MAX(IF($D$1="C",1,-1)*(A18-$M$5),0)-IF($K$10="Y",$M$13*EXP($K$6*$K$9),0))*$M$4 -> 0 | E18: =(MAX(IF($E$1="C",1,-1)*(A18-$N$5),0)-IF($K$10="Y",$N$13*EXP($K$6*$K$9),0))*$N$4 -> 0 | F18: =SUM(B18:E18) -> 26 | G18: =IF(A18<=$K$18,$K$18-A18,IF(A18>$K$19,A18-$K$19,0)) -> 26 | H18: =F18-G18 -> 0 | J18: Lower Strike | K18: 90 | AL18: =AL17+2 -> 26 | AM18: =MAX(0,(AL18^2)-120) -> 556
A19: =A18+1 -> 65 | B19: =(MAX(IF($B$1="C",1,-1)*(A19-$K$5),0)-IF($K$10="Y",$K$13*EXP($K$6*$K$9),0))*$K$4 -> 25 | C19: =(MAX(IF($C$1="C",1,-1)*(A19-$L$5),0)-IF($K$10="Y",$L$13*EXP($K$6*$K$9),0))*$L$4 -> 0 | D19: =(MAX(IF($D$1="C",1,-1)*(A19-$M$5),0)-IF($K$10="Y",$M$13*EXP($K$6*$K$9),0))*$M$4 -> 0 | E19: =(MAX(IF($E$1="C",1,-1)*(A19-$N$5),0)-IF($K$10="Y",$N$13*EXP($K$6*$K$9),0))*$N$4 -> 0 | F19: =SUM(B19:E19) -> 25 | G19: =IF(A19<=$K$18,$K$18-A19,IF(A19>$K$19,A19-$K$19,0)) -> 25 | H19: =F19-G19 -> 0 | J19: Upper Strike | K19: 110 | AL19: =AL18+2 -> 28 | AM19: =MAX(0,(AL19^2)-120) -> 664
A20: =A19+1 -> 66 | B20: =(MAX(IF($B$1="C",1,-1)*(A20-$K$5),0)-IF($K$10="Y",$K$13*EXP($K$6*$K$9),0))*$K$4 -> 24 | C20: =(MAX(IF($C$1="C",1,-1)*(A20-$L$5),0)-IF($K$10="Y",$L$13*EXP($K$6*$K$9),0))*$L$4 -> 0 | D20: =(MAX(IF($D$1="C",1,-1)*(A20-$M$5),0)-IF($K$10="Y",$M$13*EXP($K$6*$K$9),0))*$M$4 -> 0 | E20: =(MAX(IF($E$1="C",1,-1)*(A20-$N$5),0)-IF($K$10="Y",$N$13*EXP($K$6*$K$9),0))*$N$4 -> 0 | F20: =SUM(B20:E20) -> 24 | G20: =IF(A20<=$K$18,$K$18-A20,IF(A20>$K$19,A20-$K$19,0)) -> 24 | H20: =F20-G20 -> 0 | J20: Exact Value | K20: =K13+N13 -> 8.6929221 | AL20: =AL19+2 -> 30 | AM20: =MAX(0,(AL20^2)-120) -> 780
A21: =A20+1 -> 67 | B21: =(MAX(IF($B$1="C",1,-1)*(A21-$K$5),0)-IF($K$10="Y",$K$13*EXP($K$6*$K$9),0))*$K$4 -> 23 | C21: =(MAX(IF($C$1="C",1,-1)*(A21-$L$5),0)-IF($K$10="Y",$L$13*EXP($K$6*$K$9),0))*$L$4 -> 0 | D21: =(MAX(IF($D$1="C",1,-1)*(A21-$M$5),0)-IF($K$10="Y",$M$13*EXP($K$6*$K$9),0))*$M$4 -> 0 | E21: =(MAX(IF($E$1="C",1,-1)*(A21-$N$5),0)-IF($K$10="Y",$N$13*EXP($K$6*$K$9),0))*$N$4 -> 0 | F21: =SUM(B21:E21) -> 23 | G21: =IF(A21<=$K$18,$K$18-A21,IF(A21>$K$19,A21-$K$19,0)) -> 23 | H21: =F21-G21 -> 0 | AL21: =AL20+2 -> 32 | AM21: =MAX(0,(AL21^2)-120) -> 904
A22: =A21+1 -> 68 | B22: =(MAX(IF($B$1="C",1,-1)*(A22-$K$5),0)-IF($K$10="Y",$K$13*EXP($K$6*$K$9),0))*$K$4 -> 22 | C22: =(MAX(IF($C$1="C",1,-1)*(A22-$L$5),0)-IF($K$10="Y",$L$13*EXP($K$6*$K$9),0))*$L$4 -> 0 | D22: =(MAX(IF($D$1="C",1,-1)*(A22-$M$5),0)-IF($K$10="Y",$M$13*EXP($K$6*$K$9),0))*$M$4 -> 0 | E22: =(MAX(IF($E$1="C",1,-1)*(A22-$N$5),0)-IF($K$10="Y",$N$13*EXP($K$6*$K$9),0))*$N$4 -> 0 | F22: =SUM(B22:E22) -> 22 | G22: =IF(A22<=$K$18,$K$18-A22,IF(A22>$K$19,A22-$K$19,0)) -> 22 | H22: =F22-G22 -> 0 | AL22: =AL21+2 -> 34 | AM22: =MAX(0,(AL22^2)-120) -> 1036
A23: =A22+1 -> 69 | B23: =(MAX(IF($B$1="C",1,-1)*(A23-$K$5),0)-IF($K$10="Y",$K$13*EXP($K$6*$K$9),0))*$K$4 -> 21 | C23: =(MAX(IF($C$1="C",1,-1)*(A23-$L$5),0)-IF($K$10="Y",$L$13*EXP($K$6*$K$9),0))*$L$4 -> 0 | D23: =(MAX(IF($D$1="C",1,-1)*(A23-$M$5),0)-IF($K$10="Y",$M$13*EXP($K$6*$K$9),0))*$M$4 -> 0 | E23: =(MAX(IF($E$1="C",1,-1)*(A23-$N$5),0)-IF($K$10="Y",$N$13*EXP($K$6*$K$9),0))*$N$4 -> 0 | F23: =SUM(B23:E23) -> 21 | G23: =IF(A23<=$K$18,$K$18-A23,IF(A23>$K$19,A23-$K$19,0)) -> 21 | H23: =F23-G23 -> 0 | AL23: =AL22+2 -> 36 | AM23: =MAX(0,(AL23^2)-120) -> 1176
A24: =A23+1 -> 70 | B24: =(MAX(IF($B$1="C",1,-1)*(A24-$K$5),0)-IF($K$10="Y",$K$13*EXP($K$6*$K$9),0))*$K$4 -> 20 | C24: =(MAX(IF($C$1="C",1,-1)*(A24-$L$5),0)-IF($K$10="Y",$L$13*EXP($K$6*$K$9),0))*$L$4 -> 0 | D24: =(MAX(IF($D$1="C",1,-1)*(A24-$M$5),0)-IF($K$10="Y",$M$13*EXP($K$6*$K$9),0))*$M$4 -> 0 | E24: =(MAX(IF($E$1="C",1,-1)*(A24-$N$5),0)-IF($K$10="Y",$N$13*EXP($K$6*$K$9),0))*$N$4 -> 0 | F24: =SUM(B24:E24) -> 20 | G24: =IF(A24<=$K$18,$K$18-A24,IF(A24>$K$19,A24-$K$19,0)) -> 20 | H24: =F24-G24 -> 0 | AL24: =AL23+2 -> 38 | AM24: =MAX(0,(AL24^2)-120) -> 1324
A25: =A24+1 -> 71 | B25: =(MAX(IF($B$1="C",1,-1)*(A25-$K$5),0)-IF($K$10="Y",$K$13*EXP($K$6*$K$9),0))*$K$4 -> 19 | C25: =(MAX(IF($C$1="C",1,-1)*(A25-$L$5),0)-IF($K$10="Y",$L$13*EXP($K$6*$K$9),0))*$L$4 -> 0 | D25: =(MAX(IF($D$1="C",1,-1)*(A25-$M$5),0)-IF($K$10="Y",$M$13*EXP($K$6*$K$9),0))*$M$4 -> 0 | E25: =(MAX(IF($E$1="C",1,-1)*(A25-$N$5),0)-IF($K$10="Y",$N$13*EXP($K$6*$K$9),0))*$N$4 -> 0 | F25: =SUM(B25:E25) -> 19 | G25: =IF(A25<=$K$18,$K$18-A25,IF(A25>$K$19,A25-$K$19,0)) -> 19 | H25: =F25-G25 -> 0 | AL25: =AL24+2 -> 40 | AM25: =MAX(0,(AL25^2)-120) -> 1480
A26: =A25+1 -> 72 | B26: =(MAX(IF($B$1="C",1,-1)*(A26-$K$5),0)-IF($K$10="Y",$K$13*EXP($K$6*$K$9),0))*$K$4 -> 18 | C26: =(MAX(IF($C$1="C",1,-1)*(A26-$L$5),0)-IF($K$10="Y",$L$13*EXP($K$6*$K$9),0))*$L$4 -> 0 | D26: =(MAX(IF($D$1="C",1,-1)*(A26-$M$5),0)-IF($K$10="Y",$M$13*EXP($K$6*$K$9),0))*$M$4 -> 0 | E26: =(MAX(IF($E$1="C",1,-1)*(A26-$N$5),0)-IF($K$10="Y",$N$13*EXP($K$6*$K$9),0))*$N$4 -> 0 | F26: =SUM(B26:E26) -> 18 | G26: =IF(A26<=$K$18,$K$18-A26,IF(A26>$K$19,A26-$K$19,0)) -> 18 | H26: =F26-G26 -> 0 | AL26: =AL25+2 -> 42 | AM26: =MAX(0,(AL26^2)-120) -> 1644
A27: =A26+1 -> 73 | B27: =(MAX(IF($B$1="C",1,-1)*(A27-$K$5),0)-IF($K$10="Y",$K$13*EXP($K$6*$K$9),0))*$K$4 -> 17 | C27: =(MAX(IF($C$1="C",1,-1)*(A27-$L$5),0)-IF($K$10="Y",$L$13*EXP($K$6*$K$9),0))*$L$4 -> 0 | D27: =(MAX(IF($D$1="C",1,-1)*(A27-$M$5),0)-IF($K$10="Y",$M$13*EXP($K$6*$K$9),0))*$M$4 -> 0 | E27: =(MAX(IF($E$1="C",1,-1)*(A27-$N$5),0)-IF($K$10="Y",$N$13*EXP($K$6*$K$9),0))*$N$4 -> 0 | F27: =SUM(B27:E27) -> 17 | G27: =IF(A27<=$K$18,$K$18-A27,IF(A27>$K$19,A27-$K$19,0)) -> 17 | H27: =F27-G27 -> 0 | AL27: =AL26+2 -> 44 | AM27: =MAX(0,(AL27^2)-120) -> 1816
A28: =A27+1 -> 74 | B28: =(MAX(IF($B$1="C",1,-1)*(A28-$K$5),0)-IF($K$10="Y",$K$13*EXP($K$6*$K$9),0))*$K$4 -> 16 | C28: =(MAX(IF($C$1="C",1,-1)*(A28-$L$5),0)-IF($K$10="Y",$L$13*EXP($K$6*$K$9),0))*$L$4 -> 0 | D28: =(MAX(IF($D$1="C",1,-1)*(A28-$M$5),0)-IF($K$10="Y",$M$13*EXP($K$6*$K$9),0))*$M$4 -> 0 | E28: =(MAX(IF($E$1="C",1,-1)*(A28-$N$5),0)-IF($K$10="Y",$N$13*EXP($K$6*$K$9),0))*$N$4 -> 0 | F28: =SUM(B28:E28) -> 16 | G28: =IF(A28<=$K$18,$K$18-A28,IF(A28>$K$19,A28-$K$19,0)) -> 16 | H28: =F28-G28 -> 0 | AL28: =AL27+2 -> 46 | AM28: =MAX(0,(AL28^2)-120) -> 1996
A29: =A28+1 -> 75 | B29: =(MAX(IF($B$1="C",1,-1)*(A29-$K$5),0)-IF($K$10="Y",$K$13*EXP($K$6*$K$9),0))*$K$4 -> 15 | C29: =(MAX(IF($C$1="C",1,-1)*(A29-$L$5),0)-IF($K$10="Y",$L$13*EXP($K$6*$K$9),0))*$L$4 -> 0 | D29: =(MAX(IF($D$1="C",1,-1)*(A29-$M$5),0)-IF($K$10="Y",$M$13*EXP($K$6*$K$9),0))*$M$4 -> 0 | E29: =(MAX(IF($E$1="C",1,-1)*(A29-$N$5),0)-IF($K$10="Y",$N$13*EXP($K$6*$K$9),0))*$N$4 -> 0 | F29: =SUM(B29:E29) -> 15 | G29: =IF(A29<=$K$18,$K$18-A29,IF(A29>$K$19,A29-$K$19,0)) -> 15 | H29: =F29-G29 -> 0 | AL29: =AL28+2 -> 48 | AM29: =MAX(0,(AL29^2)-120) -> 2184
A30: =A29+1 -> 76 | B30: =(MAX(IF($B$1="C",1,-1)*(A30-$K$5),0)-IF($K$10="Y",$K$13*EXP($K$6*$K$9),0))*$K$4 -> 14 | C30: =(MAX(IF($C$1="C",1,-1)*(A30-$L$5),0)-IF($K$10="Y",$L$13*EXP($K$6*$K$9),0))*$L$4 -> 0 | D30: =(MAX(IF($D$1="C",1,-1)*(A30-$M$5),0)-IF($K$10="Y",$M$13*EXP($K$6*$K$9),0))*$M$4 -> 0 | E30: =(MAX(IF($E$1="C",1,-1)*(A30-$N$5),0)-IF($K$10="Y",$N$13*EXP($K$6*$K$9),0))*$N$4 -> 0 | F30: =SUM(B30:E30) -> 14 | G30: =IF(A30<=$K$18,$K$18-A30,IF(A30>$K$19,A30-$K$19,0)) -> 14 | H30: =F30-G30 -> 0 | AL30: =AL29+2 -> 50 | AM30: =MAX(0,(AL30^2)-120) -> 2380
A31: =A30+1 -> 77 | B31: =(MAX(IF($B$1="C",1,-1)*(A31-$K$5),0)-IF($K$10="Y",$K$13*EXP($K$6*$K$9),0))*$K$4 -> 13 | C31: =(MAX(IF($C$1="C",1,-1)*(A31-$L$5),0)-IF($K$10="Y",$L$13*EXP($K$6*$K$9),0))*$L$4 -> 0 | D31: =(MAX(IF($D$1="C",1,-1)*(A31-$M$5),0)-IF($K$10="Y",$M$13*EXP($K$6*$K$9),0))*$M$4 -> 0 | E31: =(MAX(IF($E$1="C",1,-1)*(A31-$N$5),0)-IF($K$10="Y",$N$13*EXP($K$6*$K$9),0))*$N$4 -> 0 | F31: =SUM(B31:E31) -> 13 | G31: =IF(A31<=$K$18,$K$18-A31,IF(A31>$K$19,A31-$K$19,0)) -> 13 | H31: =F31-G31 -> 0 | AL31: =AL30+2 -> 52 | AM31: =MAX(0,(AL31^2)-120) -> 2584
A32: =A31+1 -> 78 | B32: =(MAX(IF($B$1="C",1,-1)*(A32-$K$5),0)-IF($K$10="Y",$K$13*EXP($K$6*$K$9),0))*$K$4 -> 12 | C32: =(MAX(IF($C$1="C",1,-1)*(A32-$L$5),0)-IF($K$10="Y",$L$13*EXP($K$6*$K$9),0))*$L$4 -> 0 | D32: =(MAX(IF($D$1="C",1,-1)*(A32-$M$5),0)-IF($K$10="Y",$M$13*EXP($K$6*$K$9),0))*$M$4 -> 0 | E32: =(MAX(IF($E$1="C",1,-1)*(A32-$N$5),0)-IF($K$10="Y",$N$13*EXP($K$6*$K$9),0))*$N$4 -> 0 | F32: =SUM(B32:E32) -> 12 | G32: =IF(A32<=$K$18,$K$18-A32,IF(A32>$K$19,A32-$K$19,0)) -> 12 | H32: =F32-G32 -> 0 | AL32: =AL31+2 -> 54 | AM32: =MAX(0,(AL32^2)-120) -> 2796
... A104: =A103+1 -> 150 | B104: =(MAX(IF($B$1="C",1,-1)*(A104-$K$5),0)-IF($K$10="Y",$K$13*EXP($K$6*$K$9),0))*$K$4 -> 0 | C104: =(MAX(IF($C$1="C",1,-1)*(A104-$L$5),0)-IF($K$10="Y",$L$13*EXP($K$6*$K$9),0))*$L$4 -> 0 | D104: =(MAX(IF($D$1="C",1,-1)*(A104-$M$5),0)-IF($K$10="Y",$M$13*EXP($K$6*$K$9),0))*$M$4 -> 0 | E104: =(MAX(IF($E$1="C",1,-1)*(A104-$N$5),0)-IF($K$10="Y",$N$13*EXP($K$6*$K$9),0))*$N$4 -> 40 | F104: =SUM(B104:E104) -> 40 | G104: =IF(A104<=$K$18,$K$18-A104,IF(A104>$K$19,A104-$K$19,0)) -> 40 | H104: =F104-G104 -> 0 | AL104: =AL103+2 -> 198 | AM104: =MAX(0,(AL104^2)-120) -> 39084
AL105: =AL104+2 -> 200 | AM105: =MAX(0,(AL105^2)-120) -> 39880
AL106: =AL105+2 -> 202 | AM106: =MAX(0,(AL106^2)-120) -> 40684
AL107: =AL106+2 -> 204 | AM107: =MAX(0,(AL107^2)-120) -> 41496
AL108: =AL107+2 -> 206 | AM108: =MAX(0,(AL108^2)-120) -> 42316
AL109: =AL108+2 -> 208 | AM109: =MAX(0,(AL109^2)-120) -> 43144
AL110: =AL109+2 -> 210 | AM110: =MAX(0,(AL110^2)-120) -> 43980
AL111: =AL110+2 -> 212 | AM111: =MAX(0,(AL111^2)-120) -> 44824
AL112: =AL111+2 -> 214 | AM112: =MAX(0,(AL112^2)-120) -> 45676
AL113: =AL112+2 -> 216 | AM113: =MAX(0,(AL113^2)-120) -> 46536
AL114: =AL113+2 -> 218 | AM114: =MAX(0,(AL114^2)-120) -> 47404
AL115: =AL114+2 -> 220 | AM115: =MAX(0,(AL115^2)-120) -> 48280
AL116: =AL115+2 -> 222 | AM116: =MAX(0,(AL116^2)-120) -> 49164
... AL128: =AL127+2 -> 246 | AM128: =MAX(0,(AL128^2)-120) -> 60396

Sheet Question 3c
A1: S0 | B1: 100 | E1: Working | F1: Delta t | G1: =B7/B9 -> 0.0066666667
A2: Put Strike | B2: 90 | F2: u | G2: =EXP(B4*SQRT(G1)) -> 1.0247974
A3: Call Strike | B3: 110 | F3: d | G3: =1/G2 -> 0.97580267
A4: volatility | B4: 0.3 | F4: p | G4: =(EXP((B5-B6)*G1)-G3)/(G2-G3) -> 0.49795906
A5: Risk free | B5: 0.05 | F5: Option Value | G5: =A108 -> 7.6380858
A6: Dividend | B6: 0.02
A7: Choice Time | B7: 0.2
A8: Option Life After Choice | B8: 0.3
A9: n | B9: 30
A14: 0 | B14: Delta t | C14: 2 Delta t | D14: 3 Delta t | E14: 4 Delta t | F14: 5 Delta t | G14: 6 Delta t | H14: 7 Delta t | I14: 8 Delta t | J14: 9 Delta t | K14: 10 Delta t | L14: 11 Delta t | M14: 12 Delta t | N14: 13 Delta t | O14: 14 Delta t | P14: 15 Delta t | Q14: 16 Delta t | R14: 17 Delta t | S14: 18 Delta t | T14: 19 Delta t | U14: 20 Delta t | V14: 21 Delta t | W14: 22 Delta t | X14: 23 Delta t | Y14: 24 Delta t | Z14: 25 Delta t | AA14: 26 Delta t | AB14: 27 Delta t | AC14: 28 Delta t | AD14: 29 Delta t | AE14: 30 Delta t
AE15: =$G$2*AD16 -> 208.51628
AD16: =$G$2*AC17 -> 203.47074
AC17: =$G$2*AB18 -> 198.54729 | AE17: =$G$2*AD18 -> 198.54729
AB18: =$G$2*AA19 -> 193.74298 | AD18: =$G$2*AC19 -> 193.74298
AA19: =$G$2*Z20 -> 189.05491 | AC19: =$G$2*AB20 -> 189.05491 | AE19: =$G$2*AD20 -> 189.05491
Z20: =$G$2*Y21 -> 184.48029 | AB20: =$G$2*AA21 -> 184.48029 | AD20: =$G$2*AC21 -> 184.48029
Y21: =$G$2*X22 -> 180.01636 | AA21: =$G$2*Z22 -> 180.01636 | AC21: =$G$2*AB22 -> 180.01636 | AE21: =$G$2*AD22 -> 180.01636
X22: =$G$2*W23 -> 175.66044 | Z22: =$G$2*Y23 -> 175.66044 | AB22: =$G$2*AA23 -> 175.66044 | AD22: =$G$2*AC23 -> 175.66044
W23: =$G$2*V24 -> 171.40993 | Y23: =$G$2*X24 -> 171.40993 | AA23: =$G$2*Z24 -> 171.40993 | AC23: =$G$2*AB24 -> 171.40993 | AE23: =$G$2*AD24 -> 171.40993
V24: =$G$2*U25 -> 167.26227 | X24: =$G$2*W25 -> 167.26227 | Z24: =$G$2*Y25 -> 167.26227 | AB24: =$G$2*AA25 -> 167.26227 | AD24: =$G$2*AC25 -> 167.26227
U25: =$G$2*T26 -> 163.21496 | W25: =$G$2*V26 -> 163.21496 | Y25: =$G$2*X26 -> 163.21496 | AA25: =$G$2*Z26 -> 163.21496 | AC25: =$G$2*AB26 -> 163.21496 | AE25: =$G$2*AD26 -> 163.21496
T26: =$G$2*S27 -> 159.2656 | V26: =$G$2*U27 -> 159.2656 | X26: =$G$2*W27 -> 159.2656 | Z26: =$G$2*Y27 -> 159.2656 | AB26: =$G$2*AA27 -> 159.2656 | AD26: =$G$2*AC27 -> 159.2656
S27: =$G$2*R28 -> 155.4118 | U27: =$G$2*T28 -> 155.4118 | W27: =$G$2*V28 -> 155.4118 | Y27: =$G$2*X28 -> 155.4118 | AA27: =$G$2*Z28 -> 155.4118 | AC27: =$G$2*AB28 -> 155.4118 | AE27: =$G$2*AD28 -> 155.4118
R28: =$G$2*Q29 -> 151.65124 | T28: =$G$2*S29 -> 151.65124 | V28: =$G$2*U29 -> 151.65124 | X28: =$G$2*W29 -> 151.65124 | Z28: =$G$2*Y29 -> 151.65124 | AB28: =$G$2*AA29 -> 151.65124 | AD28: =$G$2*AC29 -> 151.65124
Q29: =$G$2*P30 -> 147.98169 | S29: =$G$2*R30 -> 147.98169 | U29: =$G$2*T30 -> 147.98169 | W29: =$G$2*V30 -> 147.98169 | Y29: =$G$2*X30 -> 147.98169 | AA29: =$G$2*Z30 -> 147.98169 | AC29: =$G$2*AB30 -> 147.98169 | AE29: =$G$2*AD30 -> 147.98169
P30: =$G$2*O31 -> 144.40093 | R30: =$G$2*Q31 -> 144.40093 | T30: =$G$2*S31 -> 144.40093 | V30: =$G$2*U31 -> 144.40093 | X30: =$G$2*W31 -> 144.40093 | Z30: =$G$2*Y31 -> 144.40093 | AB30: =$G$2*AA31 -> 144.40093 | AD30: =$G$2*AC31 -> 144.40093
O31: =$G$2*N32 -> 140.90681 | Q31: =$G$2*P32 -> 140.90681 | S31: =$G$2*R32 -> 140.90681 | U31: =$G$2*T32 -> 140.90681 | W31: =$G$2*V32 -> 140.90681 | Y31: =$G$2*X32 -> 140.90681 | AA31: =$G$2*Z32 -> 140.90681 | AC31: =$G$2*AB32 -> 140.90681 | AE31: =$G$2*AD32 -> 140.90681
N32: =$G$2*M33 -> 137.49724 | P32: =$G$2*O33 -> 137.49724 | R32: =$G$2*Q33 -> 137.49724 | T32: =$G$2*S33 -> 137.49724 | V32: =$G$2*U33 -> 137.49724 | X32: =$G$2*W33 -> 137.49724 | Z32: =$G$2*Y33 -> 137.49724 | AB32: =$G$2*AA33 -> 137.49724 | AD32: =$G$2*AC33 -> 137.49724
M33: =$G$2*L34 -> 134.17017 | O33: =$G$2*N34 -> 134.17017 | Q33: =$G$2*P34 -> 134.17017 | S33: =$G$2*R34 -> 134.17017 | U33: =$G$2*T34 -> 134.17017 | W33: =$G$2*V34 -> 134.17017 | Y33: =$G$2*X34 -> 134.17017 | AA33: =$G$2*Z34 -> 134.17017 | AC33: =$G$2*AB34 -> 134.17017 | AE33: =$G$2*AD34 -> 134.17017
L34: =$G$2*K35 -> 130.92361 | N34: =$G$2*M35 -> 130.92361 | P34: =$G$2*O35 -> 130.92361 | R34: =$G$2*Q35 -> 130.92361 | T34: =$G$2*S35 -> 130.92361 | V34: =$G$2*U35 -> 130.92361 | X34: =$G$2*W35 -> 130.92361 | Z34: =$G$2*Y35 -> 130.92361 | AB34: =$G$2*AA35 -> 130.92361 | AD34: =$G$2*AC35 -> 130.92361
K35: =$G$2*J36 -> 127.75561 | M35: =$G$2*L36 -> 127.75561 | O35: =$G$2*N36 -> 127.75561 | Q35: =$G$2*P36 -> 127.75561 | S35: =$G$2*R36 -> 127.75561 | U35: =$G$2*T36 -> 127.75561 | W35: =$G$2*V36 -> 127.75561 | Y35: =$G$2*X36 -> 127.75561 | AA35: =$G$2*Z36 -> 127.75561 | AC35: =$G$2*AB36 -> 127.75561 | AE35: =$G$2*AD36 -> 127.75561
J36: =$G$2*I37 -> 124.66427 | L36: =$G$2*K37 -> 124.66427 | N36: =$G$2*M37 -> 124.66427 | P36: =$G$2*O37 -> 124.66427 | R36: =$G$2*Q37 -> 124.66427 | T36: =$G$2*S37 -> 124.66427 | V36: =$G$2*U37 -> 124.66427 | X36: =$G$2*W37 -> 124.66427 | Z36: =$G$2*Y37 -> 124.66427 | AB36: =$G$2*AA37 -> 124.66427 | AD36: =$G$2*AC37 -> 124.66427
I37: =$G$2*H38 -> 121.64772 | K37: =$G$2*J38 -> 121.64772 | M37: =$G$2*L38 -> 121.64772 | O37: =$G$2*N38 -> 121.64772 | Q37: =$G$2*P38 -> 121.64772 | S37: =$G$2*R38 -> 121.64772 | U37: =$G$2*T38 -> 121.64772 | W37: =$G$2*V38 -> 121.64772 | Y37: =$G$2*X38 -> 121.64772 | AA37: =$G$2*Z38 -> 121.64772 | AC37: =$G$2*AB38 -> 121.64772 | AE37: =$G$2*AD38 -> 121.64772
H38: =$G$2*G39 -> 118.70417 | J38: =$G$2*I39 -> 118.70417 | L38: =$G$2*K39 -> 118.70417 | N38: =$G$2*M39 -> 118.70417 | P38: =$G$2*O39 -> 118.70417 | R38: =$G$2*Q39 -> 118.70417 | T38: =$G$2*S39 -> 118.70417 | V38: =$G$2*U39 -> 118.70417 | X38: =$G$2*W39 -> 118.70417 | Z38: =$G$2*Y39 -> 118.70417 | AB38: =$G$2*AA39 -> 118.70417 | AD38: =$G$2*AC39 -> 118.70417
G39: =$G$2*F40 -> 115.83185 | I39: =$G$2*H40 -> 115.83185 | K39: =$G$2*J40 -> 115.83185 | M39: =$G$2*L40 -> 115.83185 | O39: =$G$2*N40 -> 115.83185 | Q39: =$G$2*P40 -> 115.83185 | S39: =$G$2*R40 -> 115.83185 | U39: =$G$2*T40 -> 115.83185 | W39: =$G$2*V40 -> 115.83185 | Y39: =$G$2*X40 -> 115.83185 | AA39: =$G$2*Z40 -> 115.83185 | AC39: =$G$2*AB40 -> 115.83185 | AE39: =$G$2*AD40 -> 115.83185
F40: =$G$2*E41 -> 113.02903 | H40: =$G$2*G41 -> 113.02903 | J40: =$G$2*I41 -> 113.02903 | L40: =$G$2*K41 -> 113.02903 | N40: =$G$2*M41 -> 113.02903 | P40: =$G$2*O41 -> 113.02903 | R40: =$G$2*Q41 -> 113.02903 | T40: =$G$2*S41 -> 113.02903 | V40: =$G$2*U41 -> 113.02903 | X40: =$G$2*W41 -> 113.02903 | Z40: =$G$2*Y41 -> 113.02903 | AB40: =$G$2*AA41 -> 113.02903 | AD40: =$G$2*AC41 -> 113.02903
E41: =$G$2*D42 -> 110.29403 | G41: =$G$2*F42 -> 110.29403 | I41: =$G$2*H42 -> 110.29403 | K41: =$G$2*J42 -> 110.29403 | M41: =$G$2*L42 -> 110.29403 | O41: =$G$2*N42 -> 110.29403 | Q41: =$G$2*P42 -> 110.29403 | S41: =$G$2*R42 -> 110.29403 | U41: =$G$2*T42 -> 110.29403 | W41: =$G$2*V42 -> 110.29403 | Y41: =$G$2*X42 -> 110.29403 | AA41: =$G$2*Z42 -> 110.29403 | AC41: =$G$2*AB42 -> 110.29403 | AE41: =$G$2*AD42 -> 110.29403
D42: =$G$2*C43 -> 107.62521 | F42: =$G$2*E43 -> 107.62521 | H42: =$G$2*G43 -> 107.62521 | J42: =$G$2*I43 -> 107.62521 | L42: =$G$2*K43 -> 107.62521 | N42: =$G$2*M43 -> 107.62521 | P42: =$G$2*O43 -> 107.62521 | R42: =$G$2*Q43 -> 107.62521 | T42: =$G$2*S43 -> 107.62521 | V42: =$G$2*U43 -> 107.62521 | X42: =$G$2*W43 -> 107.62521 | Z42: =$G$2*Y43 -> 107.62521 | AB42: =$G$2*AA43 -> 107.62521 | AD42: =$G$2*AC43 -> 107.62521
C43: =$G$2*B44 -> 105.02096 | E43: =$G$2*D44 -> 105.02096 | G43: =$G$2*F44 -> 105.02096 | I43: =$G$2*H44 -> 105.02096 | K43: =$G$2*J44 -> 105.02096 | M43: =$G$2*L44 -> 105.02096 | O43: =$G$2*N44 -> 105.02096 | Q43: =$G$2*P44 -> 105.02096 | S43: =$G$2*R44 -> 105.02096 | U43: =$G$2*T44 -> 105.02096 | W43: =$G$2*V44 -> 105.02096 | Y43: =$G$2*X44 -> 105.02096 | AA43: =$G$2*Z44 -> 105.02096 | AC43: =$G$2*AB44 -> 105.02096 | AE43: =$G$2*AD44 -> 105.02096
B44: =$G$2*A45 -> 102.47974 | D44: =$G$2*C45 -> 102.47974 | F44: =$G$2*E45 -> 102.47974 | H44: =$G$2*G45 -> 102.47974 | J44: =$G$2*I45 -> 102.47974 | L44: =$G$2*K45 -> 102.47974 | N44: =$G$2*M45 -> 102.47974 | P44: =$G$2*O45 -> 102.47974 | R44: =$G$2*Q45 -> 102.47974 | T44: =$G$2*S45 -> 102.47974 | V44: =$G$2*U45 -> 102.47974 | X44: =$G$2*W45 -> 102.47974 | Z44: =$G$2*Y45 -> 102.47974 | AB44: =$G$2*AA45 -> 102.47974 | AD44: =$G$2*AC45 -> 102.47974
A45: =B1 -> 100 | C45: =$G$2*B46 -> 100 | E45: =$G$2*D46 -> 100 | G45: =$G$2*F46 -> 100 | I45: =$G$2*H46 -> 100 | K45: =$G$2*J46 -> 100 | M45: =$G$2*L46 -> 100 | O45: =$G$2*N46 -> 100 | Q45: =$G$2*P46 -> 100 | S45: =$G$2*R46 -> 100 | U45: =$G$2*T46 -> 100 | W45: =$G$2*V46 -> 100 | Y45: =$G$2*X46 -> 100 | AA45: =$G$2*Z46 -> 100 | AC45: =$G$2*AB46 -> 100 | AE45: =$G$2*AD46 -> 100
B46: =A45*$G$3 -> 97.580267 | D46: =$G$2*C47 -> 97.580267 | F46: =$G$2*E47 -> 97.580267 | H46: =$G$2*G47 -> 97.580267 | J46: =$G$2*I47 -> 97.580267 | L46: =$G$2*K47 -> 97.580267 | N46: =$G$2*M47 -> 97.580267 | P46: =$G$2*O47 -> 97.580267 | R46: =$G$2*Q47 -> 97.580267 | T46: =$G$2*S47 -> 97.580267 | V46: =$G$2*U47 -> 97.580267 | X46: =$G$2*W47 -> 97.580267 | Z46: =$G$2*Y47 -> 97.580267 | AB46: =$G$2*AA47 -> 97.580267 | AD46: =$G$2*AC47 -> 97.580267
C47: =B46*$G$3 -> 95.219085 | E47: =$G$2*D48 -> 95.219085 | G47: =$G$2*F48 -> 95.219085 | I47: =$G$2*H48 -> 95.219085 | K47: =$G$2*J48 -> 95.219085 | M47: =$G$2*L48 -> 95.219085 | O47: =$G$2*N48 -> 95.219085 | Q47: =$G$2*P48 -> 95.219085 | S47: =$G$2*R48 -> 95.219085 | U47: =$G$2*T48 -> 95.219085 | W47: =$G$2*V48 -> 95.219085 | Y47: =$G$2*X48 -> 95.219085 | AA47: =$G$2*Z48 -> 95.219085 | AC47: =$G$2*AB48 -> 95.219085 | AE47: =$G$2*AD48 -> 95.219085
D48: =C47*$G$3 -> 92.915037 | F48: =$G$2*E49 -> 92.915037 | H48: =$G$2*G49 -> 92.915037 | J48: =$G$2*I49 -> 92.915037 | L48: =$G$2*K49 -> 92.915037 | N48: =$G$2*M49 -> 92.915037 | P48: =$G$2*O49 -> 92.915037 | R48: =$G$2*Q49 -> 92.915037 | T48: =$G$2*S49 -> 92.915037 | V48: =$G$2*U49 -> 92.915037 | X48: =$G$2*W49 -> 92.915037 | Z48: =$G$2*Y49 -> 92.915037 | AB48: =$G$2*AA49 -> 92.915037 | AD48: =$G$2*AC49 -> 92.915037
E49: =D48*$G$3 -> 90.666741 | G49: =$G$2*F50 -> 90.666741 | I49: =$G$2*H50 -> 90.666741 | K49: =$G$2*J50 -> 90.666741 | M49: =$G$2*L50 -> 90.666741 | O49: =$G$2*N50 -> 90.666741 | Q49: =$G$2*P50 -> 90.666741 | S49: =$G$2*R50 -> 90.666741 | U49: =$G$2*T50 -> 90.666741 | W49: =$G$2*V50 -> 90.666741 | Y49: =$G$2*X50 -> 90.666741 | AA49: =$G$2*Z50 -> 90.666741 | AC49: =$G$2*AB50 -> 90.666741 | AE49: =$G$2*AD50 -> 90.666741
F50: =E49*$G$3 -> 88.472848 | H50: =$G$2*G51 -> 88.472848 | J50: =$G$2*I51 -> 88.472848 | L50: =$G$2*K51 -> 88.472848 | N50: =$G$2*M51 -> 88.472848 | P50: =$G$2*O51 -> 88.472848 | R50: =$G$2*Q51 -> 88.472848 | T50: =$G$2*S51 -> 88.472848 | V50: =$G$2*U51 -> 88.472848 | X50: =$G$2*W51 -> 88.472848 | Z50: =$G$2*Y51 -> 88.472848 | AB50: =$G$2*AA51 -> 88.472848 | AD50: =$G$2*AC51 -> 88.472848
G51: =F50*$G$3 -> 86.332041 | I51: =$G$2*H52 -> 86.332041 | K51: =$G$2*J52 -> 86.332041 | M51: =$G$2*L52 -> 86.332041 | O51: =$G$2*N52 -> 86.332041 | Q51: =$G$2*P52 -> 86.332041 | S51: =$G$2*R52 -> 86.332041 | U51: =$G$2*T52 -> 86.332041 | W51: =$G$2*V52 -> 86.332041 | Y51: =$G$2*X52 -> 86.332041 | AA51: =$G$2*Z52 -> 86.332041 | AC51: =$G$2*AB52 -> 86.332041 | AE51: =$G$2*AD52 -> 86.332041
H52: =G51*$G$3 -> 84.243036 | J52: =$G$2*I53 -> 84.243036 | L52: =$G$2*K53 -> 84.243036 | N52: =$G$2*M53 -> 84.243036 | P52: =$G$2*O53 -> 84.243036 | R52: =$G$2*Q53 -> 84.243036 | T52: =$G$2*S53 -> 84.243036 | V52: =$G$2*U53 -> 84.243036 | X52: =$G$2*W53 -> 84.243036 | Z52: =$G$2*Y53 -> 84.243036 | AB52: =$G$2*AA53 -> 84.243036 | AD52: =$G$2*AC53 -> 84.243036
I53: =H52*$G$3 -> 82.204579 | K53: =$G$2*J54 -> 82.204579 | M53: =$G$2*L54 -> 82.204579 | O53: =$G$2*N54 -> 82.204579 | Q53: =$G$2*P54 -> 82.204579 | S53: =$G$2*R54 -> 82.204579 | U53: =$G$2*T54 -> 82.204579 | W53: =$G$2*V54 -> 82.204579 | Y53: =$G$2*X54 -> 82.204579 | AA53: =$G$2*Z54 -> 82.204579 | AC53: =$G$2*AB54 -> 82.204579 | AE53: =$G$2*AD54 -> 82.204579
J54: =I53*$G$3 -> 80.215448 | L54: =$G$2*K55 -> 80.215448 | N54: =$G$2*M55 -> 80.215448 | P54: =$G$2*O55 -> 80.215448 | R54: =$G$2*Q55 -> 80.215448 | T54: =$G$2*S55 -> 80.215448 | V54: =$G$2*U55 -> 80.215448 | X54: =$G$2*W55 -> 80.215448 | Z54: =$G$2*Y55 -> 80.215448 | AB54: =$G$2*AA55 -> 80.215448 | AD54: =$G$2*AC55 -> 80.215448
K55: =J54*$G$3 -> 78.274448 | M55: =$G$2*L56 -> 78.274448 | O55: =$G$2*N56 -> 78.274448 | Q55: =$G$2*P56 -> 78.274448 | S55: =$G$2*R56 -> 78.274448 | U55: =$G$2*T56 -> 78.274448 | W55: =$G$2*V56 -> 78.274448 | Y55: =$G$2*X56 -> 78.274448 | AA55: =$G$2*Z56 -> 78.274448 | AC55: =$G$2*AB56 -> 78.274448 | AE55: =$G$2*AD56 -> 78.274448
L56: =K55*$G$3 -> 76.380415 | N56: =$G$2*M57 -> 76.380415 | P56: =$G$2*O57 -> 76.380415 | R56: =$G$2*Q57 -> 76.380415 | T56: =$G$2*S57 -> 76.380415 | V56: =$G$2*U57 -> 76.380415 | X56: =$G$2*W57 -> 76.380415 | Z56: =$G$2*Y57 -> 76.380415 | AB56: =$G$2*AA57 -> 76.380415 | AD56: =$G$2*AC57 -> 76.380415
M57: =L56*$G$3 -> 74.532213 | O57: =$G$2*N58 -> 74.532213 | Q57: =$G$2*P58 -> 74.532213 | S57: =$G$2*R58 -> 74.532213 | U57: =$G$2*T58 -> 74.532213 | W57: =$G$2*V58 -> 74.532213 | Y57: =$G$2*X58 -> 74.532213 | AA57: =$G$2*Z58 -> 74.532213 | AC57: =$G$2*AB58 -> 74.532213 | AE57: =$G$2*AD58 -> 74.532213
N58: =M57*$G$3 -> 72.728732 | P58: =$G$2*O59 -> 72.728732 | R58: =$G$2*Q59 -> 72.728732 | T58: =$G$2*S59 -> 72.728732 | V58: =$G$2*U59 -> 72.728732 | X58: =$G$2*W59 -> 72.728732 | Z58: =$G$2*Y59 -> 72.728732 | AB58: =$G$2*AA59 -> 72.728732 | AD58: =$G$2*AC59 -> 72.728732
O59: =N58*$G$3 -> 70.968891 | Q59: =$G$2*P60 -> 70.968891 | S59: =$G$2*R60 -> 70.968891 | U59: =$G$2*T60 -> 70.968891 | W59: =$G$2*V60 -> 70.968891 | Y59: =$G$2*X60 -> 70.968891 | AA59: =$G$2*Z60 -> 70.968891 | AC59: =$G$2*AB60 -> 70.968891 | AE59: =$G$2*AD60 -> 70.968891
P60: =O59*$G$3 -> 69.251633 | R60: =$G$2*Q61 -> 69.251633 | T60: =$G$2*S61 -> 69.251633 | V60: =$G$2*U61 -> 69.251633 | X60: =$G$2*W61 -> 69.251633 | Z60: =$G$2*Y61 -> 69.251633 | AB60: =$G$2*AA61 -> 69.251633 | AD60: =$G$2*AC61 -> 69.251633
Q61: =P60*$G$3 -> 67.575928 | S61: =$G$2*R62 -> 67.575928 | U61: =$G$2*T62 -> 67.575928 | W61: =$G$2*V62 -> 67.575928 | Y61: =$G$2*X62 -> 67.575928 | AA61: =$G$2*Z62 -> 67.575928 | AC61: =$G$2*AB62 -> 67.575928 | AE61: =$G$2*AD62 -> 67.575928
R62: =Q61*$G$3 -> 65.940771 | T62: =$G$2*S63 -> 65.940771 | V62: =$G$2*U63 -> 65.940771 | X62: =$G$2*W63 -> 65.940771 | Z62: =$G$2*Y63 -> 65.940771 | AB62: =$G$2*AA63 -> 65.940771 | AD62: =$G$2*AC63 -> 65.940771
S63: =R62*$G$3 -> 64.34518 | U63: =$G$2*T64 -> 64.34518 | W63: =$G$2*V64 -> 64.34518 | Y63: =$G$2*X64 -> 64.34518 | AA63: =$G$2*Z64 -> 64.34518 | AC63: =$G$2*AB64 -> 64.34518 | AE63: =$G$2*AD64 -> 64.34518
T64: =S63*$G$3 -> 62.788199 | V64: =$G$2*U65 -> 62.788199 | X64: =$G$2*W65 -> 62.788199 | Z64: =$G$2*Y65 -> 62.788199 | AB64: =$G$2*AA65 -> 62.788199 | AD64: =$G$2*AC65 -> 62.788199
U65: =T64*$G$3 -> 61.268892 | W65: =$G$2*V66 -> 61.268892 | Y65: =$G$2*X66 -> 61.268892 | AA65: =$G$2*Z66 -> 61.268892 | AC65: =$G$2*AB66 -> 61.268892 | AE65: =$G$2*AD66 -> 61.268892
V66: =U65*$G$3 -> 59.786348 | X66: =$G$2*W67 -> 59.786348 | Z66: =$G$2*Y67 -> 59.786348 | AB66: =$G$2*AA67 -> 59.786348 | AD66: =$G$2*AC67 -> 59.786348
W67: =V66*$G$3 -> 58.339678 | Y67: =$G$2*X68 -> 58.339678 | AA67: =$G$2*Z68 -> 58.339678 | AC67: =$G$2*AB68 -> 58.339678 | AE67: =$G$2*AD68 -> 58.339678
X68: =W67*$G$3 -> 56.928013 | Z68: =$G$2*Y69 -> 56.928013 | AB68: =$G$2*AA69 -> 56.928013 | AD68: =$G$2*AC69 -> 56.928013
Y69: =X68*$G$3 -> 55.550507 | AA69: =$G$2*Z70 -> 55.550507 | AC69: =$G$2*AB70 -> 55.550507 | AE69: =$G$2*AD70 -> 55.550507
Z70: =Y69*$G$3 -> 54.206333 | AB70: =$G$2*AA71 -> 54.206333 | AD70: =$G$2*AC71 -> 54.206333
AA71: =Z70*$G$3 -> 52.894685 | AC71: =$G$2*AB72 -> 52.894685 | AE71: =$G$2*AD72 -> 52.894685
AB72: =AA71*$G$3 -> 51.614774 | AD72: =$G$2*AC73 -> 51.614774
AC73: =AB72*$G$3 -> 50.365834 | AE73: =$G$2*AD74 -> 50.365834
AD74: =AC73*$G$3 -> 49.147116
AE75: =AD74*$G$3 -> 47.957887
AM76: Call | AP76: put
AF77: Stock Price | AG77: Strike (call) | AH77: Strike (put) | AI77: Risk Free | AJ77: Dividend | AK77: Volatility | AL77: Option Life | AM77: d1 | AN77: d2 | AO77: premium | AP77: d1 | AQ77: d2 | AR77: premium
AE78: =MAX(AO78,AR78) -> 98.906834 | AF78: =AE15 -> 208.51628 | AG78: =$B$3 -> 110 | AH78: =$B$2 -> 90 | AI78: =$B$5 -> 0.05 | AJ78: =$B$6 -> 0.02 | AK78: =$B$4 -> 0.3 | AL78: =$B$8 -> 0.3 | AM78: =(LN(AF78/AG78)+((AI78-AJ78+(0.5*AK78*AK78))*AL78))/(AK78*SQRT(AL78)) -> 4.0290273 | AN78: =AM78-(AK78*SQRT(AL78)) -> 3.8647105 | AO78: =(AF78*EXP(-AJ78*AL78)*NORMSDIST(AM78))-(AG78*EXP(-AI78*AL78)*NORMSDIST(AN78)) -> 98.906834 | AP78: =(LN(AF78/AH78)+((AI78-AJ78+(0.5*AK78*AK78))*AL78))/(AK78*SQRT(AL78)) -> 5.2502703 | AQ78: =AP78-(AK78*SQRT(AL78)) -> 5.0859535 | AR78: =-(AF78*EXP(-AJ78*AL78)*NORMSDIST(-AP78))+(AH78*EXP(-AI78*AL78)*NORMSDIST(-AQ78)) -> 4.7559432e-07
AD79: =(($G$4*AE78)+((1-$G$4)*AE80))*EXP(-$B$5*$G$1) -> 93.900903
AC80: =(($G$4*AD79)+((1-$G$4)*AD81))*EXP(-$B$5*$G$1) -> 89.017912 | AE80: =MAX(AO80,AR80) -> 88.998028 | AF80: =AE17 -> 198.54729 | AG80: =$B$3 -> 110 | AH80: =$B$2 -> 90 | AI80: =$B$5 -> 0.05 | AJ80: =$B$6 -> 0.02 | AK80: =$B$4 -> 0.3 | AL80: =$B$8 -> 0.3 | AM80: =(LN(AF80/AG80)+((AI80-AJ80+(0.5*AK80*AK80))*AL80))/(AK80*SQRT(AL80)) -> 3.7308849 | AN80: =AM80-(AK80*SQRT(AL80)) -> 3.5665681 | AO80: =(AF80*EXP(-AJ80*AL80)*NORMSDIST(AM80))-(AG80*EXP(-AI80*AL80)*NORMSDIST(AN80)) -> 88.998028 | AP80: =(LN(AF80/AH80)+((AI80-AJ80+(0.5*AK80*AK80))*AL80))/(AK80*SQRT(AL80)) -> 4.9521279 | AQ80: =AP80-(AK80*SQRT(AL80)) -> 4.7878111 | AR80: =-(AF80*EXP(-AJ80*AL80)*NORMSDIST(-AP80))+(AH80*EXP(-AI80*AL80)*NORMSDIST(-AQ80)) -> 2.3077607e-06
AB81: =(($G$4*AC80)+((1-$G$4)*AC82))*EXP(-$B$5*$G$1) -> 84.255126 | AD81: =(($G$4*AE80)+((1-$G$4)*AE82))*EXP(-$B$5*$G$1) -> 84.233737
AA82: =(($G$4*AB81)+((1-$G$4)*AB83))*EXP(-$B$5*$G$1) -> 79.610049 | AC82: =(($G$4*AD81)+((1-$G$4)*AD83))*EXP(-$B$5*$G$1) -> 79.587016 | AE82: =MAX(AO82,AR82) -> 79.564119 | AF82: =AE19 -> 189.05491 | AG82: =$B$3 -> 110 | AH82: =$B$2 -> 90 | AI82: =$B$5 -> 0.05 | AJ82: =$B$6 -> 0.02 | AK82: =$B$4 -> 0.3 | AL82: =$B$8 -> 0.3 | AM82: =(LN(AF82/AG82)+((AI82-AJ82+(0.5*AK82*AK82))*AL82))/(AK82*SQRT(AL82)) -> 3.4327425 | AN82: =AM82-(AK82*SQRT(AL82)) -> 3.2684258 | AO82: =(AF82*EXP(-AJ82*AL82)*NORMSDIST(AM82))-(AG82*EXP(-AI82*AL82)*NORMSDIST(AN82)) -> 79.564119 | AP82: =(LN(AF82/AH82)+((AI82-AJ82+(0.5*AK82*AK82))*AL82))/(AK82*SQRT(AL82)) -> 4.6539855 | AQ82: =AP82-(AK82*SQRT(AL82)) -> 4.4896687 | AR82: =-(AF82*EXP(-AJ82*AL82)*NORMSDIST(-AP82))+(AH82*EXP(-AI82*AL82)*NORMSDIST(-AQ82)) -> 1.0302814e-05
Z83: =(($G$4*AA82)+((1-$G$4)*AA84))*EXP(-$B$5*$G$1) -> 75.080507 | AB83: =(($G$4*AC82)+((1-$G$4)*AC84))*EXP(-$B$5*$G$1) -> 75.055606 | AD83: =(($G$4*AE82)+((1-$G$4)*AE84))*EXP(-$B$5*$G$1) -> 75.030926
Y84: =(($G$4*Z83)+((1-$G$4)*Z85))*EXP(-$B$5*$G$1) -> 70.664751 | AA84: =(($G$4*AB83)+((1-$G$4)*AB85))*EXP(-$B$5*$G$1) -> 70.637652 | AC84: =(($G$4*AD83)+((1-$G$4)*AD85))*EXP(-$B$5*$G$1) -> 70.610881 | AE84: =MAX(AO84,AR84) -> 70.584416 | AF84: =AE21 -> 180.01636 | AG84: =$B$3 -> 110 | AH84: =$B$2 -> 90 | AI84: =$B$5 -> 0.05 | AJ84: =$B$6 -> 0.02 | AK84: =$B$4 -> 0.3 | AL84: =$B$8 -> 0.3 | AM84: =(LN(AF84/AG84)+((AI84-AJ84+(0.5*AK84*AK84))*AL84))/(AK84*SQRT(AL84)) -> 3.1346001 | AN84: =AM84-(AK84*SQRT(AL84)) -> 2.9702834 | AO84: =(AF84*EXP(-AJ84*AL84)*NORMSDIST(AM84))-(AG84*EXP(-AI84*AL84)*NORMSDIST(AN84)) -> 70.584416 | AP84: =(LN(AF84/AH84)+((AI84-AJ84+(0.5*AK84*AK84))*AL84))/(AK84*SQRT(AL84)) -> 4.3558431 | AQ84: =AP84-(AK84*SQRT(AL84)) -> 4.1915263 | AR84: =-(AF84*EXP(-AJ84*AL84)*NORMSDIST(-AP84))+(AH84*EXP(-AI84*AL84)*NORMSDIST(-AQ84)) -> 4.2341959e-05
X85: =(($G$4*Y84)+((1-$G$4)*Y86))*EXP(-$B$5*$G$1) -> 66.361579 | Z85: =(($G$4*AA84)+((1-$G$4)*AA86))*EXP(-$B$5*$G$1) -> 66.331824 | AB85: =(($G$4*AC84)+((1-$G$4)*AC86))*EXP(-$B$5*$G$1) -> 66.302526 | AD85: =(($G$4*AE84)+((1-$G$4)*AE86))*EXP(-$B$5*$G$1) -> 66.273664
W86: =(($G$4*X85)+((1-$G$4)*X87))*EXP(-$B$5*$G$1) -> 62.17047 | Y86: =(($G$4*Z85)+((1-$G$4)*Z87))*EXP(-$B$5*$G$1) -> 62.137462 | AA86: =(($G$4*AB85)+((1-$G$4)*AB87))*EXP(-$B$5*$G$1) -> 62.105054 | AC86: =(($G$4*AD85)+((1-$G$4)*AD87))*EXP(-$B$5*$G$1) -> 62.073229 | AE86: =MAX(AO86,AR86) -> 62.041971 | AF86: =AE23 -> 171.40993 | AG86: =$B$3 -> 110 | AH86: =$B$2 -> 90 | AI86: =$B$5 -> 0.05 | AJ86: =$B$6 -> 0.02 | AK86: =$B$4 -> 0.3 | AL86: =$B$8 -> 0.3 | AM86: =(LN(AF86/AG86)+((AI86-AJ86+(0.5*AK86*AK86))*AL86))/(AK86*SQRT(AL86)) -> 2.8364577 | AN86: =AM86-(AK86*SQRT(AL86)) -> 2.672141 | AO86: =(AF86*EXP(-AJ86*AL86)*NORMSDIST(AM86))-(AG86*EXP(-AI86*AL86)*NORMSDIST(AN86)) -> 62.041971 | AP86: =(LN(AF86/AH86)+((AI86-AJ86+(0.5*AK86*AK86))*AL86))/(AK86*SQRT(AL86)) -> 4.0577007 | AQ86: =AP86-(AK86*SQRT(AL86)) -> 3.8933839 | AR86: =-(AF86*EXP(-AJ86*AL86)*NORMSDIST(-AP86))+(AH86*EXP(-AI86*AL86)*NORMSDIST(-AQ86)) -> 0.00016029075
V87: =(($G$4*W86)+((1-$G$4)*W88))*EXP(-$B$5*$G$1) -> 58.091722 | X87: =(($G$4*Y86)+((1-$G$4)*Y88))*EXP(-$B$5*$G$1) -> 58.054723 | Z87: =(($G$4*AA86)+((1-$G$4)*AA88))*EXP(-$B$5*$G$1) -> 58.018467 | AB87: =(($G$4*AC86)+((1-$G$4)*AC88))*EXP(-$B$5*$G$1) -> 57.982951 | AD87: =(($G$4*AE86)+((1-$G$4)*AE88))*EXP(-$B$5*$G$1) -> 57.948168
U88: =(($G$4*V87)+((1-$G$4)*V89))*EXP(-$B$5*$G$1) -> 54.12657 | W88: =(($G$4*X87)+((1-$G$4)*X89))*EXP(-$B$5*$G$1) -> 54.084712 | Y88: =(($G$4*Z87)+((1-$G$4)*Z89))*EXP(-$B$5*$G$1) -> 54.04373 | AA88: =(($G$4*AB87)+((1-$G$4)*AB89))*EXP(-$B$5*$G$1) -> 54.003634 | AC88: =(($G$4*AD87)+((1-$G$4)*AD89))*EXP(-$B$5*$G$1) -> 53.964433 | AE88: =MAX(AO88,AR88) -> 53.926131 | AF88: =AE25 -> 163.21496 | AG88: =$B$3 -> 110 | AH88: =$B$2 -> 90 | AI88: =$B$5 -> 0.05 | AJ88: =$B$6 -> 0.02 | AK88: =$B$4 -> 0.3 | AL88: =$B$8 -> 0.3 | AM88: =(LN(AF88/AG88)+((AI88-AJ88+(0.5*AK88*AK88))*AL88))/(AK88*SQRT(AL88)) -> 2.5383153 | AN88: =AM88-(AK88*SQRT(AL88)) -> 2.3739986 | AO88: =(AF88*EXP(-AJ88*AL88)*NORMSDIST(AM88))-(AG88*EXP(-AI88*AL88)*NORMSDIST(AN88)) -> 53.926131 | AP88: =(LN(AF88/AH88)+((AI88-AJ88+(0.5*AK88*AK88))*AL88))/(AK88*SQRT(AL88)) -> 3.7595583 | AQ88: =AP88-(AK88*SQRT(AL88)) -> 3.5952415 | AR88: =-(AF88*EXP(-AJ88*AL88)*NORMSDIST(-AP88))+(AH88*EXP(-AI88*AL88)*NORMSDIST(-AQ88)) -> 0.00055934571
T89: =(($G$4*U88)+((1-$G$4)*U90))*EXP(-$B$5*$G$1) -> 50.277279 | V89: =(($G$4*W88)+((1-$G$4)*W90))*EXP(-$B$5*$G$1) -> 50.2296 | X89: =(($G$4*Y88)+((1-$G$4)*Y90))*EXP(-$B$5*$G$1) -> 50.182897 | Z89: =(($G$4*AA88)+((1-$G$4)*AA90))*EXP(-$B$5*$G$1) -> 50.137199 | AB89: =(($G$4*AC88)+((1-$G$4)*AC90))*EXP(-$B$5*$G$1) -> 50.092534 | AD89: =(($G$4*AE88)+((1-$G$4)*AE90))*EXP(-$B$5*$G$1) -> 50.048925
S90: =(($G$4*T89)+((1-$G$4)*T91))*EXP(-$B$5*$G$1) -> 46.547183 | U90: =(($G$4*V89)+((1-$G$4)*V91))*EXP(-$B$5*$G$1) -> 46.492672 | W90: =(($G$4*X89)+((1-$G$4)*X91))*EXP(-$B$5*$G$1) -> 46.439188 | Y90: =(($G$4*Z89)+((1-$G$4)*Z91))*EXP(-$B$5*$G$1) -> 46.386779 | AA90: =(($G$4*AB89)+((1-$G$4)*AB91))*EXP(-$B$5*$G$1) -> 46.335494 | AC90: =(($G$4*AD89)+((1-$G$4)*AD91))*EXP(-$B$5*$G$1) -> 46.285379 | AE90: =MAX(AO90,AR90) -> 46.23648 | AF90: =AE27 -> 155.4118 | AG90: =$B$3 -> 110 | AH90: =$B$2 -> 90 | AI90: =$B$5 -> 0.05 | AJ90: =$B$6 -> 0.02 | AK90: =$B$4 -> 0.3 | AL90: =$B$8 -> 0.3 | AM90: =(LN(AF90/AG90)+((AI90-AJ90+(0.5*AK90*AK90))*AL90))/(AK90*SQRT(AL90)) -> 2.2401729 | AN90: =AM90-(AK90*SQRT(AL90)) -> 2.0758562 | AO90: =(AF90*EXP(-AJ90*AL90)*NORMSDIST(AM90))-(AG90*EXP(-AI90*AL90)*NORMSDIST(AN90)) -> 46.23648 | AP90: =(LN(AF90/AH90)+((AI90-AJ90+(0.5*AK90*AK90))*AL90))/(AK90*SQRT(AL90)) -> 3.4614159 | AQ90: =AP90-(AK90*SQRT(AL90)) -> 3.2970991 | AR90: =-(AF90*EXP(-AJ90*AL90)*NORMSDIST(-AP90))+(AH90*EXP(-AI90*AL90)*NORMSDIST(-AQ90)) -> 0.0018007135
R91: =(($G$4*S90)+((1-$G$4)*S92))*EXP(-$B$5*$G$1) -> 42.940661 | T91: =(($G$4*U90)+((1-$G$4)*U92))*EXP(-$B$5*$G$1) -> 42.878325 | V91: =(($G$4*W90)+((1-$G$4)*W92))*EXP(-$B$5*$G$1) -> 42.817002 | X91: =(($G$4*Y90)+((1-$G$4)*Y92))*EXP(-$B$5*$G$1) -> 42.756756 | Z91: =(($G$4*AA90)+((1-$G$4)*AA92))*EXP(-$B$5*$G$1) -> 42.697656 | AB91: =(($G$4*AC90)+((1-$G$4)*AC92))*EXP(-$B$5*$G$1) -> 42.639771 | AD91: =(($G$4*AE90)+((1-$G$4)*AE92))*EXP(-$B$5*$G$1) -> 42.583169
Q92: =(($G$4*R91)+((1-$G$4)*R93))*EXP(-$B$5*$G$1) -> 39.463039 | S92: =(($G$4*T91)+((1-$G$4)*T93))*EXP(-$B$5*$G$1) -> 39.391978 | U92: =(($G$4*V91)+((1-$G$4)*V93))*EXP(-$B$5*$G$1) -> 39.321839 | W92: =(($G$4*X91)+((1-$G$4)*X93))*EXP(-$B$5*$G$1) -> 39.252699 | Y92: =(($G$4*Z91)+((1-$G$4)*Z93))*EXP(-$B$5*$G$1) -> 39.184641 | AA92: =(($G$4*AB91)+((1-$G$4)*AB93))*EXP(-$B$5*$G$1) -> 39.11775 | AC92: =(($G$4*AD91)+((1-$G$4)*AD93))*EXP(-$B$5*$G$1) -> 39.052118 | AE92: =MAX(AO92,AR92) -> 38.98784 | AF92: =AE29 -> 147.98169 | AG92: =$B$3 -> 110 | AH92: =$B$2 -> 90 | AI92: =$B$5 -> 0.05 | AJ92: =$B$6 -> 0.02 | AK92: =$B$4 -> 0.3 | AL92: =$B$8 -> 0.3 | AM92: =(LN(AF92/AG92)+((AI92-AJ92+(0.5*AK92*AK92))*AL92))/(AK92*SQRT(AL92)) -> 1.9420305 | AN92: =AM92-(AK92*SQRT(AL92)) -> 1.7777138 | AO92: =(AF92*EXP(-AJ92*AL92)*NORMSDIST(AM92))-(AG92*EXP(-AI92*AL92)*NORMSDIST(AN92)) -> 38.98784 | AP92: =(LN(AF92/AH92)+((AI92-AJ92+(0.5*AK92*AK92))*AL92))/(AK92*SQRT(AL92)) -> 3.1632735 | AQ92: =AP92-(AK92*SQRT(AL92)) -> 2.9989567 | AR92: =-(AF92*EXP(-AJ92*AL92)*NORMSDIST(-AP92))+(AH92*EXP(-AI92*AL92)*NORMSDIST(-AQ92)) -> 0.0053532064
P93: =(($G$4*Q92)+((1-$G$4)*Q94))*EXP(-$B$5*$G$1) -> 36.120409 | R93: =(($G$4*S92)+((1-$G$4)*S94))*EXP(-$B$5*$G$1) -> 36.039897 | T93: =(($G$4*U92)+((1-$G$4)*U94))*EXP(-$B$5*$G$1) -> 35.960136 | V93: =(($G$4*W92)+((1-$G$4)*W94))*EXP(-$B$5*$G$1) -> 35.881206 | X93: =(($G$4*Y92)+((1-$G$4)*Y94))*EXP(-$B$5*$G$1) -> 35.803199 | Z93: =(($G$4*AA92)+((1-$G$4)*AA94))*EXP(-$B$5*$G$1) -> 35.726209 | AB93: =(($G$4*AC92)+((1-$G$4)*AC94))*EXP(-$B$5*$G$1) -> 35.650342 | AD93: =(($G$4*AE92)+((1-$G$4)*AE94))*EXP(-$B$5*$G$1) -> 35.57571
O94: =(($G$4*P93)+((1-$G$4)*P95))*EXP(-$B$5*$G$1) -> 32.919406 | Q94: =(($G$4*R93)+((1-$G$4)*R95))*EXP(-$B$5*$G$1) -> 32.828943 | S94: =(($G$4*T93)+((1-$G$4)*T95))*EXP(-$B$5*$G$1) -> 32.739004 | U94: =(($G$4*V93)+((1-$G$4)*V95))*EXP(-$B$5*$G$1) -> 32.649645 | W94: =(($G$4*X93)+((1-$G$4)*X95))*EXP(-$B$5*$G$1) -> 32.560953 | Y94: =(($G$4*Z93)+((1-$G$4)*Z95))*EXP(-$B$5*$G$1) -> 32.473025 | AA94: =(($G$4*AB93)+((1-$G$4)*AB95))*EXP(-$B$5*$G$1) -> 32.385968 | AC94: =(($G$4*AD93)+((1-$G$4)*AD95))*EXP(-$B$5*$G$1) -> 32.299899 | AE94: =MAX(AO94,AR94) -> 32.214947 | AF94: =AE31 -> 140.90681 | AG94: =$B$3 -> 110 | AH94: =$B$2 -> 90 | AI94: =$B$5 -> 0.05 | AJ94: =$B$6 -> 0.02 | AK94: =$B$4 -> 0.3 | AL94: =$B$8 -> 0.3 | AM94: =(LN(AF94/AG94)+((AI94-AJ94+(0.5*AK94*AK94))*AL94))/(AK94*SQRT(AL94)) -> 1.6438881 | AN94: =AM94-(AK94*SQRT(AL94)) -> 1.4795714 | AO94: =(AF94*EXP(-AJ94*AL94)*NORMSDIST(AM94))-(AG94*EXP(-AI94*AL94)*NORMSDIST(AN94)) -> 32.214947 | AP94: =(LN(AF94/AH94)+((AI94-AJ94+(0.5*AK94*AK94))*AL94))/(AK94*SQRT(AL94)) -> 2.8651311 | AQ94: =AP94-(AK94*SQRT(AL94)) -> 2.7008143 | AR94: =-(AF94*EXP(-AJ94*AL94)*NORMSDIST(-AP94))+(AH94*EXP(-AI94*AL94)*NORMSDIST(-AQ94)) -> 0.014711781
N95: =(($G$4*O94)+((1-$G$4)*O96))*EXP(-$B$5*$G$1) -> 29.867016 | P95: =(($G$4*Q94)+((1-$G$4)*Q96))*EXP(-$B$5*$G$1) -> 29.766291 | R95: =(($G$4*S94)+((1-$G$4)*S96))*EXP(-$B$5*$G$1) -> 29.665895 | T95: =(($G$4*U94)+((1-$G$4)*U96))*EXP(-$B$5*$G$1) -> 29.565803 | V95: =(($G$4*W94)+((1-$G$4)*W96))*EXP(-$B$5*$G$1) -> 29.466039 | X95: =(($G$4*Y94)+((1-$G$4)*Y96))*EXP(-$B$5*$G$1) -> 29.366691 | Z95: =(($G$4*AA94)+((1-$G$4)*AA96))*EXP(-$B$5*$G$1) -> 29.267856 | AB95: =(($G$4*AC94)+((1-$G$4)*AC96))*EXP(-$B$5*$G$1) -> 29.169642 | AD95: =(($G$4*AE94)+((1-$G$4)*AE96))*EXP(-$B$5*$G$1) -> 29.072172
M96: =(($G$4*N95)+((1-$G$4)*N97))*EXP(-$B$5*$G$1) -> 26.970517 | O96: =(($G$4*P95)+((1-$G$4)*P97))*EXP(-$B$5*$G$1) -> 26.859277 | Q96: =(($G$4*R95)+((1-$G$4)*R97))*EXP(-$B$5*$G$1) -> 26.748306 | S96: =(($G$4*T95)+((1-$G$4)*T97))*EXP(-$B$5*$G$1) -> 26.637473 | U96: =(($G$4*V95)+((1-$G$4)*V97))*EXP(-$B$5*$G$1) -> 26.526667 | W96: =(($G$4*X95)+((1-$G$4)*X97))*EXP(-$B$5*$G$1) -> 26.415856 | Y96: =(($G$4*Z95)+((1-$G$4)*Z97))*EXP(-$B$5*$G$1) -> 26.305115 | AA96: =(($G$4*AB95)+((1-$G$4)*AB97))*EXP(-$B$5*$G$1) -> 26.194531 | AC96: =(($G$4*AD95)+((1-$G$4)*AD97))*EXP(-$B$5*$G$1) -> 26.084206 | AE96: =MAX(AO96,AR96) -> 25.974255 | AF96: =AE33 -> 134.17017 | AG96: =$B$3 -> 110 | AH96: =$B$2 -> 90 | AI96: =$B$5 -> 0.05 | AJ96: =$B$6 -> 0.02 | AK96: =$B$4 -> 0.3 | AL96: =$B$8 -> 0.3 | AM96: =(LN(AF96/AG96)+((AI96-AJ96+(0.5*AK96*AK96))*AL96))/(AK96*SQRT(AL96)) -> 1.3457457 | AN96: =AM96-(AK96*SQRT(AL96)) -> 1.181429 | AO96: =(AF96*EXP(-AJ96*AL96)*NORMSDIST(AM96))-(AG96*EXP(-AI96*AL96)*NORMSDIST(AN96)) -> 25.974255 | AP96: =(LN(AF96/AH96)+((AI96-AJ96+(0.5*AK96*AK96))*AL96))/(AK96*SQRT(AL96)) -> 2.5669887 | AQ96: =AP96-(AK96*SQRT(AL96)) -> 2.4026719 | AR96: =-(AF96*EXP(-AJ96*AL96)*NORMSDIST(-AP96))+(AH96*EXP(-AI96*AL96)*NORMSDIST(-AQ96)) -> 0.037424053
L97: =(($G$4*M96)+((1-$G$4)*M98))*EXP(-$B$5*$G$1) -> 24.237617 | N97: =(($G$4*O96)+((1-$G$4)*O98))*EXP(-$B$5*$G$1) -> 24.115478 | P97: =(($G$4*Q96)+((1-$G$4)*Q98))*EXP(-$B$5*$G$1) -> 23.993735 | R97: =(($G$4*S96)+((1-$G$4)*S98))*EXP(-$B$5*$G$1) -> 23.872202 | T97: =(($G$4*U96)+((1-$G$4)*U98))*EXP(-$B$5*$G$1) -> 23.750641 | V97: =(($G$4*W96)+((1-$G$4)*W98))*EXP(-$B$5*$G$1) -> 23.62881 | X97: =(($G$4*Y96)+((1-$G$4)*Y98))*EXP(-$B$5*$G$1) -> 23.506555 | Z97: =(($G$4*AA96)+((1-$G$4)*AA98))*EXP(-$B$5*$G$1) -> 23.383931 | AB97: =(($G$4*AC96)+((1-$G$4)*AC98))*EXP(-$B$5*$G$1) -> 23.261005 | AD97: =(($G$4*AE96)+((1-$G$4)*AE98))*EXP(-$B$5*$G$1) -> 23.137856
K98: =(($G$4*L97)+((1-$G$4)*L99))*EXP(-$B$5*$G$1) -> 21.67673 | M98: =(($G$4*N97)+((1-$G$4)*N99))*EXP(-$B$5*$G$1) -> 21.543034 | O98: =(($G$4*P97)+((1-$G$4)*P99))*EXP(-$B$5*$G$1) -> 21.410002 | Q98: =(($G$4*R97)+((1-$G$4)*R99))*EXP(-$B$5*$G$1) -> 21.277494 | S98: =(($G$4*T97)+((1-$G$4)*T99))*EXP(-$B$5*$G$1) -> 21.145267 | U98: =(($G$4*V97)+((1-$G$4)*V99))*EXP(-$B$5*$G$1) -> 21.012957 | W98: =(($G$4*X97)+((1-$G$4)*X99))*EXP(-$B$5*$G$1) -> 20.880115 | Y98: =(($G$4*Z97)+((1-$G$4)*Z99))*EXP(-$B$5*$G$1) -> 20.746358 | AA98: =(($G$4*AB97)+((1-$G$4)*AB99))*EXP(-$B$5*$G$1) -> 20.611711 | AC98: =(($G$4*AD97)+((1-$G$4)*AD99))*EXP(-$B$5*$G$1) -> 20.476205 | AE98: =MAX(AO98,AR98) -> 20.339883 | AF98: =AE35 -> 127.75561 | AG98: =$B$3 -> 110 | AH98: =$B$2 -> 90 | AI98: =$B$5 -> 0.05 | AJ98: =$B$6 -> 0.02 | AK98: =$B$4 -> 0.3 | AL98: =$B$8 -> 0.3 | AM98: =(LN(AF98/AG98)+((AI98-AJ98+(0.5*AK98*AK98))*AL98))/(AK98*SQRT(AL98)) -> 1.0476033 | AN98: =AM98-(AK98*SQRT(AL98)) -> 0.88328657 | AO98: =(AF98*EXP(-AJ98*AL98)*NORMSDIST(AM98))-(AG98*EXP(-AI98*AL98)*NORMSDIST(AN98)) -> 20.339883 | AP98: =(LN(AF98/AH98)+((AI98-AJ98+(0.5*AK98*AK98))*AL98))/(AK98*SQRT(AL98)) -> 2.2688463 | AQ98: =AP98-(AK98*SQRT(AL98)) -> 2.1045295 | AR98: =-(AF98*EXP(-AJ98*AL98)*NORMSDIST(-AP98))+(AH98*EXP(-AI98*AL98)*NORMSDIST(-AQ98)) -> 0.088249429
J99: =(($G$4*K98)+((1-$G$4)*K100))*EXP(-$B$5*$G$1) -> 19.297232 | L99: =(($G$4*M98)+((1-$G$4)*M100))*EXP(-$B$5*$G$1) -> 19.15106 | N99: =(($G$4*O98)+((1-$G$4)*O100))*EXP(-$B$5*$G$1) -> 19.005811 | P99: =(($G$4*Q98)+((1-$G$4)*Q100))*EXP(-$B$5*$G$1) -> 18.861492 | R99: =(($G$4*S98)+((1-$G$4)*S100))*EXP(-$B$5*$G$1) -> 18.718012 | T99: =(($G$4*U98)+((1-$G$4)*U100))*EXP(-$B$5*$G$1) -> 18.575118 | V99: =(($G$4*W98)+((1-$G$4)*W100))*EXP(-$B$5*$G$1) -> 18.432327 | X99: =(($G$4*Y98)+((1-$G$4)*Y100))*EXP(-$B$5*$G$1) -> 18.288895 | Z99: =(($G$4*AA98)+((1-$G$4)*AA100))*EXP(-$B$5*$G$1) -> 18.144008 | AB99: =(($G$4*AC98)+((1-$G$4)*AC100))*EXP(-$B$5*$G$1) -> 17.997645 | AD99: =(($G$4*AE98)+((1-$G$4)*AE100))*EXP(-$B$5*$G$1) -> 17.849792
I100: =(($G$4*J99)+((1-$G$4)*J101))*EXP(-$B$5*$G$1) -> 17.109522 | K100: =(($G$4*L99)+((1-$G$4)*L101))*EXP(-$B$5*$G$1) -> 16.949894 | M100: =(($G$4*N99)+((1-$G$4)*N101))*EXP(-$B$5*$G$1) -> 16.791251 | O100: =(($G$4*P99)+((1-$G$4)*P101))*EXP(-$B$5*$G$1) -> 16.633788 | Q100: =(($G$4*R99)+((1-$G$4)*R101))*EXP(-$B$5*$G$1) -> 16.477659 | S100: =(($G$4*T99)+((1-$G$4)*T101))*EXP(-$B$5*$G$1) -> 16.322923 | U100: =(($G$4*V99)+((1-$G$4)*V101))*EXP(-$B$5*$G$1) -> 16.169435 | W100: =(($G$4*X99)+((1-$G$4)*X101))*EXP(-$B$5*$G$1) -> 16.016681 | Y100: =(($G$4*Z99)+((1-$G$4)*Z101))*EXP(-$B$5*$G$1) -> 15.863558 | AA100: =(($G$4*AB99)+((1-$G$4)*AB101))*EXP(-$B$5*$G$1) -> 15.708417 | AC100: =(($G$4*AD99)+((1-$G$4)*AD101))*EXP(-$B$5*$G$1) -> 15.551189 | AE100: =MAX(AO100,AR100) -> 15.391802 | AF100: =AE37 -> 121.64772 | AG100: =$B$3 -> 110 | AH100: =$B$2 -> 90 | AI100: =$B$5 -> 0.05 | AJ100: =$B$6 -> 0.02 | AK100: =$B$4 -> 0.3 | AL100: =$B$8 -> 0.3 | AM100: =(LN(AF100/AG100)+((AI100-AJ100+(0.5*AK100*AK100))*AL100))/(AK100*SQRT(AL100)) -> 0.74946094 | AN100: =AM100-(AK100*SQRT(AL100)) -> 0.58514418 | AO100: =(AF100*EXP(-AJ100*AL100)*NORMSDIST(AM100))-(AG100*EXP(-AI100*AL100)*NORMSDIST(AN100)) -> 15.391802 | AP100: =(LN(AF100/AH100)+((AI100-AJ100+(0.5*AK100*AK100))*AL100))/(AK100*SQRT(AL100)) -> 1.9707039 | AQ100: =AP100-(AK100*SQRT(AL100)) -> 1.8063871 | AR100: =-(AF100*EXP(-AJ100*AL100)*NORMSDIST(-AP100))+(AH100*EXP(-AI100*AL100)*NORMSDIST(-AQ100)) -> 0.19323851
H101: =(($G$4*I100)+((1-$G$4)*I102))*EXP(-$B$5*$G$1) -> 15.124756 | J101: =(($G$4*K100)+((1-$G$4)*K102))*EXP(-$B$5*$G$1) -> 14.950962 | L101: =(($G$4*M100)+((1-$G$4)*M102))*EXP(-$B$5*$G$1) -> 14.777881 | N101: =(($G$4*O100)+((1-$G$4)*O102))*EXP(-$B$5*$G$1) -> 14.605848 | P101: =(($G$4*Q100)+((1-$G$4)*Q102))*EXP(-$B$5*$G$1) -> 14.435243 | R101: =(($G$4*S100)+((1-$G$4)*S102))*EXP(-$B$5*$G$1) -> 14.266464 | T101: =(($G$4*U100)+((1-$G$4)*U102))*EXP(-$B$5*$G$1) -> 14.099878 | V101: =(($G$4*W100)+((1-$G$4)*W102))*EXP(-$B$5*$G$1) -> 13.935679 | X101: =(($G$4*Y100)+((1-$G$4)*Y102))*EXP(-$B$5*$G$1) -> 13.773578 | Z101: =(($G$4*AA100)+((1-$G$4)*AA102))*EXP(-$B$5*$G$1) -> 13.612184 | AB101: =(($G$4*AC100)+((1-$G$4)*AC102))*EXP(-$B$5*$G$1) -> 13.448233 | AD101: =(($G$4*AE100)+((1-$G$4)*AE102))*EXP(-$B$5*$G$1) -> 13.281601
G102: =(($G$4*H101)+((1-$G$4)*H103))*EXP(-$B$5*$G$1) -> 13.354201 | I102: =(($G$4*J101)+((1-$G$4)*J103))*EXP(-$B$5*$G$1) -> 13.166171 | K102: =(($G$4*L101)+((1-$G$4)*L103))*EXP(-$B$5*$G$1) -> 12.978211 | M102: =(($G$4*N101)+((1-$G$4)*N103))*EXP(-$B$5*$G$1) -> 12.790694 | O102: =(($G$4*P101)+((1-$G$4)*P103))*EXP(-$B$5*$G$1) -> 12.604096 | Q102: =(($G$4*R101)+((1-$G$4)*R103))*EXP(-$B$5*$G$1) -> 12.419018 | S102: =(($G$4*T101)+((1-$G$4)*T103))*EXP(-$B$5*$G$1) -> 12.2362 | U102: =(($G$4*V101)+((1-$G$4)*V103))*EXP(-$B$5*$G$1) -> 12.056512 | W102: =(($G$4*X101)+((1-$G$4)*X103))*EXP(-$B$5*$G$1) -> 11.88085 | Y102: =(($G$4*Z101)+((1-$G$4)*Z103))*EXP(-$B$5*$G$1) -> 11.709737 | AA102: =(($G$4*AB101)+((1-$G$4)*AB103))*EXP(-$B$5*$G$1) -> 11.542034 | AC102: =(($G$4*AD101)+((1-$G$4)*AD103))*EXP(-$B$5*$G$1) -> 11.371306 | AE102: =MAX(AO102,AR102) -> 11.197377 | AF102: =AE39 -> 115.83185 | AG102: =$B$3 -> 110 | AH102: =$B$2 -> 90 | AI102: =$B$5 -> 0.05 | AJ102: =$B$6 -> 0.02 | AK102: =$B$4 -> 0.3 | AL102: =$B$8 -> 0.3 | AM102: =(LN(AF102/AG102)+((AI102-AJ102+(0.5*AK102*AK102))*AL102))/(AK102*SQRT(AL102)) -> 0.45131855 | AN102: =AM102-(AK102*SQRT(AL102)) -> 0.28700178 | AO102: =(AF102*EXP(-AJ102*AL102)*NORMSDIST(AM102))-(AG102*EXP(-AI102*AL102)*NORMSDIST(AN102)) -> 11.197377 | AP102: =(LN(AF102/AH102)+((AI102-AJ102+(0.5*AK102*AK102))*AL102))/(AK102*SQRT(AL102)) -> 1.6725615 | AQ102: =AP102-(AK102*SQRT(AL102)) -> 1.5082447 | AR102: =-(AF102*EXP(-AJ102*AL102)*NORMSDIST(-AP102))+(AH102*EXP(-AI102*AL102)*NORMSDIST(-AQ102)) -> 0.39369708
F103: =(($G$4*G102)+((1-$G$4)*G104))*EXP(-$B$5*$G$1) -> 11.808313 | H103: =(($G$4*I102)+((1-$G$4)*I104))*EXP(-$B$5*$G$1) -> 11.606909 | J103: =(($G$4*K102)+((1-$G$4)*K104))*EXP(-$B$5*$G$1) -> 11.404635 | L103: =(($G$4*M102)+((1-$G$4)*M104))*EXP(-$B$5*$G$1) -> 11.201791 | N103: =(($G$4*O102)+((1-$G$4)*O104))*EXP(-$B$5*$G$1) -> 10.998791 | P103: =(($G$4*Q102)+((1-$G$4)*Q104))*EXP(-$B$5*$G$1) -> 10.796208 | R103: =(($G$4*S102)+((1-$G$4)*S104))*EXP(-$B$5*$G$1) -> 10.594839 | T103: =(($G$4*U102)+((1-$G$4)*U104))*EXP(-$B$5*$G$1) -> 10.395799 | V103: =(($G$4*W102)+((1-$G$4)*W104))*EXP(-$B$5*$G$1) -> 10.20063 | X103: =(($G$4*Y102)+((1-$G$4)*Y104))*EXP(-$B$5*$G$1) -> 10.011401 | Z103: =(($G$4*AA102)+((1-$G$4)*AA104))*EXP(-$B$5*$G$1) -> 9.8305348 | AB103: =(($G$4*AC102)+((1-$G$4)*AC104))*EXP(-$B$5*$G$1) -> 9.6589985 | AD103: =(($G$4*AE102)+((1-$G$4)*AE104))*EXP(-$B$5*$G$1) -> 9.4840941
E104: =(($G$4*F103)+((1-$G$4)*F105))*EXP(-$B$5*$G$1) -> 10.495699 | G104: =(($G$4*H103)+((1-$G$4)*H105))*EXP(-$B$5*$G$1) -> 10.282836 | I104: =(($G$4*J103)+((1-$G$4)*J105))*EXP(-$B$5*$G$1) -> 10.068032 | K104: =(($G$4*L103)+((1-$G$4)*L105))*EXP(-$B$5*$G$1) -> 9.851427 | M104: =(($G$4*N103)+((1-$G$4)*N105))*EXP(-$B$5*$G$1) -> 9.6332462 | O104: =(($G$4*P103)+((1-$G$4)*P105))*EXP(-$B$5*$G$1) -> 9.4138417 | Q104: =(($G$4*R103)+((1-$G$4)*R105))*EXP(-$B$5*$G$1) -> 9.1937612 | S104: =(($G$4*T103)+((1-$G$4)*T105))*EXP(-$B$5*$G$1) -> 8.9738601 | U104: =(($G$4*V103)+((1-$G$4)*V105))*EXP(-$B$5*$G$1) -> 8.7554924 | W104: =(($G$4*X103)+((1-$G$4)*X105))*EXP(-$B$5*$G$1) -> 8.5408443 | Y104: =(($G$4*Z103)+((1-$G$4)*Z105))*EXP(-$B$5*$G$1) -> 8.3335216 | AA104: =(($G$4*AB103)+((1-$G$4)*AB105))*EXP(-$B$5*$G$1) -> 8.139479 | AC104: =(($G$4*AD103)+((1-$G$4)*AD105))*EXP(-$B$5*$G$1) -> 7.9670273 | AE104: =MAX(AO104,AR104) -> 7.7910392 | AF104: =AE41 -> 110.29403 | AG104: =$B$3 -> 110 | AH104: =$B$2 -> 90 | AI104: =$B$5 -> 0.05 | AJ104: =$B$6 -> 0.02 | AK104: =$B$4 -> 0.3 | AL104: =$B$8 -> 0.3 | AM104: =(LN(AF104/AG104)+((AI104-AJ104+(0.5*AK104*AK104))*AL104))/(AK104*SQRT(AL104)) -> 0.15317615 | AN104: =AM104-(AK104*SQRT(AL104)) -> -0.011140617 | AO104: =(AF104*EXP(-AJ104*AL104)*NORMSDIST(AM104))-(AG104*EXP(-AI104*AL104)*NORMSDIST(AN104)) -> 7.7910392 | AP104: =(LN(AF104/AH104)+((AI104-AJ104+(0.5*AK104*AK104))*AL104))/(AK104*SQRT(AL104)) -> 1.3744191 | AQ104: =AP104-(AK104*SQRT(AL104)) -> 1.2101023 | AR104: =-(AF104*EXP(-AJ104*AL104)*NORMSDIST(-AP104))+(AH104*EXP(-AI104*AL104)*NORMSDIST(-AQ104)) -> 0.74803593
...

Sheet Question 4
C1: current stock price | D1: S0
C2: strike price | D2: S0
C3: risk free | D3: r
C4: volatility | D4: s
C5: option life | D5: T
C7: d1 | D7: [ln(S0/S0)+(r+0.5*s * s)T]/(s * ÖT)
D8: [(r+0.5*s *s)T]/(s * ÖT)
C9: d2 | D9: [(r-0.5*s *s)T]/(s * ÖT)
C11: prob(at the money spot put exercise) = N(-d2) = 0.3
C12: sensitivity at the money call = N(d1) = 0.65
C13: 10 * exp(rT) = 12
C15: a)
D16: ATM Spot Call | F16: S0[N(d1) - exp(-rT)*N(d2)]
D17: Since call prem = 2
D18: we have call prem = S0[N(d1) - exp(-rT) N(d2) ]
D19: = S0[0.65 - (10/12)*(1-0.3)]
D20: = 0.066667* S0
D21: Thus S0 = 2/0.066667
D22: S0 = 30
C25: b) Binary prem = 100 * exp (-r* 2T) * Prob (exercise)
C26: Since exp(-rT) = 10/12, we can see that exp(-r * 2T) = exp(-2rT)=[exp(-rT)]^2 = 100/144
C27: Prob (exercise) = N((r-0.5*s*s)2T/sÖ2T)=N(d2 * Ö2)
C28: But from the definition of N(d2) = 0.7, we get that d2 = 0.524401
C29: Thus N(0.524401 * Ö2) = 0.7708
C31: Hence binary premium = 100 * 100/144 * 0.7708
E32: = | F32: =100*(100/144)*0.7708 -> 53.527778

Sheet Question 5
A1: a)
B2: Date | C2: Zero Rates | D2: Cum Time | E2: ti | F2: Dfi | G2: Fi | H2: Fi * ti * Dfi | I2: ti * Dfi | L2: Swap Rate | M2: =SUM(H4:H11)/SUM(I4:I11) -> 0.1256602 | N2: <<M1
B3: 45744 | F3: 1 | M3: =(1-F11)/SUM(I4:I11) -> 0.1256602 | N3: <<M2
B4: =EDATE(B3,3) -> 45836 | C4: 0.04 | D4: =(B4-$B$3)/365 -> 0.25205479 | E4: =D4 -> 0.25205479 | F4: =EXP(-C4*D4) -> 0.98996846 | G4: =((F3/F4)-1)/E4 -> 0.040202323 | H4: =G4*E4*F4 -> 0.010031537 | I4: =E4*F4 -> 0.2495263
B5: =EDATE(B4,3) -> 45928 | C5: 0.045 | D5: =(B5-$B$3)/365 -> 0.50410959 | E5: =(D5-D4) -> 0.25205479 | F5: =EXP(-C5*D5) -> 0.97757044 | G5: =((F4/F5)-1)/E5 -> 0.050316396 | H5: =G5*E5*F5 -> 0.012398026 | I5: =E5*F5 -> 0.24640132
B6: =EDATE(B5,3) -> 46019 | C6: 0.05 | D6: =(B6-$B$3)/365 -> 0.75342466 | E6: =(D6-D5) -> 0.24931507 | F6: =EXP(-C6*D6) -> 0.9630295 | G6: =((F5/F6)-1)/E6 -> 0.060562561 | H6: =G6*E6*F6 -> 0.014540936 | I6: =E6*F6 -> 0.24009777
B7: =EDATE(B6,3) -> 46109 | C7: 0.06 | D7: =(B7-$B$3)/365 -> 1 | E7: =(D7-D6) -> 0.24657534 | F7: =EXP(-C7*D7) -> 0.94176453 | G7: =((F6/F7)-1)/E7 -> 0.091574119 | H7: =G7*E7*F7 -> 0.021264968 | I7: =E7*F7 -> 0.23221591
B8: =EDATE(B7,3) -> 46201 | C8: 0.07 | D8: =(B8-$B$3)/365 -> 1.2520548 | E8: =(D8-D7) -> 0.25205479 | F8: =EXP(-C8*D8) -> 0.9160871 | G8: =((F7/F8)-1)/E8 -> 0.11120388 | H8: =G8*E8*F8 -> 0.025677437 | I8: =E8*F8 -> 0.23090414
B9: =EDATE(B8,3) -> 46293 | C9: 0.08 | D9: =(B9-$B$3)/365 -> 1.5041096 | E9: =(D9-D8) -> 0.25205479 | F9: =EXP(-C9*D9) -> 0.88662889 | G9: =((F8/F9)-1)/E9 -> 0.13181638 | H9: =G9*E9*F9 -> 0.029458202 | I9: =E9*F9 -> 0.22347906
B10: =EDATE(B9,3) -> 46384 | C10: 0.1 | D10: =(B10-$B$3)/365 -> 1.7534247 | E10: =(D10-D9) -> 0.24931507 | F10: =EXP(-C10*D10) -> 0.83916958 | G10: =((F9/F10)-1)/E10 -> 0.22684184 | H10: =G10*E10*F10 -> 0.04745931 | I10: =E10*F10 -> 0.20921762
B11: =EDATE(B10,3) -> 46474 | C11: 0.13 | D11: =(B11-$B$3)/365 -> 2 | E11: =(D11-D10) -> 0.24657534 | F11: =EXP(-C11*D11) -> 0.77105159 | G11: =((F10/F11)-1)/E11 -> 0.35828514 | H11: =G11*E11*F11 -> 0.068117999 | I11: =E11*F11 -> 0.19012231
A13: b)
B14: Date | C14: Zero Rates | D14: Notional (millions) | E14: Cum Time | F14: ti | G14: Dfi | H14: Fi | I14: Fi * ti * Dfi*Ni | J14: ti * Dfi * Ni
B15: 45744 | G15: 1 | L15: Swap rate | M15: =SUM(I21:I23)/SUM(J21:J23) -> 0.18833762
B16: =EDATE(B15,3) -> 45836 | C16: 0.04 | E16: =(B16-$B$15)/365 -> 0.25205479 | G16: =EXP(-C16*E16) -> 0.98996846
B17: =EDATE(B16,3) -> 45928 | C17: 0.045 | E17: =(B17-$B$15)/365 -> 0.50410959 | G17: =EXP(-C17*E17) -> 0.97757044
B18: =EDATE(B17,3) -> 46019 | C18: 0.05 | E18: =(B18-$B$15)/365 -> 0.75342466 | G18: =EXP(-C18*E18) -> 0.9630295
B19: =EDATE(B18,3) -> 46109 | C19: 0.06 | D19: 30 | E19: =(B19-$B$15)/365 -> 1 | G19: =EXP(-C19*E19) -> 0.94176453
B20: =EDATE(B19,3) -> 46201 | C20: 0.07 | E20: =(B20-$B$15)/365 -> 1.2520548 | G20: =EXP(-C20*E20) -> 0.9160871
B21: =EDATE(B20,3) -> 46293 | C21: 0.08 | D21: 20 | E21: =(B21-$B$15)/365 -> 1.5041096 | F21: =(E21-E19) -> 0.50410959 | G21: =EXP(-C21*E21) -> 0.88662889 | H21: =((G19/G21)-1)/F21 -> 0.1233575 | I21: =H21*F21*G21*D19 -> 1.6540692 | J21: =F21*G21*D19 -> 13.408744
B22: =EDATE(B21,3) -> 46384 | C22: 0.1 | E22: =(B22-$B$15)/365 -> 1.7534247 | G22: =EXP(-C22*E22) -> 0.83916958
B23: =EDATE(B22,3) -> 46474 | C23: 0.13 | E23: =(B23-$B$15)/365 -> 2 | F23: =(E23-E21) -> 0.49589041 | G23: =EXP(-C23*E23) -> 0.77105159 | H23: =((G21/G23)-1)/F23 -> 0.30227584 | I23: =H23*F23*G23*D21 -> 2.3115462 | J23: =F23*G23*D21 -> 7.6471418
A25: c)
B26: Date | C26: Zero Rates | D26: Cum Time | E26: ti | F26: Dfi | G26: Fi | H26: Fi * ti * Dfi | I26: ti * Dfi | J26: PV(net rate) | L26: Old swap rate | M26: =M2 -> 0.1256602
B27: 45792 | F27: 1 | L27: new swap rate | M27: =SUM(H28:H35)/SUM(I28:I35) -> 0.050144936
B28: 45836 | C28: 0.02 | D28: =(B28-$B$27)/365 -> 0.12054795 | E28: =E4 -> 0.25205479 | F28: =EXP(-C28*D28) -> 0.99759195 | G28: =G4 -> 0.040202323 | J28: =(G28-M26)*E28*F28 -> -0.021488198 | L28: M2M | M28: =SUM(J28:J35)*10000000 -> -1470463.5
B29: 45928 | C29: 0.035 | D29: =(B29-$B$27)/365 -> 0.37260274 | E29: =(D29-D28) -> 0.25205479 | F29: =EXP(-C29*D29) -> 0.98704357 | G29: =((F28/F29)-1)/E29 -> 0.042398867 | H29: =G29*E29*F29 -> 0.010548374 | I29: =E29*F29 -> 0.24878906 | J29: =($M$27-$M$26)*E29*F29 -> -0.018787372
B30: 46019 | C30: 0.04 | D30: =(B30-$B$27)/365 -> 0.62191781 | E30: =(D30-D29) -> 0.24931507 | F30: =EXP(-C30*D30) -> 0.97543016 | G30: =((F29/F30)-1)/E30 -> 0.047754572 | H30: =G30*E30*F30 -> 0.011613408 | I30: =E30*F30 -> 0.24318944 | J30: =($M$27-$M$26)*E30*F30 -> -0.018364515
B31: 46109 | C31: 0.041 | D31: =(B31-$B$27)/365 -> 0.86849315 | E31: =(D31-D30) -> 0.24657534 | F31: =EXP(-C31*D31) -> 0.9650183 | G31: =((F30/F31)-1)/E31 -> 0.043756589 | H31: =G31*E31*F31 -> 0.010411868 | I31: =E31*F31 -> 0.23794972 | J31: =($M$27-$M$26)*E31*F31 -> -0.017968836
B32: 46201 | C32: 0.043 | D32: =(B32-$B$27)/365 -> 1.1205479 | E32: =(D32-D31) -> 0.25205479 | F32: =EXP(-C32*D32) -> 0.95295884 | G32: =((F31/F32)-1)/E32 -> 0.050206324 | H32: =G32*E32*F32 -> 0.012059451 | I32: =E32*F32 -> 0.24019785 | J32: =($M$27-$M$26)*E32*F32 -> -0.018138604
B33: 46293 | C33: 0.047 | D33: =(B33-$B$27)/365 -> 1.3726027 | E33: =(D33-D32) -> 0.25205479 | F33: =EXP(-C33*D33) -> 0.93752456 | G33: =((F32/F33)-1)/E33 -> 0.065314409 | H33: =G33*E33*F33 -> 0.015434289 | I33: =E33*F33 -> 0.23630756 | J33: =($M$27-$M$26)*E33*F33 -> -0.017844828
B34: 46384 | C34: 0.0475 | D34: =(B34-$B$27)/365 -> 1.6219178 | E34: =(D34-D33) -> 0.24931507 | F34: =EXP(-C34*D34) -> 0.9258518 | G34: =((F33/F34)-1)/E34 -> 0.050568869 | H34: =G34*E34*F34 -> 0.011672752 | I34: =E34*F34 -> 0.23082881 | J34: =($M$27-$M$26)*E34*F34 -> -0.017431098
B35: 46474 | C35: 0.048 | D35: =(B35-$B$27)/365 -> 1.8684932 | E35: =(D35-D34) -> 0.24657534 | F35: =EXP(-C35*D35) -> 0.91421668 | G35: =((F34/F35)-1)/E35 -> 0.051614575 | H35: =G35*E35*F35 -> 0.011635127 | I35: =E35*F35 -> 0.22542329 | J35: =($M$27-$M$26)*E35*F35 -> -0.017022899
A37: d)
B38: Date | C38: Zero Rates | D38: Notional (millions) | E38: Cum Time | F38: ti | G38: Dfi | H38: Fi | I38: Fi * ti * Dfi*Ni | J38: ti * Dfi * Ni | K38: PV(diff)
B39: 45792 | G39: 1 | M39: old swap rate | N39: =M15 -> 0.18833762
B40: 45836 | C40: 0.02 | E40: =(B40-$B$39)/365 -> 0.12054795 | G40: =EXP(-C40*E40) -> 0.99759195 | M40: new swap rate | N40: =SUM(I39:I47)/SUM(J39:J47) -> 0.05553638
B41: 45928 | C41: 0.035 | E41: =(B41-$B$39)/365 -> 0.37260274 | G41: =EXP(-C41*E41) -> 0.98704357 | M41: M2M | N41: =SUM(K45:K47)*1000000 -> 3087028.4
B42: 46019 | C42: 0.04 | E42: =(B42-$B$39)/365 -> 0.62191781 | G42: =EXP(-C42*E42) -> 0.97543016
B43: 46109 | C43: 0.041 | D43: 30 | E43: =(B43-$B$39)/365 -> 0.86849315 | G43: =EXP(-C43*E43) -> 0.9650183
B44: 46201 | C44: 0.043 | E44: =(B44-$B$39)/365 -> 1.1205479 | G44: =EXP(-C44*E44) -> 0.95295884
B45: 46293 | C45: 0.047 | D45: 20 | E45: =(B45-$B$39)/365 -> 1.3726027 | F45: =(E45-E43) -> 0.50410959 | G45: =EXP(-C45*E45) -> 0.93752456 | H45: =((G43/G45)-1)/F45 -> 0.058173635 | I45: =H45*F45*G45*D43 -> 0.82481218 | J45: =F45*G45*D43 -> 14.178454 | K45: =($N$39-$N$40)*D43*F45*G45 -> 1.8829162
B46: 46384 | C46: 0.0475 | E46: =(B46-$B$39)/365 -> 1.6219178 | G46: =EXP(-C46*E46) -> 0.9258518
B47: 46474 | C47: 0.048 | E47: =(B47-$B$39)/365 -> 1.8684932 | F47: =(E47-E45) -> 0.49589041 | G47: =EXP(-C47*E47) -> 0.91421668 | H47: =((G45/G47)-1)/F47 -> 0.051412403 | I47: =H47*F47*G47*D45 -> 0.46615758 | J47: =F47*G47*D45 -> 9.0670257 | K47: =($N$39-$N$40)*D45*F47*G47 -> 1.2041122
