Workbook

Sheet Slide 17
A1: uniform random number | B1: =RAND() -> 0.47247571

Sheet Slide 24a
B1: X | C1: 1 | D1: 2 | E1: 3 | F1: 4
B2: P(X=x) | C2: 0.2 | D2: 0.3 | E2: 0.45 | F2: 0.05
A3: Step 1 | B3: P(X ≤ x) | C3: =C2 -> 0.2 | D3: =D2+C3 -> 0.5 | E3: =E2+D3 -> 0.95 | F3: =F2+E3 -> 1 | G3: <<<Find the cumulative probabilities
A4: Step 2 | B4: Uniform number can be between (0, 0.2] | G4: <<<Bucket generated uniform values
B5: Uniform number can be between (0.2,0.5]
B6: Uniform number can be between (0.5, 0.95]
B7: Uniform number can be between (0.95, 1]
A8: Step 3 | B8: If uniform number is in interval (0, 0.2], assign value X = 1 | G8: <<<Assign values to buckets
B9: If uniform number is in interval (0.2, 0.5], assign value X = 2
B10: If uniform number is in interval (0.5, 0.95], assign value X = 3
B11: If uniform number is in interval (0.95, 1], assign value X = 4

Sheet Slide 24b
A1: X | B1: 0 | C1: -2 | D1: 1 | E1: 1.5
A2: P(X=x) | B2: 0.3 | C2: 0.25 | D2: 0.3 | E2: 0.15
A3: P(X ≤ x) | B3: ='Slide 24a'!C3 -> 0.2 | C3: ='Slide 24a'!D3 -> 0.5 | D3: ='Slide 24a'!E3 -> 0.95 | E3: ='Slide 24a'!F3 -> 1
A4: Rand U(0,1) | B4: =RAND() -> 0.58985066
A5: Rand Variate X | B5: =IF(B4<=B3,B1,IF(B4<=C3,C1,IF(B4<=D3,D1,E1))) -> 1

Sheet Slide 25a
A1: Step 0 | B1: X | C1: -2 | D1: 0 | E1: 1 | F1: 1.5 | G1: <<<Order the X values
B2: P(X=x) | C2: 0.25 | D2: 0.3 | E2: 0.3 | F2: 0.15
A3: Step 1 | B3: P(X ≤ x) | C3: =C2 -> 0.25 | D3: =D2+C3 -> 0.55 | E3: =E2+D3 -> 0.85 | F3: =F2+E3 -> 1 | G3: <<<Find the cumulative probabilities
A4: Step 2 | B4: Uniform number can be between (0, 0.25] | G4: <<<Bucket generated uniform values
B5: Uniform number can be between (0.25,0.55]
B6: Uniform number can be between (0.55, 0.85]
B7: Uniform number can be between (0.85, 1]
A8: Step 3 | B8: If uniform number is in interval (0, 0.25], assign value X = - 2 | G8: <<<Assign values to buckets
B9: If uniform number is in interval (0.25, 0.55], assign value X = 0
B10: If uniform number is in interval (0.55, 0.85], assign value X = 1
B11: If uniform number is in interval (0.85, 1], assign value X = 1.5

Sheet Slide 25b
A1: X | B1: ='Slide 25a'!C1 -> -2 | C1: ='Slide 25a'!D1 -> 0 | D1: ='Slide 25a'!E1 -> 1 | E1: ='Slide 25a'!F1 -> 1.5
A2: P(X=x) | B2: ='Slide 25a'!C2 -> 0.25 | C2: ='Slide 25a'!D2 -> 0.3 | D2: ='Slide 25a'!E2 -> 0.3 | E2: ='Slide 25a'!F2 -> 0.15
A3: P(X ≤ x) | B3: ='Slide 25a'!C3 -> 0.25 | C3: ='Slide 25a'!D3 -> 0.55 | D3: ='Slide 25a'!E3 -> 0.85 | E3: ='Slide 25a'!F3 -> 1
A4: Rand U(0,1) | B4: =RAND() -> 0.81222129
A5: Rand Variate X | B5: =IF(B4<=B3,B1,IF(B4<=C3,C1,IF(B4<=D3,D1,E1))) -> 1

Sheet Slide 26
A1: Success Probability | B1: 0.4
A2: X | B2: 0 | C2: 1 | D2: 2 | E2: 3 | F2: 4 | G2: 5
A3: P(X=x) | B3: =COMBIN(5,B2)*($B$1^B2)*((1-$B$1)^(5-B2)) -> 0.07776 | C3: =COMBIN(5,C2)*($B$1^C2)*((1-$B$1)^(5-C2)) -> 0.2592 | D3: =COMBIN(5,D2)*($B$1^D2)*((1-$B$1)^(5-D2)) -> 0.3456 | E3: =COMBIN(5,E2)*($B$1^E2)*((1-$B$1)^(5-E2)) -> 0.2304 | F3: =COMBIN(5,F2)*($B$1^F2)*((1-$B$1)^(5-F2)) -> 0.0768 | G3: =COMBIN(5,G2)*($B$1^G2)*((1-$B$1)^(5-G2)) -> 0.01024
A4: P(X ≤ x) | B4: =B3 -> 0.07776 | C4: =C3+B4 -> 0.33696 | D4: =D3+C4 -> 0.68256 | E4: =E3+D4 -> 0.91296 | F4: =F3+E4 -> 0.98976 | G4: =G3+F4 -> 1
A5: Rand U(0,1) | B5: =RAND() -> 0.9793197
A6: Rand Variate X | B6: =IF(B5<=B4,B2,IF(B5<=C4,C2,IF(B5<=D4,D2,IF(B5<=E4,E2,IF(B5<=F4,F2,G2))))) -> 4

Sheet Slide 27a
A1: Lower Limit | B1: 2
A2: Upper Limit | B2: 6
A3: x | B3: f(x) | I3: Step 0: | J3: See what the picture looks like - uniform on (2,4)
A4: =A5-0.0001 -> 1.9999 | B4: 0 | I4: Step 1: | J4: See how to make this look like U(0,1)
A5: =B1 -> 2 | B5: =1/($B$2-$B$1) -> 0.25 | J5: To do this, we can achieve this using 2 steps
A6: =A5+(0.01*($B$2-$B$1)) -> 2.04 | B6: =1/($B$2-$B$1) -> 0.25 | J6: 1) Subtract all observations by 2
A7: =A6+(0.01*($B$2-$B$1)) -> 2.08 | B7: =1/($B$2-$B$1) -> 0.25 | J7: The result would be a uniform on (0,4)
A8: =A7+(0.01*($B$2-$B$1)) -> 2.12 | B8: =1/($B$2-$B$1) -> 0.25 | J8: See Slide 21b
A9: =A8+(0.01*($B$2-$B$1)) -> 2.16 | B9: =1/($B$2-$B$1) -> 0.25
A10: =A9+(0.01*($B$2-$B$1)) -> 2.2 | B10: =1/($B$2-$B$1) -> 0.25
A11: =A10+(0.01*($B$2-$B$1)) -> 2.24 | B11: =1/($B$2-$B$1) -> 0.25
A12: =A11+(0.01*($B$2-$B$1)) -> 2.28 | B12: =1/($B$2-$B$1) -> 0.25
A13: =A12+(0.01*($B$2-$B$1)) -> 2.32 | B13: =1/($B$2-$B$1) -> 0.25
A14: =A13+(0.01*($B$2-$B$1)) -> 2.36 | B14: =1/($B$2-$B$1) -> 0.25
A15: =A14+(0.01*($B$2-$B$1)) -> 2.4 | B15: =1/($B$2-$B$1) -> 0.25
A16: =A15+(0.01*($B$2-$B$1)) -> 2.44 | B16: =1/($B$2-$B$1) -> 0.25
A17: =A16+(0.01*($B$2-$B$1)) -> 2.48 | B17: =1/($B$2-$B$1) -> 0.25
A18: =A17+(0.01*($B$2-$B$1)) -> 2.52 | B18: =1/($B$2-$B$1) -> 0.25
A19: =A18+(0.01*($B$2-$B$1)) -> 2.56 | B19: =1/($B$2-$B$1) -> 0.25
A20: =A19+(0.01*($B$2-$B$1)) -> 2.6 | B20: =1/($B$2-$B$1) -> 0.25
... A105: =A104+(0.01*($B$2-$B$1)) -> 6 | B105: =1/($B$2-$B$1) -> 0.25
A106: =A105+0.0001 -> 6.0001 | B106: 0

Sheet Slide 27b
A1: Lower Limit | B1: 0
A2: Upper Limit | B2: 4
A3: x | B3: f(x) | I3: Step 0: | J3: See what the picture looks like - uniform on (2,4)
A4: =A5-0.0001 -> -0.0001 | B4: 0 | I4: Step 1: | J4: See how to make this look like U(0,1)
A5: =B1 -> 0 | B5: =1/($B$2-$B$1) -> 0.25 | J5: To do this, we can achieve this using 2 steps
A6: =A5+(0.01*($B$2-$B$1)) -> 0.04 | B6: =1/($B$2-$B$1) -> 0.25 | J6: 1) Subtract all observations by 2
A7: =A6+(0.01*($B$2-$B$1)) -> 0.08 | B7: =1/($B$2-$B$1) -> 0.25 | J7: The result would be a uniform on (0,4)
A8: =A7+(0.01*($B$2-$B$1)) -> 0.12 | B8: =1/($B$2-$B$1) -> 0.25 | J8: 2) Divide all observations by 4
A9: =A8+(0.01*($B$2-$B$1)) -> 0.16 | B9: =1/($B$2-$B$1) -> 0.25 | J9: The result would be a uniform on (0,1)
A10: =A9+(0.01*($B$2-$B$1)) -> 0.2 | B10: =1/($B$2-$B$1) -> 0.25
A11: =A10+(0.01*($B$2-$B$1)) -> 0.24 | B11: =1/($B$2-$B$1) -> 0.25
A12: =A11+(0.01*($B$2-$B$1)) -> 0.28 | B12: =1/($B$2-$B$1) -> 0.25
A13: =A12+(0.01*($B$2-$B$1)) -> 0.32 | B13: =1/($B$2-$B$1) -> 0.25
A14: =A13+(0.01*($B$2-$B$1)) -> 0.36 | B14: =1/($B$2-$B$1) -> 0.25
A15: =A14+(0.01*($B$2-$B$1)) -> 0.4 | B15: =1/($B$2-$B$1) -> 0.25
A16: =A15+(0.01*($B$2-$B$1)) -> 0.44 | B16: =1/($B$2-$B$1) -> 0.25
A17: =A16+(0.01*($B$2-$B$1)) -> 0.48 | B17: =1/($B$2-$B$1) -> 0.25
A18: =A17+(0.01*($B$2-$B$1)) -> 0.52 | B18: =1/($B$2-$B$1) -> 0.25
A19: =A18+(0.01*($B$2-$B$1)) -> 0.56 | B19: =1/($B$2-$B$1) -> 0.25
A20: =A19+(0.01*($B$2-$B$1)) -> 0.6 | B20: =1/($B$2-$B$1) -> 0.25
A21: =A20+(0.01*($B$2-$B$1)) -> 0.64 | B21: =1/($B$2-$B$1) -> 0.25
... A105: =A104+(0.01*($B$2-$B$1)) -> 4 | B105: =1/($B$2-$B$1) -> 0.25
A106: =A105+0.0001 -> 4.0001 | B106: 0

Sheet Slide 27c
A1: Lower Limit | B1: 0
A2: Upper Limit | B2: 1
A3: x | B3: f(x) | I3: Step 0: | J3: See what the picture looks like - uniform on (2,4)
A4: =A5-0.0001 -> -0.0001 | B4: 0 | I4: Step 1: | J4: See how to make this look like U(0,1)
A5: =B1 -> 0 | B5: =1/($B$2-$B$1) -> 1 | J5: To do this, we can achieve this using 2 steps
A6: =A5+(0.01*($B$2-$B$1)) -> 0.01 | B6: =1/($B$2-$B$1) -> 1 | J6: 1) Subtract all observations by 2
A7: =A6+(0.01*($B$2-$B$1)) -> 0.02 | B7: =1/($B$2-$B$1) -> 1 | J7: The result would be a uniform on (0,4)
A8: =A7+(0.01*($B$2-$B$1)) -> 0.03 | B8: =1/($B$2-$B$1) -> 1 | J8: 2) Divide all observations by 4
A9: =A8+(0.01*($B$2-$B$1)) -> 0.04 | B9: =1/($B$2-$B$1) -> 1 | J9: The result would be a uniform on (0,1)
A10: =A9+(0.01*($B$2-$B$1)) -> 0.05 | B10: =1/($B$2-$B$1) -> 1
A11: =A10+(0.01*($B$2-$B$1)) -> 0.06 | B11: =1/($B$2-$B$1) -> 1 | I11: Bottom line: If Y represents any observation from U(0,1)
A12: =A11+(0.01*($B$2-$B$1)) -> 0.07 | B12: =1/($B$2-$B$1) -> 1 | J12: and X represents any observation from U(2,6)
A13: =A12+(0.01*($B$2-$B$1)) -> 0.08 | B13: =1/($B$2-$B$1) -> 1 | J13: The we have
A14: =A13+(0.01*($B$2-$B$1)) -> 0.09 | B14: =1/($B$2-$B$1) -> 1
A15: =A14+(0.01*($B$2-$B$1)) -> 0.1 | B15: =1/($B$2-$B$1) -> 1
A16: =A15+(0.01*($B$2-$B$1)) -> 0.11 | B16: =1/($B$2-$B$1) -> 1
A17: =A16+(0.01*($B$2-$B$1)) -> 0.12 | B17: =1/($B$2-$B$1) -> 1
A18: =A17+(0.01*($B$2-$B$1)) -> 0.13 | B18: =1/($B$2-$B$1) -> 1 | J18: Put another way, if we can generate a value of
A19: =A18+(0.01*($B$2-$B$1)) -> 0.14 | B19: =1/($B$2-$B$1) -> 1 | J19: Then
A20: =A19+(0.01*($B$2-$B$1)) -> 0.15 | B20: =1/($B$2-$B$1) -> 1
A21: =A20+(0.01*($B$2-$B$1)) -> 0.16 | B21: =1/($B$2-$B$1) -> 1
A22: =A21+(0.01*($B$2-$B$1)) -> 0.17 | B22: =1/($B$2-$B$1) -> 1 | J22: In general we can say that if X is uniform on (a,b)
A23: =A22+(0.01*($B$2-$B$1)) -> 0.18 | B23: =1/($B$2-$B$1) -> 1 | J23: and Y is uniform on (0,1), then
A24: =A23+(0.01*($B$2-$B$1)) -> 0.19 | B24: =1/($B$2-$B$1) -> 1
A25: =A24+(0.01*($B$2-$B$1)) -> 0.2 | B25: =1/($B$2-$B$1) -> 1
A26: =A25+(0.01*($B$2-$B$1)) -> 0.21 | B26: =1/($B$2-$B$1) -> 1
A27: =A26+(0.01*($B$2-$B$1)) -> 0.22 | B27: =1/($B$2-$B$1) -> 1
A28: =A27+(0.01*($B$2-$B$1)) -> 0.23 | B28: =1/($B$2-$B$1) -> 1
A29: =A28+(0.01*($B$2-$B$1)) -> 0.24 | B29: =1/($B$2-$B$1) -> 1
A30: =A29+(0.01*($B$2-$B$1)) -> 0.25 | B30: =1/($B$2-$B$1) -> 1
A31: =A30+(0.01*($B$2-$B$1)) -> 0.26 | B31: =1/($B$2-$B$1) -> 1
A32: =A31+(0.01*($B$2-$B$1)) -> 0.27 | B32: =1/($B$2-$B$1) -> 1
A33: =A32+(0.01*($B$2-$B$1)) -> 0.28 | B33: =1/($B$2-$B$1) -> 1
A34: =A33+(0.01*($B$2-$B$1)) -> 0.29 | B34: =1/($B$2-$B$1) -> 1
A35: =A34+(0.01*($B$2-$B$1)) -> 0.3 | B35: =1/($B$2-$B$1) -> 1
... A105: =A104+(0.01*($B$2-$B$1)) -> 1 | B105: =1/($B$2-$B$1) -> 1
A106: =A105+0.0001 -> 1.0001 | B106: 0

Sheet Slide 27d
A1: Lower Limit of Uniform (a) | B1: 2
A2: Upper Limit of Uniform (b) | B2: 6
A3: Y - Rand U(0,1) | B3: =RAND() -> 0.4732873
A4: X - Rand U(a,b) | B4: =(B3*(B2-B1))+B1 -> 3.8931492

Sheet Slide 28
A1: Lower Limit | B1: 2
A2: Upper Limit | B2: 6
A3: x | B3: f(x) | I3: Step 0: | J3: See what the picture looks like - triangle on (2,4)
A4: =A5-0.0001 -> 1.9999 | B4: 0 | I4: Step 1: | J4: See how to make this look like U(0,1)
A5: =B1 -> 2 | B5: =(A5-$B$1)*2/(($B$2-$B$1)^2) -> 0 | J5: Any ideas?
A6: =A5+(0.01*($B$2-$B$1)) -> 2.04 | B6: =(A6-$B$1)*2/(($B$2-$B$1)^2) -> 0.005
A7: =A6+(0.01*($B$2-$B$1)) -> 2.08 | B7: =(A7-$B$1)*2/(($B$2-$B$1)^2) -> 0.01
A8: =A7+(0.01*($B$2-$B$1)) -> 2.12 | B8: =(A8-$B$1)*2/(($B$2-$B$1)^2) -> 0.015
A9: =A8+(0.01*($B$2-$B$1)) -> 2.16 | B9: =(A9-$B$1)*2/(($B$2-$B$1)^2) -> 0.02
A10: =A9+(0.01*($B$2-$B$1)) -> 2.2 | B10: =(A10-$B$1)*2/(($B$2-$B$1)^2) -> 0.025
A11: =A10+(0.01*($B$2-$B$1)) -> 2.24 | B11: =(A11-$B$1)*2/(($B$2-$B$1)^2) -> 0.03
A12: =A11+(0.01*($B$2-$B$1)) -> 2.28 | B12: =(A12-$B$1)*2/(($B$2-$B$1)^2) -> 0.035
A13: =A12+(0.01*($B$2-$B$1)) -> 2.32 | B13: =(A13-$B$1)*2/(($B$2-$B$1)^2) -> 0.04
A14: =A13+(0.01*($B$2-$B$1)) -> 2.36 | B14: =(A14-$B$1)*2/(($B$2-$B$1)^2) -> 0.045
A15: =A14+(0.01*($B$2-$B$1)) -> 2.4 | B15: =(A15-$B$1)*2/(($B$2-$B$1)^2) -> 0.05
A16: =A15+(0.01*($B$2-$B$1)) -> 2.44 | B16: =(A16-$B$1)*2/(($B$2-$B$1)^2) -> 0.055
A17: =A16+(0.01*($B$2-$B$1)) -> 2.48 | B17: =(A17-$B$1)*2/(($B$2-$B$1)^2) -> 0.06
... A105: =A104+(0.01*($B$2-$B$1)) -> 6 | B105: =(A105-$B$1)*2/(($B$2-$B$1)^2) -> 0.5
A106: =A105+0.0001 -> 6.0001 | B106: 0

Sheet Slide 30 
A1: Lower Limit | B1: 2
A2: Upper Limit | B2: 6
A3: x | B3: f(x) | C3: F(x) | I3: Step 0: | J3: See what the picture looks like - triangle on (2,4)
A4: =A5-0.0001 -> 1.9999 | B4: 0 | C4: 0 | I4: Step 1: | J4: See how to make this look like U(0,1)
A5: =B1 -> 2 | B5: =(A5-$B$1)*2/(($B$2-$B$1)^2) -> 0 | C5: =IF(A5<$B$1,0,IF(A5>$B$2,1,((A5-$B$1)^2)/(($B$2-$B$1)^2))) -> 0 | J5: Any ideas?
A6: =A5+(0.01*($B$2-$B$1)) -> 2.04 | B6: =(A6-$B$1)*2/(($B$2-$B$1)^2) -> 0.005 | C6: =IF(A6<$B$1,0,IF(A6>$B$2,1,((A6-$B$1)^2)/(($B$2-$B$1)^2))) -> 0.0001
A7: =A6+(0.01*($B$2-$B$1)) -> 2.08 | B7: =(A7-$B$1)*2/(($B$2-$B$1)^2) -> 0.01 | C7: =IF(A7<$B$1,0,IF(A7>$B$2,1,((A7-$B$1)^2)/(($B$2-$B$1)^2))) -> 0.0004
A8: =A7+(0.01*($B$2-$B$1)) -> 2.12 | B8: =(A8-$B$1)*2/(($B$2-$B$1)^2) -> 0.015 | C8: =IF(A8<$B$1,0,IF(A8>$B$2,1,((A8-$B$1)^2)/(($B$2-$B$1)^2))) -> 0.0009
A9: =A8+(0.01*($B$2-$B$1)) -> 2.16 | B9: =(A9-$B$1)*2/(($B$2-$B$1)^2) -> 0.02 | C9: =IF(A9<$B$1,0,IF(A9>$B$2,1,((A9-$B$1)^2)/(($B$2-$B$1)^2))) -> 0.0016
A10: =A9+(0.01*($B$2-$B$1)) -> 2.2 | B10: =(A10-$B$1)*2/(($B$2-$B$1)^2) -> 0.025 | C10: =IF(A10<$B$1,0,IF(A10>$B$2,1,((A10-$B$1)^2)/(($B$2-$B$1)^2))) -> 0.0025
A11: =A10+(0.01*($B$2-$B$1)) -> 2.24 | B11: =(A11-$B$1)*2/(($B$2-$B$1)^2) -> 0.03 | C11: =IF(A11<$B$1,0,IF(A11>$B$2,1,((A11-$B$1)^2)/(($B$2-$B$1)^2))) -> 0.0036
A12: =A11+(0.01*($B$2-$B$1)) -> 2.28 | B12: =(A12-$B$1)*2/(($B$2-$B$1)^2) -> 0.035 | C12: =IF(A12<$B$1,0,IF(A12>$B$2,1,((A12-$B$1)^2)/(($B$2-$B$1)^2))) -> 0.0049
A13: =A12+(0.01*($B$2-$B$1)) -> 2.32 | B13: =(A13-$B$1)*2/(($B$2-$B$1)^2) -> 0.04 | C13: =IF(A13<$B$1,0,IF(A13>$B$2,1,((A13-$B$1)^2)/(($B$2-$B$1)^2))) -> 0.0064
A14: =A13+(0.01*($B$2-$B$1)) -> 2.36 | B14: =(A14-$B$1)*2/(($B$2-$B$1)^2) -> 0.045 | C14: =IF(A14<$B$1,0,IF(A14>$B$2,1,((A14-$B$1)^2)/(($B$2-$B$1)^2))) -> 0.0081
A15: =A14+(0.01*($B$2-$B$1)) -> 2.4 | B15: =(A15-$B$1)*2/(($B$2-$B$1)^2) -> 0.05 | C15: =IF(A15<$B$1,0,IF(A15>$B$2,1,((A15-$B$1)^2)/(($B$2-$B$1)^2))) -> 0.01
A16: =A15+(0.01*($B$2-$B$1)) -> 2.44 | B16: =(A16-$B$1)*2/(($B$2-$B$1)^2) -> 0.055 | C16: =IF(A16<$B$1,0,IF(A16>$B$2,1,((A16-$B$1)^2)/(($B$2-$B$1)^2))) -> 0.0121
A17: =A16+(0.01*($B$2-$B$1)) -> 2.48 | B17: =(A17-$B$1)*2/(($B$2-$B$1)^2) -> 0.06 | C17: =IF(A17<$B$1,0,IF(A17>$B$2,1,((A17-$B$1)^2)/(($B$2-$B$1)^2))) -> 0.0144
... A105: =A104+(0.01*($B$2-$B$1)) -> 6 | B105: =(A105-$B$1)*2/(($B$2-$B$1)^2) -> 0.5 | C105: =IF(A105<$B$1,0,IF(A105>$B$2,1,((A105-$B$1)^2)/(($B$2-$B$1)^2))) -> 1
A106: =A105+0.0001 -> 6.0001 | B106: 0 | C106: =IF(A106<$B$1,0,IF(A106>$B$2,1,0.25*(A106-$B$1)*(A106-$B$1)/($B$2-$B$1))) -> 1
A107: =A106+0.1 -> 6.1001 | B107: =B106 -> 0 | C107: =IF(A107<$B$1,0,IF(A107>$B$2,1,0.25*(A107-$B$1)*(A107-$B$1)/($B$2-$B$1))) -> 1
A108: =A107+0.1 -> 6.2001 | B108: =B107 -> 0 | C108: =IF(A108<$B$1,0,IF(A108>$B$2,1,0.25*(A108-$B$1)*(A108-$B$1)/($B$2-$B$1))) -> 1
A109: =A108+0.1 -> 6.3001 | B109: =B108 -> 0 | C109: =IF(A109<$B$1,0,IF(A109>$B$2,1,0.25*(A109-$B$1)*(A109-$B$1)/($B$2-$B$1))) -> 1

Sheet Simulation of pi
A1: x | B1: =RAND() -> 0.39484877 | E1: =B4 -> 1
A2: y | B2: =RAND() -> 0.75117608 | D2: 1 | E2: 1
A3: Dist from origin | B3: =SQRT((B1^2)+(B2^2)) -> 0.84862892 | D3: =D2+1 -> 2 | E3: 0
A4: Indicator | B4: =IF(B3<1,1,0) -> 1 | D4: =D3+1 -> 3 | E4: 1
A5: Pi value | B5: =AVERAGE(E2:E1001)*4 -> 3.156 | D5: =D4+1 -> 4 | E5: 1
D6: =D5+1 -> 5 | E6: 1
D7: =D6+1 -> 6 | E7: 1
D8: =D7+1 -> 7 | E8: 1
D9: =D8+1 -> 8 | E9: 1
D10: =D9+1 -> 9 | E10: 0
D11: =D10+1 -> 10 | E11: 1
D12: =D11+1 -> 11 | E12: 1
D13: =D12+1 -> 12 | E13: 1
D14: =D13+1 -> 13 | E14: 1
D15: =D14+1 -> 14 | E15: 1
D16: =D15+1 -> 15 | E16: 1
D17: =D16+1 -> 16 | E17: 1
... D1001: =D1000+1 -> 1000 | E1001: 1

Sheet Int problem 1
A1: x | B1: =RAND() -> 0.14922727 | E1: =B3 -> 0.77014633
A2: scaled x | B2: =(B1*(3-1))+1 -> 1.2984545 | D2: 1 | E2: 0.57087174
A3: 1/x | B3: =1/B2 -> 0.77014633 | D3: =D2+1 -> 2 | E3: 0.33488792
A4: area | B4: =SUM(E2:E1001)*(3-1)/1000 -> 1.0957315 | D4: =D3+1 -> 3 | E4: 0.50679911
D5: =D4+1 -> 4 | E5: 0.6442491
D6: =D5+1 -> 5 | E6: 0.50607691
D7: =D6+1 -> 6 | E7: 0.44480903
D8: =D7+1 -> 7 | E8: 0.97862526
D9: =D8+1 -> 8 | E9: 0.67571403
D10: =D9+1 -> 9 | E10: 0.48320332
D11: =D10+1 -> 10 | E11: 0.72206936
D12: =D11+1 -> 11 | E12: 0.54989433
D13: =D12+1 -> 12 | E13: 0.36228011
D14: =D13+1 -> 13 | E14: 0.41354772
D15: =D14+1 -> 14 | E15: 0.43400305
D16: =D15+1 -> 15 | E16: 0.65151405
... D1001: =D1000+1 -> 1000 | E1001: 0.33542199

Sheet Int problem 2
A1: x | B1: =RAND() -> 0.081594291 | E1: =B3 -> 0.39885929
A2: scaled x | B2: =(B1*(0.25-0)) -> 0.020398573 | D2: 1 | E2: 0.39875514
A3: transform | B3: =EXP(-0.5*B2*B2)/SQRT(2*PI()) -> 0.39885929 | D3: =D2+1 -> 2 | E3: 0.38795135
A4: area | B4: =0.5+SUM(E2:E1001)*(0.25-0)/1000 -> 0.59876317 | D4: =D3+1 -> 3 | E4: 0.39874784
D5: =D4+1 -> 4 | E5: 0.3876562
D6: =D5+1 -> 5 | E6: 0.39137166
D7: =D6+1 -> 6 | E7: 0.39340031
D8: =D7+1 -> 7 | E8: 0.39058273
D9: =D8+1 -> 8 | E9: 0.39754516
D10: =D9+1 -> 9 | E10: 0.39755552
D11: =D10+1 -> 10 | E11: 0.39801718
D12: =D11+1 -> 11 | E12: 0.39433389
D13: =D12+1 -> 12 | E13: 0.39503733
D14: =D13+1 -> 13 | E14: 0.39650691
D15: =D14+1 -> 14 | E15: 0.38933449
D16: =D15+1 -> 15 | E16: 0.39225438
... D1001: =D1000+1 -> 1000 | E1001: 0.39612096

Sheet Slide 33_s (1 path)
A1: S0 | B1: 100
A2: r | B2: 0.1
A3: q | B3: 0.03 | J3: Time | K3: uni rand numbers | L3: normal random numbers | M3: stock price path
A4: vol | B4: 0.3 | J4: 0 | M4: =B1 -> 100
A5: Time | B5: 0.5 | J5: =J4+$B$6 -> 0.041666667 | K5: =RAND() -> 0.87787586 | L5: =NORMSINV(K5) -> 1.1644337 | M5: =M4*EXP(($B$2-$B$3-(0.5*$B$4*$B$4))*$B$6)*EXP($B$4*SQRT($B$6)*L5) -> 107.50298
A6: delta t | B6: =B5/12 -> 0.041666667 | C6: years | J6: =J5+$B$6 -> 0.083333333 | K6: =RAND() -> 0.87120772 | L6: =NORMSINV(K6) -> 1.1321187 | M6: =M5*EXP(($B$2-$B$3-(0.5*$B$4*$B$4))*$B$6)*EXP($B$4*SQRT($B$6)*L6) -> 115.34043
J7: =J6+$B$6 -> 0.125 | K7: =RAND() -> 0.66517573 | L7: =NORMSINV(K7) -> 0.42663042 | M7: =M6*EXP(($B$2-$B$3-(0.5*$B$4*$B$4))*$B$6)*EXP($B$4*SQRT($B$6)*L7) -> 118.51688
J8: =J7+$B$6 -> 0.16666667 | K8: =RAND() -> 0.64285281 | L8: =NORMSINV(K8) -> 0.36609473 | M8: =M7*EXP(($B$2-$B$3-(0.5*$B$4*$B$4))*$B$6)*EXP($B$4*SQRT($B$6)*L8) -> 121.33019
J9: =J8+$B$6 -> 0.20833333 | K9: =RAND() -> 0.12265796 | L9: =NORMSINV(K9) -> -1.161802 | M9: =M8*EXP(($B$2-$B$3-(0.5*$B$4*$B$4))*$B$6)*EXP($B$4*SQRT($B$6)*L9) -> 113.11577
J10: =J9+$B$6 -> 0.25 | K10: =RAND() -> 0.90281095 | L10: =NORMSINV(K10) -> 1.2977359 | M10: =M9*EXP(($B$2-$B$3-(0.5*$B$4*$B$4))*$B$6)*EXP($B$4*SQRT($B$6)*L10) -> 122.59954
J11: =J10+$B$6 -> 0.29166667 | K11: =RAND() -> 0.99275354 | L11: =NORMSINV(K11) -> 2.4448084 | M11: =M10*EXP(($B$2-$B$3-(0.5*$B$4*$B$4))*$B$6)*EXP($B$4*SQRT($B$6)*L11) -> 142.54792
J12: =J11+$B$6 -> 0.33333333 | K12: =RAND() -> 0.80533131 | L12: =NORMSINV(K12) -> 0.86081965 | M12: =M11*EXP(($B$2-$B$3-(0.5*$B$4*$B$4))*$B$6)*EXP($B$4*SQRT($B$6)*L12) -> 150.42041
J13: =J12+$B$6 -> 0.375 | K13: =RAND() -> 0.86107727 | L13: =NORMSINV(K13) -> 1.085172 | M13: =M12*EXP(($B$2-$B$3-(0.5*$B$4*$B$4))*$B$6)*EXP($B$4*SQRT($B$6)*L13) -> 160.92344
J14: =J13+$B$6 -> 0.41666667 | K14: =RAND() -> 0.68111962 | L14: =NORMSINV(K14) -> 0.47083194 | M14: =M13*EXP(($B$2-$B$3-(0.5*$B$4*$B$4))*$B$6)*EXP($B$4*SQRT($B$6)*L14) -> 165.80342
J15: =J14+$B$6 -> 0.45833333 | K15: =RAND() -> 0.54374464 | L15: =NORMSINV(K15) -> 0.10987221 | M15: =M14*EXP(($B$2-$B$3-(0.5*$B$4*$B$4))*$B$6)*EXP($B$4*SQRT($B$6)*L15) -> 167.09672
J16: =J15+$B$6 -> 0.5 | K16: =RAND() -> 0.20426898 | L16: =NORMSINV(K16) -> -0.82646923 | M16: =M15*EXP(($B$2-$B$3-(0.5*$B$4*$B$4))*$B$6)*EXP($B$4*SQRT($B$6)*L16) -> 159.01583

Sheet Slide 33_o (1 path)
A1: S0 | B1: 100
A2: X | B2: 120
A3: r | B3: 0.1 | J3: Time | K3: uni rand numbers | L3: normal random numbers | M3: stock price path
A4: q | B4: 0.03 | J4: 0 | M4: =B1 -> 100
A5: vol | B5: 0.3 | J5: =J4+$B$7 -> 0.041666667 | K5: =RAND() -> 0.96394347 | L5: =NORMSINV(K5) -> 1.7984037 | M5: =M4*EXP(($B$3-$B$4-(0.5*$B$5*$B$5))*$B$7)*EXP($B$5*SQRT($B$7)*L5) -> 111.75859
A6: Time | B6: 0.5 | J6: =J5+$B$7 -> 0.083333333 | K6: =RAND() -> 0.2520922 | L6: =NORMSINV(K6) -> -0.66792041 | M6: =M5*EXP(($B$3-$B$4-(0.5*$B$5*$B$5))*$B$7)*EXP($B$5*SQRT($B$7)*L6) -> 107.39152
A7: delta t | B7: =B6/12 -> 0.041666667 | C7: years | J7: =J6+$B$7 -> 0.125 | K7: =RAND() -> 0.37178465 | L7: =NORMSINV(K7) -> -0.32713034 | M7: =M6*EXP(($B$3-$B$4-(0.5*$B$5*$B$5))*$B$7)*EXP($B$5*SQRT($B$7)*L7) -> 105.3713
J8: =J7+$B$7 -> 0.16666667 | K8: =RAND() -> 0.16168933 | L8: =NORMSINV(K8) -> -0.9875386 | M8: =M7*EXP(($B$3-$B$4-(0.5*$B$5*$B$5))*$B$7)*EXP($B$5*SQRT($B$7)*L8) -> 99.291288
J9: =J8+$B$7 -> 0.20833333 | K9: =RAND() -> 0.46457891 | L9: =NORMSINV(K9) -> -0.088904489 | M9: =M8*EXP(($B$3-$B$4-(0.5*$B$5*$B$5))*$B$7)*EXP($B$5*SQRT($B$7)*L9) -> 98.855109
J10: =J9+$B$7 -> 0.25 | K10: =RAND() -> 0.040759296 | L10: =NORMSINV(K10) -> -1.741942 | M10: =M9*EXP(($B$3-$B$4-(0.5*$B$5*$B$5))*$B$7)*EXP($B$5*SQRT($B$7)*L10) -> 88.94562
J11: =J10+$B$7 -> 0.29166667 | K11: =RAND() -> 0.45332765 | L11: =NORMSINV(K11) -> -0.1172584 | M11: =M10*EXP(($B$3-$B$4-(0.5*$B$5*$B$5))*$B$7)*EXP($B$5*SQRT($B$7)*L11) -> 88.401263
J12: =J11+$B$7 -> 0.33333333 | K12: =RAND() -> 0.034319441 | L12: =NORMSINV(K12) -> -1.8207894 | M12: =M11*EXP(($B$3-$B$4-(0.5*$B$5*$B$5))*$B$7)*EXP($B$5*SQRT($B$7)*L12) -> 79.156571
J13: =J12+$B$7 -> 0.375 | K13: =RAND() -> 0.4642842 | L13: =NORMSINV(K13) -> -0.089646171 | M13: =M12*EXP(($B$3-$B$4-(0.5*$B$5*$B$5))*$B$7)*EXP($B$5*SQRT($B$7)*L13) -> 78.805263
J14: =J13+$B$7 -> 0.41666667 | K14: =RAND() -> 0.88914442 | L14: =NORMSINV(K14) -> 1.2219907 | M14: =M13*EXP(($B$3-$B$4-(0.5*$B$5*$B$5))*$B$7)*EXP($B$5*SQRT($B$7)*L14) -> 85.017132
J15: =J14+$B$7 -> 0.45833333 | K15: =RAND() -> 0.52684879 | L15: =NORMSINV(K15) -> 0.067350821 | M15: =M14*EXP(($B$3-$B$4-(0.5*$B$5*$B$5))*$B$7)*EXP($B$5*SQRT($B$7)*L15) -> 85.457471
J16: =J15+$B$7 -> 0.5 | K16: =RAND() -> 0.633051 | L16: =NORMSINV(K16) -> 0.33994493 | M16: =M15*EXP(($B$3-$B$4-(0.5*$B$5*$B$5))*$B$7)*EXP($B$5*SQRT($B$7)*L16) -> 87.346048
L17: Option Payoff (1 path) | M17: =MAX(M16-B2,0) -> 0
L18: PV (Option payoff (1 path)) | M18: =M17*EXP(-B3*B6) -> 0

Sheet Slide 34_ R
A1: S0 | B1: 100
A2: X | B2: 100
A3: r | B3: 0.1 | J3: Time | K3: uni rand numbers | L3: normal random numbers | M3: stock price path
A4: q | B4: 0.03 | J4: 0 | M4: =B1 -> 100 | P4: Path | Q4: =M12 -> 0
A5: vol | B5: 0.3 | J5: =J4+$B$7 -> 0.083333333 | K5: =RAND() -> 0.80405172 | L5: =NORMSINV(K5) -> 0.85618301 | M5: =M4*EXP(($B$3-$B$4-(0.5*$B$5*$B$5))*$B$7)*EXP($B$5*SQRT($B$7)*L5) -> 107.92118 | P5: 1 | Q5: 3.8937523
A6: Time | B6: 0.5 | J6: =J5+$B$7 -> 0.16666667 | K6: =RAND() -> 0.3008047 | L6: =NORMSINV(K6) -> -0.52208753 | M6: =M5*EXP(($B$3-$B$4-(0.5*$B$5*$B$5))*$B$7)*EXP($B$5*SQRT($B$7)*L6) -> 103.36541 | P6: =P5+1 -> 2 | Q6: 0
A7: delta t | B7: =B6/6 -> 0.083333333 | C7: years | J7: =J6+$B$7 -> 0.25 | K7: =RAND() -> 0.54342702 | L7: =NORMSINV(K7) -> 0.10907128 | M7: =M6*EXP(($B$3-$B$4-(0.5*$B$5*$B$5))*$B$7)*EXP($B$5*SQRT($B$7)*L7) -> 104.56402 | P7: =P6+1 -> 3 | Q7: 0
J8: =J7+$B$7 -> 0.33333333 | K8: =RAND() -> 0.10685088 | L8: =NORMSINV(K8) -> -1.2434508 | M8: =M7*EXP(($B$3-$B$4-(0.5*$B$5*$B$5))*$B$7)*EXP($B$5*SQRT($B$7)*L8) -> 94.084836 | P8: =P7+1 -> 4 | Q8: 0
J9: =J8+$B$7 -> 0.41666667 | K9: =RAND() -> 0.10968214 | L9: =NORMSINV(K9) -> -1.2282203 | M9: =M8*EXP(($B$3-$B$4-(0.5*$B$5*$B$5))*$B$7)*EXP($B$5*SQRT($B$7)*L9) -> 84.767586 | P9: =P8+1 -> 5 | Q9: 2.6513056
J10: =J9+$B$7 -> 0.5 | K10: =RAND() -> 0.023739043 | L10: =NORMSINV(K10) -> -1.9820103 | M10: =M9*EXP(($B$3-$B$4-(0.5*$B$5*$B$5))*$B$7)*EXP($B$5*SQRT($B$7)*L10) -> 71.546632 | P10: =P9+1 -> 6 | Q10: 0
L11: Option Payoff (T) | M11: =MAX(AVERAGE(M5:M10)-B2,0) -> 0 | P11: =P10+1 -> 7 | Q11: 33.031955
L12: Option Payoff (0) | M12: =M11*EXP(-B3*B6) -> 0 | P12: =P11+1 -> 8 | Q12: 15.632542
L13: Option Premium | M13: =AVERAGE(Q5:Q5004) -> 6.3606192 | P13: =P12+1 -> 9 | Q13: 2.4977401
P14: =P13+1 -> 10 | Q14: 0.0023923055
P15: =P14+1 -> 11 | Q15: 0
P16: =P15+1 -> 12 | Q16: 0
P17: =P16+1 -> 13 | Q17: 0
P18: =P17+1 -> 14 | Q18: 22.916211
P19: =P18+1 -> 15 | Q19: 16.475979
P20: =P19+1 -> 16 | Q20: 0
P21: =P20+1 -> 17 | Q21: 0
P22: =P21+1 -> 18 | Q22: 21.007639
P23: =P22+1 -> 19 | Q23: 0
P24: =P23+1 -> 20 | Q24: 0
P25: =P24+1 -> 21 | Q25: 3.4350872
... P5004: =P5003+1 -> 5000 | Q5004: 0

Sheet Slide 35_ R
A1: S0 | B1: 100
A2: r | B2: 0.1
A3: q | B3: 0.03 | J3: Time | K3: uni rand numbers | L3: normal random numbers | M3: stock price path
A4: vol | B4: 0.3 | J4: 0 | M4: =B1 -> 100 | P4: Path | Q4: =M12 -> 0
A5: Time | B5: 0.5 | J5: =J4+$B$6 -> 0.083333333 | K5: =RAND() -> 0.16798765 | L5: =NORMSINV(K5) -> -0.96214794 | M5: =M4*EXP(($B$2-$B$3-(0.5*$B$4*$B$4))*$B$6)*EXP($B$4*SQRT($B$6)*L5) -> 92.197136 | P5: 1 | Q5: 4.3320952
A6: delta t | B6: =B5/6 -> 0.083333333 | C6: years | J6: =J5+$B$6 -> 0.16666667 | K6: =RAND() -> 0.0092226783 | L6: =NORMSINV(K6) -> -2.3565546 | M6: =M5*EXP(($B$2-$B$3-(0.5*$B$4*$B$4))*$B$6)*EXP($B$4*SQRT($B$6)*L6) -> 75.333791 | P6: =P5+1 -> 2 | Q6: 6.4776234
J7: =J6+$B$6 -> 0.25 | K7: =RAND() -> 0.067994546 | L7: =NORMSINV(K7) -> -1.4908949 | M7: =M6*EXP(($B$2-$B$3-(0.5*$B$4*$B$4))*$B$6)*EXP($B$4*SQRT($B$6)*L7) -> 66.346886 | P7: =P6+1 -> 3 | Q7: 0
J8: =J7+$B$6 -> 0.33333333 | K8: =RAND() -> 0.20011623 | L8: =NORMSINV(K8) -> -0.84120613 | M8: =M7*EXP(($B$2-$B$3-(0.5*$B$4*$B$4))*$B$6)*EXP($B$4*SQRT($B$6)*L8) -> 61.813982 | P8: =P7+1 -> 4 | Q8: 0
J9: =J8+$B$6 -> 0.41666667 | K9: =RAND() -> 0.50631115 | L9: =NORMSINV(K9) -> 0.015820355 | M9: =M8*EXP(($B$2-$B$3-(0.5*$B$4*$B$4))*$B$6)*EXP($B$4*SQRT($B$6)*L9) -> 62.02782 | P9: =P8+1 -> 5 | Q9: 5.489016
J10: =J9+$B$6 -> 0.5 | K10: =RAND() -> 0.63461648 | L10: =NORMSINV(K10) -> 0.34410537 | M10: =M9*EXP(($B$2-$B$3-(0.5*$B$4*$B$4))*$B$6)*EXP($B$4*SQRT($B$6)*L10) -> 64.037364 | P10: =P9+1 -> 6 | Q10: 0
L11: Option Payoff (T) | M11: =MAX(M10-M7,0) -> 0 | P11: =P10+1 -> 7 | Q11: 11.380498
L12: Option Payoff (0) | M12: =M11*EXP(-B2*B5) -> 0 | P12: =P11+1 -> 8 | Q12: 0
L13: Option Premium | M13: =AVERAGE(Q5:Q5004) -> 6.85673 | P13: =P12+1 -> 9 | Q13: 1.0158595
P14: =P13+1 -> 10 | Q14: 6.0086383
P15: =P14+1 -> 11 | Q15: 0.72627437
P16: =P15+1 -> 12 | Q16: 30.066755
P17: =P16+1 -> 13 | Q17: 6.7451268
P18: =P17+1 -> 14 | Q18: 4.7850605
P19: =P18+1 -> 15 | Q19: 24.221874
P20: =P19+1 -> 16 | Q20: 0
P21: =P20+1 -> 17 | Q21: 19.605008
P22: =P21+1 -> 18 | Q22: 9.8923095
P23: =P22+1 -> 19 | Q23: 0
P24: =P23+1 -> 20 | Q24: 0
P25: =P24+1 -> 21 | Q25: 0
... P5004: =P5003+1 -> 5000 | Q5004: 0

Sheet Slide 36_R
A1: S0 | B1: 100
A2: X | B2: 120
A3: H | B3: 90 | J3: Time | K3: uni rand numbers | L3: normal random numbers | M3: stock price path
A4: r | B4: 0.1 | J4: 0 | M4: =B1 -> 100 | P4: Path | Q4: =M12 -> 10.742714
A5: q | B5: 0.03 | J5: =J4+$B$8 -> 0.083333333 | K5: =RAND() -> 0.46544885 | L5: =NORMSINV(K5) -> -0.086715454 | M5: =M4*EXP(($B$4-$B$5-(0.5*$B$6*$B$6))*$B$8)*EXP($B$6*SQRT($B$8)*L5) -> 99.458825 | P5: 1 | Q5: 28.527695
A6: vol | B6: 0.3 | J6: =J5+$B$8 -> 0.16666667 | K6: =RAND() -> 0.56040771 | L6: =NORMSINV(K6) -> 0.15200299 | M6: =M5*EXP(($B$4-$B$5-(0.5*$B$6*$B$6))*$B$8)*EXP($B$6*SQRT($B$8)*L6) -> 100.98691 | P6: =P5+1 -> 2 | Q6: 0
A7: Time | B7: 0.5 | J7: =J6+$B$8 -> 0.25 | K7: =RAND() -> 0.68492587 | L7: =NORMSINV(K7) -> 0.48151819 | M7: =M6*EXP(($B$4-$B$5-(0.5*$B$6*$B$6))*$B$8)*EXP($B$6*SQRT($B$8)*L7) -> 105.50675 | P7: =P6+1 -> 3 | Q7: 0
A8: delta t | B8: =B7/6 -> 0.083333333 | C8: years | J8: =J7+$B$8 -> 0.33333333 | K8: =RAND() -> 0.32721345 | L8: =NORMSINV(K8) -> -0.44762078 | M8: =M7*EXP(($B$4-$B$5-(0.5*$B$6*$B$6))*$B$8)*EXP($B$6*SQRT($B$8)*L8) -> 101.7067 | P8: =P7+1 -> 4 | Q8: 12.610208
J9: =J8+$B$8 -> 0.41666667 | K9: =RAND() -> 0.87767121 | L9: =NORMSINV(K9) -> 1.1634238 | M9: =M8*EXP(($B$4-$B$5-(0.5*$B$6*$B$6))*$B$8)*EXP($B$6*SQRT($B$8)*L9) -> 112.72283 | P9: =P8+1 -> 5 | Q9: 0
J10: =J9+$B$8 -> 0.5 | K10: =RAND() -> 0.95879763 | L10: =NORMSINV(K10) -> 1.7369005 | M10: =M9*EXP(($B$4-$B$5-(0.5*$B$6*$B$6))*$B$8)*EXP($B$6*SQRT($B$8)*L10) -> 131.2935 | P10: =P9+1 -> 6 | Q10: 0
L11: Option Payoff (T) | M11: =IF(MIN(M5:M9)>90,MAX(M10-B2,0),0) -> 11.293505 | P11: =P10+1 -> 7 | Q11: 0
L12: Option Payoff (0) | M12: =M11*EXP(-B4*B7) -> 10.742714 | P12: =P11+1 -> 8 | Q12: 0
L13: Option Premium | M13: =AVERAGE(Q5:Q5004) -> 3.3388432 | P13: =P12+1 -> 9 | Q13: 26.77257
P14: =P13+1 -> 10 | Q14: 0
P15: =P14+1 -> 11 | Q15: 0
P16: =P15+1 -> 12 | Q16: 0
P17: =P16+1 -> 13 | Q17: 3.4711967
P18: =P17+1 -> 14 | Q18: 0
P19: =P18+1 -> 15 | Q19: 15.25587
P20: =P19+1 -> 16 | Q20: 0
P21: =P20+1 -> 17 | Q21: 0
P22: =P21+1 -> 18 | Q22: 0
P23: =P22+1 -> 19 | Q23: 0
P24: =P23+1 -> 20 | Q24: 0
P25: =P24+1 -> 21 | Q25: 0
... P5004: =P5003+1 -> 5000 | Q5004: 49.43091

Sheet Slide 37_data
A1: Term (mths) | B1: Zero Rates | C1: Dividend Rates | D1: Spot Volatility
A2: 0.5 | B2: 0.03 | C2: 0.0005 | D2: 0.3
A3: =A2+0.5 -> 1 | B3: =B2+0.0025 -> 0.0325 | C3: =C2+0.0025 -> 0.003 | D3: =D2+0.05 -> 0.35
A4: =A3+0.5 -> 1.5 | B4: =B3+0.0025 -> 0.035 | C4: =C3+0.0025 -> 0.0055 | D4: =D3+0.05 -> 0.4
A5: =A4+0.5 -> 2 | B5: =B4+0.0025 -> 0.0375 | C5: =C4+0.0025 -> 0.008 | D5: =D4+0.05 -> 0.45
A6: =A5+0.5 -> 2.5 | B6: =B5+0.0025 -> 0.04 | C6: =C5+0.0025 -> 0.0105 | D6: =D5+0.05 -> 0.5
A7: =A6+0.5 -> 3 | B7: =B6+0.0025 -> 0.0425 | C7: =C6+0.0025 -> 0.013 | D7: =D6+0.05 -> 0.55
A8: =A7+0.5 -> 3.5 | B8: =B7+0.0025 -> 0.045 | C8: =C7+0.0025 -> 0.0155 | D8: =D7+0.05 -> 0.6
A9: =A8+0.5 -> 4 | B9: =B8+0.0025 -> 0.0475 | C9: =C8+0.0025 -> 0.018 | D9: =D8+0.05 -> 0.65
A10: =A9+0.5 -> 4.5 | B10: =B9+0.0025 -> 0.05 | C10: =C9+0.0025 -> 0.0205 | D10: =D9+0.05 -> 0.7
A11: =A10+0.5 -> 5 | B11: =B10+0.0025 -> 0.0525 | C11: =C10+0.0025 -> 0.023 | D11: =D10+0.05 -> 0.75
A12: =A11+0.5 -> 5.5 | B12: =B11+0.0025 -> 0.055 | C12: =C11+0.0025 -> 0.0255 | D12: =D11+0.05 -> 0.8
A13: =A12+0.5 -> 6 | B13: =B12+0.0025 -> 0.0575 | C13: =C12+0.0025 -> 0.028 | D13: =D12+0.05 -> 0.85

Sheet Slide 37_R (simple)
B3: S0 | C3: 100 | F3: Time (mths) | G3: zero risk free | H3: zero dividend | I3: spot volatility | J3: uni rand numbers | K3: normal random numbers | L3: stock price path
A4: Call | B4: Strike | C4: 120 | F4: 0 | L4: =C3 -> 100 | O4: Path | P4: =L16 -> 1.6540637
B5: Option Life (yrs) | C5: =3/12 -> 0.25 | F5: 2 | G5: =B9 -> 0.05 | H5: =B10 -> 0.02 | I5: =B11 -> 0.3 | J5: =RAND() -> 0.64546739 | K5: =NORMSINV(J5) -> 0.37311181 | L5: =L4*EXP((G5-H5-(0.5*I5*I5))*F5/12)*EXP(I5*SQRT((F5-F4)/12)*K5) -> 104.41432 | O5: 1 | P5: 2.8199114
A6: Put | B6: Strike | C6: 90 | K6: Option Type | L6: Call | M6: Put | O6: =O5+1 -> 2 | P6: 3.3973954
B7: Option Life (yrs) | C7: =4/12 -> 0.33333333 | K7: Spot | L7: =L5 -> 104.41432 | M7: =L5 -> 104.41432 | O7: =O6+1 -> 3 | P7: 4.9252461
K8: Strike | L8: =C4 -> 120 | M8: =C6 -> 90 | O8: =O7+1 -> 4 | P8: 7.1088157
A9: r | B9: 0.05 | K9: Option Life | L9: =C5 -> 0.25 | M9: =C7 -> 0.33333333 | O9: =O8+1 -> 5 | P9: 1.9085479
A10: q | B10: 0.02 | K10: Risk-free | L10: =B9 -> 0.05 | M10: =L10 -> 0.05 | O10: =O9+1 -> 6 | P10: 5.2011794
A11: sigma | B11: 0.3 | K11: Dividend | L11: =B10 -> 0.02 | M11: =L11 -> 0.02 | O11: =O10+1 -> 7 | P11: 4.4291977
K12: Volatility | L12: =B11 -> 0.3 | M12: =L12 -> 0.3 | O12: =O11+1 -> 8 | P12: 2.6524741
K13: d1 | L13: =(LN(L7/L8)+((L10-L11+(0.5*L9*L9))*L9))/(L9*SQRT(L9)) -> -0.99049903 | M13: =(LN(M7/M8)+((M10-M11+(0.5*M9*M9))*M9))/(M9*SQRT(M9)) -> 0.92011239 | O13: =O12+1 -> 9 | P13: 1.9818911
K14: d2 | L14: =L13-(L12*SQRT(L9)) -> -1.140499 | M14: =M13-(M12*SQRT(M9)) -> 0.74690731 | O14: =O13+1 -> 10 | P14: 6.2388982
K15: Option Premium | L15: =(L7*EXP(-L11*L9)*NORMSDIST(L13))-(L8*EXP(-L10*L9)*NORMSDIST(L14)) -> 1.6679051 | M15: =(-M7*EXP(-M11*M9)*NORMSDIST(-M13))+(M8*EXP(-M10*M9)*NORMSDIST(-M14)) -> 1.6010925 | O15: =O14+1 -> 11 | P15: 6.0397032
K16: Best Choice Value | L16: =MAX(L15,M15)*EXP(-G5*F5/12) -> 1.6540637 | O16: =O15+1 -> 12 | P16: 2.2720055
K17: Option Premium | L17: =AVERAGE(P5:P5004) -> 5.0005953 | O17: =O16+1 -> 13 | P17: 3.6879458
O18: =O17+1 -> 14 | P18: 6.0981231
O19: =O18+1 -> 15 | P19: 5.1513515
O20: =O19+1 -> 16 | P20: 9.5748099
O21: =O20+1 -> 17 | P21: 6.147869
O22: =O21+1 -> 18 | P22: 5.6298787
O23: =O22+1 -> 19 | P23: 2.6018768
O24: =O23+1 -> 20 | P24: 8.2324982
O25: =O24+1 -> 21 | P25: 10.029498
O26: =O25+1 -> 22 | P26: 4.3197357
O27: =O26+1 -> 23 | P27: 3.3690963
O28: =O27+1 -> 24 | P28: 3.0715356
O29: =O28+1 -> 25 | P29: 2.4300039
... O5004: =O5003+1 -> 5000 | P5004: 4.9016959

Sheet Slide 37_R
A1: Term (mths) | B1: Zero Rates | C1: Dividend Rates | D1: Spot Volatility
A2: 0.5 | B2: 0.03 | C2: 0.0005 | D2: 0.3
A3: =A2+0.5 -> 1 | B3: =B2+0.0025 -> 0.0325 | C3: =C2+0.0025 -> 0.003 | D3: =D2+0.05 -> 0.35 | G3: S0 | H3: 100 | J3: Time (mths) | K3: zero risk free | L3: zero dividend | M3: spot volatility | N3: uni rand numbers | O3: normal random numbers | P3: stock price path
A4: =A3+0.5 -> 1.5 | B4: =B3+0.0025 -> 0.035 | C4: =C3+0.0025 -> 0.0055 | D4: =D3+0.05 -> 0.4 | F4: Call | G4: Strike | H4: 120 | J4: 0 | P4: =H3 -> 100 | S4: Path | T4: =P16 -> 20.38643
A5: =A4+0.5 -> 2 | B5: =B4+0.0025 -> 0.0375 | C5: =C4+0.0025 -> 0.008 | D5: =D4+0.05 -> 0.45 | G5: Option Life (yrs) | H5: =3/12 -> 0.25 | J5: 2 | K5: =VLOOKUP(J5,$A$2:$B$13,2,FALSE) -> 0.0375 | L5: =VLOOKUP(J5,$A$2:$C$13,3,FALSE) -> 0.008 | M5: =VLOOKUP(J5,$A$2:$D$13,4,FALSE) -> 0.45 | N5: =RAND() -> 0.18922262 | O5: =NORMSINV(N5) -> -0.8807646 | P5: =P4*EXP((K5-L5-(0.5*M5*M5))*J5/12)*EXP(M5*SQRT((J5-J4)/12)*O5) -> 84.049429 | S5: 1 | T5: 22.9147
A6: =A5+0.5 -> 2.5 | B6: =B5+0.0025 -> 0.04 | C6: =C5+0.0025 -> 0.0105 | D6: =D5+0.05 -> 0.5 | F6: Put | G6: Strike | H6: 90 | O6: Option Type | P6: Call | Q6: Put | S6: =S5+1 -> 2 | T6: 19.937182
A7: =A6+0.5 -> 3 | B7: =B6+0.0025 -> 0.0425 | C7: =C6+0.0025 -> 0.013 | D7: =D6+0.05 -> 0.55 | G7: Option Life (yrs) | H7: =4/12 -> 0.33333333 | O7: Spot | P7: =P5 -> 84.049429 | Q7: =P5 -> 84.049429 | S7: =S6+1 -> 3 | T7: 19.097224
A8: =A7+0.5 -> 3.5 | B8: =B7+0.0025 -> 0.045 | C8: =C7+0.0025 -> 0.0155 | D8: =D7+0.05 -> 0.6 | O8: Strike | P8: =H4 -> 120 | Q8: =H6 -> 90 | S8: =S7+1 -> 4 | T8: 20.854288
A9: =A8+0.5 -> 4 | B9: =B8+0.0025 -> 0.0475 | C9: =C8+0.0025 -> 0.018 | D9: =D8+0.05 -> 0.65 | O9: Option Life | P9: =H5 -> 0.25 | Q9: =H7 -> 0.33333333 | S9: =S8+1 -> 5 | T9: 30.555597
A10: =A9+0.5 -> 4.5 | B10: =B9+0.0025 -> 0.05 | C10: =C9+0.0025 -> 0.0205 | D10: =D9+0.05 -> 0.7 | O10: Risk-free | P10: =((B11*A11/12)-(B5*A5/12))/((A11-A5)/12) -> 0.0625 | Q10: =((B13*A13/12)-(B5*A5/12))/((A13-A5)/12) -> 0.0675 | S10: =S9+1 -> 6 | T10: 27.116719
A11: =A10+0.5 -> 5 | B11: =B10+0.0025 -> 0.0525 | C11: =C10+0.0025 -> 0.023 | D11: =D10+0.05 -> 0.75 | O11: Dividend | P11: =((C11*A11/12)-(C5*A5/12))/((A11-A5)/12) -> 0.033 | Q11: =((C13*A13/12)-(C5*A5/12))/((A13-A5)/12) -> 0.038 | S11: =S10+1 -> 7 | T11: 26.386914
A12: =A11+0.5 -> 5.5 | B12: =B11+0.0025 -> 0.055 | C12: =C11+0.0025 -> 0.0255 | D12: =D11+0.05 -> 0.8 | O12: Volatility | P12: =SQRT(((D11*D11*A11/12)-(D5*D5*A5/12))/((A11-A5)/12)) -> 0.89582364 | Q12: =SQRT(((D13*D13*A13/12)-(D5*D5*A5/12))/((A13-A5)/12)) -> 0.99121138 | S12: =S11+1 -> 8 | T12: 18.724
A13: =A12+0.5 -> 6 | B13: =B12+0.0025 -> 0.0575 | C13: =C12+0.0025 -> 0.028 | D13: =D12+0.05 -> 0.85 | O13: d1 | P13: =(LN(P7/P8)+((P10-P11+(0.5*P9*P9))*P9))/(P9*SQRT(P9)) -> -2.7271934 | Q13: =(LN(Q7/Q8)+((Q10-Q11+(0.5*Q9*Q9))*Q9))/(Q9*SQRT(Q9)) -> -0.20812022 | S13: =S12+1 -> 9 | T13: 24.891785
O14: d2 | P14: =P13-(P12*SQRT(P9)) -> -3.1751053 | Q14: =Q13-(Q12*SQRT(Q9)) -> -0.78039637 | S14: =S13+1 -> 10 | T14: 18.170194
O15: Option Premium | P15: =(P7*EXP(-P11*P9)*NORMSDIST(P13))-(P8*EXP(-P10*P9)*NORMSDIST(P14)) -> 0.17775383 | Q15: =(-Q7*EXP(-Q11*Q9)*NORMSDIST(-Q13))+(Q8*EXP(-Q10*Q9)*NORMSDIST(-Q14)) -> 20.514244 | S15: =S14+1 -> 11 | T15: 18.966213
O16: Best Choice Value | P16: =MAX(P15,Q15)*EXP(-K5*J5/12) -> 20.38643 | S16: =S15+1 -> 12 | T16: 30.23905
O17: Option Premium | P17: =AVERAGE(T5:T5004) -> 19.078388 | S17: =S16+1 -> 13 | T17: 21.084672
S18: =S17+1 -> 14 | T18: 15.95239
S19: =S18+1 -> 15 | T19: 22.523208
S20: =S19+1 -> 16 | T20: 20.394171
S21: =S20+1 -> 17 | T21: 18.602976
S22: =S21+1 -> 18 | T22: 19.713586
S23: =S22+1 -> 19 | T23: 21.605782
S24: =S23+1 -> 20 | T24: 18.556084
S25: =S24+1 -> 21 | T25: 17.503326
S26: =S25+1 -> 22 | T26: 14.962198
S27: =S26+1 -> 23 | T27: 20.474633
S28: =S27+1 -> 24 | T28: 20.376757
S29: =S28+1 -> 25 | T29: 12.57744
... S5004: =S5003+1 -> 5000 | T5004: 26.552689

Sheet Slide 41
A1: S0 | B1: 1.6 | C1: USD per GBP
A2: K | B2: 1.7 | C2: USD per GBP | G2: Now that we have all the inputs mapped out,
A3: Volatility | B3: 0.141 | G3: What does call on £ mean? Call opiton or put option
A4: Risk free | B4: 0.08 | C4: <<dom risk free (US)
A5: Dividend | B5: 0.11 | C5: <<for risk free (GBP)
A6: Term | B6: =1/3 -> 0.33333333 | C6: years
A11: USD - domestic rate
A12: GBP - foreign rate

Sheet Slide 42
A1: S0 | B1: 1.6 | C1: USD per GBP | F1: d1 | G1: =(LN(B1/B2)+(((B4-B5)+(0.5*B3*B3))*B6))/(B3*SQRT(B6)) -> -0.82685307
A2: K | B2: 1.7 | C2: USD per GBP | F2: d2 | G2: =G1-(B3*SQRT(B6)) -> -0.90825946
A3: Volatility | B3: 0.141
A4: Risk free | B4: 0.08 | C4: <<dom risk free (US) | F4: Call (on £) | G4: =(B1*EXP(-B5*B6)*NORMSDIST(G1))-(B2*EXP(-B4*B6)*NORMSDIST(G2)) -> 0.013851662 | H4: USD per GBP | I4: <<<rate
A5: Dividend | B5: 0.11 | C5: <<for risk free (GBP)
A6: Term | B6: =1/3 -> 0.33333333 | C6: years
A11: USD - domestic rate
A12: GBP - foreign rate

Sheet Slide 43a
B2: Options On Stocks | C2: Options of Currencies
A3: underlying | B3: stock (prices) | C3: currency (rates)
A4: strike | B4: price | C4: rate
A5: r | B5: zero rate (domestic) | C5: zero rate (domestic)
A6: q | B6: dividend rate | C6: zero rate (foreign)
A7: sigma | B7: stock volatility | C7: rate volatility
A8: time | B8: option life | C8: option life
A9: notional | B9: Number of stocks | C9: Currency ($ or £ or USD)
A10: type | B10: call or put | C10: call on currency or put on currency

Sheet Slide 43b
A1: S0 | B1: 1.6 | C1: USD per GBP | F1: d1 | G1: =(LN(B1/B2)+(((B4-B5)+(0.5*B3*B3))*B6))/(B3*SQRT(B6)) -> -0.82685307
A2: K | B2: 1.7 | C2: USD per GBP | F2: d2 | G2: =G1-(B3*SQRT(B6)) -> -0.90825946
A3: Volatility | B3: 0.141
A4: Risk free | B4: 0.08 | C4: <<dom risk free (US) | F4: Call (on £) | G4: =(B1*EXP(-B5*B6)*NORMSDIST(G1))-(B2*EXP(-B4*B6)*NORMSDIST(G2)) -> 0.013851662 | H4: USD per GBP | I4: <<<rate
A5: Dividend | B5: 0.11 | C5: <<for risk free (GBP) | F5: Call premium | G5: =G4*B7 -> 1385.1662 | H5: USD | I5: <<<dollars
A6: Term | B6: =1/3 -> 0.33333333 | C6: years
A7: Notional | B7: 100000 | C7: £
A11: USD - domestic rate
A12: GBP - foreign rate

Sheet Slide 44
A1: S0 | B1: =1/1.6 -> 0.625 | C1: GBP per USD | F1: d1 | G1: =(LN(B1/B2)+(((B4-B5)+(0.5*B3*B3))*B6))/(B3*SQRT(B6)) -> 0.90825946
A2: K | B2: =1/1.7 -> 0.58823529 | C2: GBP per USD | F2: d2 | G2: =G1-(B3*SQRT(B6)) -> 0.82685307
A3: Volatility | B3: 0.141
A4: Risk free | B4: 0.11 | C4: <<dom risk free (GBP) | F4: Put (on £) | G4: =(-B1*EXP(-B5*B6)*NORMSDIST(-G1))+(B2*EXP(-B4*B6)*NORMSDIST(-G2)) -> 0.0050925229 | H4: GBP per USD | I4: <<<rate
A5: Dividend | B5: 0.08 | C5: <<for risk free (USD) | F5: Put premium | G5: =G4*B7 -> 865.72889 | H5: GBP | I5: <<<dollars
A6: Term | B6: =1/3 -> 0.33333333 | C6: years | F6: Put premium | G6: =G5/B1 -> 1385.1662 | H6: USD
A7: Notional | B7: 170000 | C7: USD
A11: USD - domestic rate
A12: GBP - foreign rate

Sheet Slide 45
A1: S0 | B1: 1.6 | C1: USD per GBP | F1: d1 | G1: =(LN(B1/B2)+(((B4-B5)+(0.5*B3*B3))*B6))/(B3*SQRT(B6)) -> -0.82685307 | L1: S0 | M1: =1/B1 -> 0.625 | N1: GBP per USD | Q1: d1 | R1: =(LN(M1/M2)+(((M4-M5)+(0.5*M3*M3))*M6))/(M3*SQRT(M6)) -> 0.90825946
A2: K | B2: 1.7 | C2: USD per GBP | F2: d2 | G2: =G1-(B3*SQRT(B6)) -> -0.90825946 | L2: K | M2: =1/B2 -> 0.58823529 | N2: GBP per USD | Q2: d2 | R2: =R1-(M3*SQRT(M6)) -> 0.82685307
A3: Volatility | B3: 0.141 | L3: Volatility | M3: 0.141
A4: Risk free | B4: 0.08 | C4: <<dom risk free (US) | F4: Call (GBP) | G4: =(B1*EXP(-B5*B6)*NORMSDIST(G1))-(B2*EXP(-B4*B6)*NORMSDIST(G2)) -> 0.013851662 | H4: USD per GBP | I4: <<<rate | L4: Risk free | M4: =B5 -> 0.11 | N4: <<dom risk free GBP | Q4: Call (USD) | R4: =(M1*EXP(-M5*M6)*NORMSDIST(R1))-(M2*EXP(-M4*M6)*NORMSDIST(R2)) -> 0.046588814 | S4: GBP per USD | T4: <<<rate
A5: Dividend | B5: 0.11 | C5: <<for risk free (GBP) | F5: Put (GBP) | G5: =(-B1*EXP(-B5*B6)*NORMSDIST(-G1))+(B2*EXP(-B4*B6)*NORMSDIST(-G2)) -> 0.12672157 | H5: USD per GBP | I5: <<<rate | L5: Dividend | M5: =B4 -> 0.08 | N5: <<for risk free (US) | Q5: Put (USD) | R5: =(-M1*EXP(-M5*M6)*NORMSDIST(-R1))+(M2*EXP(-M4*M6)*NORMSDIST(-R2)) -> 0.0050925229 | S5: GBP per USD | T5: <<<rate
A6: Term | B6: =1/3 -> 0.33333333 | C6: years | L6: Term | M6: =1/3 -> 0.33333333 | N6: years
F7: On 100,000 GBP notional | Q7: On 170,000 USD notional
F8: call (GBP) prem | G8: =G4*100000 -> 1385.1662 | H8: USD | Q8: call (USD) prem | R8: =R4*170000 -> 7920.0983 | S8: GBP
F9: put (GBP) prem | G9: =G5*100000 -> 12672.157 | H9: USD | Q9: put (USD) prem | R9: =R5*170000 -> 865.72889 | S9: GBP
A11: USD - domestic rate | F11: to pay in GBP
A12: GBP - foreign rate | F12: call (GBP) prem | G12: =G8/B1 -> 865.72889 | H12: GBP
F13: put (GBP) prem | G13: =G9/B1 -> 7920.0983 | H13: GBP

Sheet Slide 46_R
E2: Spot | F2: 135 | G2: ISK per USD | K2: option premium to increase as ISK increase
E3: strike | F3: 140 | G3: ISK per USD | K3: looking for a put
E4: dom risk (ISK) | F4: 0.1
E5: for risk (USD) | F5: 0.05
E6: volatility | F6: 0.3
E7: Time | F7: 0.5
E8: Notional (ISK) | F8: 100000000
E9: Notional (USD) | F9: =F8/F3 -> 714285.71
E12: d1 | F12: =(LN(F2/F3)+((F4-F5+(0.5*F6*F6))*F7))/(F6*SQRT(F7)) -> 0.052478429
E13: d2 | F13: =F12-(F6*SQRT(F7)) -> -0.15965361
E14: put (USD) | F14: =(-F2*EXP(-F5*F7)*NORMSDIST(-F12))+(F3*EXP(-F4*F7)*NORMSDIST(-F13)) -> 11.954114 | G14: ISK per USD
E15: put (USD) | F15: =F14*F9 -> 8538652.6 | G15: ISK

Sheet Slide 47_data
A1: Time (yrs) | B1: Zero Rate (US) | C1: Zero Rate (ISK) | D1: FX Volatility | F1: Spot (USD/ISK) | G1: 135 | H1: <<ISK per USD
A2: 0.25 | B2: 0.04 | C2: 0.07 | D2: 0.2 | F2: Quarterly Revenue | G2: 10000000 | H2: USD
A3: 0.5 | B3: 0.045 | C3: 0.05 | D3: 0.22
A4: 0.75 | B4: 0.05 | C4: 0.03 | D4: 0.24
A5: 1 | B5: 0.055 | C5: 0.01 | D5: 0.26

Sheet Slide 47_R
A1: Time (yrs) | B1: Zero Rate (US) | C1: Zero Rate (ISK) | D1: FX Volatility | E1: Forwards | F1: Revenue (USD) | G1: Revenue (ISK) | H1: Disc Factor (ISK) | I1: FV(Revenue in ISK) | K1: Spot (USD/ISK) | L1: 135 | M1: <<ISK per USD
A2: 0.25 | B2: 0.04 | C2: 0.07 | D2: 0.2 | E2: =$L$1*EXP((C2-B2)*A2) -> 136.01631 | F2: =L2 -> 10000000 | G2: =F2*E2 -> 1.3601631e+09 | H2: =EXP(-C2*A2) -> 0.98265224 | I2: =G2*H2/$H$5 -> 1.35e+09 | K2: Quarterly Revenue | L2: 10000000 | M2: USD
A3: =A2+0.25 -> 0.5 | B3: =B2+0.005 -> 0.045 | C3: 0.05 | D3: 0.22 | E3: =$L$1*EXP((C3-B3)*A3) -> 135.33792 | F3: =F2 -> 10000000 | G3: =F3*E3 -> 1.3533792e+09 | H3: =EXP(-C3*A3) -> 0.97530991 | I3: =G3*H3/$H$5 -> 1.33323e+09
A4: =A3+0.25 -> 0.75 | B4: =B3+0.005 -> 0.05 | C4: 0.03 | D4: 0.24 | E4: =$L$1*EXP((C4-B4)*A4) -> 132.99011 | F4: =F3 -> 10000000 | G4: =F4*E4 -> 1.3299011e+09 | H4: =EXP(-C4*A4) -> 0.97775124 | I4: =G4*H4/$H$5 -> 1.3133808e+09
A5: =A4+0.25 -> 1 | B5: =B4+0.005 -> 0.055 | C5: 0.01 | D5: 0.26 | E5: =$L$1*EXP((C5-B5)*A5) -> 129.05966 | F5: =F4 -> 10000000 | G5: =F5*E5 -> 1.2905966e+09 | H5: =EXP(-C5*A5) -> 0.99004983 | I5: =G5*H5/$H$5 -> 1.2905966e+09
I6: =SUM(I2:I5) -> 5.2872075e+09
C7: S1) | D7: Using the 4 forwards, the expected revenue at the end of 12 months is
D8: =I6 -> 5.2872075e+09 | E8: ISK. Cost of strategy is NOTHING
H9: premiums
A10: Time (yrs) | B10: Zero Rate (US) | C10: Zero Rate (ISK) | D10: FX Volatility | E10: Strikes | F10: d1 | G10: d2 | H10: rates (ISK per USD) | I10: ISK | J10: Future Value
A11: =A2 -> 0.25 | B11: =B2 -> 0.04 | C11: =C2 -> 0.07 | D11: =D2 -> 0.2 | E11: =E2 -> 136.01631 | F11: =(LN($L$1/E11)+((C11-B11+(0.5*D11*D11))*A11))/(D11*SQRT(A11)) -> 0.05 | G11: =F11-(D11*SQRT(A11)) -> -0.05 | H11: =-($L$1*EXP(-B11*A11)*NORMSDIST(-F11))+(E11*EXP(-C11*A11)*NORMSDIST(-G11)) -> 5.3299111 | I11: =H11*F2 -> 53299111 | J11: =I11/$H$5 -> 53834776
A12: =A3 -> 0.5 | B12: =B3 -> 0.045 | C12: =C3 -> 0.05 | D12: =D3 -> 0.22 | E12: =E3 -> 135.33792 | F12: =(LN($L$1/E12)+((C12-B12+(0.5*D12*D12))*A12))/(D12*SQRT(A12)) -> 0.077781746 | G12: =F12-(D12*SQRT(A12)) -> -0.077781746 | H12: =-($L$1*EXP(-B12*A12)*NORMSDIST(-F12))+(E12*EXP(-C12*A12)*NORMSDIST(-G12)) -> 8.1835578 | I12: =H12*F3 -> 81835578 | J12: =I12/$H$5 -> 82658039
A13: =A4 -> 0.75 | B13: =B4 -> 0.05 | C13: =C4 -> 0.03 | D13: =D4 -> 0.24 | E13: =E4 -> 132.99011 | F13: =(LN($L$1/E13)+((C13-B13+(0.5*D13*D13))*A13))/(D13*SQRT(A13)) -> 0.10392305 | G13: =F13-(D13*SQRT(A13)) -> -0.10392305 | H13: =-($L$1*EXP(-B13*A13)*NORMSDIST(-F13))+(E13*EXP(-C13*A13)*NORMSDIST(-G13)) -> 10.762632 | I13: =H13*F4 -> 1.0762632e+08 | J13: =I13/$H$5 -> 1.0870798e+08
A14: =A5 -> 1 | B14: =B5 -> 0.055 | C14: =C5 -> 0.01 | D14: =D5 -> 0.26 | E14: =E5 -> 129.05966 | F14: =(LN($L$1/E14)+((C14-B14+(0.5*D14*D14))*A14))/(D14*SQRT(A14)) -> 0.13 | G14: =F14-(D14*SQRT(A14)) -> -0.13 | H14: =-($L$1*EXP(-B14*A14)*NORMSDIST(-F14))+(E14*EXP(-C14*A14)*NORMSDIST(-G14)) -> 13.216276 | I14: =H14*F5 -> 1.3216276e+08 | J14: =I14/$H$5 -> 1.3349102e+08
J15: =SUM(J11:J14) -> 3.7869182e+08
C16: S2) | D16: To protect against the weakening of the USD, the treasurer would need to purchase 4 put options that
D17: are struck at the forwards given in Cells F2 - E5
D18: FV cost of strategy is 378,691,817 ISK
D19: The total FV(revenue) with this strategy is floored at | G19: =D8-J15 -> 4.9085156e+09 | H19: ISK
D20: But there is unlimited upside to that revenue
A22: Time (yrs) | B22: Zero Rate (US) | C22: Zero Rate (ISK) | D22: FX Volatility | E22: Fwd rate (US) | F22: Fwd rate (ISK) | G22: Fwd volatility | H22: uniform rand | I22: normal rand | J22: FX Rate | N22: =J30 -> 0
A23: 0 | J23: =L1 -> 135 | M23: 1 | N23: 0
A24: =A11 -> 0.25 | B24: =B11 -> 0.04 | C24: =C11 -> 0.07 | D24: =D11 -> 0.2 | E24: =B24 -> 0.04 | F24: =C24 -> 0.07 | G24: =D24 -> 0.2 | H24: =RAND() -> 0.78734232 | I24: =NORMSINV(H24) -> 0.79723363 | J24: =J23*EXP((F24-E24-(0.5*G24*G24))*0.25)*EXP(G24*I24*SQRT(0.25)) -> 146.56927 | M24: =M23+1 -> 2 | N24: 0
A25: =A12 -> 0.5 | B25: =B12 -> 0.045 | C25: =C12 -> 0.05 | D25: =D12 -> 0.22 | E25: =((B25*A25)-(B24*A24))/(A25-A24) -> 0.05 | F25: =((C25*A25)-(C24*A24))/(A25-A24) -> 0.03 | G25: =SQRT(((D25*D25*A25)-(D24*D24*A24))/(A25-A24)) -> 0.23832751 | H25: =RAND() -> 0.92360257 | I25: =NORMSINV(H25) -> 1.4297289 | J25: =J24*EXP((F25-E25-(0.5*G25*G25))*0.25)*EXP(G25*I25*SQRT(0.25)) -> 171.70365 | M25: =M24+1 -> 3 | N25: 0
A26: =A13 -> 0.75 | B26: =B13 -> 0.05 | C26: =C13 -> 0.03 | D26: =D13 -> 0.24 | E26: =((B26*A26)-(B25*A25))/(A26-A25) -> 0.06 | F26: =((C26*A26)-(C25*A25))/(A26-A25) -> -0.01 | G26: =SQRT(((D26*D26*A26)-(D25*D25*A25))/(A26-A25)) -> 0.27568098 | H26: =RAND() -> 0.84320672 | I26: =NORMSINV(H26) -> 1.0077249 | J26: =J25*EXP((F26-E26-(0.5*G26*G26))*0.25)*EXP(G26*I26*SQRT(0.25)) -> 192.03455 | M26: =M25+1 -> 4 | N26: 0
A27: =A14 -> 1 | B27: =B14 -> 0.055 | C27: =C14 -> 0.01 | D27: =D14 -> 0.26 | E27: =((B27*A27)-(B26*A26))/(A27-A26) -> 0.07 | F27: =((C27*A27)-(C26*A26))/(A27-A26) -> -0.05 | G27: =SQRT(((D27*D27*A27)-(D26*D26*A26))/(A27-A26)) -> 0.31240999 | H27: =RAND() -> 0.80575841 | I27: =NORMSINV(H27) -> 0.86237138 | J27: =J26*EXP((F27-E27-(0.5*G27*G27))*0.25)*EXP(G27*I27*SQRT(0.25)) -> 210.64663 | M27: =M26+1 -> 5 | N27: 5.4906055e+08
I28: Total Revenue (1 year) | J28: =SUMPRODUCT(J24:J27,F2:F5) -> 7.2095409e+09 | M28: =M27+1 -> 6 | N28: 2.6521131e+08
I29: Strike of cashflow option | J29: =D8 -> 5.2872075e+09 | M29: =M28+1 -> 7 | N29: 0
I30: Shortfall | J30: =MAX(J29-J28,0) -> 0 | M30: =M29+1 -> 8 | N30: 0
I31: Cost of option | J31: =AVERAGE(N23:N2522) -> 2.9918161e+08 | M31: =M30+1 -> 9 | N31: 0
M32: =M31+1 -> 10 | N32: 9.1891734e+08
C33: S3) | D33: The cost of the cashflow option is 313925555 | M33: =M32+1 -> 11 | N33: 1.1690784e+08
D34: it is definitely cheaper than buying all the 4 options | M34: =M33+1 -> 12 | N34: 0
D35: The floor of the revenue is trivially | F35: =J29-J31 -> 4.9880258e+09 | G35: ISK | M35: =M34+1 -> 13 | N35: 6.8728066e+08
D36: with an unlimited upside (but less than S2) | M36: =M35+1 -> 14 | N36: 0
M37: =M36+1 -> 15 | N37: 6.7245201e+08
M38: =M37+1 -> 16 | N38: 0
M39: =M38+1 -> 17 | N39: 3.5699727e+08
M40: =M39+1 -> 18 | N40: 0
M41: =M40+1 -> 19 | N41: 0
M42: =M41+1 -> 20 | N42: 0
M43: =M42+1 -> 21 | N43: 0
M44: =M43+1 -> 22 | N44: 0
M45: =M44+1 -> 23 | N45: 2.5874058e+08
M46: =M45+1 -> 24 | N46: 0
M47: =M46+1 -> 25 | N47: 0
M48: =M47+1 -> 26 | N48: 0
... M2522: =M2521+1 -> 2500 | N2522: 1.388262e+09

Sheet Slide 51
A2: Time | B2: Forward Rates | C2: ti | D2: Dfi | E2: Fi | F2: ti* Fi * Dfi | G2: ti * dfi
A3: 0 | B3: 0.042 | D3: 1
A4: 0.5 | B4: 0.048 | C4: =(A4-A3) -> 0.5 | D4: =D3/(1+(B3*C4)) -> 0.97943193 | E4: =B4 -> 0.048
A5: 1 | B5: 0.053 | C5: =(A5-A4) -> 0.5 | D5: =D4/(1+(B4*C5)) -> 0.95647649 | E5: =B5 -> 0.053 | F5: =E4*C5*D5 -> 0.022955436 | G5: =C5*D5 -> 0.47823825
A6: 1.5 | B6: 0.055 | C6: =(A6-A5) -> 0.5 | D6: =D5/(1+(B5*C6)) -> 0.93178421 | E6: =B6 -> 0.055 | F6: =E5*C6*D6 -> 0.024692282 | G6: =C6*D6 -> 0.46589211
A7: 2 | B7: 0.056 | C7: =(A7-A6) -> 0.5 | D7: =D6/(1+(B6*C7)) -> 0.90684595 | E7: =B7 -> 0.056 | F7: =E6*C7*D7 -> 0.024938264 | G7: =C7*D7 -> 0.45342297
A8: 2.5 | B8: 0.059 | C8: =(A8-A7) -> 0.5 | D8: =D7/(1+(B7*C8)) -> 0.88214586 | E8: =B8 -> 0.059 | F8: =E7*C8*D8 -> 0.024700084 | G8: =C8*D8 -> 0.44107293
A9: 3 | C9: =(A9-A8) -> 0.5 | D9: =D8/(1+(B8*C9)) -> 0.85686825
F10: =SUM(F5:F8) -> 0.097286065 | G10: =SUM(G5:G8) -> 1.8386263
A14: If I tell you that the option expires in 6 months and on expiry it settles into a 2 year semi-annual reset swap
A15: ----> forward rate is the 2-year semi0annual swap starting 6 months from now (first floating rate gets set in 6 months) | N15: F0 | O15: =F10/G10 -> 0.052912366 | P15: =(D4-D8)/G10 -> 0.052912366
N16: X | O16: 0.06
N17: volatility | O17: 0.2
N18: N | O18: 100000000
A19: If I tell you that the option expires in 2 years and on expiry it settles into a 5 year annual reset swap | N19: sum tidfi | O19: =G10 -> 1.8386263
A20: ----> forward rate is the 5-year annual swap starting 2 years from now (first floating rate gets set in 2 years) | N20: option life | O20: 0.5
N22: d1 | O22: =(LN(O15/O16)+(0.5*O17*O17*O20))/(O17*SQRT(O20)) -> -0.81817552
N23: d2 | O23: =O22-(O17*SQRT(O20)) -> -0.95959688
N25: RTP (call) | O25: =O18*((O15*NORMSDIST(O22))-(O16*NORMSDIST(O23)))*O19 -> 149932.21
N26: RTR (put) | O26: =O18*((-O15*NORMSDIST(-O22))+(O16*NORMSDIST(-O23)))*O19 -> 1453083.2

Sheet Slide 52_data
A1: Time | B1: Discount Factor | F1: Swaption Implied Volatility Matrix
A2: 0 | B2: 1 | F2: Maturity\U/L Swap | G2: 1year (semi-annually reset) | H2: 1year (annually reset) | I2: 2 year (semi-annually reset) | J2: 2 year (annually reset)
A3: 0.5 | B3: 0.97628571 | F3: 0.5 years | G3: 0.3 | H3: 0.28 | I3: 0.28 | J3: 0.25
A4: 1 | B4: 0.94838001 | F4: 1 year | G4: 0.35 | H4: 0.32 | I4: 0.32 | J4: 0.27
A5: 1.5 | B5: 0.92081144 | F5: 1.5 years | G5: 0.37 | H5: 0.35 | I5: 0.35 | J5: 0.3
A6: 2 | B6: 0.89404426 | F6: 2 years | G6: 0.39 | H6: 0.35 | I6: 0.37 | J6: 0.33
A7: 2.5 | B7: 0.86286244 | F7: 2.5 years | G7: 0.41 | H7: 0.37 | I7: 0.4 | J7: 0.37
A8: 3 | B8: 0.83527021 | F8: 3 years | G8: 0.45 | H8: 0.39 | I8: 0.43 | J8: 0.39

Sheet Slide 52_R_Q1
A1: Time | B1: Discount Factor | C1: Ti | D1: Fi | E1: ti* fi* dfi | F1: ti*dfi | J1: Swaption Implied Volatility Matrix
A2: 0 | B2: 1 | J2: Maturity\U/L Swap | K2: 1year (semi-annually reset) | L2: 1year (annually reset) | M2: 2 year (semi-annually reset) | N2: 2 year (annually reset)
A3: 0.5 | B3: 0.97628571 | J3: 0.5 years | K3: 0.3 | L3: 0.28 | M3: 0.28 | N3: 0.25
A4: 1 | B4: 0.94838001 | J4: 1 year | K4: 0.35 | L4: 0.32 | M4: 0.32 | N4: 0.27
A5: 1.5 | B5: 0.92081144 | C5: =(A5-A4) -> 0.5 | D5: =((B4/B5)-1)/C5 -> 0.059878871 | E5: =C5*D5*B5 -> 0.027568575 | F5: =C5*B5 -> 0.46040572 | J5: 1.5 years | K5: 0.37 | L5: 0.35 | M5: 0.35 | N5: 0.3
A6: 2 | B6: 0.89404426 | C6: =(A6-A5) -> 0.5 | D6: =((B5/B6)-1)/C6 -> 0.059878871 | E6: =C6*D6*B6 -> 0.02676718 | F6: =C6*B6 -> 0.44702213 | J6: 2 years | K6: 0.39 | L6: 0.35 | M6: 0.37 | N6: 0.33
A7: 2.5 | B7: 0.86286244 | J7: 2.5 years | K7: 0.41 | L7: 0.37 | M7: 0.4 | N7: 0.37
A8: 3 | B8: 0.83527021 | J8: 3 years | K8: 0.45 | L8: 0.39 | M8: 0.43 | N8: 0.39
E9: =SUM(E5:E6) -> 0.054335755 | F9: =SUM(F5:F6) -> 0.90742785
A11: ATM Fwd RTP (call) Swaption
A12: F0 | B12: =E9/F9 -> 0.059878871 | C12: <<fwd start swap rate for a 1-year sem-annual reset swap (whose first floating rate gets set in 12 months)
A13: X | B13: =B12 -> 0.059878871 | C13: << since the option is ATM forward
A14: volatility | B14: =K4 -> 0.35
A15: N | B15: 100000000
A16: sum tidfi | B16: =F9 -> 0.90742785
A17: option life | B17: 1
A19: d1 | B19: =(LN(B12/B13)+(0.5*B14*B14*B17))/(B14*SQRT(B17)) -> 0.175
A20: d2 | B20: =B19-(B14*SQRT(B17)) -> -0.175
A21: RTP premium | B21: =B15*((B12*NORMSDIST(B19))-(B13*NORMSDIST(B20)))*B16 -> 754834.3
A22: ATM RTR (put) Swaption | B22: =B15*((-B12*NORMSDIST(-B19))+(B13*NORMSDIST(-B20)))*B16 -> 754834.3

Sheet Slide 52_R_Q2
A1: Time | B1: Discount Factor | C1: Ti | D1: Fi | E1: ti* fi* dfi | F1: ti*dfi | J1: Swaption Implied Volatility Matrix
A2: 0 | B2: 1 | J2: Maturity\U/L Swap | K2: 1year (semi-annually reset) | L2: 1year (annually reset) | M2: 2 year (semi-annually reset) | N2: 2 year (annually reset)
A3: 0.5 | B3: 0.97628571 | J3: 0.5 years | K3: 0.3 | L3: 0.28 | M3: 0.28 | N3: 0.25
A4: 1 | B4: 0.94838001 | J4: 1 year | K4: 0.35 | L4: 0.32 | M4: 0.32 | N4: 0.27
A5: 1.5 | B5: 0.92081144 | J5: 1.5 years | K5: 0.37 | L5: 0.35 | M5: 0.35 | N5: 0.3
A6: 2 | B6: 0.89404426 | C6: =(A6-A4) -> 1 | D6: =((B4/B6)-1)/C6 -> 0.060775241 | E6: =C6*D6*B6 -> 0.054335755 | F6: =C6*B6 -> 0.89404426 | J6: 2 years | K6: 0.39 | L6: 0.35 | M6: 0.37 | N6: 0.33
A7: 2.5 | B7: 0.86286244 | J7: 2.5 years | K7: 0.41 | L7: 0.37 | M7: 0.4 | N7: 0.37
A8: 3 | B8: 0.83527021 | C8: =(A8-A6) -> 1 | D8: =((B6/B8)-1)/C8 -> 0.070365308 | E8: =C8*D8*B8 -> 0.058774046 | F8: =C8*B8 -> 0.83527021 | J8: 3 years | K8: 0.45 | L8: 0.39 | M8: 0.43 | N8: 0.39
E9: =SUM(E5:E8) -> 0.1131098 | F9: =SUM(F5:F8) -> 1.7293145
A11: ATM Fwd RTR (put) Swaption
A12: F0 | B12: =E9/F9 -> 0.065407306 | C12: <<fwd start swap rate for a 2-year annual reset swap (whose first floating rate gets set in 12 months)
A13: X | B13: =B12 -> 0.065407306 | C13: << since the option is ATM forward
A14: volatility | B14: =N4 -> 0.27
A15: N | B15: 100000000
A16: sum tidfi | B16: =F9 -> 1.7293145
A17: option life | B17: 1
A19: d1 | B19: =(LN(B12/B13)+(0.5*B14*B14*B17))/(B14*SQRT(B17)) -> 0.135
A20: d2 | B20: =B19-(B14*SQRT(B17)) -> -0.135
A21: ATM RTR (put) Swaption | B21: =B15*((-B12*NORMSDIST(-B19))+(B13*NORMSDIST(-B20)))*B16 -> 1214665

Sheet Slide 54_R_Caplet_6%
A1: Time | B1: Discount Factor | C1: Ti | D1: Fi | E1: ti* fi* dfi | F1: ti*dfi
A2: 0 | B2: 1
A3: 0.5 | B3: 0.97628571
A4: 1 | B4: 0.94838001 | C4: =A4-A3 -> 0.5 | D4: =((B3/B4)-1)/C4 -> 0.058849189 | E4: =C4*D4*B4 -> 0.027905697 | F4: =C4*B4 -> 0.47419001
A5: 1.5 | B5: 0.92081144
A6: 2 | B6: 0.89404426
A7: 2.5 | B7: 0.86286244
A8: 3 | B8: 0.83527021
E9: =E4 -> 0.027905697 | F9: =F4 -> 0.47419001
A12: F0 | B12: =E9/F9 -> 0.058849189
A13: X | B13: 0.06
A14: volatility | B14: 0.25
A15: N | B15: 1000000
A16: sum tidfi | B16: =F4 -> 0.47419001
A17: option life | B17: 0.5
A19: d1 | B19: =(LN(B12/B13)+(0.5*B14*B14*B17))/(B14*SQRT(B17)) -> -0.021165178
A20: d2 | B20: =B19-(B14*SQRT(B17)) -> -0.19794187
A21: Caplet premium | B21: =B15*((B12*NORMSDIST(B19))-(B13*NORMSDIST(B20)))*B16 -> 1723.686

Sheet Slide 54_R_Caplet_ATM
A1: Time | B1: Discount Factor | C1: Ti | D1: Fi | E1: ti* fi* dfi | F1: ti*dfi
A2: 0 | B2: 1
A3: 0.5 | B3: 0.97628571
A4: 1 | B4: 0.94838001 | C4: =A4-A3 -> 0.5 | D4: =((B3/B4)-1)/C4 -> 0.058849189 | E4: =C4*D4*B4 -> 0.027905697 | F4: =C4*B4 -> 0.47419001
A5: 1.5 | B5: 0.92081144
A6: 2 | B6: 0.89404426
A7: 2.5 | B7: 0.86286244
A8: 3 | B8: 0.83527021
E9: =E4 -> 0.027905697 | F9: =F4 -> 0.47419001
A12: F0 | B12: =E9/F9 -> 0.058849189
A13: X | B13: =B12 -> 0.058849189
A14: volatility | B14: 0.25
A15: N | B15: 1000000
A16: sum tidfi | B16: =F4 -> 0.47419001
A17: option life | B17: 0.5
A19: d1 | B19: =(LN(B12/B13)+(0.5*B14*B14*B17))/(B14*SQRT(B17)) -> 0.088388348
A20: d2 | B20: =B19-(B14*SQRT(B17)) -> -0.088388348
A21: Caplet premium | B21: =B15*((B12*NORMSDIST(B19))-(B13*NORMSDIST(B20)))*B16 -> 1965.4534

Sheet Slide 54_R_Cap
A1: Time | B1: Discount Factor | C1: Ti | D1: Fi | E1: ti* fi* dfi | F1: ti*dfi
A2: 0 | B2: 1
A3: 0.5 | B3: 0.97628571
A4: 1 | B4: 0.94838001 | C4: =A4-A3 -> 0.5 | D4: =((B3/B4)-1)/C4 -> 0.058849189 | E4: =C4*D4*B4 -> 0.027905697 | F4: =C4*B4 -> 0.47419001
A5: 1.5 | B5: 0.92081144 | C5: =A5-A4 -> 0.5 | D5: =((B4/B5)-1)/C5 -> 0.059878871 | E5: =C5*D5*B5 -> 0.027568575 | F5: =C5*B5 -> 0.46040572
A6: 2 | B6: 0.89404426 | C6: =A6-A5 -> 0.5 | D6: =((B5/B6)-1)/C6 -> 0.059878871 | E6: =C6*D6*B6 -> 0.02676718 | F6: =C6*B6 -> 0.44702213
A7: 2.5 | B7: 0.86286244 | C7: =A7-A6 -> 0.5 | D7: =((B6/B7)-1)/C7 -> 0.072275296 | E7: =C7*D7*B7 -> 0.031181819 | F7: =C7*B7 -> 0.43143122
A8: 3 | B8: 0.83527021 | C8: =A8-A7 -> 0.5 | D8: =((B7/B8)-1)/C8 -> 0.066067786 | E8: =C8*D8*B8 -> 0.027592227 | F8: =C8*B8 -> 0.41763511
E9: =E4 -> 0.027905697 | F9: =F4 -> 0.47419001
A11: 1st caplet
A12: F0 | B12: =E9/F9 -> 0.058849189
A13: X | B13: 0.06
A14: volatility | B14: 0.25
A15: N | B15: 1000000 | D15: cap value | E15: =B21+B33+B45+B57+B69 -> 20372.622
A16: sum tidfi | B16: =F4 -> 0.47419001
A17: option life | B17: 0.5
A19: d1 | B19: =(LN(B12/B13)+(0.5*B14*B14*B17))/(B14*SQRT(B17)) -> -0.021165178
A20: d2 | B20: =B19-(B14*SQRT(B17)) -> -0.19794187
A21: RTP (call) Swaption | B21: =B15*((B12*NORMSDIST(B19))-(B13*NORMSDIST(B20)))*B16 -> 1723.686
A23: 2nd caplet
A24: F0 | B24: =D5 -> 0.059878871
A25: X | B25: 0.06
A26: volatility | B26: 0.25
A27: N | B27: 1000000
A28: sum tidfi | B28: =F5 -> 0.46040572
A29: option life | B29: 1
A31: d1 | B31: =(LN(B24/B25)+(0.5*B26*B26*B29))/(B26*SQRT(B29)) -> 0.11691657
A32: d2 | B32: =B31-(B26*SQRT(B29)) -> -0.13308343
A33: RTP (call) Swaption | B33: =B27*((B24*NORMSDIST(B31))-(B25*NORMSDIST(B32)))*B28 -> 2717.4027
A35: 3rd caplet
A36: F0 | B36: =D6 -> 0.059878871
A37: X | B37: 0.06
A38: volatility | B38: 0.25
A39: N | B39: 1000000
A40: sum tidfi | B40: =F6 -> 0.44702213
A41: option life | B41: 1.5
A43: d1 | B43: =(LN(B36/B37)+(0.5*B38*B38*B41))/(B38*SQRT(B41)) -> 0.14649301
A44: d2 | B44: =B43-(B38*SQRT(B41)) -> -0.1596932
A45: RTP (call) Swaption | B45: =B39*((B36*NORMSDIST(B43))-(B37*NORMSDIST(B44)))*B40 -> 3233.1916
A47: 4th caplet
A48: F0 | B48: =D7 -> 0.072275296
A49: X | B49: 0.06
A50: volatility | B50: 0.25
A51: N | B51: 1000000
A52: sum tidfi | B52: =F7 -> 0.43143122
A53: option life | B53: 2
A55: d1 | B55: =(LN(B48/B49)+(0.5*B50*B50*B53))/(B50*SQRT(B53)) -> 0.70325397
A56: d2 | B56: =B55-(B50*SQRT(B53)) -> 0.34970058
A57: RTP (call) Swaption | B57: =B51*((B48*NORMSDIST(B55))-(B49*NORMSDIST(B56)))*B52 -> 7186.5901
A59: 5th caplet
A60: F0 | B60: =D8 -> 0.066067786
A61: X | B61: 0.06
A62: volatility | B62: 0.25
A63: N | B63: 1000000
A64: sum tidfi | B64: =F8 -> 0.41763511
A65: option life | B65: 2.5
A67: d1 | B67: =(LN(B60/B61)+(0.5*B62*B62*B65))/(B62*SQRT(B65)) -> 0.44135711
A68: d2 | B68: =B67-(B62*SQRT(B65)) -> 0.046072406
A69: RTP (call) Swaption | B69: =B63*((B60*NORMSDIST(B67))-(B61*NORMSDIST(B68)))*B64 -> 5511.752

Sheet Slide 56_(changing notional)_R
A1: S0 | B1: 135 | C1: ISK per USD | E1: Working | F1: Delta t | G1: =B6/B7 -> 0.016666667
A2: X | B2: 140 | C2: ISK per USD | F2: u | G2: =EXP(B3*SQRT(G1)) -> 1.0394896
A3: volatility | B3: 0.3 | F3: d | G3: =1/G2 -> 0.96201058
A4: Dom Risk free (ISK) | B4: 0.1 | F4: p | G4: =(EXP((B4-B5)*G1)-G3)/(G2-G3) -> 0.50107883
A5: For Risk Free (USD) | B5: 0.05 | F5: Option Value | G5: =A108 -> 12.582318 | H5: ISK per USD
A6: Term (yrs) | B6: 0.5 | G6: =G5*B9 -> 8987369.8 | H6: ISK
A7: n | B7: 30 | G7: =G6/B1 -> 66573.11 | H7: USD
A8: Notional | B8: 100000000 | C8: ISK
A9: Notional | B9: =B8/B2 -> 714285.71 | C9: USD
A14: 0 | B14: Delta t | C14: 2 Delta t | D14: 3 Delta t | E14: 4 Delta t | F14: 5 Delta t | G14: 6 Delta t | H14: 7 Delta t | I14: 8 Delta t | J14: 9 Delta t | K14: 10 Delta t | L14: 11 Delta t | M14: 12 Delta t | N14: 13 Delta t | O14: 14 Delta t | P14: 15 Delta t | Q14: 16 Delta t | R14: 17 Delta t | S14: 18 Delta t | T14: 19 Delta t | U14: 20 Delta t | V14: 21 Delta t | W14: 22 Delta t | X14: 23 Delta t | Y14: 24 Delta t | Z14: 25 Delta t | AA14: 26 Delta t | AB14: 27 Delta t | AC14: 28 Delta t | AD14: 29 Delta t | AE14: 30 Delta t
AE15: =$G$2*AD16 -> 431.45783
AD16: =$G$2*AC17 -> 415.067
AC17: =$G$2*AB18 -> 399.29884 | AE17: =$G$2*AD18 -> 399.29884
AB18: =$G$2*AA19 -> 384.12971 | AD18: =$G$2*AC19 -> 384.12971
AA19: =$G$2*Z20 -> 369.53684 | AC19: =$G$2*AB20 -> 369.53684 | AE19: =$G$2*AD20 -> 369.53684
Z20: =$G$2*Y21 -> 355.49835 | AB20: =$G$2*AA21 -> 355.49835 | AD20: =$G$2*AC21 -> 355.49835
Y21: =$G$2*X22 -> 341.99318 | AA21: =$G$2*Z22 -> 341.99318 | AC21: =$G$2*AB22 -> 341.99318 | AE21: =$G$2*AD22 -> 341.99318
X22: =$G$2*W23 -> 329.00105 | Z22: =$G$2*Y23 -> 329.00105 | AB22: =$G$2*AA23 -> 329.00105 | AD22: =$G$2*AC23 -> 329.00105
W23: =$G$2*V24 -> 316.50249 | Y23: =$G$2*X24 -> 316.50249 | AA23: =$G$2*Z24 -> 316.50249 | AC23: =$G$2*AB24 -> 316.50249 | AE23: =$G$2*AD24 -> 316.50249
V24: =$G$2*U25 -> 304.47874 | X24: =$G$2*W25 -> 304.47874 | Z24: =$G$2*Y25 -> 304.47874 | AB24: =$G$2*AA25 -> 304.47874 | AD24: =$G$2*AC25 -> 304.47874
U25: =$G$2*T26 -> 292.91177 | W25: =$G$2*V26 -> 292.91177 | Y25: =$G$2*X26 -> 292.91177 | AA25: =$G$2*Z26 -> 292.91177 | AC25: =$G$2*AB26 -> 292.91177 | AE25: =$G$2*AD26 -> 292.91177
T26: =$G$2*S27 -> 281.78422 | V26: =$G$2*U27 -> 281.78422 | X26: =$G$2*W27 -> 281.78422 | Z26: =$G$2*Y27 -> 281.78422 | AB26: =$G$2*AA27 -> 281.78422 | AD26: =$G$2*AC27 -> 281.78422
S27: =$G$2*R28 -> 271.0794 | U27: =$G$2*T28 -> 271.0794 | W27: =$G$2*V28 -> 271.0794 | Y27: =$G$2*X28 -> 271.0794 | AA27: =$G$2*Z28 -> 271.0794 | AC27: =$G$2*AB28 -> 271.0794 | AE27: =$G$2*AD28 -> 271.0794
R28: =$G$2*Q29 -> 260.78125 | T28: =$G$2*S29 -> 260.78125 | V28: =$G$2*U29 -> 260.78125 | X28: =$G$2*W29 -> 260.78125 | Z28: =$G$2*Y29 -> 260.78125 | AB28: =$G$2*AA29 -> 260.78125 | AD28: =$G$2*AC29 -> 260.78125
Q29: =$G$2*P30 -> 250.87432 | S29: =$G$2*R30 -> 250.87432 | U29: =$G$2*T30 -> 250.87432 | W29: =$G$2*V30 -> 250.87432 | Y29: =$G$2*X30 -> 250.87432 | AA29: =$G$2*Z30 -> 250.87432 | AC29: =$G$2*AB30 -> 250.87432 | AE29: =$G$2*AD30 -> 250.87432
P30: =$G$2*O31 -> 241.34375 | R30: =$G$2*Q31 -> 241.34375 | T30: =$G$2*S31 -> 241.34375 | V30: =$G$2*U31 -> 241.34375 | X30: =$G$2*W31 -> 241.34375 | Z30: =$G$2*Y31 -> 241.34375 | AB30: =$G$2*AA31 -> 241.34375 | AD30: =$G$2*AC31 -> 241.34375
O31: =$G$2*N32 -> 232.17524 | Q31: =$G$2*P32 -> 232.17524 | S31: =$G$2*R32 -> 232.17524 | U31: =$G$2*T32 -> 232.17524 | W31: =$G$2*V32 -> 232.17524 | Y31: =$G$2*X32 -> 232.17524 | AA31: =$G$2*Z32 -> 232.17524 | AC31: =$G$2*AB32 -> 232.17524 | AE31: =$G$2*AD32 -> 232.17524
N32: =$G$2*M33 -> 223.35504 | P32: =$G$2*O33 -> 223.35504 | R32: =$G$2*Q33 -> 223.35504 | T32: =$G$2*S33 -> 223.35504 | V32: =$G$2*U33 -> 223.35504 | X32: =$G$2*W33 -> 223.35504 | Z32: =$G$2*Y33 -> 223.35504 | AB32: =$G$2*AA33 -> 223.35504 | AD32: =$G$2*AC33 -> 223.35504
M33: =$G$2*L34 -> 214.86991 | O33: =$G$2*N34 -> 214.86991 | Q33: =$G$2*P34 -> 214.86991 | S33: =$G$2*R34 -> 214.86991 | U33: =$G$2*T34 -> 214.86991 | W33: =$G$2*V34 -> 214.86991 | Y33: =$G$2*X34 -> 214.86991 | AA33: =$G$2*Z34 -> 214.86991 | AC33: =$G$2*AB34 -> 214.86991 | AE33: =$G$2*AD34 -> 214.86991
L34: =$G$2*K35 -> 206.70713 | N34: =$G$2*M35 -> 206.70713 | P34: =$G$2*O35 -> 206.70713 | R34: =$G$2*Q35 -> 206.70713 | T34: =$G$2*S35 -> 206.70713 | V34: =$G$2*U35 -> 206.70713 | X34: =$G$2*W35 -> 206.70713 | Z34: =$G$2*Y35 -> 206.70713 | AB34: =$G$2*AA35 -> 206.70713 | AD34: =$G$2*AC35 -> 206.70713
K35: =$G$2*J36 -> 198.85444 | M35: =$G$2*L36 -> 198.85444 | O35: =$G$2*N36 -> 198.85444 | Q35: =$G$2*P36 -> 198.85444 | S35: =$G$2*R36 -> 198.85444 | U35: =$G$2*T36 -> 198.85444 | W35: =$G$2*V36 -> 198.85444 | Y35: =$G$2*X36 -> 198.85444 | AA35: =$G$2*Z36 -> 198.85444 | AC35: =$G$2*AB36 -> 198.85444 | AE35: =$G$2*AD36 -> 198.85444
J36: =$G$2*I37 -> 191.30008 | L36: =$G$2*K37 -> 191.30008 | N36: =$G$2*M37 -> 191.30008 | P36: =$G$2*O37 -> 191.30008 | R36: =$G$2*Q37 -> 191.30008 | T36: =$G$2*S37 -> 191.30008 | V36: =$G$2*U37 -> 191.30008 | X36: =$G$2*W37 -> 191.30008 | Z36: =$G$2*Y37 -> 191.30008 | AB36: =$G$2*AA37 -> 191.30008 | AD36: =$G$2*AC37 -> 191.30008
I37: =$G$2*H38 -> 184.0327 | K37: =$G$2*J38 -> 184.0327 | M37: =$G$2*L38 -> 184.0327 | O37: =$G$2*N38 -> 184.0327 | Q37: =$G$2*P38 -> 184.0327 | S37: =$G$2*R38 -> 184.0327 | U37: =$G$2*T38 -> 184.0327 | W37: =$G$2*V38 -> 184.0327 | Y37: =$G$2*X38 -> 184.0327 | AA37: =$G$2*Z38 -> 184.0327 | AC37: =$G$2*AB38 -> 184.0327 | AE37: =$G$2*AD38 -> 184.0327
H38: =$G$2*G39 -> 177.0414 | J38: =$G$2*I39 -> 177.0414 | L38: =$G$2*K39 -> 177.0414 | N38: =$G$2*M39 -> 177.0414 | P38: =$G$2*O39 -> 177.0414 | R38: =$G$2*Q39 -> 177.0414 | T38: =$G$2*S39 -> 177.0414 | V38: =$G$2*U39 -> 177.0414 | X38: =$G$2*W39 -> 177.0414 | Z38: =$G$2*Y39 -> 177.0414 | AB38: =$G$2*AA39 -> 177.0414 | AD38: =$G$2*AC39 -> 177.0414
G39: =$G$2*F40 -> 170.3157 | I39: =$G$2*H40 -> 170.3157 | K39: =$G$2*J40 -> 170.3157 | M39: =$G$2*L40 -> 170.3157 | O39: =$G$2*N40 -> 170.3157 | Q39: =$G$2*P40 -> 170.3157 | S39: =$G$2*R40 -> 170.3157 | U39: =$G$2*T40 -> 170.3157 | W39: =$G$2*V40 -> 170.3157 | Y39: =$G$2*X40 -> 170.3157 | AA39: =$G$2*Z40 -> 170.3157 | AC39: =$G$2*AB40 -> 170.3157 | AE39: =$G$2*AD40 -> 170.3157
F40: =$G$2*E41 -> 163.84551 | H40: =$G$2*G41 -> 163.84551 | J40: =$G$2*I41 -> 163.84551 | L40: =$G$2*K41 -> 163.84551 | N40: =$G$2*M41 -> 163.84551 | P40: =$G$2*O41 -> 163.84551 | R40: =$G$2*Q41 -> 163.84551 | T40: =$G$2*S41 -> 163.84551 | V40: =$G$2*U41 -> 163.84551 | X40: =$G$2*W41 -> 163.84551 | Z40: =$G$2*Y41 -> 163.84551 | AB40: =$G$2*AA41 -> 163.84551 | AD40: =$G$2*AC41 -> 163.84551
E41: =$G$2*D42 -> 157.62111 | G41: =$G$2*F42 -> 157.62111 | I41: =$G$2*H42 -> 157.62111 | K41: =$G$2*J42 -> 157.62111 | M41: =$G$2*L42 -> 157.62111 | O41: =$G$2*N42 -> 157.62111 | Q41: =$G$2*P42 -> 157.62111 | S41: =$G$2*R42 -> 157.62111 | U41: =$G$2*T42 -> 157.62111 | W41: =$G$2*V42 -> 157.62111 | Y41: =$G$2*X42 -> 157.62111 | AA41: =$G$2*Z42 -> 157.62111 | AC41: =$G$2*AB42 -> 157.62111 | AE41: =$G$2*AD42 -> 157.62111
D42: =$G$2*C43 -> 151.63317 | F42: =$G$2*E43 -> 151.63317 | H42: =$G$2*G43 -> 151.63317 | J42: =$G$2*I43 -> 151.63317 | L42: =$G$2*K43 -> 151.63317 | N42: =$G$2*M43 -> 151.63317 | P42: =$G$2*O43 -> 151.63317 | R42: =$G$2*Q43 -> 151.63317 | T42: =$G$2*S43 -> 151.63317 | V42: =$G$2*U43 -> 151.63317 | X42: =$G$2*W43 -> 151.63317 | Z42: =$G$2*Y43 -> 151.63317 | AB42: =$G$2*AA43 -> 151.63317 | AD42: =$G$2*AC43 -> 151.63317
C43: =$G$2*B44 -> 145.87272 | E43: =$G$2*D44 -> 145.87272 | G43: =$G$2*F44 -> 145.87272 | I43: =$G$2*H44 -> 145.87272 | K43: =$G$2*J44 -> 145.87272 | M43: =$G$2*L44 -> 145.87272 | O43: =$G$2*N44 -> 145.87272 | Q43: =$G$2*P44 -> 145.87272 | S43: =$G$2*R44 -> 145.87272 | U43: =$G$2*T44 -> 145.87272 | W43: =$G$2*V44 -> 145.87272 | Y43: =$G$2*X44 -> 145.87272 | AA43: =$G$2*Z44 -> 145.87272 | AC43: =$G$2*AB44 -> 145.87272 | AE43: =$G$2*AD44 -> 145.87272
B44: =$G$2*A45 -> 140.3311 | D44: =$G$2*C45 -> 140.3311 | F44: =$G$2*E45 -> 140.3311 | H44: =$G$2*G45 -> 140.3311 | J44: =$G$2*I45 -> 140.3311 | L44: =$G$2*K45 -> 140.3311 | N44: =$G$2*M45 -> 140.3311 | P44: =$G$2*O45 -> 140.3311 | R44: =$G$2*Q45 -> 140.3311 | T44: =$G$2*S45 -> 140.3311 | V44: =$G$2*U45 -> 140.3311 | X44: =$G$2*W45 -> 140.3311 | Z44: =$G$2*Y45 -> 140.3311 | AB44: =$G$2*AA45 -> 140.3311 | AD44: =$G$2*AC45 -> 140.3311
A45: =B1 -> 135 | C45: =$G$2*B46 -> 135 | E45: =$G$2*D46 -> 135 | G45: =$G$2*F46 -> 135 | I45: =$G$2*H46 -> 135 | K45: =$G$2*J46 -> 135 | M45: =$G$2*L46 -> 135 | O45: =$G$2*N46 -> 135 | Q45: =$G$2*P46 -> 135 | S45: =$G$2*R46 -> 135 | U45: =$G$2*T46 -> 135 | W45: =$G$2*V46 -> 135 | Y45: =$G$2*X46 -> 135 | AA45: =$G$2*Z46 -> 135 | AC45: =$G$2*AB46 -> 135 | AE45: =$G$2*AD46 -> 135
B46: =A45*$G$3 -> 129.87143 | D46: =$G$2*C47 -> 129.87143 | F46: =$G$2*E47 -> 129.87143 | H46: =$G$2*G47 -> 129.87143 | J46: =$G$2*I47 -> 129.87143 | L46: =$G$2*K47 -> 129.87143 | N46: =$G$2*M47 -> 129.87143 | P46: =$G$2*O47 -> 129.87143 | R46: =$G$2*Q47 -> 129.87143 | T46: =$G$2*S47 -> 129.87143 | V46: =$G$2*U47 -> 129.87143 | X46: =$G$2*W47 -> 129.87143 | Z46: =$G$2*Y47 -> 129.87143 | AB46: =$G$2*AA47 -> 129.87143 | AD46: =$G$2*AC47 -> 129.87143
C47: =B46*$G$3 -> 124.93769 | E47: =$G$2*D48 -> 124.93769 | G47: =$G$2*F48 -> 124.93769 | I47: =$G$2*H48 -> 124.93769 | K47: =$G$2*J48 -> 124.93769 | M47: =$G$2*L48 -> 124.93769 | O47: =$G$2*N48 -> 124.93769 | Q47: =$G$2*P48 -> 124.93769 | S47: =$G$2*R48 -> 124.93769 | U47: =$G$2*T48 -> 124.93769 | W47: =$G$2*V48 -> 124.93769 | Y47: =$G$2*X48 -> 124.93769 | AA47: =$G$2*Z48 -> 124.93769 | AC47: =$G$2*AB48 -> 124.93769 | AE47: =$G$2*AD48 -> 124.93769
D48: =C47*$G$3 -> 120.19138 | F48: =$G$2*E49 -> 120.19138 | H48: =$G$2*G49 -> 120.19138 | J48: =$G$2*I49 -> 120.19138 | L48: =$G$2*K49 -> 120.19138 | N48: =$G$2*M49 -> 120.19138 | P48: =$G$2*O49 -> 120.19138 | R48: =$G$2*Q49 -> 120.19138 | T48: =$G$2*S49 -> 120.19138 | V48: =$G$2*U49 -> 120.19138 | X48: =$G$2*W49 -> 120.19138 | Z48: =$G$2*Y49 -> 120.19138 | AB48: =$G$2*AA49 -> 120.19138 | AD48: =$G$2*AC49 -> 120.19138
E49: =D48*$G$3 -> 115.62538 | G49: =$G$2*F50 -> 115.62538 | I49: =$G$2*H50 -> 115.62538 | K49: =$G$2*J50 -> 115.62538 | M49: =$G$2*L50 -> 115.62538 | O49: =$G$2*N50 -> 115.62538 | Q49: =$G$2*P50 -> 115.62538 | S49: =$G$2*R50 -> 115.62538 | U49: =$G$2*T50 -> 115.62538 | W49: =$G$2*V50 -> 115.62538 | Y49: =$G$2*X50 -> 115.62538 | AA49: =$G$2*Z50 -> 115.62538 | AC49: =$G$2*AB50 -> 115.62538 | AE49: =$G$2*AD50 -> 115.62538
F50: =E49*$G$3 -> 111.23283 | H50: =$G$2*G51 -> 111.23283 | J50: =$G$2*I51 -> 111.23283 | L50: =$G$2*K51 -> 111.23283 | N50: =$G$2*M51 -> 111.23283 | P50: =$G$2*O51 -> 111.23283 | R50: =$G$2*Q51 -> 111.23283 | T50: =$G$2*S51 -> 111.23283 | V50: =$G$2*U51 -> 111.23283 | X50: =$G$2*W51 -> 111.23283 | Z50: =$G$2*Y51 -> 111.23283 | AB50: =$G$2*AA51 -> 111.23283 | AD50: =$G$2*AC51 -> 111.23283
G51: =F50*$G$3 -> 107.00716 | I51: =$G$2*H52 -> 107.00716 | K51: =$G$2*J52 -> 107.00716 | M51: =$G$2*L52 -> 107.00716 | O51: =$G$2*N52 -> 107.00716 | Q51: =$G$2*P52 -> 107.00716 | S51: =$G$2*R52 -> 107.00716 | U51: =$G$2*T52 -> 107.00716 | W51: =$G$2*V52 -> 107.00716 | Y51: =$G$2*X52 -> 107.00716 | AA51: =$G$2*Z52 -> 107.00716 | AC51: =$G$2*AB52 -> 107.00716 | AE51: =$G$2*AD52 -> 107.00716
H52: =G51*$G$3 -> 102.94202 | J52: =$G$2*I53 -> 102.94202 | L52: =$G$2*K53 -> 102.94202 | N52: =$G$2*M53 -> 102.94202 | P52: =$G$2*O53 -> 102.94202 | R52: =$G$2*Q53 -> 102.94202 | T52: =$G$2*S53 -> 102.94202 | V52: =$G$2*U53 -> 102.94202 | X52: =$G$2*W53 -> 102.94202 | Z52: =$G$2*Y53 -> 102.94202 | AB52: =$G$2*AA53 -> 102.94202 | AD52: =$G$2*AC53 -> 102.94202
I53: =H52*$G$3 -> 99.031315 | K53: =$G$2*J54 -> 99.031315 | M53: =$G$2*L54 -> 99.031315 | O53: =$G$2*N54 -> 99.031315 | Q53: =$G$2*P54 -> 99.031315 | S53: =$G$2*R54 -> 99.031315 | U53: =$G$2*T54 -> 99.031315 | W53: =$G$2*V54 -> 99.031315 | Y53: =$G$2*X54 -> 99.031315 | AA53: =$G$2*Z54 -> 99.031315 | AC53: =$G$2*AB54 -> 99.031315 | AE53: =$G$2*AD54 -> 99.031315
J54: =I53*$G$3 -> 95.269172 | L54: =$G$2*K55 -> 95.269172 | N54: =$G$2*M55 -> 95.269172 | P54: =$G$2*O55 -> 95.269172 | R54: =$G$2*Q55 -> 95.269172 | T54: =$G$2*S55 -> 95.269172 | V54: =$G$2*U55 -> 95.269172 | X54: =$G$2*W55 -> 95.269172 | Z54: =$G$2*Y55 -> 95.269172 | AB54: =$G$2*AA55 -> 95.269172 | AD54: =$G$2*AC55 -> 95.269172
K55: =J54*$G$3 -> 91.649951 | M55: =$G$2*L56 -> 91.649951 | O55: =$G$2*N56 -> 91.649951 | Q55: =$G$2*P56 -> 91.649951 | S55: =$G$2*R56 -> 91.649951 | U55: =$G$2*T56 -> 91.649951 | W55: =$G$2*V56 -> 91.649951 | Y55: =$G$2*X56 -> 91.649951 | AA55: =$G$2*Z56 -> 91.649951 | AC55: =$G$2*AB56 -> 91.649951 | AE55: =$G$2*AD56 -> 91.649951
L56: =K55*$G$3 -> 88.168223 | N56: =$G$2*M57 -> 88.168223 | P56: =$G$2*O57 -> 88.168223 | R56: =$G$2*Q57 -> 88.168223 | T56: =$G$2*S57 -> 88.168223 | V56: =$G$2*U57 -> 88.168223 | X56: =$G$2*W57 -> 88.168223 | Z56: =$G$2*Y57 -> 88.168223 | AB56: =$G$2*AA57 -> 88.168223 | AD56: =$G$2*AC57 -> 88.168223
M57: =L56*$G$3 -> 84.818763 | O57: =$G$2*N58 -> 84.818763 | Q57: =$G$2*P58 -> 84.818763 | S57: =$G$2*R58 -> 84.818763 | U57: =$G$2*T58 -> 84.818763 | W57: =$G$2*V58 -> 84.818763 | Y57: =$G$2*X58 -> 84.818763 | AA57: =$G$2*Z58 -> 84.818763 | AC57: =$G$2*AB58 -> 84.818763 | AE57: =$G$2*AD58 -> 84.818763
N58: =M57*$G$3 -> 81.596547 | P58: =$G$2*O59 -> 81.596547 | R58: =$G$2*Q59 -> 81.596547 | T58: =$G$2*S59 -> 81.596547 | V58: =$G$2*U59 -> 81.596547 | X58: =$G$2*W59 -> 81.596547 | Z58: =$G$2*Y59 -> 81.596547 | AB58: =$G$2*AA59 -> 81.596547 | AD58: =$G$2*AC59 -> 81.596547
O59: =N58*$G$3 -> 78.496741 | Q59: =$G$2*P60 -> 78.496741 | S59: =$G$2*R60 -> 78.496741 | U59: =$G$2*T60 -> 78.496741 | W59: =$G$2*V60 -> 78.496741 | Y59: =$G$2*X60 -> 78.496741 | AA59: =$G$2*Z60 -> 78.496741 | AC59: =$G$2*AB60 -> 78.496741 | AE59: =$G$2*AD60 -> 78.496741
P60: =O59*$G$3 -> 75.514695 | R60: =$G$2*Q61 -> 75.514695 | T60: =$G$2*S61 -> 75.514695 | V60: =$G$2*U61 -> 75.514695 | X60: =$G$2*W61 -> 75.514695 | Z60: =$G$2*Y61 -> 75.514695 | AB60: =$G$2*AA61 -> 75.514695 | AD60: =$G$2*AC61 -> 75.514695
Q61: =P60*$G$3 -> 72.645936 | S61: =$G$2*R62 -> 72.645936 | U61: =$G$2*T62 -> 72.645936 | W61: =$G$2*V62 -> 72.645936 | Y61: =$G$2*X62 -> 72.645936 | AA61: =$G$2*Z62 -> 72.645936 | AC61: =$G$2*AB62 -> 72.645936 | AE61: =$G$2*AD62 -> 72.645936
R62: =Q61*$G$3 -> 69.886158 | T62: =$G$2*S63 -> 69.886158 | V62: =$G$2*U63 -> 69.886158 | X62: =$G$2*W63 -> 69.886158 | Z62: =$G$2*Y63 -> 69.886158 | AB62: =$G$2*AA63 -> 69.886158 | AD62: =$G$2*AC63 -> 69.886158
S63: =R62*$G$3 -> 67.231224 | U63: =$G$2*T64 -> 67.231224 | W63: =$G$2*V64 -> 67.231224 | Y63: =$G$2*X64 -> 67.231224 | AA63: =$G$2*Z64 -> 67.231224 | AC63: =$G$2*AB64 -> 67.231224 | AE63: =$G$2*AD64 -> 67.231224
T64: =S63*$G$3 -> 64.677148 | V64: =$G$2*U65 -> 64.677148 | X64: =$G$2*W65 -> 64.677148 | Z64: =$G$2*Y65 -> 64.677148 | AB64: =$G$2*AA65 -> 64.677148 | AD64: =$G$2*AC65 -> 64.677148
U65: =T64*$G$3 -> 62.220101 | W65: =$G$2*V66 -> 62.220101 | Y65: =$G$2*X66 -> 62.220101 | AA65: =$G$2*Z66 -> 62.220101 | AC65: =$G$2*AB66 -> 62.220101 | AE65: =$G$2*AD66 -> 62.220101
V66: =U65*$G$3 -> 59.856395 | X66: =$G$2*W67 -> 59.856395 | Z66: =$G$2*Y67 -> 59.856395 | AB66: =$G$2*AA67 -> 59.856395 | AD66: =$G$2*AC67 -> 59.856395
W67: =V66*$G$3 -> 57.582485 | Y67: =$G$2*X68 -> 57.582485 | AA67: =$G$2*Z68 -> 57.582485 | AC67: =$G$2*AB68 -> 57.582485 | AE67: =$G$2*AD68 -> 57.582485
X68: =W67*$G$3 -> 55.39496 | Z68: =$G$2*Y69 -> 55.39496 | AB68: =$G$2*AA69 -> 55.39496 | AD68: =$G$2*AC69 -> 55.39496
Y69: =X68*$G$3 -> 53.290537 | AA69: =$G$2*Z70 -> 53.290537 | AC69: =$G$2*AB70 -> 53.290537 | AE69: =$G$2*AD70 -> 53.290537
Z70: =Y69*$G$3 -> 51.26606 | AB70: =$G$2*AA71 -> 51.26606 | AD70: =$G$2*AC71 -> 51.26606
AA71: =Z70*$G$3 -> 49.318492 | AC71: =$G$2*AB72 -> 49.318492 | AE71: =$G$2*AD72 -> 49.318492
AB72: =AA71*$G$3 -> 47.444911 | AD72: =$G$2*AC73 -> 47.444911
AC73: =AB72*$G$3 -> 45.642506 | AE73: =$G$2*AD74 -> 45.642506
AD74: =AC73*$G$3 -> 43.908574
AE75: =AD74*$G$3 -> 42.240513
AE78: =MAX($B$2-AE15,0) -> 0
AD79: =MAX((($G$4*AE78)+((1-$G$4)*AE80))*EXP(-$B$4*$G$1),$B$2-AD16) -> 0
AC80: =MAX((($G$4*AD79)+((1-$G$4)*AD81))*EXP(-$B$4*$G$1),$B$2-AC17) -> 0 | AE80: =MAX($B$2-AE17,0) -> 0
AB81: =MAX((($G$4*AC80)+((1-$G$4)*AC82))*EXP(-$B$4*$G$1),$B$2-AB18) -> 0 | AD81: =MAX((($G$4*AE80)+((1-$G$4)*AE82))*EXP(-$B$4*$G$1),$B$2-AD18) -> 0
AA82: =MAX((($G$4*AB81)+((1-$G$4)*AB83))*EXP(-$B$4*$G$1),$B$2-AA19) -> 0 | AC82: =MAX((($G$4*AD81)+((1-$G$4)*AD83))*EXP(-$B$4*$G$1),$B$2-AC19) -> 0 | AE82: =MAX($B$2-AE19,0) -> 0
Z83: =MAX((($G$4*AA82)+((1-$G$4)*AA84))*EXP(-$B$4*$G$1),$B$2-Z20) -> 0 | AB83: =MAX((($G$4*AC82)+((1-$G$4)*AC84))*EXP(-$B$4*$G$1),$B$2-AB20) -> 0 | AD83: =MAX((($G$4*AE82)+((1-$G$4)*AE84))*EXP(-$B$4*$G$1),$B$2-AD20) -> 0
Y84: =MAX((($G$4*Z83)+((1-$G$4)*Z85))*EXP(-$B$4*$G$1),$B$2-Y21) -> 0 | AA84: =MAX((($G$4*AB83)+((1-$G$4)*AB85))*EXP(-$B$4*$G$1),$B$2-AA21) -> 0 | AC84: =MAX((($G$4*AD83)+((1-$G$4)*AD85))*EXP(-$B$4*$G$1),$B$2-AC21) -> 0 | AE84: =MAX($B$2-AE21,0) -> 0
X85: =MAX((($G$4*Y84)+((1-$G$4)*Y86))*EXP(-$B$4*$G$1),$B$2-X22) -> 0 | Z85: =MAX((($G$4*AA84)+((1-$G$4)*AA86))*EXP(-$B$4*$G$1),$B$2-Z22) -> 0 | AB85: =MAX((($G$4*AC84)+((1-$G$4)*AC86))*EXP(-$B$4*$G$1),$B$2-AB22) -> 0 | AD85: =MAX((($G$4*AE84)+((1-$G$4)*AE86))*EXP(-$B$4*$G$1),$B$2-AD22) -> 0
W86: =MAX((($G$4*X85)+((1-$G$4)*X87))*EXP(-$B$4*$G$1),$B$2-W23) -> 0 | Y86: =MAX((($G$4*Z85)+((1-$G$4)*Z87))*EXP(-$B$4*$G$1),$B$2-Y23) -> 0 | AA86: =MAX((($G$4*AB85)+((1-$G$4)*AB87))*EXP(-$B$4*$G$1),$B$2-AA23) -> 0 | AC86: =MAX((($G$4*AD85)+((1-$G$4)*AD87))*EXP(-$B$4*$G$1),$B$2-AC23) -> 0 | AE86: =MAX($B$2-AE23,0) -> 0
V87: =MAX((($G$4*W86)+((1-$G$4)*W88))*EXP(-$B$4*$G$1),$B$2-V24) -> 0 | X87: =MAX((($G$4*Y86)+((1-$G$4)*Y88))*EXP(-$B$4*$G$1),$B$2-X24) -> 0 | Z87: =MAX((($G$4*AA86)+((1-$G$4)*AA88))*EXP(-$B$4*$G$1),$B$2-Z24) -> 0 | AB87: =MAX((($G$4*AC86)+((1-$G$4)*AC88))*EXP(-$B$4*$G$1),$B$2-AB24) -> 0 | AD87: =MAX((($G$4*AE86)+((1-$G$4)*AE88))*EXP(-$B$4*$G$1),$B$2-AD24) -> 0
U88: =MAX((($G$4*V87)+((1-$G$4)*V89))*EXP(-$B$4*$G$1),$B$2-U25) -> 0 | W88: =MAX((($G$4*X87)+((1-$G$4)*X89))*EXP(-$B$4*$G$1),$B$2-W25) -> 0 | Y88: =MAX((($G$4*Z87)+((1-$G$4)*Z89))*EXP(-$B$4*$G$1),$B$2-Y25) -> 0 | AA88: =MAX((($G$4*AB87)+((1-$G$4)*AB89))*EXP(-$B$4*$G$1),$B$2-AA25) -> 0 | AC88: =MAX((($G$4*AD87)+((1-$G$4)*AD89))*EXP(-$B$4*$G$1),$B$2-AC25) -> 0 | AE88: =MAX($B$2-AE25,0) -> 0
T89: =MAX((($G$4*U88)+((1-$G$4)*U90))*EXP(-$B$4*$G$1),$B$2-T26) -> 0 | V89: =MAX((($G$4*W88)+((1-$G$4)*W90))*EXP(-$B$4*$G$1),$B$2-V26) -> 0 | X89: =MAX((($G$4*Y88)+((1-$G$4)*Y90))*EXP(-$B$4*$G$1),$B$2-X26) -> 0 | Z89: =MAX((($G$4*AA88)+((1-$G$4)*AA90))*EXP(-$B$4*$G$1),$B$2-Z26) -> 0 | AB89: =MAX((($G$4*AC88)+((1-$G$4)*AC90))*EXP(-$B$4*$G$1),$B$2-AB26) -> 0 | AD89: =MAX((($G$4*AE88)+((1-$G$4)*AE90))*EXP(-$B$4*$G$1),$B$2-AD26) -> 0
S90: =MAX((($G$4*T89)+((1-$G$4)*T91))*EXP(-$B$4*$G$1),$B$2-S27) -> 0 | U90: =MAX((($G$4*V89)+((1-$G$4)*V91))*EXP(-$B$4*$G$1),$B$2-U27) -> 0 | W90: =MAX((($G$4*X89)+((1-$G$4)*X91))*EXP(-$B$4*$G$1),$B$2-W27) -> 0 | Y90: =MAX((($G$4*Z89)+((1-$G$4)*Z91))*EXP(-$B$4*$G$1),$B$2-Y27) -> 0 | AA90: =MAX((($G$4*AB89)+((1-$G$4)*AB91))*EXP(-$B$4*$G$1),$B$2-AA27) -> 0 | AC90: =MAX((($G$4*AD89)+((1-$G$4)*AD91))*EXP(-$B$4*$G$1),$B$2-AC27) -> 0 | AE90: =MAX($B$2-AE27,0) -> 0
R91: =MAX((($G$4*S90)+((1-$G$4)*S92))*EXP(-$B$4*$G$1),$B$2-R28) -> 0 | T91: =MAX((($G$4*U90)+((1-$G$4)*U92))*EXP(-$B$4*$G$1),$B$2-T28) -> 0 | V91: =MAX((($G$4*W90)+((1-$G$4)*W92))*EXP(-$B$4*$G$1),$B$2-V28) -> 0 | X91: =MAX((($G$4*Y90)+((1-$G$4)*Y92))*EXP(-$B$4*$G$1),$B$2-X28) -> 0 | Z91: =MAX((($G$4*AA90)+((1-$G$4)*AA92))*EXP(-$B$4*$G$1),$B$2-Z28) -> 0 | AB91: =MAX((($G$4*AC90)+((1-$G$4)*AC92))*EXP(-$B$4*$G$1),$B$2-AB28) -> 0 | AD91: =MAX((($G$4*AE90)+((1-$G$4)*AE92))*EXP(-$B$4*$G$1),$B$2-AD28) -> 0
Q92: =MAX((($G$4*R91)+((1-$G$4)*R93))*EXP(-$B$4*$G$1),$B$2-Q29) -> 0 | S92: =MAX((($G$4*T91)+((1-$G$4)*T93))*EXP(-$B$4*$G$1),$B$2-S29) -> 0 | U92: =MAX((($G$4*V91)+((1-$G$4)*V93))*EXP(-$B$4*$G$1),$B$2-U29) -> 0 | W92: =MAX((($G$4*X91)+((1-$G$4)*X93))*EXP(-$B$4*$G$1),$B$2-W29) -> 0 | Y92: =MAX((($G$4*Z91)+((1-$G$4)*Z93))*EXP(-$B$4*$G$1),$B$2-Y29) -> 0 | AA92: =MAX((($G$4*AB91)+((1-$G$4)*AB93))*EXP(-$B$4*$G$1),$B$2-AA29) -> 0 | AC92: =MAX((($G$4*AD91)+((1-$G$4)*AD93))*EXP(-$B$4*$G$1),$B$2-AC29) -> 0 | AE92: =MAX($B$2-AE29,0) -> 0
P93: =MAX((($G$4*Q92)+((1-$G$4)*Q94))*EXP(-$B$4*$G$1),$B$2-P30) -> 0.00014407598 | R93: =MAX((($G$4*S92)+((1-$G$4)*S94))*EXP(-$B$4*$G$1),$B$2-R30) -> 0 | T93: =MAX((($G$4*U92)+((1-$G$4)*U94))*EXP(-$B$4*$G$1),$B$2-T30) -> 0 | V93: =MAX((($G$4*W92)+((1-$G$4)*W94))*EXP(-$B$4*$G$1),$B$2-V30) -> 0 | X93: =MAX((($G$4*Y92)+((1-$G$4)*Y94))*EXP(-$B$4*$G$1),$B$2-X30) -> 0 | Z93: =MAX((($G$4*AA92)+((1-$G$4)*AA94))*EXP(-$B$4*$G$1),$B$2-Z30) -> 0 | AB93: =MAX((($G$4*AC92)+((1-$G$4)*AC94))*EXP(-$B$4*$G$1),$B$2-AB30) -> 0 | AD93: =MAX((($G$4*AE92)+((1-$G$4)*AE94))*EXP(-$B$4*$G$1),$B$2-AD30) -> 0
O94: =MAX((($G$4*P93)+((1-$G$4)*P95))*EXP(-$B$4*$G$1),$B$2-O31) -> 0.0013729548 | Q94: =MAX((($G$4*R93)+((1-$G$4)*R95))*EXP(-$B$4*$G$1),$B$2-Q31) -> 0.00028925674 | S94: =MAX((($G$4*T93)+((1-$G$4)*T95))*EXP(-$B$4*$G$1),$B$2-S31) -> 0 | U94: =MAX((($G$4*V93)+((1-$G$4)*V95))*EXP(-$B$4*$G$1),$B$2-U31) -> 0 | W94: =MAX((($G$4*X93)+((1-$G$4)*X95))*EXP(-$B$4*$G$1),$B$2-W31) -> 0 | Y94: =MAX((($G$4*Z93)+((1-$G$4)*Z95))*EXP(-$B$4*$G$1),$B$2-Y31) -> 0 | AA94: =MAX((($G$4*AB93)+((1-$G$4)*AB95))*EXP(-$B$4*$G$1),$B$2-AA31) -> 0 | AC94: =MAX((($G$4*AD93)+((1-$G$4)*AD95))*EXP(-$B$4*$G$1),$B$2-AC31) -> 0 | AE94: =MAX($B$2-AE31,0) -> 0
N95: =MAX((($G$4*O94)+((1-$G$4)*O96))*EXP(-$B$4*$G$1),$B$2-N32) -> 0.0069505253 | P95: =MAX((($G$4*Q94)+((1-$G$4)*Q96))*EXP(-$B$4*$G$1),$B$2-P32) -> 0.0026117384 | R95: =MAX((($G$4*S94)+((1-$G$4)*S96))*EXP(-$B$4*$G$1),$B$2-R32) -> 0.0005807315 | T95: =MAX((($G$4*U94)+((1-$G$4)*U96))*EXP(-$B$4*$G$1),$B$2-T32) -> 0 | V95: =MAX((($G$4*W94)+((1-$G$4)*W96))*EXP(-$B$4*$G$1),$B$2-V32) -> 0 | X95: =MAX((($G$4*Y94)+((1-$G$4)*Y96))*EXP(-$B$4*$G$1),$B$2-X32) -> 0 | Z95: =MAX((($G$4*AA94)+((1-$G$4)*AA96))*EXP(-$B$4*$G$1),$B$2-Z32) -> 0 | AB95: =MAX((($G$4*AC94)+((1-$G$4)*AC96))*EXP(-$B$4*$G$1),$B$2-AB32) -> 0 | AD95: =MAX((($G$4*AE94)+((1-$G$4)*AE96))*EXP(-$B$4*$G$1),$B$2-AD32) -> 0
M96: =MAX((($G$4*N95)+((1-$G$4)*N97))*EXP(-$B$4*$G$1),$B$2-M33) -> 0.024856247 | O96: =MAX((($G$4*P95)+((1-$G$4)*P97))*EXP(-$B$4*$G$1),$B$2-O33) -> 0.012575455 | Q96: =MAX((($G$4*R95)+((1-$G$4)*R97))*EXP(-$B$4*$G$1),$B$2-Q33) -> 0.004952996 | S96: =MAX((($G$4*T95)+((1-$G$4)*T97))*EXP(-$B$4*$G$1),$B$2-S33) -> 0.001165916 | U96: =MAX((($G$4*V95)+((1-$G$4)*V97))*EXP(-$B$4*$G$1),$B$2-U33) -> 0 | W96: =MAX((($G$4*X95)+((1-$G$4)*X97))*EXP(-$B$4*$G$1),$B$2-W33) -> 0 | Y96: =MAX((($G$4*Z95)+((1-$G$4)*Z97))*EXP(-$B$4*$G$1),$B$2-Y33) -> 0 | AA96: =MAX((($G$4*AB95)+((1-$G$4)*AB97))*EXP(-$B$4*$G$1),$B$2-AA33) -> 0 | AC96: =MAX((($G$4*AD95)+((1-$G$4)*AD97))*EXP(-$B$4*$G$1),$B$2-AC33) -> 0 | AE96: =MAX($B$2-AE33,0) -> 0
L97: =MAX((($G$4*M96)+((1-$G$4)*M98))*EXP(-$B$4*$G$1),$B$2-L34) -> 0.07047537 | N97: =MAX((($G$4*O96)+((1-$G$4)*O98))*EXP(-$B$4*$G$1),$B$2-N34) -> 0.042922508 | P97: =MAX((($G$4*Q96)+((1-$G$4)*Q98))*EXP(-$B$4*$G$1),$B$2-P34) -> 0.022624305 | R97: =MAX((($G$4*S96)+((1-$G$4)*S98))*EXP(-$B$4*$G$1),$B$2-R34) -> 0.0093607285 | T97: =MAX((($G$4*U96)+((1-$G$4)*U98))*EXP(-$B$4*$G$1),$B$2-T34) -> 0.0023407723 | V97: =MAX((($G$4*W96)+((1-$G$4)*W98))*EXP(-$B$4*$G$1),$B$2-V34) -> 0 | X97: =MAX((($G$4*Y96)+((1-$G$4)*Y98))*EXP(-$B$4*$G$1),$B$2-X34) -> 0 | Z97: =MAX((($G$4*AA96)+((1-$G$4)*AA98))*EXP(-$B$4*$G$1),$B$2-Z34) -> 0 | AB97: =MAX((($G$4*AC96)+((1-$G$4)*AC98))*EXP(-$B$4*$G$1),$B$2-AB34) -> 0 | AD97: =MAX((($G$4*AE96)+((1-$G$4)*AE98))*EXP(-$B$4*$G$1),$B$2-AD34) -> 0
K98: =MAX((($G$4*L97)+((1-$G$4)*L99))*EXP(-$B$4*$G$1),$B$2-K35) -> 0.16863138 | M98: =MAX((($G$4*N97)+((1-$G$4)*N99))*EXP(-$B$4*$G$1),$B$2-M35) -> 0.1165274 | O98: =MAX((($G$4*P97)+((1-$G$4)*P99))*EXP(-$B$4*$G$1),$B$2-O35) -> 0.073544307 | Q98: =MAX((($G$4*R97)+((1-$G$4)*R99))*EXP(-$B$4*$G$1),$B$2-Q35) -> 0.040447676 | S98: =MAX((($G$4*T97)+((1-$G$4)*T99))*EXP(-$B$4*$G$1),$B$2-S35) -> 0.017622277 | U98: =MAX((($G$4*V97)+((1-$G$4)*V99))*EXP(-$B$4*$G$1),$B$2-U35) -> 0.0046994936 | W98: =MAX((($G$4*X97)+((1-$G$4)*X99))*EXP(-$B$4*$G$1),$B$2-W35) -> 0 | Y98: =MAX((($G$4*Z97)+((1-$G$4)*Z99))*EXP(-$B$4*$G$1),$B$2-Y35) -> 0 | AA98: =MAX((($G$4*AB97)+((1-$G$4)*AB99))*EXP(-$B$4*$G$1),$B$2-AA35) -> 0 | AC98: =MAX((($G$4*AD97)+((1-$G$4)*AD99))*EXP(-$B$4*$G$1),$B$2-AC35) -> 0 | AE98: =MAX($B$2-AE35,0) -> 0
J99: =MAX((($G$4*K98)+((1-$G$4)*K100))*EXP(-$B$4*$G$1),$B$2-J36) -> 0.35404169 | L99: =MAX((($G$4*M98)+((1-$G$4)*M100))*EXP(-$B$4*$G$1),$B$2-L36) -> 0.26777567 | N99: =MAX((($G$4*O98)+((1-$G$4)*O100))*EXP(-$B$4*$G$1),$B$2-N36) -> 0.1908402 | P99: =MAX((($G$4*Q98)+((1-$G$4)*Q100))*EXP(-$B$4*$G$1),$B$2-P36) -> 0.1249304 | R99: =MAX((($G$4*S98)+((1-$G$4)*S100))*EXP(-$B$4*$G$1),$B$2-R36) -> 0.071804295 | T99: =MAX((($G$4*U98)+((1-$G$4)*U100))*EXP(-$B$4*$G$1),$B$2-T36) -> 0.033028785 | V99: =MAX((($G$4*W98)+((1-$G$4)*W100))*EXP(-$B$4*$G$1),$B$2-V36) -> 0.0094350229 | X99: =MAX((($G$4*Y98)+((1-$G$4)*Y100))*EXP(-$B$4*$G$1),$B$2-X36) -> 0 | Z99: =MAX((($G$4*AA98)+((1-$G$4)*AA100))*EXP(-$B$4*$G$1),$B$2-Z36) -> 0 | AB99: =MAX((($G$4*AC98)+((1-$G$4)*AC100))*EXP(-$B$4*$G$1),$B$2-AB36) -> 0 | AD99: =MAX((($G$4*AE98)+((1-$G$4)*AE100))*EXP(-$B$4*$G$1),$B$2-AD36) -> 0
I100: =MAX((($G$4*J99)+((1-$G$4)*J101))*EXP(-$B$4*$G$1),$B$2-I37) -> 0.66971558 | K100: =MAX((($G$4*L99)+((1-$G$4)*L101))*EXP(-$B$4*$G$1),$B$2-K37) -> 0.54143751 | M100: =MAX((($G$4*N99)+((1-$G$4)*N101))*EXP(-$B$4*$G$1),$B$2-M37) -> 0.4205733 | O100: =MAX((($G$4*P99)+((1-$G$4)*P101))*EXP(-$B$4*$G$1),$B$2-O37) -> 0.3092814 | Q100: =MAX((($G$4*R99)+((1-$G$4)*R101))*EXP(-$B$4*$G$1),$B$2-Q37) -> 0.21019617 | S100: =MAX((($G$4*T99)+((1-$G$4)*T101))*EXP(-$B$4*$G$1),$B$2-S37) -> 0.1264607 | U100: =MAX((($G$4*V99)+((1-$G$4)*V101))*EXP(-$B$4*$G$1),$B$2-U37) -> 0.061591018 | W100: =MAX((($G$4*X99)+((1-$G$4)*X101))*EXP(-$B$4*$G$1),$B$2-W37) -> 0.018942393 | Y100: =MAX((($G$4*Z99)+((1-$G$4)*Z101))*EXP(-$B$4*$G$1),$B$2-Y37) -> 0 | AA100: =MAX((($G$4*AB99)+((1-$G$4)*AB101))*EXP(-$B$4*$G$1),$B$2-AA37) -> 0 | AC100: =MAX((($G$4*AD99)+((1-$G$4)*AD101))*EXP(-$B$4*$G$1),$B$2-AC37) -> 0 | AE100: =MAX($B$2-AE37,0) -> 0
H101: =MAX((($G$4*I100)+((1-$G$4)*I102))*EXP(-$B$4*$G$1),$B$2-H38) -> 1.163433 | J101: =MAX((($G$4*K100)+((1-$G$4)*K102))*EXP(-$B$4*$G$1),$B$2-J38) -> 0.98899373 | L101: =MAX((($G$4*M100)+((1-$G$4)*M102))*EXP(-$B$4*$G$1),$B$2-L38) -> 0.81809305 | N101: =MAX((($G$4*O100)+((1-$G$4)*O102))*EXP(-$B$4*$G$1),$B$2-N38) -> 0.65270604 | P101: =MAX((($G$4*Q100)+((1-$G$4)*Q102))*EXP(-$B$4*$G$1),$B$2-P38) -> 0.49546368 | R101: =MAX((($G$4*S100)+((1-$G$4)*S102))*EXP(-$B$4*$G$1),$B$2-R38) -> 0.3498893 | T101: =MAX((($G$4*U100)+((1-$G$4)*U102))*EXP(-$B$4*$G$1),$B$2-T38) -> 0.22071947 | V101: =MAX((($G$4*W100)+((1-$G$4)*W102))*EXP(-$B$4*$G$1),$B$2-V38) -> 0.11417849 | X101: =MAX((($G$4*Y100)+((1-$G$4)*Y102))*EXP(-$B$4*$G$1),$B$2-X38) -> 0.038030037 | Z101: =MAX((($G$4*AA100)+((1-$G$4)*AA102))*EXP(-$B$4*$G$1),$B$2-Z38) -> 0 | AB101: =MAX((($G$4*AC100)+((1-$G$4)*AC102))*EXP(-$B$4*$G$1),$B$2-AB38) -> 0 | AD101: =MAX((($G$4*AE100)+((1-$G$4)*AE102))*EXP(-$B$4*$G$1),$B$2-AD38) -> 0
G102: =MAX((($G$4*H101)+((1-$G$4)*H103))*EXP(-$B$4*$G$1),$B$2-G39) -> 1.8830059 | I102: =MAX((($G$4*J101)+((1-$G$4)*J103))*EXP(-$B$4*$G$1),$B$2-I39) -> 1.6631753 | K102: =MAX((($G$4*L101)+((1-$G$4)*L103))*EXP(-$B$4*$G$1),$B$2-K39) -> 1.441792 | M102: =MAX((($G$4*N101)+((1-$G$4)*N103))*EXP(-$B$4*$G$1),$B$2-M39) -> 1.2200671 | O102: =MAX((($G$4*P101)+((1-$G$4)*P103))*EXP(-$B$4*$G$1),$B$2-O39) -> 0.99979808 | Q102: =MAX((($G$4*R101)+((1-$G$4)*R103))*EXP(-$B$4*$G$1),$B$2-Q39) -> 0.78362136 | S102: =MAX((($G$4*T101)+((1-$G$4)*T103))*EXP(-$B$4*$G$1),$B$2-S39) -> 0.57545395 | U102: =MAX((($G$4*V101)+((1-$G$4)*V103))*EXP(-$B$4*$G$1),$B$2-U39) -> 0.38127403 | W102: =MAX((($G$4*X101)+((1-$G$4)*X103))*EXP(-$B$4*$G$1),$B$2-W39) -> 0.21020818 | Y102: =MAX((($G$4*Z101)+((1-$G$4)*Z103))*EXP(-$B$4*$G$1),$B$2-Y39) -> 0.076351687 | AA102: =MAX((($G$4*AB101)+((1-$G$4)*AB103))*EXP(-$B$4*$G$1),$B$2-AA39) -> 0 | AC102: =MAX((($G$4*AD101)+((1-$G$4)*AD103))*EXP(-$B$4*$G$1),$B$2-AC39) -> 0 | AE102: =MAX($B$2-AE39,0) -> 0
F103: =MAX((($G$4*G102)+((1-$G$4)*G104))*EXP(-$B$4*$G$1),$B$2-F40) -> 2.8713097 | H103: =MAX((($G$4*I102)+((1-$G$4)*I104))*EXP(-$B$4*$G$1),$B$2-H40) -> 2.6119862 | J103: =MAX((($G$4*K102)+((1-$G$4)*K104))*EXP(-$B$4*$G$1),$B$2-J40) -> 2.3458331 | L103: =MAX((($G$4*M102)+((1-$G$4)*M104))*EXP(-$B$4*$G$1),$B$2-L40) -> 2.0730086 | N103: =MAX((($G$4*O102)+((1-$G$4)*O104))*EXP(-$B$4*$G$1),$B$2-N40) -> 1.7939609 | P103: =MAX((($G$4*Q102)+((1-$G$4)*Q104))*EXP(-$B$4*$G$1),$B$2-P40) -> 1.5096562 | R103: =MAX((($G$4*S102)+((1-$G$4)*S104))*EXP(-$B$4*$G$1),$B$2-R40) -> 1.2218491 | T103: =MAX((($G$4*U102)+((1-$G$4)*U104))*EXP(-$B$4*$G$1),$B$2-T40) -> 0.93364648 | V103: =MAX((($G$4*W102)+((1-$G$4)*W104))*EXP(-$B$4*$G$1),$B$2-V40) -> 0.6507994 | X103: =MAX((($G$4*Y102)+((1-$G$4)*Y104))*EXP(-$B$4*$G$1),$B$2-X40) -> 0.38383374 | Z103: =MAX((($G$4*AA102)+((1-$G$4)*AA104))*EXP(-$B$4*$G$1),$B$2-Z40) -> 0.15328884 | AB103: =MAX((($G$4*AC102)+((1-$G$4)*AC104))*EXP(-$B$4*$G$1),$B$2-AB40) -> 0 | AD103: =MAX((($G$4*AE102)+((1-$G$4)*AE104))*EXP(-$B$4*$G$1),$B$2-AD40) -> 0
E104: =MAX((($G$4*F103)+((1-$G$4)*F105))*EXP(-$B$4*$G$1),$B$2-E41) -> 4.1620048 | G104: =MAX((($G$4*H103)+((1-$G$4)*H105))*EXP(-$B$4*$G$1),$B$2-G41) -> 3.8734874 | I104: =MAX((($G$4*J103)+((1-$G$4)*J105))*EXP(-$B$4*$G$1),$B$2-I41) -> 3.573633 | K104: =MAX((($G$4*L103)+((1-$G$4)*L105))*EXP(-$B$4*$G$1),$B$2-K41) -> 3.2616268 | M104: =MAX((($G$4*N103)+((1-$G$4)*N105))*EXP(-$B$4*$G$1),$B$2-M41) -> 2.9365696 | O104: =MAX((($G$4*P103)+((1-$G$4)*P105))*EXP(-$B$4*$G$1),$B$2-O41) -> 2.5975559 | Q104: =MAX((($G$4*R103)+((1-$G$4)*R105))*EXP(-$B$4*$G$1),$B$2-Q41) -> 2.2438782 | S104: =MAX((($G$4*T103)+((1-$G$4)*T105))*EXP(-$B$4*$G$1),$B$2-S41) -> 1.8751247 | U104: =MAX((($G$4*V103)+((1-$G$4)*V105))*EXP(-$B$4*$G$1),$B$2-U41) -> 1.4915292 | W104: =MAX((($G$4*X103)+((1-$G$4)*X105))*EXP(-$B$4*$G$1),$B$2-W41) -> 1.0954719 | Y104: =MAX((($G$4*Z103)+((1-$G$4)*Z105))*EXP(-$B$4*$G$1),$B$2-Y41) -> 0.69392882 | AA104: =MAX((($G$4*AB103)+((1-$G$4)*AB105))*EXP(-$B$4*$G$1),$B$2-AA41) -> 0.30775309 | AC104: =MAX((($G$4*AD103)+((1-$G$4)*AD105))*EXP(-$B$4*$G$1),$B$2-AC41) -> 0 | AE104: =MAX($B$2-AE41,0) -> 0
D105: =MAX((($G$4*E104)+((1-$G$4)*E106))*EXP(-$B$4*$G$1),$B$2-D42) -> 5.776548 | F105: =MAX((($G$4*G104)+((1-$G$4)*G106))*EXP(-$B$4*$G$1),$B$2-F42) -> 5.4721966 | H105: =MAX((($G$4*I104)+((1-$G$4)*I106))*EXP(-$B$4*$G$1),$B$2-H42) -> 5.1533945 | J105: =MAX((($G$4*K104)+((1-$G$4)*K106))*EXP(-$B$4*$G$1),$B$2-J42) -> 4.8186905 | L105: =MAX((($G$4*M104)+((1-$G$4)*M106))*EXP(-$B$4*$G$1),$B$2-L42) -> 4.46629 | N105: =MAX((($G$4*O104)+((1-$G$4)*O106))*EXP(-$B$4*$G$1),$B$2-N42) -> 4.0939375 | P105: =MAX((($G$4*Q104)+((1-$G$4)*Q106))*EXP(-$B$4*$G$1),$B$2-P42) -> 3.698845 | R105: =MAX((($G$4*S104)+((1-$G$4)*S106))*EXP(-$B$4*$G$1),$B$2-R42) -> 3.2778292 | T105: =MAX((($G$4*U104)+((1-$G$4)*U106))*EXP(-$B$4*$G$1),$B$2-T42) -> 2.8269436 | V105: =MAX((($G$4*W104)+((1-$G$4)*W106))*EXP(-$B$4*$G$1),$B$2-V42) -> 2.3408816 | X105: =MAX((($G$4*Y104)+((1-$G$4)*Y106))*EXP(-$B$4*$G$1),$B$2-X42) -> 1.8138501 | Z105: =MAX((($G$4*AA104)+((1-$G$4)*AA106))*EXP(-$B$4*$G$1),$B$2-Z42) -> 1.2392269 | AB105: =MAX((($G$4*AC104)+((1-$G$4)*AC106))*EXP(-$B$4*$G$1),$B$2-AB42) -> 0.61786603 | AD105: =MAX((($G$4*AE104)+((1-$G$4)*AE106))*EXP(-$B$4*$G$1),$B$2-AD42) -> 0
C106: =MAX((($G$4*D105)+((1-$G$4)*D107))*EXP(-$B$4*$G$1),$B$2-C43) -> 7.7230132 | E106: =MAX((($G$4*F105)+((1-$G$4)*F107))*EXP(-$B$4*$G$1),$B$2-E43) -> 7.4173865 | G106: =MAX((($G$4*H105)+((1-$G$4)*H107))*EXP(-$B$4*$G$1),$B$2-G43) -> 7.0961151 | I106: =MAX((($G$4*J105)+((1-$G$4)*J107))*EXP(-$B$4*$G$1),$B$2-I43) -> 6.7572174 | K106: =MAX((($G$4*L105)+((1-$G$4)*L107))*EXP(-$B$4*$G$1),$B$2-K43) -> 6.3985984 | M106: =MAX((($G$4*N105)+((1-$G$4)*N107))*EXP(-$B$4*$G$1),$B$2-M43) -> 6.0175582 | O106: =MAX((($G$4*P105)+((1-$G$4)*P107))*EXP(-$B$4*$G$1),$B$2-O43) -> 5.6104778 | Q106: =MAX((($G$4*R105)+((1-$G$4)*R107))*EXP(-$B$4*$G$1),$B$2-Q43) -> 5.1724704 | S106: =MAX((($G$4*T105)+((1-$G$4)*T107))*EXP(-$B$4*$G$1),$B$2-S43) -> 4.6975589 | U106: =MAX((($G$4*V105)+((1-$G$4)*V107))*EXP(-$B$4*$G$1),$B$2-U43) -> 4.1775846 | W106: =MAX((($G$4*X105)+((1-$G$4)*X107))*EXP(-$B$4*$G$1),$B$2-W43) -> 3.5995036 | Y106: =MAX((($G$4*Z105)+((1-$G$4)*Z107))*EXP(-$B$4*$G$1),$B$2-Y43) -> 2.9446789 | AA106: =MAX((($G$4*AB105)+((1-$G$4)*AB107))*EXP(-$B$4*$G$1),$B$2-AA43) -> 2.1788722 | AC106: =MAX((($G$4*AD105)+((1-$G$4)*AD107))*EXP(-$B$4*$G$1),$B$2-AC43) -> 1.2404699 | AE106: =MAX($B$2-AE43,0) -> 0
...

Sheet Slide 56_(inverting rates)_R
A1: S0 | B1: =1/'Slide 56_(changing notional)_R'!B1 -> 0.0074074074 | C1: USD per ISK | E1: Working | F1: Delta t | G1: =B6/B7 -> 0.016666667
A2: X | B2: =1/'Slide 56_(changing notional)_R'!B2 -> 0.0071428571 | C2: USD per ISK | F2: u | G2: =EXP(B3*SQRT(G1)) -> 1.0394896
A3: volatility | B3: 0.3 | F3: d | G3: =1/G2 -> 0.96201058
A4: Dom Risk free (USD) | B4: ='Slide 56_(changing notional)_R'!B5 -> 0.05 | F4: p | G4: =(EXP((B4-B5)*G1)-G3)/(G2-G3) -> 0.47956763
A5: For Risk Free (ISK) | B5: ='Slide 56_(changing notional)_R'!B4 -> 0.1 | F5: Option Value | G5: =A108 -> 0.0006657311 | H5: USD per ISK
A6: Term (yrs) | B6: 0.5 | G6: =G5*B8 -> 66573.11 | H6: USD
A7: n | B7: 30
A8: Notional | B8: 100000000 | C8: ISK
A14: 0 | B14: Delta t | C14: 2 Delta t | D14: 3 Delta t | E14: 4 Delta t | F14: 5 Delta t | G14: 6 Delta t | H14: 7 Delta t | I14: 8 Delta t | J14: 9 Delta t | K14: 10 Delta t | L14: 11 Delta t | M14: 12 Delta t | N14: 13 Delta t | O14: 14 Delta t | P14: 15 Delta t | Q14: 16 Delta t | R14: 17 Delta t | S14: 18 Delta t | T14: 19 Delta t | U14: 20 Delta t | V14: 21 Delta t | W14: 22 Delta t | X14: 23 Delta t | Y14: 24 Delta t | Z14: 25 Delta t | AA14: 26 Delta t | AB14: 27 Delta t | AC14: 28 Delta t | AD14: 29 Delta t | AE14: 30 Delta t
AE15: =$G$2*AD16 -> 0.023673955
AD16: =$G$2*AC17 -> 0.022774595
AC17: =$G$2*AB18 -> 0.021909402 | AE17: =$G$2*AD18 -> 0.021909402
AB18: =$G$2*AA19 -> 0.021077076 | AD18: =$G$2*AC19 -> 0.021077076
AA19: =$G$2*Z20 -> 0.02027637 | AC19: =$G$2*AB20 -> 0.02027637 | AE19: =$G$2*AD20 -> 0.02027637
Z20: =$G$2*Y21 -> 0.019506082 | AB20: =$G$2*AA21 -> 0.019506082 | AD20: =$G$2*AC21 -> 0.019506082
Y21: =$G$2*X22 -> 0.018765058 | AA21: =$G$2*Z22 -> 0.018765058 | AC21: =$G$2*AB22 -> 0.018765058 | AE21: =$G$2*AD22 -> 0.018765058
X22: =$G$2*W23 -> 0.018052184 | Z22: =$G$2*Y23 -> 0.018052184 | AB22: =$G$2*AA23 -> 0.018052184 | AD22: =$G$2*AC23 -> 0.018052184
W23: =$G$2*V24 -> 0.017366392 | Y23: =$G$2*X24 -> 0.017366392 | AA23: =$G$2*Z24 -> 0.017366392 | AC23: =$G$2*AB24 -> 0.017366392 | AE23: =$G$2*AD24 -> 0.017366392
V24: =$G$2*U25 -> 0.016706653 | X24: =$G$2*W25 -> 0.016706653 | Z24: =$G$2*Y25 -> 0.016706653 | AB24: =$G$2*AA25 -> 0.016706653 | AD24: =$G$2*AC25 -> 0.016706653
U25: =$G$2*T26 -> 0.016071977 | W25: =$G$2*V26 -> 0.016071977 | Y25: =$G$2*X26 -> 0.016071977 | AA25: =$G$2*Z26 -> 0.016071977 | AC25: =$G$2*AB26 -> 0.016071977 | AE25: =$G$2*AD26 -> 0.016071977
T26: =$G$2*S27 -> 0.015461411 | V26: =$G$2*U27 -> 0.015461411 | X26: =$G$2*W27 -> 0.015461411 | Z26: =$G$2*Y27 -> 0.015461411 | AB26: =$G$2*AA27 -> 0.015461411 | AD26: =$G$2*AC27 -> 0.015461411
S27: =$G$2*R28 -> 0.014874041 | U27: =$G$2*T28 -> 0.014874041 | W27: =$G$2*V28 -> 0.014874041 | Y27: =$G$2*X28 -> 0.014874041 | AA27: =$G$2*Z28 -> 0.014874041 | AC27: =$G$2*AB28 -> 0.014874041 | AE27: =$G$2*AD28 -> 0.014874041
R28: =$G$2*Q29 -> 0.014308985 | T28: =$G$2*S29 -> 0.014308985 | V28: =$G$2*U29 -> 0.014308985 | X28: =$G$2*W29 -> 0.014308985 | Z28: =$G$2*Y29 -> 0.014308985 | AB28: =$G$2*AA29 -> 0.014308985 | AD28: =$G$2*AC29 -> 0.014308985
Q29: =$G$2*P30 -> 0.013765395 | S29: =$G$2*R30 -> 0.013765395 | U29: =$G$2*T30 -> 0.013765395 | W29: =$G$2*V30 -> 0.013765395 | Y29: =$G$2*X30 -> 0.013765395 | AA29: =$G$2*Z30 -> 0.013765395 | AC29: =$G$2*AB30 -> 0.013765395 | AE29: =$G$2*AD30 -> 0.013765395
P30: =$G$2*O31 -> 0.013242456 | R30: =$G$2*Q31 -> 0.013242456 | T30: =$G$2*S31 -> 0.013242456 | V30: =$G$2*U31 -> 0.013242456 | X30: =$G$2*W31 -> 0.013242456 | Z30: =$G$2*Y31 -> 0.013242456 | AB30: =$G$2*AA31 -> 0.013242456 | AD30: =$G$2*AC31 -> 0.013242456
O31: =$G$2*N32 -> 0.012739382 | Q31: =$G$2*P32 -> 0.012739382 | S31: =$G$2*R32 -> 0.012739382 | U31: =$G$2*T32 -> 0.012739382 | W31: =$G$2*V32 -> 0.012739382 | Y31: =$G$2*X32 -> 0.012739382 | AA31: =$G$2*Z32 -> 0.012739382 | AC31: =$G$2*AB32 -> 0.012739382 | AE31: =$G$2*AD32 -> 0.012739382
N32: =$G$2*M33 -> 0.012255421 | P32: =$G$2*O33 -> 0.012255421 | R32: =$G$2*Q33 -> 0.012255421 | T32: =$G$2*S33 -> 0.012255421 | V32: =$G$2*U33 -> 0.012255421 | X32: =$G$2*W33 -> 0.012255421 | Z32: =$G$2*Y33 -> 0.012255421 | AB32: =$G$2*AA33 -> 0.012255421 | AD32: =$G$2*AC33 -> 0.012255421
M33: =$G$2*L34 -> 0.011789844 | O33: =$G$2*N34 -> 0.011789844 | Q33: =$G$2*P34 -> 0.011789844 | S33: =$G$2*R34 -> 0.011789844 | U33: =$G$2*T34 -> 0.011789844 | W33: =$G$2*V34 -> 0.011789844 | Y33: =$G$2*X34 -> 0.011789844 | AA33: =$G$2*Z34 -> 0.011789844 | AC33: =$G$2*AB34 -> 0.011789844 | AE33: =$G$2*AD34 -> 0.011789844
L34: =$G$2*K35 -> 0.011341955 | N34: =$G$2*M35 -> 0.011341955 | P34: =$G$2*O35 -> 0.011341955 | R34: =$G$2*Q35 -> 0.011341955 | T34: =$G$2*S35 -> 0.011341955 | V34: =$G$2*U35 -> 0.011341955 | X34: =$G$2*W35 -> 0.011341955 | Z34: =$G$2*Y35 -> 0.011341955 | AB34: =$G$2*AA35 -> 0.011341955 | AD34: =$G$2*AC35 -> 0.011341955
K35: =$G$2*J36 -> 0.010911081 | M35: =$G$2*L36 -> 0.010911081 | O35: =$G$2*N36 -> 0.010911081 | Q35: =$G$2*P36 -> 0.010911081 | S35: =$G$2*R36 -> 0.010911081 | U35: =$G$2*T36 -> 0.010911081 | W35: =$G$2*V36 -> 0.010911081 | Y35: =$G$2*X36 -> 0.010911081 | AA35: =$G$2*Z36 -> 0.010911081 | AC35: =$G$2*AB36 -> 0.010911081 | AE35: =$G$2*AD36 -> 0.010911081
J36: =$G$2*I37 -> 0.010496575 | L36: =$G$2*K37 -> 0.010496575 | N36: =$G$2*M37 -> 0.010496575 | P36: =$G$2*O37 -> 0.010496575 | R36: =$G$2*Q37 -> 0.010496575 | T36: =$G$2*S37 -> 0.010496575 | V36: =$G$2*U37 -> 0.010496575 | X36: =$G$2*W37 -> 0.010496575 | Z36: =$G$2*Y37 -> 0.010496575 | AB36: =$G$2*AA37 -> 0.010496575 | AD36: =$G$2*AC37 -> 0.010496575
I37: =$G$2*H38 -> 0.010097816 | K37: =$G$2*J38 -> 0.010097816 | M37: =$G$2*L38 -> 0.010097816 | O37: =$G$2*N38 -> 0.010097816 | Q37: =$G$2*P38 -> 0.010097816 | S37: =$G$2*R38 -> 0.010097816 | U37: =$G$2*T38 -> 0.010097816 | W37: =$G$2*V38 -> 0.010097816 | Y37: =$G$2*X38 -> 0.010097816 | AA37: =$G$2*Z38 -> 0.010097816 | AC37: =$G$2*AB38 -> 0.010097816 | AE37: =$G$2*AD38 -> 0.010097816
H38: =$G$2*G39 -> 0.0097142059 | J38: =$G$2*I39 -> 0.0097142059 | L38: =$G$2*K39 -> 0.0097142059 | N38: =$G$2*M39 -> 0.0097142059 | P38: =$G$2*O39 -> 0.0097142059 | R38: =$G$2*Q39 -> 0.0097142059 | T38: =$G$2*S39 -> 0.0097142059 | V38: =$G$2*U39 -> 0.0097142059 | X38: =$G$2*W39 -> 0.0097142059 | Z38: =$G$2*Y39 -> 0.0097142059 | AB38: =$G$2*AA39 -> 0.0097142059 | AD38: =$G$2*AC39 -> 0.0097142059
G39: =$G$2*F40 -> 0.0093451688 | I39: =$G$2*H40 -> 0.0093451688 | K39: =$G$2*J40 -> 0.0093451688 | M39: =$G$2*L40 -> 0.0093451688 | O39: =$G$2*N40 -> 0.0093451688 | Q39: =$G$2*P40 -> 0.0093451688 | S39: =$G$2*R40 -> 0.0093451688 | U39: =$G$2*T40 -> 0.0093451688 | W39: =$G$2*V40 -> 0.0093451688 | Y39: =$G$2*X40 -> 0.0093451688 | AA39: =$G$2*Z40 -> 0.0093451688 | AC39: =$G$2*AB40 -> 0.0093451688 | AE39: =$G$2*AD40 -> 0.0093451688
F40: =$G$2*E41 -> 0.0089901512 | H40: =$G$2*G41 -> 0.0089901512 | J40: =$G$2*I41 -> 0.0089901512 | L40: =$G$2*K41 -> 0.0089901512 | N40: =$G$2*M41 -> 0.0089901512 | P40: =$G$2*O41 -> 0.0089901512 | R40: =$G$2*Q41 -> 0.0089901512 | T40: =$G$2*S41 -> 0.0089901512 | V40: =$G$2*U41 -> 0.0089901512 | X40: =$G$2*W41 -> 0.0089901512 | Z40: =$G$2*Y41 -> 0.0089901512 | AB40: =$G$2*AA41 -> 0.0089901512 | AD40: =$G$2*AC41 -> 0.0089901512
E41: =$G$2*D42 -> 0.0086486206 | G41: =$G$2*F42 -> 0.0086486206 | I41: =$G$2*H42 -> 0.0086486206 | K41: =$G$2*J42 -> 0.0086486206 | M41: =$G$2*L42 -> 0.0086486206 | O41: =$G$2*N42 -> 0.0086486206 | Q41: =$G$2*P42 -> 0.0086486206 | S41: =$G$2*R42 -> 0.0086486206 | U41: =$G$2*T42 -> 0.0086486206 | W41: =$G$2*V42 -> 0.0086486206 | Y41: =$G$2*X42 -> 0.0086486206 | AA41: =$G$2*Z42 -> 0.0086486206 | AC41: =$G$2*AB42 -> 0.0086486206 | AE41: =$G$2*AD42 -> 0.0086486206
D42: =$G$2*C43 -> 0.0083200644 | F42: =$G$2*E43 -> 0.0083200644 | H42: =$G$2*G43 -> 0.0083200644 | J42: =$G$2*I43 -> 0.0083200644 | L42: =$G$2*K43 -> 0.0083200644 | N42: =$G$2*M43 -> 0.0083200644 | P42: =$G$2*O43 -> 0.0083200644 | R42: =$G$2*Q43 -> 0.0083200644 | T42: =$G$2*S43 -> 0.0083200644 | V42: =$G$2*U43 -> 0.0083200644 | X42: =$G$2*W43 -> 0.0083200644 | Z42: =$G$2*Y43 -> 0.0083200644 | AB42: =$G$2*AA43 -> 0.0083200644 | AD42: =$G$2*AC43 -> 0.0083200644
C43: =$G$2*B44 -> 0.00800399 | E43: =$G$2*D44 -> 0.00800399 | G43: =$G$2*F44 -> 0.00800399 | I43: =$G$2*H44 -> 0.00800399 | K43: =$G$2*J44 -> 0.00800399 | M43: =$G$2*L44 -> 0.00800399 | O43: =$G$2*N44 -> 0.00800399 | Q43: =$G$2*P44 -> 0.00800399 | S43: =$G$2*R44 -> 0.00800399 | U43: =$G$2*T44 -> 0.00800399 | W43: =$G$2*V44 -> 0.00800399 | Y43: =$G$2*X44 -> 0.00800399 | AA43: =$G$2*Z44 -> 0.00800399 | AC43: =$G$2*AB44 -> 0.00800399 | AE43: =$G$2*AD44 -> 0.00800399
B44: =$G$2*A45 -> 0.007699923 | D44: =$G$2*C45 -> 0.007699923 | F44: =$G$2*E45 -> 0.007699923 | H44: =$G$2*G45 -> 0.007699923 | J44: =$G$2*I45 -> 0.007699923 | L44: =$G$2*K45 -> 0.007699923 | N44: =$G$2*M45 -> 0.007699923 | P44: =$G$2*O45 -> 0.007699923 | R44: =$G$2*Q45 -> 0.007699923 | T44: =$G$2*S45 -> 0.007699923 | V44: =$G$2*U45 -> 0.007699923 | X44: =$G$2*W45 -> 0.007699923 | Z44: =$G$2*Y45 -> 0.007699923 | AB44: =$G$2*AA45 -> 0.007699923 | AD44: =$G$2*AC45 -> 0.007699923
A45: =B1 -> 0.0074074074 | C45: =$G$2*B46 -> 0.0074074074 | E45: =$G$2*D46 -> 0.0074074074 | G45: =$G$2*F46 -> 0.0074074074 | I45: =$G$2*H46 -> 0.0074074074 | K45: =$G$2*J46 -> 0.0074074074 | M45: =$G$2*L46 -> 0.0074074074 | O45: =$G$2*N46 -> 0.0074074074 | Q45: =$G$2*P46 -> 0.0074074074 | S45: =$G$2*R46 -> 0.0074074074 | U45: =$G$2*T46 -> 0.0074074074 | W45: =$G$2*V46 -> 0.0074074074 | Y45: =$G$2*X46 -> 0.0074074074 | AA45: =$G$2*Z46 -> 0.0074074074 | AC45: =$G$2*AB46 -> 0.0074074074 | AE45: =$G$2*AD46 -> 0.0074074074
B46: =A45*$G$3 -> 0.0071260043 | D46: =$G$2*C47 -> 0.0071260043 | F46: =$G$2*E47 -> 0.0071260043 | H46: =$G$2*G47 -> 0.0071260043 | J46: =$G$2*I47 -> 0.0071260043 | L46: =$G$2*K47 -> 0.0071260043 | N46: =$G$2*M47 -> 0.0071260043 | P46: =$G$2*O47 -> 0.0071260043 | R46: =$G$2*Q47 -> 0.0071260043 | T46: =$G$2*S47 -> 0.0071260043 | V46: =$G$2*U47 -> 0.0071260043 | X46: =$G$2*W47 -> 0.0071260043 | Z46: =$G$2*Y47 -> 0.0071260043 | AB46: =$G$2*AA47 -> 0.0071260043 | AD46: =$G$2*AC47 -> 0.0071260043
C47: =B46*$G$3 -> 0.0068552915 | E47: =$G$2*D48 -> 0.0068552915 | G47: =$G$2*F48 -> 0.0068552915 | I47: =$G$2*H48 -> 0.0068552915 | K47: =$G$2*J48 -> 0.0068552915 | M47: =$G$2*L48 -> 0.0068552915 | O47: =$G$2*N48 -> 0.0068552915 | Q47: =$G$2*P48 -> 0.0068552915 | S47: =$G$2*R48 -> 0.0068552915 | U47: =$G$2*T48 -> 0.0068552915 | W47: =$G$2*V48 -> 0.0068552915 | Y47: =$G$2*X48 -> 0.0068552915 | AA47: =$G$2*Z48 -> 0.0068552915 | AC47: =$G$2*AB48 -> 0.0068552915 | AE47: =$G$2*AD48 -> 0.0068552915
D48: =C47*$G$3 -> 0.0065948629 | F48: =$G$2*E49 -> 0.0065948629 | H48: =$G$2*G49 -> 0.0065948629 | J48: =$G$2*I49 -> 0.0065948629 | L48: =$G$2*K49 -> 0.0065948629 | N48: =$G$2*M49 -> 0.0065948629 | P48: =$G$2*O49 -> 0.0065948629 | R48: =$G$2*Q49 -> 0.0065948629 | T48: =$G$2*S49 -> 0.0065948629 | V48: =$G$2*U49 -> 0.0065948629 | X48: =$G$2*W49 -> 0.0065948629 | Z48: =$G$2*Y49 -> 0.0065948629 | AB48: =$G$2*AA49 -> 0.0065948629 | AD48: =$G$2*AC49 -> 0.0065948629
E49: =D48*$G$3 -> 0.0063443279 | G49: =$G$2*F50 -> 0.0063443279 | I49: =$G$2*H50 -> 0.0063443279 | K49: =$G$2*J50 -> 0.0063443279 | M49: =$G$2*L50 -> 0.0063443279 | O49: =$G$2*N50 -> 0.0063443279 | Q49: =$G$2*P50 -> 0.0063443279 | S49: =$G$2*R50 -> 0.0063443279 | U49: =$G$2*T50 -> 0.0063443279 | W49: =$G$2*V50 -> 0.0063443279 | Y49: =$G$2*X50 -> 0.0063443279 | AA49: =$G$2*Z50 -> 0.0063443279 | AC49: =$G$2*AB50 -> 0.0063443279 | AE49: =$G$2*AD50 -> 0.0063443279
F50: =E49*$G$3 -> 0.0061033105 | H50: =$G$2*G51 -> 0.0061033105 | J50: =$G$2*I51 -> 0.0061033105 | L50: =$G$2*K51 -> 0.0061033105 | N50: =$G$2*M51 -> 0.0061033105 | P50: =$G$2*O51 -> 0.0061033105 | R50: =$G$2*Q51 -> 0.0061033105 | T50: =$G$2*S51 -> 0.0061033105 | V50: =$G$2*U51 -> 0.0061033105 | X50: =$G$2*W51 -> 0.0061033105 | Z50: =$G$2*Y51 -> 0.0061033105 | AB50: =$G$2*AA51 -> 0.0061033105 | AD50: =$G$2*AC51 -> 0.0061033105
G51: =F50*$G$3 -> 0.0058714493 | I51: =$G$2*H52 -> 0.0058714493 | K51: =$G$2*J52 -> 0.0058714493 | M51: =$G$2*L52 -> 0.0058714493 | O51: =$G$2*N52 -> 0.0058714493 | Q51: =$G$2*P52 -> 0.0058714493 | S51: =$G$2*R52 -> 0.0058714493 | U51: =$G$2*T52 -> 0.0058714493 | W51: =$G$2*V52 -> 0.0058714493 | Y51: =$G$2*X52 -> 0.0058714493 | AA51: =$G$2*Z52 -> 0.0058714493 | AC51: =$G$2*AB52 -> 0.0058714493 | AE51: =$G$2*AD52 -> 0.0058714493
H52: =G51*$G$3 -> 0.0056483963 | J52: =$G$2*I53 -> 0.0056483963 | L52: =$G$2*K53 -> 0.0056483963 | N52: =$G$2*M53 -> 0.0056483963 | P52: =$G$2*O53 -> 0.0056483963 | R52: =$G$2*Q53 -> 0.0056483963 | T52: =$G$2*S53 -> 0.0056483963 | V52: =$G$2*U53 -> 0.0056483963 | X52: =$G$2*W53 -> 0.0056483963 | Z52: =$G$2*Y53 -> 0.0056483963 | AB52: =$G$2*AA53 -> 0.0056483963 | AD52: =$G$2*AC53 -> 0.0056483963
I53: =H52*$G$3 -> 0.005433817 | K53: =$G$2*J54 -> 0.005433817 | M53: =$G$2*L54 -> 0.005433817 | O53: =$G$2*N54 -> 0.005433817 | Q53: =$G$2*P54 -> 0.005433817 | S53: =$G$2*R54 -> 0.005433817 | U53: =$G$2*T54 -> 0.005433817 | W53: =$G$2*V54 -> 0.005433817 | Y53: =$G$2*X54 -> 0.005433817 | AA53: =$G$2*Z54 -> 0.005433817 | AC53: =$G$2*AB54 -> 0.005433817 | AE53: =$G$2*AD54 -> 0.005433817
J54: =I53*$G$3 -> 0.0052273894 | L54: =$G$2*K55 -> 0.0052273894 | N54: =$G$2*M55 -> 0.0052273894 | P54: =$G$2*O55 -> 0.0052273894 | R54: =$G$2*Q55 -> 0.0052273894 | T54: =$G$2*S55 -> 0.0052273894 | V54: =$G$2*U55 -> 0.0052273894 | X54: =$G$2*W55 -> 0.0052273894 | Z54: =$G$2*Y55 -> 0.0052273894 | AB54: =$G$2*AA55 -> 0.0052273894 | AD54: =$G$2*AC55 -> 0.0052273894
K55: =J54*$G$3 -> 0.0050288039 | M55: =$G$2*L56 -> 0.0050288039 | O55: =$G$2*N56 -> 0.0050288039 | Q55: =$G$2*P56 -> 0.0050288039 | S55: =$G$2*R56 -> 0.0050288039 | U55: =$G$2*T56 -> 0.0050288039 | W55: =$G$2*V56 -> 0.0050288039 | Y55: =$G$2*X56 -> 0.0050288039 | AA55: =$G$2*Z56 -> 0.0050288039 | AC55: =$G$2*AB56 -> 0.0050288039 | AE55: =$G$2*AD56 -> 0.0050288039
L56: =K55*$G$3 -> 0.0048377626 | N56: =$G$2*M57 -> 0.0048377626 | P56: =$G$2*O57 -> 0.0048377626 | R56: =$G$2*Q57 -> 0.0048377626 | T56: =$G$2*S57 -> 0.0048377626 | V56: =$G$2*U57 -> 0.0048377626 | X56: =$G$2*W57 -> 0.0048377626 | Z56: =$G$2*Y57 -> 0.0048377626 | AB56: =$G$2*AA57 -> 0.0048377626 | AD56: =$G$2*AC57 -> 0.0048377626
M57: =L56*$G$3 -> 0.0046539788 | O57: =$G$2*N58 -> 0.0046539788 | Q57: =$G$2*P58 -> 0.0046539788 | S57: =$G$2*R58 -> 0.0046539788 | U57: =$G$2*T58 -> 0.0046539788 | W57: =$G$2*V58 -> 0.0046539788 | Y57: =$G$2*X58 -> 0.0046539788 | AA57: =$G$2*Z58 -> 0.0046539788 | AC57: =$G$2*AB58 -> 0.0046539788 | AE57: =$G$2*AD58 -> 0.0046539788
N58: =M57*$G$3 -> 0.0044771768 | P58: =$G$2*O59 -> 0.0044771768 | R58: =$G$2*Q59 -> 0.0044771768 | T58: =$G$2*S59 -> 0.0044771768 | V58: =$G$2*U59 -> 0.0044771768 | X58: =$G$2*W59 -> 0.0044771768 | Z58: =$G$2*Y59 -> 0.0044771768 | AB58: =$G$2*AA59 -> 0.0044771768 | AD58: =$G$2*AC59 -> 0.0044771768
O59: =N58*$G$3 -> 0.0043070914 | Q59: =$G$2*P60 -> 0.0043070914 | S59: =$G$2*R60 -> 0.0043070914 | U59: =$G$2*T60 -> 0.0043070914 | W59: =$G$2*V60 -> 0.0043070914 | Y59: =$G$2*X60 -> 0.0043070914 | AA59: =$G$2*Z60 -> 0.0043070914 | AC59: =$G$2*AB60 -> 0.0043070914 | AE59: =$G$2*AD60 -> 0.0043070914
P60: =O59*$G$3 -> 0.0041434675 | R60: =$G$2*Q61 -> 0.0041434675 | T60: =$G$2*S61 -> 0.0041434675 | V60: =$G$2*U61 -> 0.0041434675 | X60: =$G$2*W61 -> 0.0041434675 | Z60: =$G$2*Y61 -> 0.0041434675 | AB60: =$G$2*AA61 -> 0.0041434675 | AD60: =$G$2*AC61 -> 0.0041434675
Q61: =P60*$G$3 -> 0.0039860596 | S61: =$G$2*R62 -> 0.0039860596 | U61: =$G$2*T62 -> 0.0039860596 | W61: =$G$2*V62 -> 0.0039860596 | Y61: =$G$2*X62 -> 0.0039860596 | AA61: =$G$2*Z62 -> 0.0039860596 | AC61: =$G$2*AB62 -> 0.0039860596 | AE61: =$G$2*AD62 -> 0.0039860596
R62: =Q61*$G$3 -> 0.0038346315 | T62: =$G$2*S63 -> 0.0038346315 | V62: =$G$2*U63 -> 0.0038346315 | X62: =$G$2*W63 -> 0.0038346315 | Z62: =$G$2*Y63 -> 0.0038346315 | AB62: =$G$2*AA63 -> 0.0038346315 | AD62: =$G$2*AC63 -> 0.0038346315
S63: =R62*$G$3 -> 0.003688956 | U63: =$G$2*T64 -> 0.003688956 | W63: =$G$2*V64 -> 0.003688956 | Y63: =$G$2*X64 -> 0.003688956 | AA63: =$G$2*Z64 -> 0.003688956 | AC63: =$G$2*AB64 -> 0.003688956 | AE63: =$G$2*AD64 -> 0.003688956
T64: =S63*$G$3 -> 0.0035488147 | V64: =$G$2*U65 -> 0.0035488147 | X64: =$G$2*W65 -> 0.0035488147 | Z64: =$G$2*Y65 -> 0.0035488147 | AB64: =$G$2*AA65 -> 0.0035488147 | AD64: =$G$2*AC65 -> 0.0035488147
U65: =T64*$G$3 -> 0.0034139973 | W65: =$G$2*V66 -> 0.0034139973 | Y65: =$G$2*X66 -> 0.0034139973 | AA65: =$G$2*Z66 -> 0.0034139973 | AC65: =$G$2*AB66 -> 0.0034139973 | AE65: =$G$2*AD66 -> 0.0034139973
V66: =U65*$G$3 -> 0.0032843015 | X66: =$G$2*W67 -> 0.0032843015 | Z66: =$G$2*Y67 -> 0.0032843015 | AB66: =$G$2*AA67 -> 0.0032843015 | AD66: =$G$2*AC67 -> 0.0032843015
W67: =V66*$G$3 -> 0.0031595328 | Y67: =$G$2*X68 -> 0.0031595328 | AA67: =$G$2*Z68 -> 0.0031595328 | AC67: =$G$2*AB68 -> 0.0031595328 | AE67: =$G$2*AD68 -> 0.0031595328
X68: =W67*$G$3 -> 0.003039504 | Z68: =$G$2*Y69 -> 0.003039504 | AB68: =$G$2*AA69 -> 0.003039504 | AD68: =$G$2*AC69 -> 0.003039504
Y69: =X68*$G$3 -> 0.002924035 | AA69: =$G$2*Z70 -> 0.002924035 | AC69: =$G$2*AB70 -> 0.002924035 | AE69: =$G$2*AD70 -> 0.002924035
Z70: =Y69*$G$3 -> 0.0028129526 | AB70: =$G$2*AA71 -> 0.0028129526 | AD70: =$G$2*AC71 -> 0.0028129526
AA71: =Z70*$G$3 -> 0.0027060901 | AC71: =$G$2*AB72 -> 0.0027060901 | AE71: =$G$2*AD72 -> 0.0027060901
AB72: =AA71*$G$3 -> 0.0026032873 | AD72: =$G$2*AC73 -> 0.0026032873
AC73: =AB72*$G$3 -> 0.0025043899 | AE73: =$G$2*AD74 -> 0.0025043899
AD74: =AC73*$G$3 -> 0.0024092496
AE75: =AD74*$G$3 -> 0.0023177236
AE78: =MAX(AE15-$B$2,0) -> 0.016531098
AD79: =MAX((($G$4*AE78)+((1-$G$4)*AE80))*EXP(-$B$4*$G$1),AD16-$B$2) -> 0.015631738
AC80: =MAX((($G$4*AD79)+((1-$G$4)*AD81))*EXP(-$B$4*$G$1),AC17-$B$2) -> 0.014766544 | AE80: =MAX(AE17-$B$2,0) -> 0.014766544
AB81: =MAX((($G$4*AC80)+((1-$G$4)*AC82))*EXP(-$B$4*$G$1),AB18-$B$2) -> 0.013934219 | AD81: =MAX((($G$4*AE80)+((1-$G$4)*AE82))*EXP(-$B$4*$G$1),AD18-$B$2) -> 0.013934219
AA82: =MAX((($G$4*AB81)+((1-$G$4)*AB83))*EXP(-$B$4*$G$1),AA19-$B$2) -> 0.013133513 | AC82: =MAX((($G$4*AD81)+((1-$G$4)*AD83))*EXP(-$B$4*$G$1),AC19-$B$2) -> 0.013133513 | AE82: =MAX(AE19-$B$2,0) -> 0.013133513
Z83: =MAX((($G$4*AA82)+((1-$G$4)*AA84))*EXP(-$B$4*$G$1),Z20-$B$2) -> 0.012363225 | AB83: =MAX((($G$4*AC82)+((1-$G$4)*AC84))*EXP(-$B$4*$G$1),AB20-$B$2) -> 0.012363225 | AD83: =MAX((($G$4*AE82)+((1-$G$4)*AE84))*EXP(-$B$4*$G$1),AD20-$B$2) -> 0.012363225
Y84: =MAX((($G$4*Z83)+((1-$G$4)*Z85))*EXP(-$B$4*$G$1),Y21-$B$2) -> 0.0116222 | AA84: =MAX((($G$4*AB83)+((1-$G$4)*AB85))*EXP(-$B$4*$G$1),AA21-$B$2) -> 0.0116222 | AC84: =MAX((($G$4*AD83)+((1-$G$4)*AD85))*EXP(-$B$4*$G$1),AC21-$B$2) -> 0.0116222 | AE84: =MAX(AE21-$B$2,0) -> 0.0116222
X85: =MAX((($G$4*Y84)+((1-$G$4)*Y86))*EXP(-$B$4*$G$1),X22-$B$2) -> 0.010909327 | Z85: =MAX((($G$4*AA84)+((1-$G$4)*AA86))*EXP(-$B$4*$G$1),Z22-$B$2) -> 0.010909327 | AB85: =MAX((($G$4*AC84)+((1-$G$4)*AC86))*EXP(-$B$4*$G$1),AB22-$B$2) -> 0.010909327 | AD85: =MAX((($G$4*AE84)+((1-$G$4)*AE86))*EXP(-$B$4*$G$1),AD22-$B$2) -> 0.010909327
W86: =MAX((($G$4*X85)+((1-$G$4)*X87))*EXP(-$B$4*$G$1),W23-$B$2) -> 0.010223535 | Y86: =MAX((($G$4*Z85)+((1-$G$4)*Z87))*EXP(-$B$4*$G$1),Y23-$B$2) -> 0.010223535 | AA86: =MAX((($G$4*AB85)+((1-$G$4)*AB87))*EXP(-$B$4*$G$1),AA23-$B$2) -> 0.010223535 | AC86: =MAX((($G$4*AD85)+((1-$G$4)*AD87))*EXP(-$B$4*$G$1),AC23-$B$2) -> 0.010223535 | AE86: =MAX(AE23-$B$2,0) -> 0.010223535
V87: =MAX((($G$4*W86)+((1-$G$4)*W88))*EXP(-$B$4*$G$1),V24-$B$2) -> 0.0095637955 | X87: =MAX((($G$4*Y86)+((1-$G$4)*Y88))*EXP(-$B$4*$G$1),X24-$B$2) -> 0.0095637955 | Z87: =MAX((($G$4*AA86)+((1-$G$4)*AA88))*EXP(-$B$4*$G$1),Z24-$B$2) -> 0.0095637955 | AB87: =MAX((($G$4*AC86)+((1-$G$4)*AC88))*EXP(-$B$4*$G$1),AB24-$B$2) -> 0.0095637955 | AD87: =MAX((($G$4*AE86)+((1-$G$4)*AE88))*EXP(-$B$4*$G$1),AD24-$B$2) -> 0.0095637955
U88: =MAX((($G$4*V87)+((1-$G$4)*V89))*EXP(-$B$4*$G$1),U25-$B$2) -> 0.0089291194 | W88: =MAX((($G$4*X87)+((1-$G$4)*X89))*EXP(-$B$4*$G$1),W25-$B$2) -> 0.0089291194 | Y88: =MAX((($G$4*Z87)+((1-$G$4)*Z89))*EXP(-$B$4*$G$1),Y25-$B$2) -> 0.0089291194 | AA88: =MAX((($G$4*AB87)+((1-$G$4)*AB89))*EXP(-$B$4*$G$1),AA25-$B$2) -> 0.0089291194 | AC88: =MAX((($G$4*AD87)+((1-$G$4)*AD89))*EXP(-$B$4*$G$1),AC25-$B$2) -> 0.0089291194 | AE88: =MAX(AE25-$B$2,0) -> 0.0089291194
T89: =MAX((($G$4*U88)+((1-$G$4)*U90))*EXP(-$B$4*$G$1),T26-$B$2) -> 0.0083185543 | V89: =MAX((($G$4*W88)+((1-$G$4)*W90))*EXP(-$B$4*$G$1),V26-$B$2) -> 0.0083185543 | X89: =MAX((($G$4*Y88)+((1-$G$4)*Y90))*EXP(-$B$4*$G$1),X26-$B$2) -> 0.0083185543 | Z89: =MAX((($G$4*AA88)+((1-$G$4)*AA90))*EXP(-$B$4*$G$1),Z26-$B$2) -> 0.0083185543 | AB89: =MAX((($G$4*AC88)+((1-$G$4)*AC90))*EXP(-$B$4*$G$1),AB26-$B$2) -> 0.0083185543 | AD89: =MAX((($G$4*AE88)+((1-$G$4)*AE90))*EXP(-$B$4*$G$1),AD26-$B$2) -> 0.0083185543
S90: =MAX((($G$4*T89)+((1-$G$4)*T91))*EXP(-$B$4*$G$1),S27-$B$2) -> 0.0077311842 | U90: =MAX((($G$4*V89)+((1-$G$4)*V91))*EXP(-$B$4*$G$1),U27-$B$2) -> 0.0077311842 | W90: =MAX((($G$4*X89)+((1-$G$4)*X91))*EXP(-$B$4*$G$1),W27-$B$2) -> 0.0077311842 | Y90: =MAX((($G$4*Z89)+((1-$G$4)*Z91))*EXP(-$B$4*$G$1),Y27-$B$2) -> 0.0077311842 | AA90: =MAX((($G$4*AB89)+((1-$G$4)*AB91))*EXP(-$B$4*$G$1),AA27-$B$2) -> 0.0077311842 | AC90: =MAX((($G$4*AD89)+((1-$G$4)*AD91))*EXP(-$B$4*$G$1),AC27-$B$2) -> 0.0077311842 | AE90: =MAX(AE27-$B$2,0) -> 0.0077311842
R91: =MAX((($G$4*S90)+((1-$G$4)*S92))*EXP(-$B$4*$G$1),R28-$B$2) -> 0.007166128 | T91: =MAX((($G$4*U90)+((1-$G$4)*U92))*EXP(-$B$4*$G$1),T28-$B$2) -> 0.007166128 | V91: =MAX((($G$4*W90)+((1-$G$4)*W92))*EXP(-$B$4*$G$1),V28-$B$2) -> 0.007166128 | X91: =MAX((($G$4*Y90)+((1-$G$4)*Y92))*EXP(-$B$4*$G$1),X28-$B$2) -> 0.007166128 | Z91: =MAX((($G$4*AA90)+((1-$G$4)*AA92))*EXP(-$B$4*$G$1),Z28-$B$2) -> 0.007166128 | AB91: =MAX((($G$4*AC90)+((1-$G$4)*AC92))*EXP(-$B$4*$G$1),AB28-$B$2) -> 0.007166128 | AD91: =MAX((($G$4*AE90)+((1-$G$4)*AE92))*EXP(-$B$4*$G$1),AD28-$B$2) -> 0.007166128
Q92: =MAX((($G$4*R91)+((1-$G$4)*R93))*EXP(-$B$4*$G$1),Q29-$B$2) -> 0.0066225379 | S92: =MAX((($G$4*T91)+((1-$G$4)*T93))*EXP(-$B$4*$G$1),S29-$B$2) -> 0.0066225379 | U92: =MAX((($G$4*V91)+((1-$G$4)*V93))*EXP(-$B$4*$G$1),U29-$B$2) -> 0.0066225379 | W92: =MAX((($G$4*X91)+((1-$G$4)*X93))*EXP(-$B$4*$G$1),W29-$B$2) -> 0.0066225379 | Y92: =MAX((($G$4*Z91)+((1-$G$4)*Z93))*EXP(-$B$4*$G$1),Y29-$B$2) -> 0.0066225379 | AA92: =MAX((($G$4*AB91)+((1-$G$4)*AB93))*EXP(-$B$4*$G$1),AA29-$B$2) -> 0.0066225379 | AC92: =MAX((($G$4*AD91)+((1-$G$4)*AD93))*EXP(-$B$4*$G$1),AC29-$B$2) -> 0.0066225379 | AE92: =MAX(AE29-$B$2,0) -> 0.0066225379
P93: =MAX((($G$4*Q92)+((1-$G$4)*Q94))*EXP(-$B$4*$G$1),P30-$B$2) -> 0.0060995985 | R93: =MAX((($G$4*S92)+((1-$G$4)*S94))*EXP(-$B$4*$G$1),R30-$B$2) -> 0.0060995985 | T93: =MAX((($G$4*U92)+((1-$G$4)*U94))*EXP(-$B$4*$G$1),T30-$B$2) -> 0.0060995985 | V93: =MAX((($G$4*W92)+((1-$G$4)*W94))*EXP(-$B$4*$G$1),V30-$B$2) -> 0.0060995985 | X93: =MAX((($G$4*Y92)+((1-$G$4)*Y94))*EXP(-$B$4*$G$1),X30-$B$2) -> 0.0060995985 | Z93: =MAX((($G$4*AA92)+((1-$G$4)*AA94))*EXP(-$B$4*$G$1),Z30-$B$2) -> 0.0060995985 | AB93: =MAX((($G$4*AC92)+((1-$G$4)*AC94))*EXP(-$B$4*$G$1),AB30-$B$2) -> 0.0060995985 | AD93: =MAX((($G$4*AE92)+((1-$G$4)*AE94))*EXP(-$B$4*$G$1),AD30-$B$2) -> 0.0060995985
O94: =MAX((($G$4*P93)+((1-$G$4)*P95))*EXP(-$B$4*$G$1),O31-$B$2) -> 0.0055965252 | Q94: =MAX((($G$4*R93)+((1-$G$4)*R95))*EXP(-$B$4*$G$1),Q31-$B$2) -> 0.0055965252 | S94: =MAX((($G$4*T93)+((1-$G$4)*T95))*EXP(-$B$4*$G$1),S31-$B$2) -> 0.0055965252 | U94: =MAX((($G$4*V93)+((1-$G$4)*V95))*EXP(-$B$4*$G$1),U31-$B$2) -> 0.0055965252 | W94: =MAX((($G$4*X93)+((1-$G$4)*X95))*EXP(-$B$4*$G$1),W31-$B$2) -> 0.0055965252 | Y94: =MAX((($G$4*Z93)+((1-$G$4)*Z95))*EXP(-$B$4*$G$1),Y31-$B$2) -> 0.0055965252 | AA94: =MAX((($G$4*AB93)+((1-$G$4)*AB95))*EXP(-$B$4*$G$1),AA31-$B$2) -> 0.0055965252 | AC94: =MAX((($G$4*AD93)+((1-$G$4)*AD95))*EXP(-$B$4*$G$1),AC31-$B$2) -> 0.0055965252 | AE94: =MAX(AE31-$B$2,0) -> 0.0055965252
N95: =MAX((($G$4*O94)+((1-$G$4)*O96))*EXP(-$B$4*$G$1),N32-$B$2) -> 0.0051125634 | P95: =MAX((($G$4*Q94)+((1-$G$4)*Q96))*EXP(-$B$4*$G$1),P32-$B$2) -> 0.0051125634 | R95: =MAX((($G$4*S94)+((1-$G$4)*S96))*EXP(-$B$4*$G$1),R32-$B$2) -> 0.0051125634 | T95: =MAX((($G$4*U94)+((1-$G$4)*U96))*EXP(-$B$4*$G$1),T32-$B$2) -> 0.0051125634 | V95: =MAX((($G$4*W94)+((1-$G$4)*W96))*EXP(-$B$4*$G$1),V32-$B$2) -> 0.0051125634 | X95: =MAX((($G$4*Y94)+((1-$G$4)*Y96))*EXP(-$B$4*$G$1),X32-$B$2) -> 0.0051125634 | Z95: =MAX((($G$4*AA94)+((1-$G$4)*AA96))*EXP(-$B$4*$G$1),Z32-$B$2) -> 0.0051125634 | AB95: =MAX((($G$4*AC94)+((1-$G$4)*AC96))*EXP(-$B$4*$G$1),AB32-$B$2) -> 0.0051125634 | AD95: =MAX((($G$4*AE94)+((1-$G$4)*AE96))*EXP(-$B$4*$G$1),AD32-$B$2) -> 0.0051125634
M96: =MAX((($G$4*N95)+((1-$G$4)*N97))*EXP(-$B$4*$G$1),M33-$B$2) -> 0.0046469871 | O96: =MAX((($G$4*P95)+((1-$G$4)*P97))*EXP(-$B$4*$G$1),O33-$B$2) -> 0.0046469871 | Q96: =MAX((($G$4*R95)+((1-$G$4)*R97))*EXP(-$B$4*$G$1),Q33-$B$2) -> 0.0046469871 | S96: =MAX((($G$4*T95)+((1-$G$4)*T97))*EXP(-$B$4*$G$1),S33-$B$2) -> 0.0046469871 | U96: =MAX((($G$4*V95)+((1-$G$4)*V97))*EXP(-$B$4*$G$1),U33-$B$2) -> 0.0046469871 | W96: =MAX((($G$4*X95)+((1-$G$4)*X97))*EXP(-$B$4*$G$1),W33-$B$2) -> 0.0046469871 | Y96: =MAX((($G$4*Z95)+((1-$G$4)*Z97))*EXP(-$B$4*$G$1),Y33-$B$2) -> 0.0046469871 | AA96: =MAX((($G$4*AB95)+((1-$G$4)*AB97))*EXP(-$B$4*$G$1),AA33-$B$2) -> 0.0046469871 | AC96: =MAX((($G$4*AD95)+((1-$G$4)*AD97))*EXP(-$B$4*$G$1),AC33-$B$2) -> 0.0046469871 | AE96: =MAX(AE33-$B$2,0) -> 0.0046469871
L97: =MAX((($G$4*M96)+((1-$G$4)*M98))*EXP(-$B$4*$G$1),L34-$B$2) -> 0.0041990977 | N97: =MAX((($G$4*O96)+((1-$G$4)*O98))*EXP(-$B$4*$G$1),N34-$B$2) -> 0.0041990977 | P97: =MAX((($G$4*Q96)+((1-$G$4)*Q98))*EXP(-$B$4*$G$1),P34-$B$2) -> 0.0041990977 | R97: =MAX((($G$4*S96)+((1-$G$4)*S98))*EXP(-$B$4*$G$1),R34-$B$2) -> 0.0041990977 | T97: =MAX((($G$4*U96)+((1-$G$4)*U98))*EXP(-$B$4*$G$1),T34-$B$2) -> 0.0041990977 | V97: =MAX((($G$4*W96)+((1-$G$4)*W98))*EXP(-$B$4*$G$1),V34-$B$2) -> 0.0041990977 | X97: =MAX((($G$4*Y96)+((1-$G$4)*Y98))*EXP(-$B$4*$G$1),X34-$B$2) -> 0.0041990977 | Z97: =MAX((($G$4*AA96)+((1-$G$4)*AA98))*EXP(-$B$4*$G$1),Z34-$B$2) -> 0.0041990977 | AB97: =MAX((($G$4*AC96)+((1-$G$4)*AC98))*EXP(-$B$4*$G$1),AB34-$B$2) -> 0.0041990977 | AD97: =MAX((($G$4*AE96)+((1-$G$4)*AE98))*EXP(-$B$4*$G$1),AD34-$B$2) -> 0.0041990977
K98: =MAX((($G$4*L97)+((1-$G$4)*L99))*EXP(-$B$4*$G$1),K35-$B$2) -> 0.0037682234 | M98: =MAX((($G$4*N97)+((1-$G$4)*N99))*EXP(-$B$4*$G$1),M35-$B$2) -> 0.0037682234 | O98: =MAX((($G$4*P97)+((1-$G$4)*P99))*EXP(-$B$4*$G$1),O35-$B$2) -> 0.0037682234 | Q98: =MAX((($G$4*R97)+((1-$G$4)*R99))*EXP(-$B$4*$G$1),Q35-$B$2) -> 0.0037682234 | S98: =MAX((($G$4*T97)+((1-$G$4)*T99))*EXP(-$B$4*$G$1),S35-$B$2) -> 0.0037682234 | U98: =MAX((($G$4*V97)+((1-$G$4)*V99))*EXP(-$B$4*$G$1),U35-$B$2) -> 0.0037682234 | W98: =MAX((($G$4*X97)+((1-$G$4)*X99))*EXP(-$B$4*$G$1),W35-$B$2) -> 0.0037682234 | Y98: =MAX((($G$4*Z97)+((1-$G$4)*Z99))*EXP(-$B$4*$G$1),Y35-$B$2) -> 0.0037682234 | AA98: =MAX((($G$4*AB97)+((1-$G$4)*AB99))*EXP(-$B$4*$G$1),AA35-$B$2) -> 0.0037682234 | AC98: =MAX((($G$4*AD97)+((1-$G$4)*AD99))*EXP(-$B$4*$G$1),AC35-$B$2) -> 0.0037682234 | AE98: =MAX(AE35-$B$2,0) -> 0.0037682234
J99: =MAX((($G$4*K98)+((1-$G$4)*K100))*EXP(-$B$4*$G$1),J36-$B$2) -> 0.0033537177 | L99: =MAX((($G$4*M98)+((1-$G$4)*M100))*EXP(-$B$4*$G$1),L36-$B$2) -> 0.0033537177 | N99: =MAX((($G$4*O98)+((1-$G$4)*O100))*EXP(-$B$4*$G$1),N36-$B$2) -> 0.0033537177 | P99: =MAX((($G$4*Q98)+((1-$G$4)*Q100))*EXP(-$B$4*$G$1),P36-$B$2) -> 0.0033537177 | R99: =MAX((($G$4*S98)+((1-$G$4)*S100))*EXP(-$B$4*$G$1),R36-$B$2) -> 0.0033537177 | T99: =MAX((($G$4*U98)+((1-$G$4)*U100))*EXP(-$B$4*$G$1),T36-$B$2) -> 0.0033537177 | V99: =MAX((($G$4*W98)+((1-$G$4)*W100))*EXP(-$B$4*$G$1),V36-$B$2) -> 0.0033537177 | X99: =MAX((($G$4*Y98)+((1-$G$4)*Y100))*EXP(-$B$4*$G$1),X36-$B$2) -> 0.0033537177 | Z99: =MAX((($G$4*AA98)+((1-$G$4)*AA100))*EXP(-$B$4*$G$1),Z36-$B$2) -> 0.0033537177 | AB99: =MAX((($G$4*AC98)+((1-$G$4)*AC100))*EXP(-$B$4*$G$1),AB36-$B$2) -> 0.0033537177 | AD99: =MAX((($G$4*AE98)+((1-$G$4)*AE100))*EXP(-$B$4*$G$1),AD36-$B$2) -> 0.0033537177
I100: =MAX((($G$4*J99)+((1-$G$4)*J101))*EXP(-$B$4*$G$1),I37-$B$2) -> 0.0029549589 | K100: =MAX((($G$4*L99)+((1-$G$4)*L101))*EXP(-$B$4*$G$1),K37-$B$2) -> 0.0029549589 | M100: =MAX((($G$4*N99)+((1-$G$4)*N101))*EXP(-$B$4*$G$1),M37-$B$2) -> 0.0029549589 | O100: =MAX((($G$4*P99)+((1-$G$4)*P101))*EXP(-$B$4*$G$1),O37-$B$2) -> 0.0029549589 | Q100: =MAX((($G$4*R99)+((1-$G$4)*R101))*EXP(-$B$4*$G$1),Q37-$B$2) -> 0.0029549589 | S100: =MAX((($G$4*T99)+((1-$G$4)*T101))*EXP(-$B$4*$G$1),S37-$B$2) -> 0.0029549589 | U100: =MAX((($G$4*V99)+((1-$G$4)*V101))*EXP(-$B$4*$G$1),U37-$B$2) -> 0.0029549589 | W100: =MAX((($G$4*X99)+((1-$G$4)*X101))*EXP(-$B$4*$G$1),W37-$B$2) -> 0.0029549589 | Y100: =MAX((($G$4*Z99)+((1-$G$4)*Z101))*EXP(-$B$4*$G$1),Y37-$B$2) -> 0.0029549589 | AA100: =MAX((($G$4*AB99)+((1-$G$4)*AB101))*EXP(-$B$4*$G$1),AA37-$B$2) -> 0.0029549589 | AC100: =MAX((($G$4*AD99)+((1-$G$4)*AD101))*EXP(-$B$4*$G$1),AC37-$B$2) -> 0.0029549589 | AE100: =MAX(AE37-$B$2,0) -> 0.0029549589
H101: =MAX((($G$4*I100)+((1-$G$4)*I102))*EXP(-$B$4*$G$1),H38-$B$2) -> 0.0025713487 | J101: =MAX((($G$4*K100)+((1-$G$4)*K102))*EXP(-$B$4*$G$1),J38-$B$2) -> 0.0025713487 | L101: =MAX((($G$4*M100)+((1-$G$4)*M102))*EXP(-$B$4*$G$1),L38-$B$2) -> 0.0025713487 | N101: =MAX((($G$4*O100)+((1-$G$4)*O102))*EXP(-$B$4*$G$1),N38-$B$2) -> 0.0025713487 | P101: =MAX((($G$4*Q100)+((1-$G$4)*Q102))*EXP(-$B$4*$G$1),P38-$B$2) -> 0.0025713487 | R101: =MAX((($G$4*S100)+((1-$G$4)*S102))*EXP(-$B$4*$G$1),R38-$B$2) -> 0.0025713487 | T101: =MAX((($G$4*U100)+((1-$G$4)*U102))*EXP(-$B$4*$G$1),T38-$B$2) -> 0.0025713487 | V101: =MAX((($G$4*W100)+((1-$G$4)*W102))*EXP(-$B$4*$G$1),V38-$B$2) -> 0.0025713487 | X101: =MAX((($G$4*Y100)+((1-$G$4)*Y102))*EXP(-$B$4*$G$1),X38-$B$2) -> 0.0025713487 | Z101: =MAX((($G$4*AA100)+((1-$G$4)*AA102))*EXP(-$B$4*$G$1),Z38-$B$2) -> 0.0025713487 | AB101: =MAX((($G$4*AC100)+((1-$G$4)*AC102))*EXP(-$B$4*$G$1),AB38-$B$2) -> 0.0025713487 | AD101: =MAX((($G$4*AE100)+((1-$G$4)*AE102))*EXP(-$B$4*$G$1),AD38-$B$2) -> 0.0025713487
G102: =MAX((($G$4*H101)+((1-$G$4)*H103))*EXP(-$B$4*$G$1),G39-$B$2) -> 0.0022023116 | I102: =MAX((($G$4*J101)+((1-$G$4)*J103))*EXP(-$B$4*$G$1),I39-$B$2) -> 0.0022023116 | K102: =MAX((($G$4*L101)+((1-$G$4)*L103))*EXP(-$B$4*$G$1),K39-$B$2) -> 0.0022023116 | M102: =MAX((($G$4*N101)+((1-$G$4)*N103))*EXP(-$B$4*$G$1),M39-$B$2) -> 0.0022023116 | O102: =MAX((($G$4*P101)+((1-$G$4)*P103))*EXP(-$B$4*$G$1),O39-$B$2) -> 0.0022023116 | Q102: =MAX((($G$4*R101)+((1-$G$4)*R103))*EXP(-$B$4*$G$1),Q39-$B$2) -> 0.0022023116 | S102: =MAX((($G$4*T101)+((1-$G$4)*T103))*EXP(-$B$4*$G$1),S39-$B$2) -> 0.0022023116 | U102: =MAX((($G$4*V101)+((1-$G$4)*V103))*EXP(-$B$4*$G$1),U39-$B$2) -> 0.0022023116 | W102: =MAX((($G$4*X101)+((1-$G$4)*X103))*EXP(-$B$4*$G$1),W39-$B$2) -> 0.0022023116 | Y102: =MAX((($G$4*Z101)+((1-$G$4)*Z103))*EXP(-$B$4*$G$1),Y39-$B$2) -> 0.0022023116 | AA102: =MAX((($G$4*AB101)+((1-$G$4)*AB103))*EXP(-$B$4*$G$1),AA39-$B$2) -> 0.0022023116 | AC102: =MAX((($G$4*AD101)+((1-$G$4)*AD103))*EXP(-$B$4*$G$1),AC39-$B$2) -> 0.0022023116 | AE102: =MAX(AE39-$B$2,0) -> 0.0022023116
F103: =MAX((($G$4*G102)+((1-$G$4)*G104))*EXP(-$B$4*$G$1),F40-$B$2) -> 0.0018570396 | H103: =MAX((($G$4*I102)+((1-$G$4)*I104))*EXP(-$B$4*$G$1),H40-$B$2) -> 0.0018535312 | J103: =MAX((($G$4*K102)+((1-$G$4)*K104))*EXP(-$B$4*$G$1),J40-$B$2) -> 0.0018502043 | L103: =MAX((($G$4*M102)+((1-$G$4)*M104))*EXP(-$B$4*$G$1),L40-$B$2) -> 0.0018474337 | N103: =MAX((($G$4*O102)+((1-$G$4)*O104))*EXP(-$B$4*$G$1),N40-$B$2) -> 0.0018472941 | P103: =MAX((($G$4*Q102)+((1-$G$4)*Q104))*EXP(-$B$4*$G$1),P40-$B$2) -> 0.0018472941 | R103: =MAX((($G$4*S102)+((1-$G$4)*S104))*EXP(-$B$4*$G$1),R40-$B$2) -> 0.0018472941 | T103: =MAX((($G$4*U102)+((1-$G$4)*U104))*EXP(-$B$4*$G$1),T40-$B$2) -> 0.0018472941 | V103: =MAX((($G$4*W102)+((1-$G$4)*W104))*EXP(-$B$4*$G$1),V40-$B$2) -> 0.0018472941 | X103: =MAX((($G$4*Y102)+((1-$G$4)*Y104))*EXP(-$B$4*$G$1),X40-$B$2) -> 0.0018472941 | Z103: =MAX((($G$4*AA102)+((1-$G$4)*AA104))*EXP(-$B$4*$G$1),Z40-$B$2) -> 0.0018472941 | AB103: =MAX((($G$4*AC102)+((1-$G$4)*AC104))*EXP(-$B$4*$G$1),AB40-$B$2) -> 0.0018472941 | AD103: =MAX((($G$4*AE102)+((1-$G$4)*AE104))*EXP(-$B$4*$G$1),AD40-$B$2) -> 0.0018472941
E104: =MAX((($G$4*F103)+((1-$G$4)*F105))*EXP(-$B$4*$G$1),E41-$B$2) -> 0.0015486665 | G104: =MAX((($G$4*H103)+((1-$G$4)*H105))*EXP(-$B$4*$G$1),G41-$B$2) -> 0.0015418534 | I104: =MAX((($G$4*J103)+((1-$G$4)*J105))*EXP(-$B$4*$G$1),I41-$B$2) -> 0.0015351065 | K104: =MAX((($G$4*L103)+((1-$G$4)*L105))*EXP(-$B$4*$G$1),K41-$B$2) -> 0.0015287085 | M104: =MAX((($G$4*N103)+((1-$G$4)*N105))*EXP(-$B$4*$G$1),M41-$B$2) -> 0.0015233804 | O104: =MAX((($G$4*P103)+((1-$G$4)*P105))*EXP(-$B$4*$G$1),O41-$B$2) -> 0.0015179912 | Q104: =MAX((($G$4*R103)+((1-$G$4)*R105))*EXP(-$B$4*$G$1),Q41-$B$2) -> 0.0015126572 | S104: =MAX((($G$4*T103)+((1-$G$4)*T105))*EXP(-$B$4*$G$1),S41-$B$2) -> 0.0015078475 | U104: =MAX((($G$4*V103)+((1-$G$4)*V105))*EXP(-$B$4*$G$1),U41-$B$2) -> 0.0015057634 | W104: =MAX((($G$4*X103)+((1-$G$4)*X105))*EXP(-$B$4*$G$1),W41-$B$2) -> 0.0015057634 | Y104: =MAX((($G$4*Z103)+((1-$G$4)*Z105))*EXP(-$B$4*$G$1),Y41-$B$2) -> 0.0015057634 | AA104: =MAX((($G$4*AB103)+((1-$G$4)*AB105))*EXP(-$B$4*$G$1),AA41-$B$2) -> 0.0015057634 | AC104: =MAX((($G$4*AD103)+((1-$G$4)*AD105))*EXP(-$B$4*$G$1),AC41-$B$2) -> 0.0015057634 | AE104: =MAX(AE41-$B$2,0) -> 0.0015057634
D105: =MAX((($G$4*E104)+((1-$G$4)*E106))*EXP(-$B$4*$G$1),D42-$B$2) -> 0.0012766847 | F105: =MAX((($G$4*G104)+((1-$G$4)*G106))*EXP(-$B$4*$G$1),F42-$B$2) -> 0.0012669879 | H105: =MAX((($G$4*I104)+((1-$G$4)*I106))*EXP(-$B$4*$G$1),H42-$B$2) -> 0.0012571186 | J105: =MAX((($G$4*K104)+((1-$G$4)*K106))*EXP(-$B$4*$G$1),J42-$B$2) -> 0.0012472094 | L105: =MAX((($G$4*M104)+((1-$G$4)*M106))*EXP(-$B$4*$G$1),L42-$B$2) -> 0.0012374587 | N105: =MAX((($G$4*O104)+((1-$G$4)*O106))*EXP(-$B$4*$G$1),N42-$B$2) -> 0.0012273409 | P105: =MAX((($G$4*Q104)+((1-$G$4)*Q106))*EXP(-$B$4*$G$1),P42-$B$2) -> 0.0012169771 | R105: =MAX((($G$4*S104)+((1-$G$4)*S106))*EXP(-$B$4*$G$1),R42-$B$2) -> 0.0012067195 | T105: =MAX((($G$4*U104)+((1-$G$4)*U106))*EXP(-$B$4*$G$1),T42-$B$2) -> 0.0011974699 | V105: =MAX((($G$4*W104)+((1-$G$4)*W106))*EXP(-$B$4*$G$1),V42-$B$2) -> 0.0011889029 | X105: =MAX((($G$4*Y104)+((1-$G$4)*Y106))*EXP(-$B$4*$G$1),X42-$B$2) -> 0.0011808147 | Z105: =MAX((($G$4*AA104)+((1-$G$4)*AA106))*EXP(-$B$4*$G$1),Z42-$B$2) -> 0.0011772073 | AB105: =MAX((($G$4*AC104)+((1-$G$4)*AC106))*EXP(-$B$4*$G$1),AB42-$B$2) -> 0.0011772073 | AD105: =MAX((($G$4*AE104)+((1-$G$4)*AE106))*EXP(-$B$4*$G$1),AD42-$B$2) -> 0.0011772073
C106: =MAX((($G$4*D105)+((1-$G$4)*D107))*EXP(-$B$4*$G$1),C43-$B$2) -> 0.0010400612 | E106: =MAX((($G$4*F105)+((1-$G$4)*F107))*EXP(-$B$4*$G$1),E43-$B$2) -> 0.0010281042 | G106: =MAX((($G$4*H105)+((1-$G$4)*H107))*EXP(-$B$4*$G$1),G43-$B$2) -> 0.0010157347 | I106: =MAX((($G$4*J105)+((1-$G$4)*J107))*EXP(-$B$4*$G$1),I43-$B$2) -> 0.0010029724 | K106: =MAX((($G$4*L105)+((1-$G$4)*L107))*EXP(-$B$4*$G$1),K43-$B$2) -> 0.00098981177 | M106: =MAX((($G$4*N105)+((1-$G$4)*N107))*EXP(-$B$4*$G$1),M43-$B$2) -> 0.00097597013 | O106: =MAX((($G$4*P105)+((1-$G$4)*P107))*EXP(-$B$4*$G$1),O43-$B$2) -> 0.00096147877 | Q106: =MAX((($G$4*R105)+((1-$G$4)*R107))*EXP(-$B$4*$G$1),Q43-$B$2) -> 0.00094646345 | S106: =MAX((($G$4*T105)+((1-$G$4)*T107))*EXP(-$B$4*$G$1),S43-$B$2) -> 0.00093116932 | U106: =MAX((($G$4*V105)+((1-$G$4)*V107))*EXP(-$B$4*$G$1),U43-$B$2) -> 0.00091530198 | W106: =MAX((($G$4*X105)+((1-$G$4)*X107))*EXP(-$B$4*$G$1),W43-$B$2) -> 0.0008988271 | Y106: =MAX((($G$4*Z105)+((1-$G$4)*Z107))*EXP(-$B$4*$G$1),Y43-$B$2) -> 0.00088327271 | AA106: =MAX((($G$4*AB105)+((1-$G$4)*AB107))*EXP(-$B$4*$G$1),AA43-$B$2) -> 0.00086864706 | AC106: =MAX((($G$4*AD105)+((1-$G$4)*AD107))*EXP(-$B$4*$G$1),AC43-$B$2) -> 0.00086113286 | AE106: =MAX(AE43-$B$2,0) -> 0.00086113286
B107: =MAX((($G$4*C106)+((1-$G$4)*C108))*EXP(-$B$4*$G$1),B44-$B$2) -> 0.00083715413 | D107: =MAX((($G$4*E106)+((1-$G$4)*E108))*EXP(-$B$4*$G$1),D44-$B$2) -> 0.0008236836 | F107: =MAX((($G$4*G106)+((1-$G$4)*G108))*EXP(-$B$4*$G$1),F44-$B$2) -> 0.00080962476 | H107: =MAX((($G$4*I106)+((1-$G$4)*I108))*EXP(-$B$4*$G$1),H44-$B$2) -> 0.00079493146 | J107: =MAX((($G$4*K106)+((1-$G$4)*K108))*EXP(-$B$4*$G$1),J44-$B$2) -> 0.0007795197 | L107: =MAX((($G$4*M106)+((1-$G$4)*M108))*EXP(-$B$4*$G$1),L44-$B$2) -> 0.00076319582 | N107: =MAX((($G$4*O106)+((1-$G$4)*O108))*EXP(-$B$4*$G$1),N44-$B$2) -> 0.00074590057 | P107: =MAX((($G$4*Q106)+((1-$G$4)*Q108))*EXP(-$B$4*$G$1),P44-$B$2) -> 0.00072758256 | R107: =MAX((($G$4*S106)+((1-$G$4)*S108))*EXP(-$B$4*$G$1),R44-$B$2) -> 0.00070815906 | T107: =MAX((($G$4*U106)+((1-$G$4)*U108))*EXP(-$B$4*$G$1),T44-$B$2) -> 0.00068727053 | V107: =MAX((($G$4*W106)+((1-$G$4)*W108))*EXP(-$B$4*$G$1),V44-$B$2) -> 0.00066465058 | X107: =MAX((($G$4*Y106)+((1-$G$4)*Y108))*EXP(-$B$4*$G$1),X44-$B$2) -> 0.00064042122 | Z107: =MAX((($G$4*AA106)+((1-$G$4)*AA108))*EXP(-$B$4*$G$1),Z44-$B$2) -> 0.000613833 | AB107: =MAX((($G$4*AC106)+((1-$G$4)*AC108))*EXP(-$B$4*$G$1),AB44-$B$2) -> 0.00058570668 | AD107: =MAX((($G$4*AE106)+((1-$G$4)*AE108))*EXP(-$B$4*$G$1),AD44-$B$2) -> 0.0005570659
...

Sheet Slide 57_R 
A1: S0 | B1: =1/135 -> 0.0074074074 | C1: USD per ISK
A2: X | B2: 2000000
A3: Dom Risk free (USD) | B3: 0.05 | J3: Time | K3: uni rand numbers | L3: normal random numbers | M3: stock price path
A4: For Risk Free (ISK) | B4: 0.1 | J4: 0 | M4: =B1 -> 0.0074074074 | P4: Path | Q4: =M12 -> 0
A5: vol | B5: 0.3 | J5: =J4+$B$7 -> 0.25 | K5: =RAND() -> 0.74740892 | L5: =NORMSINV(K5) -> 0.66635822 | M5: =M4*EXP(($B$3-$B$4-(0.5*$B$5*$B$5))*$B$7)*EXP($B$5*SQRT($B$7)*L5) -> 0.0079939438 | P5: 1 | Q5: 64082.967
A6: Time | B6: 0.5 | J6: =J5+$B$7 -> 0.5 | K6: =RAND() -> 0.76552393 | L6: =NORMSINV(K6) -> 0.72418504 | M6: =M5*EXP(($B$3-$B$4-(0.5*$B$5*$B$5))*$B$7)*EXP($B$5*SQRT($B$7)*L6) -> 0.0087020792 | P6: =P5+1 -> 2 | Q6: 0
A7: delta t | B7: =B6/2 -> 0.25 | C7: years | P7: =P6+1 -> 3 | Q7: 0
P8: =P7+1 -> 4 | Q8: 240285.96
P9: =P8+1 -> 5 | Q9: 19275.003
P10: =P9+1 -> 6 | Q10: 89765.563
L11: Option Payoff (T) | M11: =MAX(B2-(100000000*M5)-(200000000*M6),0) -> 0 | P11: =P10+1 -> 7 | Q11: 0
L12: Option Payoff (0) | M12: =M11*EXP(-B3*B6) -> 0 | P12: =P11+1 -> 8 | Q12: 344175.83
L13: Option Premium | M13: =AVERAGE(Q5:Q5004) -> 78048.64 | N13: USD | P13: =P12+1 -> 9 | Q13: 47499.699
P14: =P13+1 -> 10 | Q14: 352593.04
P15: =P14+1 -> 11 | Q15: 0
P16: =P15+1 -> 12 | Q16: 26459.218
P17: =P16+1 -> 13 | Q17: 0
P18: =P17+1 -> 14 | Q18: 0
P19: =P18+1 -> 15 | Q19: 357248.48
P20: =P19+1 -> 16 | Q20: 0
P21: =P20+1 -> 17 | Q21: 96992.473
P22: =P21+1 -> 18 | Q22: 0
P23: =P22+1 -> 19 | Q23: 0
P24: =P23+1 -> 20 | Q24: 0
P25: =P24+1 -> 21 | Q25: 0
... P5004: =P5003+1 -> 5000 | Q5004: 61532.822

Sheet Slide 58_perfect sensitivity
A1: S0 | B1: 150 | C1: =B1+1 -> 151
A2: X | B2: 120 | C2: =B2 -> 120
A3: r | B3: 0.1 | C3: =B3 -> 0.1
A4: q | B4: 0.03 | C4: =B4 -> 0.03
A5: vol | B5: 0.3 | C5: =B5 -> 0.3
A6: Time | B6: =5/365 -> 0.01369863 | C6: =B6 -> 0.01369863
A8: d1 | B8: =(LN(B1/B2)+((B3-B4+(0.5*B5*B5))*B6))/(B5*SQRT(B6)) -> 6.3999969 | C8: =(LN(C1/C2)+((C3-C4+(0.5*C5*C5))*C6))/(C5*SQRT(C6)) -> 6.5892336
A9: d2 | B9: =(LN(B1/B2)+((B3-B4-(0.5*B5*B5))*B6))/(B5*SQRT(B6)) -> 6.3648846 | C9: =(LN(C1/C2)+((C3-C4-(0.5*C5*C5))*C6))/(C5*SQRT(C6)) -> 6.5541212
A10: call premium | B10: =(B1*EXP(-B4*B6)*NORMSDIST(B8))-(B2*EXP(-B3*B6)*NORMSDIST(B9)) -> 30.10264 | C10: =(C1*EXP(-C4*C6)*NORMSDIST(C8))-(C2*EXP(-C3*C6)*NORMSDIST(C9)) -> 31.102229
A11: sensitivity | B11: =(C10-B10)/(C1-B1) -> 0.99958913 | C11: <<when the underlying stock changes by a $1, the option premium changes by close to a dollar$1

Sheet Slide 58_perfect insensitivity
A1: S0 | B1: 100 | C1: =B1+1 -> 101
A2: X | B2: 120 | C2: =B2 -> 120
A3: r | B3: 0.1 | C3: =B3 -> 0.1
A4: q | B4: 0.03 | C4: =B4 -> 0.03
A5: vol | B5: 0.3 | C5: =B5 -> 0.3
A6: Time | B6: =5/365 -> 0.01369863 | C6: =B6 -> 0.01369863
A8: d1 | B8: =(LN(B1/B2)+((B3-B4+(0.5*B5*B5))*B6))/(B5*SQRT(B6)) -> -5.1476544 | C8: =(LN(C1/C2)+((C3-C4+(0.5*C5*C5))*C6))/(C5*SQRT(C6)) -> -4.8642689
A9: d2 | B9: =(LN(B1/B2)+((B3-B4-(0.5*B5*B5))*B6))/(B5*SQRT(B6)) -> -5.1827668 | C9: =(LN(C1/C2)+((C3-C4-(0.5*C5*C5))*C6))/(C5*SQRT(C6)) -> -4.8993812
A10: call premium | B10: =(B1*EXP(-B4*B6)*NORMSDIST(B8))-(B2*EXP(-B3*B6)*NORMSDIST(B9)) -> 8.3628725e-08 | C10: =(C1*EXP(-C4*C6)*NORMSDIST(C8))-(C2*EXP(-C3*C6)*NORMSDIST(C9)) -> 3.8649066e-07
A11: sensitivity (delta) | B11: =(C10-B10)/(C1-B1) -> 3.0286193e-07

Sheet Slide 60_R
A1: S0 | B1: 100 | C1: =B1+1 -> 101
A2: X | B2: 120 | C2: =B2 -> 120
A3: r | B3: 0.1 | C3: =B3 -> 0.1
A4: q | B4: 0.03 | C4: =B4 -> 0.03
A5: vol | B5: 0.3 | C5: =B5 -> 0.3
A6: Time | B6: =0.5 -> 0.5 | C6: =B6 -> 0.5
A8: d1 | B8: =(LN(B1/B2)+((B3-B4+(0.5*B5*B5))*B6))/(B5*SQRT(B6)) -> -0.58841446 | C8: =(LN(C1/C2)+((C3-C4+(0.5*C5*C5))*C6))/(C5*SQRT(C6)) -> -0.54150815
A9: d2 | B9: =(LN(B1/B2)+((B3-B4-(0.5*B5*B5))*B6))/(B5*SQRT(B6)) -> -0.8005465 | C9: =(LN(C1/C2)+((C3-C4-(0.5*C5*C5))*C6))/(C5*SQRT(C6)) -> -0.75364019
A10: call premium | B10: =(B1*EXP(-B4*B6)*NORMSDIST(B8))-(B2*EXP(-B3*B6)*NORMSDIST(B9)) -> 3.2339261 | C10: =(C1*EXP(-C4*C6)*NORMSDIST(C8))-(C2*EXP(-C3*C6)*NORMSDIST(C9)) -> 3.5157478
A11: sensitivity (delta) | B11: =(C10-B10)/(C1-B1) -> 0.28182169 | C11: <<when the underlying stock changes by a $1, the option premium changes by $1
A12: Call delta | B12: =EXP(-B4*B6)*NORMSDIST(B8) -> 0.27398629
A14: https://en.wikipedia.org/wiki/Greeks_(finance)

Sheet Slide 61
A1: Time 0: 21 Mar 26 (1000 hours) | D1: Time 0: 21 Mar 26 (1000 hours)
A2: S0 | B2: 130 | D2: S0 | E2: 120
A3: X | B3: 120 | D3: X | E3: 120
A4: r | B4: 0.1 | D4: r | E4: 0.1
A5: q | B5: 0.03 | D5: q | E5: 0.03
A6: vol | B6: 0.3 | D6: vol | E6: 0.4
A7: Time | B7: =0.5 -> 0.5 | D7: Time | E7: =0.5 -> 0.5
A8: d1 | B8: =(LN(B2/B3)+((B4-B5+(0.5*B6*B6))*B7))/(B6*SQRT(B7)) -> 0.64838254 | D8: d1 | E8: =(LN(E2/E3)+((E4-E5+(0.5*E6*E6))*E7))/(E6*SQRT(E7)) -> 0.26516504
A9: d2 | B9: =(LN(B2/B3)+((B4-B5-(0.5*B6*B6))*B7))/(B6*SQRT(B7)) -> 0.43625051 | D9: d2 | E9: =(LN(E2/E3)+((E4-E5-(0.5*E6*E6))*E7))/(E6*SQRT(E7)) -> -0.01767767
A10: call premium | B10: =(B2*EXP(-B5*B7)*NORMSDIST(B8))-(B3*EXP(-B4*B7)*NORMSDIST(B9)) -> 18.649354 | D10: call premium | E10: =(E2*EXP(-E5*E7)*NORMSDIST(E8))-(E3*EXP(-E4*E7)*NORMSDIST(E9)) -> 15.198179
A11: Call delta | B11: =EXP(-B5*B7)*NORMSDIST(B8) -> 0.73058977 | D11: Call delta | E11: =EXP(-E5*E7)*NORMSDIST(E8) -> 0.59555813
A13: S1: Don’t Do Anything | C13: Date | D13: Time | E13: Position | F13: Option Type | G13: Strike | H13: Book Value | I13: Mkt Value | J13: M2M Value | K13: Delta
C14: 46102 | D14: 1000 | E14: 1000 | F14: Call | G14: 120 | H14: =E14*B10 -> 18649.354 | I14: =H14 -> 18649.354 | J14: =I14-H14 -> 0 | K14: =B11*E14 -> 730.58977
C15: 46102 | D15: 1500 | E15: 1000 | F15: Call | G15: 120 | H15: =H14 -> 18649.354 | I15: =E10*E15 -> 15198.179 | J15: =I15-H15 -> -3451.1756 | K15: =E11*E15 -> 595.55813
A17: S2: Delta Hedging | C17: Date | D17: Time | E17: Position | F17: Option Type | G17: Strike | H17: Book Value | I17: Mkt Value | J17: M2M Value | K17: Delta
C18: 46102 | D18: 1000 | E18: 1000 | F18: Call | G18: 120 | H18: =H14 -> 18649.354 | I18: =H18 -> 18649.354 | J18: =I18-H18 -> 0 | K18: =K14 -> 730.58977
E19: -730 | H19: =E19*B2 -> -94900 | I19: =H19 -> -94900 | J19: =I19-H19 -> 0 | K19: =E19*1 -> -730
E20: Net Position | J20: =J18+J19 -> 0 | K20: =K18+K19 -> 0.58977008
C21: 46102 | D21: 1500 | E21: 1000 | F21: Call | G21: 120 | H21: =H18 -> 18649.354 | I21: =I15 -> 15198.179 | J21: =I21-H21 -> -3451.1756 | K21: =K15 -> 595.55813
E22: -730 | H22: =H19 -> -94900 | I22: =E22*E2 -> -87600 | J22: =I22-H22 -> 7300 | K22: =K19 -> -730
E23: Net Position | J23: =J21+J22 -> 3848.8244 | K23: =K21+K22 -> -134.44187
